Workbook
Name Financial_Summary: #REF!
Name IQ_CH: 110000
Name IQ_CQ: 5000
Name IQ_CY: 10000
Name IQ_DAILY: 500000
Name IQ_FH: 100000
Name IQ_FQ: 500
Name IQ_FY: 1000
Name IQ_LTM: 2000
Name IQ_MONTH: 15000
Name IQ_NTM: 6000
Name IQ_WEEK: 50000
Name IQ_YTD: 3000

Sheet Sheet4
A1: Picture
D2: Stats
D3: Rent Roll
A4: Address | D4: Unit Count
D5: Yields

Sheet Diligence and Notes
B3: Notes
B4: 1 | C4: [This is a space to take notes on the deal]
B5: 2
B6: 3
B8: Diligence Questions
B9: 1 | C9: [This is a space to record diligence questions / items on the deal]
B10: 2
B11: 3

Sheet Underwriting Assumptions
C3: Underwriting Assumptions
J4: Monthly | K4: Annual | M4: Notes
C5: Pro Forma Rent Roll | J5: =+K5/12 -> 165312.07 | K5: =+Assumptions!K124 -> 1983744.8 | M5: Current Rent Roll
C6: ="Plus: "&Assumptions!B131 -> Plus: Total Amenity Income | J6: =+K6/12 -> 7721 | K6: =+Assumptions!J131 -> 92652 | M6: Laundry Currently
C7: Less: Vacancy, Turnover, Bad Debt | G7: =-Assumptions!G148-Assumptions!G147-Assumptions!K146 -> -0.076666667 | J7: =+$G$7*J5 -> -12673.925 | K7: =+$G$7*K5 -> -152087.1 | M7: 5% Vacancy + 20% Turnover
C8: Effective Gross Income | J8: =SUM(J5:J7) -> 160359.14 | K8: =SUM(K5:K7) -> 1924309.7
C10: =Assumptions!B150 -> Operating Expenses | H10: =Assumptions!G150 -> Factor | I10: =Assumptions!H150 -> Statistic | J10: =Assumptions!I150 -> Monthly | K10: =Assumptions!J150 -> Annual
C11: =Assumptions!B151 -> Property Taxes | H11: =Assumptions!G151 -> 3815.7179 | I11: =Assumptions!H151 -> 78 | J11: =Assumptions!I151 -> 24802.167 | K11: =Assumptions!J151 -> 297626 | M11: Broker
C12: =Assumptions!B152 -> Insurance | H12: =Assumptions!G152 -> 910 | I12: =Assumptions!H152 -> 78 | J12: =Assumptions!I152 -> 5915 | K12: =Assumptions!J152 -> 70980 | M12: Estimate
C13: =Assumptions!B153 -> Water / Sewer | H13: =Assumptions!G153 -> 600.89744 | I13: =Assumptions!H153 -> 78 | J13: =Assumptions!I153 -> 3905.8333 | K13: =Assumptions!J153 -> 46870 | M13: Estimate
C14: =Assumptions!B154 -> Repairs & Maintenance | H14: =Assumptions!G154 -> 500 | I14: =Assumptions!H154 -> 78 | J14: =Assumptions!I154 -> 3250 | K14: =Assumptions!J154 -> 39000 | M14: Estimate
C15: =Assumptions!B155 -> Bank fees | J15: =Assumptions!I155 -> 162.5 | K15: =Assumptions!J155 -> 1950 | M15: Estimate
C16: =Assumptions!B156 -> Trash | J16: =Assumptions!I156 -> 200 | K16: =Assumptions!J156 -> 2400 | M16: Estimate (NEW)
C17: =Assumptions!B158 -> Security, Internet | J17: =Assumptions!I158 -> 200 | K17: =Assumptions!J158 -> 2400 | M17: Estimate (NEW)
C18: =Assumptions!B159 -> Pest Control | H18: =Assumptions!G159 -> 75 | I18: =Assumptions!H159 -> 78 | J18: =Assumptions!I159 -> 487.5 | K18: =Assumptions!J159 -> 5850 | M18: Estimate (NEW)
C19: =Assumptions!B162 -> Common Area Electric | H19: =Assumptions!G162 -> 0.67009901 | I19: =Assumptions!H162 -> 5050 | J19: =Assumptions!I162 -> 282 | K19: =Assumptions!J162 -> 3384 | M19: Broker
C20: =Assumptions!B163 -> Landscaping / Snow Removal | J20: =Assumptions!I163 -> 1250 | K20: =Assumptions!J163 -> 15000 | M20: Estimate
C21: =Assumptions!B164 -> Property Management | H21: =Assumptions!G164 -> 0.03 | I21: =Assumptions!H164 -> 1937970.4 | J21: =Assumptions!I164 -> 4844.926 | K21: =Assumptions!J164 -> 58139.112 | M21: PCG PM Fee
C22: =Assumptions!B165 -> Accounting / Legal | J22: =Assumptions!I165 -> 291.66667 | K22: =Assumptions!J165 -> 3500 | M22: Estimate (NEW)
C23: =+Assumptions!B166 -> Total Operating Expenses | J23: =Assumptions!I166 -> 55431.926 | K23: =Assumptions!J166 -> 665183.11
C24: Operating Expense Margin | K24: =+K23/K8 -> 0.34567362
C26: Net Operating Income | J26: =+J8-J23 -> 104927.22 | K26: =+K8-K23 -> 1259126.6
C27: ="Implied Stabilized Cap Rate at "&TEXT(Assumptions!G22,"$#,##0")&" Purchase" -> Implied Stabilized Cap Rate at $14,900,000 Purchase | K27: =+K26/Assumptions!G22 -> 0.084505143

Sheet NOI
C3: Net Operating Income Summary
G4: 1 | H4: =+G4+1 -> 2 | I4: =+H4+1 -> 3 | J4: =+I4+1 -> 4 | K4: =+J4+1 -> 5
C5: ='NOI Walk'!B20 -> Gross Potential Rent | G5: =+SUMIFS('NOI Walk'!$E20:$CW20,'NOI Walk'!$E$14:$CW$14,NOI!G$4) -> 2010814.3 | H5: =+SUMIFS('NOI Walk'!$E20:$CW20,'NOI Walk'!$E$14:$CW$14,NOI!H$4) -> 2061664.7 | I5: =+SUMIFS('NOI Walk'!$E20:$CW20,'NOI Walk'!$E$14:$CW$14,NOI!I$4) -> 2113801 | J5: =+SUMIFS('NOI Walk'!$E20:$CW20,'NOI Walk'!$E$14:$CW$14,NOI!J$4) -> 2167255.8 | K5: =+SUMIFS('NOI Walk'!$E20:$CW20,'NOI Walk'!$E$14:$CW$14,NOI!K$4) -> 2222062.4
C6: Loss-to-Lease | G6: =+SUMIFS('NOI Walk'!$E21:$CW21,'NOI Walk'!$E$14:$CW$14,NOI!G$4) -> -459561.05 | H6: =+SUMIFS('NOI Walk'!$E21:$CW21,'NOI Walk'!$E$14:$CW$14,NOI!H$4) -> -212925.15 | I6: =+SUMIFS('NOI Walk'!$E21:$CW21,'NOI Walk'!$E$14:$CW$14,NOI!I$4) -> 34561.397 | J6: =+SUMIFS('NOI Walk'!$E21:$CW21,'NOI Walk'!$E$14:$CW$14,NOI!J$4) -> 99676.363 | K6: =+SUMIFS('NOI Walk'!$E21:$CW21,'NOI Walk'!$E$14:$CW$14,NOI!K$4) -> 101023.89
C7: Vacancy | G7: =+SUMIFS('NOI Walk'!$E22:$CW22,'NOI Walk'!$E$14:$CW$14,NOI!G$4) -> -150388.05 | H7: =+SUMIFS('NOI Walk'!$E22:$CW22,'NOI Walk'!$E$14:$CW$14,NOI!H$4) -> -223199.3 | I7: =+SUMIFS('NOI Walk'!$E22:$CW22,'NOI Walk'!$E$14:$CW$14,NOI!I$4) -> -154449.3 | J7: =+SUMIFS('NOI Walk'!$E22:$CW22,'NOI Walk'!$E$14:$CW$14,NOI!J$4) -> -107949.15 | K7: =+SUMIFS('NOI Walk'!$E22:$CW22,'NOI Walk'!$E$14:$CW$14,NOI!K$4) -> -110623.15
C8: ='NOI Walk'!B23 -> Vacancy | G8: =-G7/G5 -> 0.074789623 | H8: =-H7/H5 -> 0.10826169 | I8: =-I7/I5 -> 0.073067096 | J8: =-J7/J5 -> 0.049809141 | K8: =-K7/K5 -> 0.049784001
C9: Rental Income | G9: =+SUMIFS('NOI Walk'!$E24:$CW24,'NOI Walk'!$E$14:$CW$14,NOI!G$4) -> 1400865.2 | H9: =+SUMIFS('NOI Walk'!$E24:$CW24,'NOI Walk'!$E$14:$CW$14,NOI!H$4) -> 1625540.3 | I9: =+SUMIFS('NOI Walk'!$E24:$CW24,'NOI Walk'!$E$14:$CW$14,NOI!I$4) -> 1993913.1 | J9: =+SUMIFS('NOI Walk'!$E24:$CW24,'NOI Walk'!$E$14:$CW$14,NOI!J$4) -> 2158983 | K9: =+SUMIFS('NOI Walk'!$E24:$CW24,'NOI Walk'!$E$14:$CW$14,NOI!K$4) -> 2212463.1
C10: ='NOI Walk'!B25 -> Parking Income | G10: =+SUMIFS('NOI Walk'!$E25:$CW25,'NOI Walk'!$E$14:$CW$14,NOI!G$4) -> 4870.1051 | H10: =+SUMIFS('NOI Walk'!$E25:$CW25,'NOI Walk'!$E$14:$CW$14,NOI!H$4) -> 60474.335 | I10: =+SUMIFS('NOI Walk'!$E25:$CW25,'NOI Walk'!$E$14:$CW$14,NOI!I$4) -> 66738.292 | J10: =+SUMIFS('NOI Walk'!$E25:$CW25,'NOI Walk'!$E$14:$CW$14,NOI!J$4) -> 71582.162 | K10: =+SUMIFS('NOI Walk'!$E25:$CW25,'NOI Walk'!$E$14:$CW$14,NOI!K$4) -> 73027.002
C11: ='NOI Walk'!B26 -> Storage Income | G11: =+SUMIFS('NOI Walk'!$E26:$CW26,'NOI Walk'!$E$14:$CW$14,NOI!G$4) -> 2597.3894 | H11: =+SUMIFS('NOI Walk'!$E26:$CW26,'NOI Walk'!$E$14:$CW$14,NOI!H$4) -> 32252.978 | I11: =+SUMIFS('NOI Walk'!$E26:$CW26,'NOI Walk'!$E$14:$CW$14,NOI!I$4) -> 35593.755 | J11: =+SUMIFS('NOI Walk'!$E26:$CW26,'NOI Walk'!$E$14:$CW$14,NOI!J$4) -> 38177.153 | K11: =+SUMIFS('NOI Walk'!$E26:$CW26,'NOI Walk'!$E$14:$CW$14,NOI!K$4) -> 38947.734
C12: ='NOI Walk'!B27 -> Laundry Income | G12: =+SUMIFS('NOI Walk'!$E27:$CW27,'NOI Walk'!$E$14:$CW$14,NOI!G$4) -> 1883.1871 | H12: =+SUMIFS('NOI Walk'!$E27:$CW27,'NOI Walk'!$E$14:$CW$14,NOI!H$4) -> 1867.2777 | I12: =+SUMIFS('NOI Walk'!$E27:$CW27,'NOI Walk'!$E$14:$CW$14,NOI!I$4) -> 2060.6911 | J12: =+SUMIFS('NOI Walk'!$E27:$CW27,'NOI Walk'!$E$14:$CW$14,NOI!J$4) -> 2210.2562 | K12: =+SUMIFS('NOI Walk'!$E27:$CW27,'NOI Walk'!$E$14:$CW$14,NOI!K$4) -> 2254.8688
C13: ='NOI Walk'!B28 -> Gym / Amenity Space Income | G13: =+SUMIFS('NOI Walk'!$E28:$CW28,'NOI Walk'!$E$14:$CW$14,NOI!G$4) -> 42799.706 | H13: =+SUMIFS('NOI Walk'!$E28:$CW28,'NOI Walk'!$E$14:$CW$14,NOI!H$4) -> 42438.129 | I13: =+SUMIFS('NOI Walk'!$E28:$CW28,'NOI Walk'!$E$14:$CW$14,NOI!I$4) -> 46833.889 | J13: =+SUMIFS('NOI Walk'!$E28:$CW28,'NOI Walk'!$E$14:$CW$14,NOI!J$4) -> 50233.096 | K13: =+SUMIFS('NOI Walk'!$E28:$CW28,'NOI Walk'!$E$14:$CW$14,NOI!K$4) -> 51247.019
C14: ='NOI Walk'!B29 -> Turnover Costs | G14: =+SUMIFS('NOI Walk'!$E29:$CW29,'NOI Walk'!$E$14:$CW$14,NOI!G$4) -> 0 | H14: =+SUMIFS('NOI Walk'!$E29:$CW29,'NOI Walk'!$E$14:$CW$14,NOI!H$4) -> 0 | I14: =+SUMIFS('NOI Walk'!$E29:$CW29,'NOI Walk'!$E$14:$CW$14,NOI!I$4) -> -17664.032 | J14: =+SUMIFS('NOI Walk'!$E29:$CW29,'NOI Walk'!$E$14:$CW$14,NOI!J$4) -> -35983.05 | K14: =+SUMIFS('NOI Walk'!$E29:$CW29,'NOI Walk'!$E$14:$CW$14,NOI!K$4) -> -36874.385
C15: ='NOI Walk'!B31 -> Effective Gross Income | G15: =+SUMIFS('NOI Walk'!$E31:$CW31,'NOI Walk'!$E$14:$CW$14,NOI!G$4) -> 1438485.5 | H15: =+SUMIFS('NOI Walk'!$E31:$CW31,'NOI Walk'!$E$14:$CW$14,NOI!H$4) -> 1744947.3 | I15: =+SUMIFS('NOI Walk'!$E31:$CW31,'NOI Walk'!$E$14:$CW$14,NOI!I$4) -> 2106024.3 | J15: =+SUMIFS('NOI Walk'!$E31:$CW31,'NOI Walk'!$E$14:$CW$14,NOI!J$4) -> 2261990.8 | K15: =+SUMIFS('NOI Walk'!$E31:$CW31,'NOI Walk'!$E$14:$CW$14,NOI!K$4) -> 2317285.9
C17: ='NOI Walk'!B33 -> Operating Expenses
C18: ='NOI Walk'!B34 -> Property Taxes | G18: =+SUMIFS('NOI Walk'!$E34:$CW34,'NOI Walk'!$E$14:$CW$14,NOI!G$4) -> 300870.07 | H18: =+SUMIFS('NOI Walk'!$E34:$CW34,'NOI Walk'!$E$14:$CW$14,NOI!H$4) -> 306942.94 | I18: =+SUMIFS('NOI Walk'!$E34:$CW34,'NOI Walk'!$E$14:$CW$14,NOI!I$4) -> 313138.38 | J18: =+SUMIFS('NOI Walk'!$E34:$CW34,'NOI Walk'!$E$14:$CW$14,NOI!J$4) -> 319458.88 | K18: =+SUMIFS('NOI Walk'!$E34:$CW34,'NOI Walk'!$E$14:$CW$14,NOI!K$4) -> 325906.95
C19: ='NOI Walk'!B35 -> Insurance | G19: =+SUMIFS('NOI Walk'!$E35:$CW35,'NOI Walk'!$E$14:$CW$14,NOI!G$4) -> 71753.669 | H19: =+SUMIFS('NOI Walk'!$E35:$CW35,'NOI Walk'!$E$14:$CW$14,NOI!H$4) -> 73201.97 | I19: =+SUMIFS('NOI Walk'!$E35:$CW35,'NOI Walk'!$E$14:$CW$14,NOI!I$4) -> 74679.505 | J19: =+SUMIFS('NOI Walk'!$E35:$CW35,'NOI Walk'!$E$14:$CW$14,NOI!J$4) -> 76186.863 | K19: =+SUMIFS('NOI Walk'!$E35:$CW35,'NOI Walk'!$E$14:$CW$14,NOI!K$4) -> 77724.645
C20: ='NOI Walk'!B36 -> Water / Sewer | G20: =+SUMIFS('NOI Walk'!$E36:$CW36,'NOI Walk'!$E$14:$CW$14,NOI!G$4) -> 42863.723 | H20: =+SUMIFS('NOI Walk'!$E36:$CW36,'NOI Walk'!$E$14:$CW$14,NOI!H$4) -> 42501.605 | I20: =+SUMIFS('NOI Walk'!$E36:$CW36,'NOI Walk'!$E$14:$CW$14,NOI!I$4) -> 46903.939 | J20: =+SUMIFS('NOI Walk'!$E36:$CW36,'NOI Walk'!$E$14:$CW$14,NOI!J$4) -> 50308.231 | K20: =+SUMIFS('NOI Walk'!$E36:$CW36,'NOI Walk'!$E$14:$CW$14,NOI!K$4) -> 51323.67
C21: ='NOI Walk'!B37 -> Repairs & Maintenance | G21: =+SUMIFS('NOI Walk'!$E37:$CW37,'NOI Walk'!$E$14:$CW$14,NOI!G$4) -> 35666.422 | H21: =+SUMIFS('NOI Walk'!$E37:$CW37,'NOI Walk'!$E$14:$CW$14,NOI!H$4) -> 35365.108 | I21: =+SUMIFS('NOI Walk'!$E37:$CW37,'NOI Walk'!$E$14:$CW$14,NOI!I$4) -> 39028.241 | J21: =+SUMIFS('NOI Walk'!$E37:$CW37,'NOI Walk'!$E$14:$CW$14,NOI!J$4) -> 41860.914 | K21: =+SUMIFS('NOI Walk'!$E37:$CW37,'NOI Walk'!$E$14:$CW$14,NOI!K$4) -> 42705.849
C22: ='NOI Walk'!B38 -> Bank fees | G22: =+SUMIFS('NOI Walk'!$E38:$CW38,'NOI Walk'!$E$14:$CW$14,NOI!G$4) -> 1971.2546 | H22: =+SUMIFS('NOI Walk'!$E38:$CW38,'NOI Walk'!$E$14:$CW$14,NOI!H$4) -> 2011.0431 | I22: =+SUMIFS('NOI Walk'!$E38:$CW38,'NOI Walk'!$E$14:$CW$14,NOI!I$4) -> 2051.6348 | J22: =+SUMIFS('NOI Walk'!$E38:$CW38,'NOI Walk'!$E$14:$CW$14,NOI!J$4) -> 2093.0457 | K22: =+SUMIFS('NOI Walk'!$E38:$CW38,'NOI Walk'!$E$14:$CW$14,NOI!K$4) -> 2135.2925
C23: ='NOI Walk'!B39 -> Trash | G23: =+SUMIFS('NOI Walk'!$E39:$CW39,'NOI Walk'!$E$14:$CW$14,NOI!G$4) -> 2426.1596 | H23: =+SUMIFS('NOI Walk'!$E39:$CW39,'NOI Walk'!$E$14:$CW$14,NOI!H$4) -> 2475.13 | I23: =+SUMIFS('NOI Walk'!$E39:$CW39,'NOI Walk'!$E$14:$CW$14,NOI!I$4) -> 2525.0889 | J23: =+SUMIFS('NOI Walk'!$E39:$CW39,'NOI Walk'!$E$14:$CW$14,NOI!J$4) -> 2576.0562 | K23: =+SUMIFS('NOI Walk'!$E39:$CW39,'NOI Walk'!$E$14:$CW$14,NOI!K$4) -> 2628.0523
C24: ='NOI Walk'!B40 -> Cleaning | G24: =+SUMIFS('NOI Walk'!$E40:$CW40,'NOI Walk'!$E$14:$CW$14,NOI!G$4) -> 11827.528 | H24: =+SUMIFS('NOI Walk'!$E40:$CW40,'NOI Walk'!$E$14:$CW$14,NOI!H$4) -> 12066.259 | I24: =+SUMIFS('NOI Walk'!$E40:$CW40,'NOI Walk'!$E$14:$CW$14,NOI!I$4) -> 12309.809 | J24: =+SUMIFS('NOI Walk'!$E40:$CW40,'NOI Walk'!$E$14:$CW$14,NOI!J$4) -> 12558.274 | K24: =+SUMIFS('NOI Walk'!$E40:$CW40,'NOI Walk'!$E$14:$CW$14,NOI!K$4) -> 12811.755
C25: ='NOI Walk'!B41 -> Security, Internet | G25: =+SUMIFS('NOI Walk'!$E41:$CW41,'NOI Walk'!$E$14:$CW$14,NOI!G$4) -> 2426.1596 | H25: =+SUMIFS('NOI Walk'!$E41:$CW41,'NOI Walk'!$E$14:$CW$14,NOI!H$4) -> 2475.13 | I25: =+SUMIFS('NOI Walk'!$E41:$CW41,'NOI Walk'!$E$14:$CW$14,NOI!I$4) -> 2525.0889 | J25: =+SUMIFS('NOI Walk'!$E41:$CW41,'NOI Walk'!$E$14:$CW$14,NOI!J$4) -> 2576.0562 | K25: =+SUMIFS('NOI Walk'!$E41:$CW41,'NOI Walk'!$E$14:$CW$14,NOI!K$4) -> 2628.0523
C26: ='NOI Walk'!B42 -> Pest Control | G26: =+SUMIFS('NOI Walk'!$E42:$CW42,'NOI Walk'!$E$14:$CW$14,NOI!G$4) -> 5913.7639 | H26: =+SUMIFS('NOI Walk'!$E42:$CW42,'NOI Walk'!$E$14:$CW$14,NOI!H$4) -> 6033.1294 | I26: =+SUMIFS('NOI Walk'!$E42:$CW42,'NOI Walk'!$E$14:$CW$14,NOI!I$4) -> 6154.9043 | J26: =+SUMIFS('NOI Walk'!$E42:$CW42,'NOI Walk'!$E$14:$CW$14,NOI!J$4) -> 6279.137 | K26: =+SUMIFS('NOI Walk'!$E42:$CW42,'NOI Walk'!$E$14:$CW$14,NOI!K$4) -> 6405.8774
C27: ='NOI Walk'!B43 -> Super (Payroll) | G27: =+SUMIFS('NOI Walk'!$E43:$CW43,'NOI Walk'!$E$14:$CW$14,NOI!G$4) -> 39425.093 | H27: =+SUMIFS('NOI Walk'!$E43:$CW43,'NOI Walk'!$E$14:$CW$14,NOI!H$4) -> 40220.863 | I27: =+SUMIFS('NOI Walk'!$E43:$CW43,'NOI Walk'!$E$14:$CW$14,NOI!I$4) -> 41032.695 | J27: =+SUMIFS('NOI Walk'!$E43:$CW43,'NOI Walk'!$E$14:$CW$14,NOI!J$4) -> 41860.914 | K27: =+SUMIFS('NOI Walk'!$E43:$CW43,'NOI Walk'!$E$14:$CW$14,NOI!K$4) -> 42705.849
C28: ='NOI Walk'!B44 -> Heat (Gas) | G28: =+SUMIFS('NOI Walk'!$E44:$CW44,'NOI Walk'!$E$14:$CW$14,NOI!G$4) -> 68118.473 | H28: =+SUMIFS('NOI Walk'!$E44:$CW44,'NOI Walk'!$E$14:$CW$14,NOI!H$4) -> 69493.401 | I28: =+SUMIFS('NOI Walk'!$E44:$CW44,'NOI Walk'!$E$14:$CW$14,NOI!I$4) -> 70896.08 | J28: =+SUMIFS('NOI Walk'!$E44:$CW44,'NOI Walk'!$E$14:$CW$14,NOI!J$4) -> 72327.072 | K28: =+SUMIFS('NOI Walk'!$E44:$CW44,'NOI Walk'!$E$14:$CW$14,NOI!K$4) -> 73786.947
C29: ='NOI Walk'!B45 -> Common Area Electric | G29: =+SUMIFS('NOI Walk'!$E45:$CW45,'NOI Walk'!$E$14:$CW$14,NOI!G$4) -> 3420.885 | H29: =+SUMIFS('NOI Walk'!$E45:$CW45,'NOI Walk'!$E$14:$CW$14,NOI!H$4) -> 3489.9333 | I29: =+SUMIFS('NOI Walk'!$E45:$CW45,'NOI Walk'!$E$14:$CW$14,NOI!I$4) -> 3560.3754 | J29: =+SUMIFS('NOI Walk'!$E45:$CW45,'NOI Walk'!$E$14:$CW$14,NOI!J$4) -> 3632.2393 | K29: =+SUMIFS('NOI Walk'!$E45:$CW45,'NOI Walk'!$E$14:$CW$14,NOI!K$4) -> 3705.5537
... C35: ='NOI Walk'!B51 -> Multifamily NOI | G35: =+SUMIFS('NOI Walk'!$E51:$CW51,'NOI Walk'!$E$14:$CW$14,NOI!G$4) -> 789946.05 | H35: =+SUMIFS('NOI Walk'!$E51:$CW51,'NOI Walk'!$E$14:$CW$14,NOI!H$4) -> 1077243.2 | I35: =+SUMIFS('NOI Walk'!$E51:$CW51,'NOI Walk'!$E$14:$CW$14,NOI!I$4) -> 1408573.6 | J35: =+SUMIFS('NOI Walk'!$E51:$CW51,'NOI Walk'!$E$14:$CW$14,NOI!J$4) -> 1542556.3 | K35: =+SUMIFS('NOI Walk'!$E51:$CW51,'NOI Walk'!$E$14:$CW$14,NOI!K$4) -> 1583041
C36: ='NOI Walk'!B55 -> Reserves | G36: =-SUMIFS('NOI Walk'!$E56:$CW56,'NOI Walk'!$E$14:$CW$14,NOI!G$4) -> -14384.855 | H36: =-SUMIFS('NOI Walk'!$E56:$CW56,'NOI Walk'!$E$14:$CW$14,NOI!H$4) -> -17449.473 | I36: =-SUMIFS('NOI Walk'!$E56:$CW56,'NOI Walk'!$E$14:$CW$14,NOI!I$4) -> -21060.243 | J36: =-SUMIFS('NOI Walk'!$E56:$CW56,'NOI Walk'!$E$14:$CW$14,NOI!J$4) -> -22619.908 | K36: =-SUMIFS('NOI Walk'!$E56:$CW56,'NOI Walk'!$E$14:$CW$14,NOI!K$4) -> -23172.859
C37: Total Property NOI, net of reserves | G37: =SUM(G35:G36) -> 775561.2 | H37: =SUM(H35:H36) -> 1059793.7 | I37: =SUM(I35:I36) -> 1387513.4 | J37: =SUM(J35:J36) -> 1519936.4 | K37: =SUM(K35:K36) -> 1559868.1
C38: Yield on Cost | G38: =+G37/Assumptions!$F$17 -> 0.046538605 | H38: =+H37/Assumptions!$F$17 -> 0.063594366 | I38: =+I37/Assumptions!$F$17 -> 0.08325963 | J38: =+J37/Assumptions!$F$17 -> 0.091205851 | K38: =+K37/Assumptions!$F$17 -> 0.093602009

Sheet Cash Flow and Exit
B2: CASH FLOW
F3: 0 | G3: =+F3+1 -> 1 | H3: =+G3+1 -> 2 | I3: =+H3+1 -> 3 | J3: =+I3+1 -> 4 | K3: =+J3+1 -> 5
F5: Closing | G5: =+G3 -> 1 | H5: =+H3 -> 2 | I5: =+I3 -> 3 | J5: =+J3 -> 4 | K5: =+K3 -> 5
B6: Net Operating Income, After Reserves | F6: =+SUMIFS(Model!$G26:$DW26,Model!$G$3:$DW$3,'Cash Flow and Exit'!F$3) -> 0 | G6: =+SUMIFS(Model!$G26:$DW26,Model!$G$3:$DW$3,'Cash Flow and Exit'!G$3) -> 775561.2 | H6: =+SUMIFS(Model!$G26:$DW26,Model!$G$3:$DW$3,'Cash Flow and Exit'!H$3) -> 1059793.7 | I6: =+SUMIFS(Model!$G26:$DW26,Model!$G$3:$DW$3,'Cash Flow and Exit'!I$3) -> 1387513.4 | J6: =+SUMIFS(Model!$G26:$DW26,Model!$G$3:$DW$3,'Cash Flow and Exit'!J$3) -> 1519936.4 | K6: =+SUMIFS(Model!$G26:$DW26,Model!$G$3:$DW$3,'Cash Flow and Exit'!K$3) -> 1559868.1
B8: Acquisition Loan Draw | F8: =+SUMIFS(Model!$G40:$DW40,Model!$G$3:$DW$3,'Cash Flow and Exit'!F$3) -> 10430000 | G8: =+SUMIFS(Model!$G40:$DW40,Model!$G$3:$DW$3,'Cash Flow and Exit'!G$3) -> -471651.98 | H8: =+SUMIFS(Model!$G40:$DW40,Model!$G$3:$DW$3,'Cash Flow and Exit'!H$3) -> 102967.95 | I8: =+SUMIFS(Model!$G40:$DW40,Model!$G$3:$DW$3,'Cash Flow and Exit'!I$3) -> 0 | J8: =+SUMIFS(Model!$G40:$DW40,Model!$G$3:$DW$3,'Cash Flow and Exit'!J$3) -> 0 | K8: =+SUMIFS(Model!$G40:$DW40,Model!$G$3:$DW$3,'Cash Flow and Exit'!K$3) -> 0
B9: Acqusition Loan Debt Service | F9: =-SUMIFS(Model!$G41:$DW41,Model!$G$3:$DW$3,'Cash Flow and Exit'!F$3)+SUMIFS(Model!$G47:$DW47,Model!$G$3:$DW$3,'Cash Flow and Exit'!F$3) -> 0 | G9: =-SUMIFS(Model!$G41:$DW41,Model!$G$3:$DW$3,'Cash Flow and Exit'!G$3)+SUMIFS(Model!$G47:$DW47,Model!$G$3:$DW$3,'Cash Flow and Exit'!G$3) -> 875136.88 | H9: =-SUMIFS(Model!$G41:$DW41,Model!$G$3:$DW$3,'Cash Flow and Exit'!H$3)+SUMIFS(Model!$G47:$DW47,Model!$G$3:$DW$3,'Cash Flow and Exit'!H$3) -> 875136.88 | I9: =-SUMIFS(Model!$G41:$DW41,Model!$G$3:$DW$3,'Cash Flow and Exit'!I$3)+SUMIFS(Model!$G47:$DW47,Model!$G$3:$DW$3,'Cash Flow and Exit'!I$3) -> 875136.88 | J9: =-SUMIFS(Model!$G41:$DW41,Model!$G$3:$DW$3,'Cash Flow and Exit'!J$3)+SUMIFS(Model!$G47:$DW47,Model!$G$3:$DW$3,'Cash Flow and Exit'!J$3) -> 0 | K9: =-SUMIFS(Model!$G41:$DW41,Model!$G$3:$DW$3,'Cash Flow and Exit'!K$3)+SUMIFS(Model!$G47:$DW47,Model!$G$3:$DW$3,'Cash Flow and Exit'!K$3) -> 0
B10: Acqusition Loan Paydown | F10: =+SUMIFS(Model!$G42:$DW42,Model!$G$3:$DW$3,'Cash Flow and Exit'!F$3) -> 0 | G10: =+SUMIFS(Model!$G42:$DW42,Model!$G$3:$DW$3,'Cash Flow and Exit'!G$3) -> 0 | H10: =+SUMIFS(Model!$G42:$DW42,Model!$G$3:$DW$3,'Cash Flow and Exit'!H$3) -> 0 | I10: =+SUMIFS(Model!$G42:$DW42,Model!$G$3:$DW$3,'Cash Flow and Exit'!I$3) -> -9749902 | J10: =+SUMIFS(Model!$G42:$DW42,Model!$G$3:$DW$3,'Cash Flow and Exit'!J$3) -> 0 | K10: =+SUMIFS(Model!$G42:$DW42,Model!$G$3:$DW$3,'Cash Flow and Exit'!K$3) -> 0
B12: Refi Loan Draw | F12: =+SUMIFS(Model!$G59:$DW59,Model!$G$3:$DW$3,'Cash Flow and Exit'!F$3) -> 0 | G12: =+SUMIFS(Model!$G59:$DW59,Model!$G$3:$DW$3,'Cash Flow and Exit'!G$3) -> 0 | H12: =+SUMIFS(Model!$G59:$DW59,Model!$G$3:$DW$3,'Cash Flow and Exit'!H$3) -> 0 | I12: =+SUMIFS(Model!$G59:$DW59,Model!$G$3:$DW$3,'Cash Flow and Exit'!I$3) -> 17127872 | J12: =+SUMIFS(Model!$G59:$DW59,Model!$G$3:$DW$3,'Cash Flow and Exit'!J$3) -> 0 | K12: =+SUMIFS(Model!$G59:$DW59,Model!$G$3:$DW$3,'Cash Flow and Exit'!K$3) -> 0
B13: Refi Loan Debt Service | F13: =-SUMIFS(Model!$G60:$DW60,Model!$G$3:$DW$3,'Cash Flow and Exit'!F$3)-SUMIFS(Model!$G62:$DW62,Model!$G$3:$DW$3,'Cash Flow and Exit'!F$3) -> 0 | G13: =-SUMIFS(Model!$G60:$DW60,Model!$G$3:$DW$3,'Cash Flow and Exit'!G$3)-SUMIFS(Model!$G62:$DW62,Model!$G$3:$DW$3,'Cash Flow and Exit'!G$3) -> 0 | H13: =-SUMIFS(Model!$G60:$DW60,Model!$G$3:$DW$3,'Cash Flow and Exit'!H$3)-SUMIFS(Model!$G62:$DW62,Model!$G$3:$DW$3,'Cash Flow and Exit'!H$3) -> 0 | I13: =-SUMIFS(Model!$G60:$DW60,Model!$G$3:$DW$3,'Cash Flow and Exit'!I$3)-SUMIFS(Model!$G62:$DW62,Model!$G$3:$DW$3,'Cash Flow and Exit'!I$3) -> 0 | J13: =-SUMIFS(Model!$G60:$DW60,Model!$G$3:$DW$3,'Cash Flow and Exit'!J$3)-SUMIFS(Model!$G62:$DW62,Model!$G$3:$DW$3,'Cash Flow and Exit'!J$3) -> -749522.19 | K13: =-SUMIFS(Model!$G60:$DW60,Model!$G$3:$DW$3,'Cash Flow and Exit'!K$3)-SUMIFS(Model!$G62:$DW62,Model!$G$3:$DW$3,'Cash Flow and Exit'!K$3) -> -723498.27
B14: Refi Loan Paydown | F14: =+SUMIFS(Model!$G61:$DW61,Model!$G$3:$DW$3,'Cash Flow and Exit'!F$3) -> 0 | G14: =+SUMIFS(Model!$G61:$DW61,Model!$G$3:$DW$3,'Cash Flow and Exit'!G$3) -> 0 | H14: =+SUMIFS(Model!$G61:$DW61,Model!$G$3:$DW$3,'Cash Flow and Exit'!H$3) -> 0 | I14: =+SUMIFS(Model!$G61:$DW61,Model!$G$3:$DW$3,'Cash Flow and Exit'!I$3) -> 0 | J14: =+SUMIFS(Model!$G61:$DW61,Model!$G$3:$DW$3,'Cash Flow and Exit'!J$3) -> 0 | K14: =+SUMIFS(Model!$G61:$DW61,Model!$G$3:$DW$3,'Cash Flow and Exit'!K$3) -> -16670621
B16: Exit Proceeds | F16: =+SUMIFS(Model!$G18:$DW18,Model!$G$3:$DW$3,'Cash Flow and Exit'!F$3) -> 0 | G16: =+SUMIFS(Model!$G18:$DW18,Model!$G$3:$DW$3,'Cash Flow and Exit'!G$3) -> 0 | H16: =+SUMIFS(Model!$G18:$DW18,Model!$G$3:$DW$3,'Cash Flow and Exit'!H$3) -> 0 | I16: =+SUMIFS(Model!$G18:$DW18,Model!$G$3:$DW$3,'Cash Flow and Exit'!I$3) -> 0 | J16: =+SUMIFS(Model!$G18:$DW18,Model!$G$3:$DW$3,'Cash Flow and Exit'!J$3) -> 0 | K16: =+SUMIFS(Model!$G18:$DW18,Model!$G$3:$DW$3,'Cash Flow and Exit'!K$3) -> 26327178
B18: Levered Cash Flow | F18: =+SUMIFS(Model!$G65:$DW65,Model!$G$3:$DW$3,'Cash Flow and Exit'!F$3) -> -5340556.3 | G18: =+SUMIFS(Model!$G65:$DW65,Model!$G$3:$DW$3,'Cash Flow and Exit'!G$3) -> -945265.11 | H18: =+SUMIFS(Model!$G65:$DW65,Model!$G$3:$DW$3,'Cash Flow and Exit'!H$3) -> -33380.037 | I18: =+SUMIFS(Model!$G65:$DW65,Model!$G$3:$DW$3,'Cash Flow and Exit'!I$3) -> 7603725.7 | J18: =+SUMIFS(Model!$G65:$DW65,Model!$G$3:$DW$3,'Cash Flow and Exit'!J$3) -> 326174.52 | K18: =+SUMIFS(Model!$G65:$DW65,Model!$G$3:$DW$3,'Cash Flow and Exit'!K$3) -> 10022664
B19: Cash-on-Cash | G19: =-G18/$F$18 -> -0.1769975 | H19: =-H18/$F$18 -> -0.0062502921 | I19: =-I18/$F$18 -> 1.4237704 | J19: =-J18/$F$18 -> 0.061075008 | K19: =-K18/$F$18 -> 1.8767079
B21: Total Equity Invested | E21: =-Model!$G$66 -> 6794409.5 | H21: Unlevered Returns | K21: =+TEXT(Model!F31,"0.0%")&" / "&TEXT(Model!F32,"0.00x") -> 16.5% / 2.02x
B22: Totel Equity Returned | E22: =+E23+E21 -> 17977607 | H22: Levered Gross Returns | K22: =+TEXT(Model!G68,"0.0%")&" / "&TEXT(Model!G69,"0.00x") -> 30.4% / 2.65x
B23: Gross Profit | E23: =+Model!G67 -> 11183197 | H23: Levered Net Returns | K23: =+TEXT(Model!E95,"0.0%")&" / "&TEXT(Model!E96,"0.00x") -> 22.8% / 2.20x
M24: =+Assumptions!B174 -> Multifamily
M25: =+Assumptions!B175 -> Exit (June 30, 2030) | P25: =+Assumptions!E175 -> 60
M26: =+Assumptions!B176 -> NTM NOI in Month 60 | P26: =+Assumptions!E176 -> 1628485.3
M27: =+Assumptions!B177 -> Applied Exit Cap Rate | P27: =+Assumptions!E177 -> 0.06
M28: =+Assumptions!B178 -> Implied Asset Value | P28: =+Assumptions!E178 -> 27141421
M29: =+Assumptions!B179 -> Less: Selling Costs | P29: =+Assumptions!E179 -> 0.03
M30: =+Assumptions!B180 -> Less: Selling Costs | P30: =+Assumptions!E180 -> -814242.63
M31: =+Assumptions!B181 -> Net Reversion Proceeds | P31: =+Assumptions!E181 -> 26327178
M32: =+Assumptions!B182 -> $ / Unit | P32: =+Assumptions!E182 -> 347966.94
Q34: Exit Cap Rate | R34: Implied Valuation | S34: $ / Unit | T34: $ / SF | U34: Gross Returns
Q35: 0.08 | R35: =+$P$26/Q35 -> 20356066 | S35: =+R35/Assumptions!$E$124 -> 260975.2 | T35: =+R35/Assumptions!$G$24 -> 370.11029 | U35: =+TEXT(Assumptions!G191,"0.0%")&" / "&TEXT(Assumptions!G201,"0.0x") -> 36.4% / 3.2x
Q36: =+Q35-0.25% -> 0.0775 | R36: =+$P$26/Q36 -> 21012713 | S36: =+R36/Assumptions!$E$124 -> 269393.76 | T36: =+R36/Assumptions!$G$24 -> 382.04933 | U36: =+TEXT(Assumptions!G192,"0.0%")&" / "&TEXT(Assumptions!G202,"0.0x") -> 34.7% / 3.0x
Q37: =+Q36-0.25% -> 0.075 | R37: =+$P$26/Q37 -> 21713137 | S37: =+R37/Assumptions!$E$124 -> 278373.55 | T37: =+R37/Assumptions!$G$24 -> 394.78431 | U37: =+TEXT(Assumptions!G193,"0.0%")&" / "&TEXT(Assumptions!G203,"0.0x") -> 33.1% / 2.8x
Q38: =+Q37-0.25% -> 0.0725 | R38: =+$P$26/Q38 -> 22461866 | S38: =+R38/Assumptions!$E$124 -> 287972.64 | T38: =+R38/Assumptions!$G$24 -> 408.39756 | U38: =+TEXT(Assumptions!G194,"0.0%")&" / "&TEXT(Assumptions!G204,"0.0x") -> 31.5% / 2.7x
Q39: =+Q38-0.25% -> 0.07 | R39: =+$P$26/Q39 -> 23264075 | S39: =+R39/Assumptions!$E$124 -> 298257.37 | T39: =+R39/Assumptions!$G$24 -> 422.98318 | U39: =+TEXT(Assumptions!G195,"0.0%")&" / "&TEXT(Assumptions!G205,"0.0x") -> 29.9% / 2.5x

Sheet Model
EM1: x
G2: =+Assumptions!F2 -> 45838 | H2: =+EOMONTH(G2,1) -> 45869 | I2: =+EOMONTH(H2,1) -> 45900 | J2: =+EOMONTH(I2,1) -> 45930 | K2: =+EOMONTH(J2,1) -> 45961 | L2: =+EOMONTH(K2,1) -> 45991 | M2: =+EOMONTH(L2,1) -> 46022 | N2: =+EOMONTH(M2,1) -> 46053 | O2: =+EOMONTH(N2,1) -> 46081 | ... EI2: =+EOMONTH(EH2,1) -> 49856 | EM2: x
G3: =ROUNDUP(G4/12,0) -> 0 | H3: =ROUNDUP(H4/12,0) -> 1 | I3: =ROUNDUP(I4/12,0) -> 1 | J3: =ROUNDUP(J4/12,0) -> 1 | K3: =ROUNDUP(K4/12,0) -> 1 | L3: =ROUNDUP(L4/12,0) -> 1 | M3: =ROUNDUP(M4/12,0) -> 1 | N3: =ROUNDUP(N4/12,0) -> 1 | ... EI3: =ROUNDUP(EI4/12,0) -> 11 | EM3: x
G4: 0 | H4: =+G4+1 -> 1 | I4: =+H4+1 -> 2 | J4: =+I4+1 -> 3 | K4: =+J4+1 -> 4 | L4: =+K4+1 -> 5 | M4: =+L4+1 -> 6 | N4: =+M4+1 -> 7 | O4: =+N4+1 -> 8 | ... EI4: =+EH4+1 -> 132 | EM4: x
B5: =SUM(G5:EI5) -> 14900000 | D5: Acquisition of Property | G5: =+IF(G4=Assumptions!$G$23,Assumptions!$G$22,0) -> 14900000 | H5: =+IF(H4=Assumptions!$G$23,Assumptions!$G$22,0) -> 0 | I5: =+IF(I4=Assumptions!$G$23,Assumptions!$G$22,0) -> 0 | J5: =+IF(J4=Assumptions!$G$23,Assumptions!$G$22,0) -> 0 | K5: =+IF(K4=Assumptions!$G$23,Assumptions!$G$22,0) -> 0 | L5: =+IF(L4=Assumptions!$G$23,Assumptions!$G$22,0) -> 0 | M5: =+IF(M4=Assumptions!$G$23,Assumptions!$G$22,0) -> 0 | N5: =+IF(N4=Assumptions!$G$23,Assumptions!$G$22,0) -> 0 | ... EI5: =+IF(EI4=Assumptions!$G$23,Assumptions!$G$22,0) -> 0 | EM5: x
B6: =SUM(G6:EI6) -> 646260.72 | D6: =+'Closing Costs'!B4 -> Closing Costs | G6: {=INDEX('Closing Costs'!$J$18:$EL$18,,MATCH(Model!G$4,'Closing Costs'!$J$4:$EL$4,0))} -> 646260.72 | H6: {=INDEX('Closing Costs'!$J$18:$EL$18,,MATCH(Model!H$4,'Closing Costs'!$J$4:$EL$4,0))} -> 0 | I6: {=INDEX('Closing Costs'!$J$18:$EL$18,,MATCH(Model!I$4,'Closing Costs'!$J$4:$EL$4,0))} -> 0 | J6: {=INDEX('Closing Costs'!$J$18:$EL$18,,MATCH(Model!J$4,'Closing Costs'!$J$4:$EL$4,0))} -> 0 | K6: {=INDEX('Closing Costs'!$J$18:$EL$18,,MATCH(Model!K$4,'Closing Costs'!$J$4:$EL$4,0))} -> 0 | L6: {=INDEX('Closing Costs'!$J$18:$EL$18,,MATCH(Model!L$4,'Closing Costs'!$J$4:$EL$4,0))} -> 0 | M6: {=INDEX('Closing Costs'!$J$18:$EL$18,,MATCH(Model!M$4,'Closing Costs'!$J$4:$EL$4,0))} -> 0 | N6: {=INDEX('Closing Costs'!$J$18:$EL$18,,MATCH(Model!N$4,'Closing Costs'!$J$4:$EL$4,0))} -> 0 | ... EI6: {=INDEX('Closing Costs'!$J$18:$EL$18,,MATCH(Model!EI$4,'Closing Costs'!$J$4:$EL$4,0))} -> 0 | EM6: x
B7: =SUM(G7:EI7) -> 34650 | D7: =+'Legal and Pre-Dev'!B4 -> Legal and Setup Costs | G7: {=INDEX('Legal and Pre-Dev'!$J$12:$EL$12,,MATCH(Model!G$4,'Legal and Pre-Dev'!$J$4:$EL$4,0))} -> 34650 | H7: {=INDEX('Legal and Pre-Dev'!$J$12:$EL$12,,MATCH(Model!H$4,'Legal and Pre-Dev'!$J$4:$EL$4,0))} -> 0 | I7: {=INDEX('Legal and Pre-Dev'!$J$12:$EL$12,,MATCH(Model!I$4,'Legal and Pre-Dev'!$J$4:$EL$4,0))} -> 0 | J7: {=INDEX('Legal and Pre-Dev'!$J$12:$EL$12,,MATCH(Model!J$4,'Legal and Pre-Dev'!$J$4:$EL$4,0))} -> 0 | K7: {=INDEX('Legal and Pre-Dev'!$J$12:$EL$12,,MATCH(Model!K$4,'Legal and Pre-Dev'!$J$4:$EL$4,0))} -> 0 | L7: {=INDEX('Legal and Pre-Dev'!$J$12:$EL$12,,MATCH(Model!L$4,'Legal and Pre-Dev'!$J$4:$EL$4,0))} -> 0 | M7: {=INDEX('Legal and Pre-Dev'!$J$12:$EL$12,,MATCH(Model!M$4,'Legal and Pre-Dev'!$J$4:$EL$4,0))} -> 0 | N7: {=INDEX('Legal and Pre-Dev'!$J$12:$EL$12,,MATCH(Model!N$4,'Legal and Pre-Dev'!$J$4:$EL$4,0))} -> 0 | ... EI7: {=INDEX('Legal and Pre-Dev'!$J$12:$EL$12,,MATCH(Model!EI$4,'Legal and Pre-Dev'!$J$4:$EL$4,0))} -> 0 | EM7: x
B8: =SUM(G8:EI8) -> 386152.2 | D8: =+Reserves!B4 -> Reserves | G8: {=INDEX(Reserves!$J$12:$EL$12,,MATCH(Model!G$4,Reserves!$J$4:$EL$4,0))} -> 119645.55 | H8: {=INDEX(Reserves!$J$12:$EL$12,,MATCH(Model!H$4,Reserves!$J$4:$EL$4,0))} -> 7012.1788 | I8: {=INDEX(Reserves!$J$12:$EL$12,,MATCH(Model!I$4,Reserves!$J$4:$EL$4,0))} -> 7012.1788 | J8: {=INDEX(Reserves!$J$12:$EL$12,,MATCH(Model!J$4,Reserves!$J$4:$EL$4,0))} -> 7012.1788 | K8: {=INDEX(Reserves!$J$12:$EL$12,,MATCH(Model!K$4,Reserves!$J$4:$EL$4,0))} -> 7012.1788 | L8: {=INDEX(Reserves!$J$12:$EL$12,,MATCH(Model!L$4,Reserves!$J$4:$EL$4,0))} -> 7012.1788 | M8: {=INDEX(Reserves!$J$12:$EL$12,,MATCH(Model!M$4,Reserves!$J$4:$EL$4,0))} -> 7012.1788 | N8: {=INDEX(Reserves!$J$12:$EL$12,,MATCH(Model!N$4,Reserves!$J$4:$EL$4,0))} -> 7012.1788 | ... EI8: {=INDEX(Reserves!$J$12:$EL$12,,MATCH(Model!EI$4,Reserves!$J$4:$EL$4,0))} -> 0 | EM8: x
B9: =SUM(G9:EI9) -> 596750 | D9: =+'Hard Costs'!B4 -> Hard Costs | G9: {=INDEX('Hard Costs'!$J$17:$EL$17,,MATCH(Model!G$4,'Hard Costs'!$J$4:$EL$4,0))} -> 70000 | H9: {=INDEX('Hard Costs'!$J$17:$EL$17,,MATCH(Model!H$4,'Hard Costs'!$J$4:$EL$4,0))} -> 0 | I9: {=INDEX('Hard Costs'!$J$17:$EL$17,,MATCH(Model!I$4,'Hard Costs'!$J$4:$EL$4,0))} -> 16217.391 | J9: {=INDEX('Hard Costs'!$J$17:$EL$17,,MATCH(Model!J$4,'Hard Costs'!$J$4:$EL$4,0))} -> 16217.391 | K9: {=INDEX('Hard Costs'!$J$17:$EL$17,,MATCH(Model!K$4,'Hard Costs'!$J$4:$EL$4,0))} -> 16217.391 | L9: {=INDEX('Hard Costs'!$J$17:$EL$17,,MATCH(Model!L$4,'Hard Costs'!$J$4:$EL$4,0))} -> 77467.391 | M9: {=INDEX('Hard Costs'!$J$17:$EL$17,,MATCH(Model!M$4,'Hard Costs'!$J$4:$EL$4,0))} -> 47467.391 | N9: {=INDEX('Hard Costs'!$J$17:$EL$17,,MATCH(Model!N$4,'Hard Costs'!$J$4:$EL$4,0))} -> 16217.391 | ... EI9: {=INDEX('Hard Costs'!$J$17:$EL$17,,MATCH(Model!EI$4,'Hard Costs'!$J$4:$EL$4,0))} -> 0 | EM9: x
B10: =SUM(G10:EI10) -> -16563813 | D10: Total Project Costs | G10: =-SUM(G5:G9) -> -15770556 | H10: =-SUM(H5:H9) -> -7012.1788 | I10: =-SUM(I5:I9) -> -23229.57 | J10: =-SUM(J5:J9) -> -23229.57 | K10: =-SUM(K5:K9) -> -23229.57 | L10: =-SUM(L5:L9) -> -84479.57 | M10: =-SUM(M5:M9) -> -54479.57 | N10: =-SUM(N5:N9) -> -23229.57 | ... EI10: =-SUM(EI5:EI9) -> 0 | EM10: x
EM11: x
D12: Retail Sale | G12: =IF(G$4=Assumptions!$J$175,Assumptions!$J$178,0) -> 0 | H12: =IF(H$4=Assumptions!$J$175,Assumptions!$J$178,0) -> 0 | I12: =IF(I$4=Assumptions!$J$175,Assumptions!$J$178,0) -> 0 | J12: =IF(J$4=Assumptions!$J$175,Assumptions!$J$178,0) -> 0 | K12: =IF(K$4=Assumptions!$J$175,Assumptions!$J$178,0) -> 0 | L12: =IF(L$4=Assumptions!$J$175,Assumptions!$J$178,0) -> 0 | M12: =IF(M$4=Assumptions!$J$175,Assumptions!$J$178,0) -> 0 | N12: =IF(N$4=Assumptions!$J$175,Assumptions!$J$178,0) -> 0 | ... EI12: =IF(EI$4=Assumptions!$J$175,Assumptions!$J$178,0) -> 0 | EM12: x
D13: Less: Selling Costs | G13: =IF(G$4=Assumptions!$J$175,Assumptions!$J$180,0) -> 0 | H13: =IF(H$4=Assumptions!$J$175,Assumptions!$J$180,0) -> 0 | I13: =IF(I$4=Assumptions!$J$175,Assumptions!$J$180,0) -> 0 | J13: =IF(J$4=Assumptions!$J$175,Assumptions!$J$180,0) -> 0 | K13: =IF(K$4=Assumptions!$J$175,Assumptions!$J$180,0) -> 0 | L13: =IF(L$4=Assumptions!$J$175,Assumptions!$J$180,0) -> 0 | M13: =IF(M$4=Assumptions!$J$175,Assumptions!$J$180,0) -> 0 | N13: =IF(N$4=Assumptions!$J$175,Assumptions!$J$180,0) -> 0 | ... EI13: =IF(EI$4=Assumptions!$J$175,Assumptions!$J$180,0) -> 0 | EM13: x
D14: Retail Proceeds, net | G14: =IF(G$4=Assumptions!$J$175,Assumptions!$J$181,0) -> 0 | H14: =IF(H$4=Assumptions!$J$175,Assumptions!$J$181,0) -> 0 | I14: =IF(I$4=Assumptions!$J$175,Assumptions!$J$181,0) -> 0 | J14: =IF(J$4=Assumptions!$J$175,Assumptions!$J$181,0) -> 0 | K14: =IF(K$4=Assumptions!$J$175,Assumptions!$J$181,0) -> 0 | L14: =IF(L$4=Assumptions!$J$175,Assumptions!$J$181,0) -> 0 | M14: =IF(M$4=Assumptions!$J$175,Assumptions!$J$181,0) -> 0 | N14: =IF(N$4=Assumptions!$J$175,Assumptions!$J$181,0) -> 0 | ... EI14: =IF(EI$4=Assumptions!$J$175,Assumptions!$J$181,0) -> 0 | EM14: x
EM15: x
D16: Multifamily Sale | G16: =IF(G4=Assumptions!$E$175,Assumptions!$E$178,0) -> 0 | H16: =IF(H4=Assumptions!$E$175,Assumptions!$E$178,0) -> 0 | I16: =IF(I4=Assumptions!$E$175,Assumptions!$E$178,0) -> 0 | J16: =IF(J4=Assumptions!$E$175,Assumptions!$E$178,0) -> 0 | K16: =IF(K4=Assumptions!$E$175,Assumptions!$E$178,0) -> 0 | L16: =IF(L4=Assumptions!$E$175,Assumptions!$E$178,0) -> 0 | M16: =IF(M4=Assumptions!$E$175,Assumptions!$E$178,0) -> 0 | N16: =IF(N4=Assumptions!$E$175,Assumptions!$E$178,0) -> 0 | ... EI16: =IF(EI4=Assumptions!$E$175,Assumptions!$E$178,0) -> 0 | EM16: x
D17: Less: Selling Costs | G17: =IF(G4=Assumptions!$E$175,Assumptions!$E$180,0) -> 0 | H17: =IF(H4=Assumptions!$E$175,Assumptions!$E$180,0) -> 0 | I17: =IF(I4=Assumptions!$E$175,Assumptions!$E$180,0) -> 0 | J17: =IF(J4=Assumptions!$E$175,Assumptions!$E$180,0) -> 0 | K17: =IF(K4=Assumptions!$E$175,Assumptions!$E$180,0) -> 0 | L17: =IF(L4=Assumptions!$E$175,Assumptions!$E$180,0) -> 0 | M17: =IF(M4=Assumptions!$E$175,Assumptions!$E$180,0) -> 0 | N17: =IF(N4=Assumptions!$E$175,Assumptions!$E$180,0) -> 0 | ... EI17: =IF(EI4=Assumptions!$E$175,Assumptions!$E$180,0) -> 0 | EM17: x
D18: Multifamily Proceeds, net | G18: =IF(G4=Assumptions!$E$175,Assumptions!$E$181,0) -> 0 | H18: =IF(H4=Assumptions!$E$175,Assumptions!$E$181,0) -> 0 | I18: =IF(I4=Assumptions!$E$175,Assumptions!$E$181,0) -> 0 | J18: =IF(J4=Assumptions!$E$175,Assumptions!$E$181,0) -> 0 | K18: =IF(K4=Assumptions!$E$175,Assumptions!$E$181,0) -> 0 | L18: =IF(L4=Assumptions!$E$175,Assumptions!$E$181,0) -> 0 | M18: =IF(M4=Assumptions!$E$175,Assumptions!$E$181,0) -> 0 | N18: =IF(N4=Assumptions!$E$175,Assumptions!$E$181,0) -> 0 | ... EI18: =IF(EI4=Assumptions!$E$175,Assumptions!$E$181,0) -> 0 | EM18: x
EM19: x
D20: Retail Income | G20: {=IFERROR(INDEX('NOI Walk'!$E$58:$EF$58,,MATCH(Model!G$4,'NOI Walk'!$E$15:$EF$15,0)),0)} -> 0 | H20: {=IFERROR(INDEX('NOI Walk'!$E$58:$EF$58,,MATCH(Model!H$4,'NOI Walk'!$E$15:$EF$15,0)),0)} -> 0 | I20: {=IFERROR(INDEX('NOI Walk'!$E$58:$EF$58,,MATCH(Model!I$4,'NOI Walk'!$E$15:$EF$15,0)),0)} -> 0 | J20: {=IFERROR(INDEX('NOI Walk'!$E$58:$EF$58,,MATCH(Model!J$4,'NOI Walk'!$E$15:$EF$15,0)),0)} -> 0 | K20: {=IFERROR(INDEX('NOI Walk'!$E$58:$EF$58,,MATCH(Model!K$4,'NOI Walk'!$E$15:$EF$15,0)),0)} -> 0 | L20: {=IFERROR(INDEX('NOI Walk'!$E$58:$EF$58,,MATCH(Model!L$4,'NOI Walk'!$E$15:$EF$15,0)),0)} -> 0 | M20: {=IFERROR(INDEX('NOI Walk'!$E$58:$EF$58,,MATCH(Model!M$4,'NOI Walk'!$E$15:$EF$15,0)),0)} -> 0 | N20: {=IFERROR(INDEX('NOI Walk'!$E$58:$EF$58,,MATCH(Model!N$4,'NOI Walk'!$E$15:$EF$15,0)),0)} -> 0 | ... EI20: {=IFERROR(INDEX('NOI Walk'!$E$58:$EF$58,,MATCH(Model!EI$4,'NOI Walk'!$E$15:$EF$15,0)),0)} -> 0 | EM20: x
D21: Less: Leasing Cost Reserves | G21: {=-IFERROR(INDEX('NOI Walk'!$E$62:$EF$62,,MATCH(Model!G$4,'NOI Walk'!$E$15:$EF$15,0)),0)} -> 0 | H21: {=-IFERROR(INDEX('NOI Walk'!$E$62:$EF$62,,MATCH(Model!H$4,'NOI Walk'!$E$15:$EF$15,0)),0)} -> 0 | I21: {=-IFERROR(INDEX('NOI Walk'!$E$62:$EF$62,,MATCH(Model!I$4,'NOI Walk'!$E$15:$EF$15,0)),0)} -> 0 | J21: {=-IFERROR(INDEX('NOI Walk'!$E$62:$EF$62,,MATCH(Model!J$4,'NOI Walk'!$E$15:$EF$15,0)),0)} -> 0 | K21: {=-IFERROR(INDEX('NOI Walk'!$E$62:$EF$62,,MATCH(Model!K$4,'NOI Walk'!$E$15:$EF$15,0)),0)} -> 0 | L21: {=-IFERROR(INDEX('NOI Walk'!$E$62:$EF$62,,MATCH(Model!L$4,'NOI Walk'!$E$15:$EF$15,0)),0)} -> 0 | M21: {=-IFERROR(INDEX('NOI Walk'!$E$62:$EF$62,,MATCH(Model!M$4,'NOI Walk'!$E$15:$EF$15,0)),0)} -> 0 | N21: {=-IFERROR(INDEX('NOI Walk'!$E$62:$EF$62,,MATCH(Model!N$4,'NOI Walk'!$E$15:$EF$15,0)),0)} -> 0 | ... EI21: {=-IFERROR(INDEX('NOI Walk'!$E$62:$EF$62,,MATCH(Model!EI$4,'NOI Walk'!$E$15:$EF$15,0)),0)} -> 0 | EM21: x
D22: Retail Cash Flow | G22: =SUM(G20:G21) -> 0 | H22: =SUM(H20:H21) -> 0 | I22: =SUM(I20:I21) -> 0 | J22: =SUM(J20:J21) -> 0 | K22: =SUM(K20:K21) -> 0 | L22: =SUM(L20:L21) -> 0 | M22: =SUM(M20:M21) -> 0 | N22: =SUM(N20:N21) -> 0 | ... EI22: =SUM(EI20:EI21) -> 0 | EM22: x
EM23: x
D24: Multifamily NOI | G24: {=IFERROR(INDEX('NOI Walk'!$E$51:$EF$51,,MATCH(Model!G$4,'NOI Walk'!$E$15:$EF$15,0)),0)} -> 0 | H24: {=IFERROR(INDEX('NOI Walk'!$E$51:$EF$51,,MATCH(Model!H$4,'NOI Walk'!$E$15:$EF$15,0)),0)} -> 70898.852 | I24: {=IFERROR(INDEX('NOI Walk'!$E$51:$EF$51,,MATCH(Model!I$4,'NOI Walk'!$E$15:$EF$15,0)),0)} -> 66624.242 | J24: {=IFERROR(INDEX('NOI Walk'!$E$51:$EF$51,,MATCH(Model!J$4,'NOI Walk'!$E$15:$EF$15,0)),0)} -> 66780.797 | K24: {=IFERROR(INDEX('NOI Walk'!$E$51:$EF$51,,MATCH(Model!K$4,'NOI Walk'!$E$15:$EF$15,0)),0)} -> 64365.759 | L24: {=IFERROR(INDEX('NOI Walk'!$E$51:$EF$51,,MATCH(Model!L$4,'NOI Walk'!$E$15:$EF$15,0)),0)} -> 60566.879 | M24: {=IFERROR(INDEX('NOI Walk'!$E$51:$EF$51,,MATCH(Model!M$4,'NOI Walk'!$E$15:$EF$15,0)),0)} -> 64755.397 | N24: {=IFERROR(INDEX('NOI Walk'!$E$51:$EF$51,,MATCH(Model!N$4,'NOI Walk'!$E$15:$EF$15,0)),0)} -> 60694.106 | ... EI24: {=IFERROR(INDEX('NOI Walk'!$E$51:$EF$51,,MATCH(Model!EI$4,'NOI Walk'!$E$15:$EF$15,0)),0)} -> 155913.05 | EM24: x
D25: Less: CapEx | G25: {=-IFERROR(INDEX('NOI Walk'!$E$56:$EF$56,,MATCH(Model!G$4,'NOI Walk'!$E$15:$EF$15,0)),0)} -> 0 | H25: {=-IFERROR(INDEX('NOI Walk'!$E$56:$EF$56,,MATCH(Model!H$4,'NOI Walk'!$E$15:$EF$15,0)),0)} -> -1253.3007 | I25: {=-IFERROR(INDEX('NOI Walk'!$E$56:$EF$56,,MATCH(Model!I$4,'NOI Walk'!$E$15:$EF$15,0)),0)} -> -1207.2563 | J25: {=-IFERROR(INDEX('NOI Walk'!$E$56:$EF$56,,MATCH(Model!J$4,'NOI Walk'!$E$15:$EF$15,0)),0)} -> -1209.7376 | K25: {=-IFERROR(INDEX('NOI Walk'!$E$56:$EF$56,,MATCH(Model!K$4,'NOI Walk'!$E$15:$EF$15,0)),0)} -> -1183.8049 | L25: {=-IFERROR(INDEX('NOI Walk'!$E$56:$EF$56,,MATCH(Model!L$4,'NOI Walk'!$E$15:$EF$15,0)),0)} -> -1142.6472 | M25: {=-IFERROR(INDEX('NOI Walk'!$E$56:$EF$56,,MATCH(Model!M$4,'NOI Walk'!$E$15:$EF$15,0)),0)} -> -1187.6468 | N25: {=-IFERROR(INDEX('NOI Walk'!$E$56:$EF$56,,MATCH(Model!N$4,'NOI Walk'!$E$15:$EF$15,0)),0)} -> -1143.774 | ... EI25: {=-IFERROR(INDEX('NOI Walk'!$E$56:$EF$56,,MATCH(Model!EI$4,'NOI Walk'!$E$15:$EF$15,0)),0)} -> -2257.0803 | EM25: x
D26: Multifamily Cash Flow | G26: =SUM(G24:G25) -> 0 | H26: =SUM(H24:H25) -> 69645.551 | I26: =SUM(I24:I25) -> 65416.985 | J26: =SUM(J24:J25) -> 65571.059 | K26: =SUM(K24:K25) -> 63181.954 | L26: =SUM(L24:L25) -> 59424.232 | M26: =SUM(M24:M25) -> 63567.75 | N26: =SUM(N24:N25) -> 59550.332 | ... EI26: =SUM(EI24:EI25) -> 153655.97 | EM26: x
EM27: x
D28: Total Unlevered Cash Flow | G28: =IF(G4>Assumptions!$E$175,0,SUM(G26,G22,G10,G18,G14)) -> -15770556 | H28: =IF(H4>Assumptions!$E$175,0,SUM(H26,H22,H10,H18,H14)) -> 62633.373 | I28: =IF(I4>Assumptions!$E$175,0,SUM(I26,I22,I10,I18,I14)) -> 42187.415 | J28: =IF(J4>Assumptions!$E$175,0,SUM(J26,J22,J10,J18,J14)) -> 42341.489 | K28: =IF(K4>Assumptions!$E$175,0,SUM(K26,K22,K10,K18,K14)) -> 39952.384 | L28: =IF(L4>Assumptions!$E$175,0,SUM(L26,L22,L10,L18,L14)) -> -25055.338 | M28: =IF(M4>Assumptions!$E$175,0,SUM(M26,M22,M10,M18,M14)) -> 9088.1802 | N28: =IF(N4>Assumptions!$E$175,0,SUM(N26,N22,N10,N18,N14)) -> 36320.762 | ... EI28: =IF(EI4>Assumptions!$E$175,0,SUM(EI26,EI22,EI10,EI18,EI14)) -> 0 | EM28: x
D29: Equity In | F29: =SUM(G29:EI29) -> -16563813 | G29: =+MIN(G10,0) -> -15770556 | H29: =+MIN(H10,0) -> -7012.1788 | I29: =+MIN(I10,0) -> -23229.57 | J29: =+MIN(J10,0) -> -23229.57 | K29: =+MIN(K10,0) -> -23229.57 | L29: =+MIN(L10,0) -> -84479.57 | M29: =+MIN(M10,0) -> -54479.57 | N29: =+MIN(N10,0) -> -23229.57 | ... EI29: =+MIN(EI10,0) -> 0 | EM29: x
D30: Profit | F30: =+SUM(G28:OFFSET(G28,,Assumptions!$E$175)) -> 16066038 | EM30: x
D31: Unlevered IRR | F31: =XIRR(G28:EI28,$G$2:$EI$2) -> 0.16472445 | EM31: x
D32: Unlevered MOIC | F32: =-(F30-G29)/G29 -> 2.0187363 | EM32: x
EM33: x
D34: Financable Costs | G34: =-G5-G9 -> -14970000 | H34: =-H5-H9 -> 0 | I34: =-I5-I9 -> -16217.391 | J34: =-J5-J9 -> -16217.391 | K34: =-K5-K9 -> -16217.391 | L34: =-L5-L9 -> -77467.391 | M34: =-M5-M9 -> -47467.391 | N34: =-N5-N9 -> -16217.391 | ... S34: =-S5-S9 -> -15217.391 | T34: =+T29 -> -22229.57 | U34: =+U29 -> -22229.57 | V34: =+V29 -> -22229.57 | W34: =+W29 -> -22229.57 | X34: =+X29 -> -22229.57 | Y34: =+Y29 -> -22229.57 | Z34: =+Z29 -> -22229.57 | AA34: =+AA29 -> -22229.57 | ... EI34: =+EI29 -> 0 | EM34: x
D35: Remaining Costs | G35: =+G29-G34 -> -800556.28 | H35: =+H29-H34 -> -7012.1788 | I35: =+I29-I34 -> -7012.1788 | J35: =+J29-J34 -> -7012.1788 | K35: =+K29-K34 -> -7012.1788 | L35: =+L29-L34 -> -7012.1788 | M35: =+M29-M34 -> -7012.1788 | N35: =+N29-N34 -> -7012.1788 | ... EI35: =+EI29-EI34 -> 0 | EM35: x
D36: Cash Available for DSCR Loan Paydown | G36: =+G54 -> 0 | H36: =+H54 -> 0 | I36: =+I54 -> 0 | J36: =+J54 -> 0 | K36: =+K54 -> 0 | L36: =+L54 -> 0 | M36: =+M54 -> 0 | N36: =+N54 -> 0 | ... BN36: =+BN54 -> 0 | BO36: =IF(AND(Assumptions!$G$34="No",Model!BO4=Assumptions!$E$175),BO28,BO54) -> 0 | BP36: =+BP54 -> 0 | BQ36: =+BQ54 -> 0 | BR36: =+BR54 -> 0 | BS36: =+BS54 -> 0 | BT36: =+BT54 -> 0 | BU36: =+BU54 -> 0 | BV36: =+BV54 -> 0 | BW36: =+BW54 -> 0 | ... EI36: =+EI54 -> 0 | EM36: x
EM37: x
B38: =+Assumptions!G31 -> 9870490.4 | D38: Bridge Loan | EM38: x
D39: Beginning Balance | H39: =+G43 -> 10430000 | I39: =+H43 -> 9862749.8 | J39: =+I43 -> 9862701.4 | K39: =+J43 -> 9862652.7 | L39: =+K43 -> 9862603.8 | M39: =+L43 -> 9862554.5 | N39: =+M43 -> 9862504.9 | O39: =+N43 -> 9862455 | ... EI39: =+EH43 -> 0 | EM39: x
D40: Draw | G40: =IF(G4=Assumptions!$G$23,Assumptions!$R$30,MIN(G5*Assumptions!$G$29+G9*Assumptions!$G$30,Assumptions!$G$31-G39)) -> 10430000 | H40: =IF(H4=Assumptions!$G$23,Assumptions!$R$30,MIN(H5*Assumptions!$G$29+H9*Assumptions!$G$30,Assumptions!$G$31-H39)) -> -559509.63 | I40: =IF(I4=Assumptions!$G$23,Assumptions!$R$30,MIN(I5*Assumptions!$G$29+I9*Assumptions!$G$30,Assumptions!$G$31-I39)) -> 7740.5732 | J40: =IF(J4=Assumptions!$G$23,Assumptions!$R$30,MIN(J5*Assumptions!$G$29+J9*Assumptions!$G$30,Assumptions!$G$31-J39)) -> 7788.9518 | K40: =IF(K4=Assumptions!$G$23,Assumptions!$R$30,MIN(K5*Assumptions!$G$29+K9*Assumptions!$G$30,Assumptions!$G$31-K39)) -> 7837.6328 | L40: =IF(L4=Assumptions!$G$23,Assumptions!$R$30,MIN(L5*Assumptions!$G$29+L9*Assumptions!$G$30,Assumptions!$G$31-L39)) -> 7886.618 | M40: =IF(M4=Assumptions!$G$23,Assumptions!$R$30,MIN(M5*Assumptions!$G$29+M9*Assumptions!$G$30,Assumptions!$G$31-M39)) -> 7935.9093 | N40: =IF(N4=Assumptions!$G$23,Assumptions!$R$30,MIN(N5*Assumptions!$G$29+N9*Assumptions!$G$30,Assumptions!$G$31-N39)) -> 7985.5088 | ... EI40: =IF(EI4=Assumptions!$G$23,Assumptions!$R$30,MIN(EI5*Assumptions!$G$29+EI9*Assumptions!$G$30,Assumptions!$G$31-EI39)) -> 0 | EM40: x
D41: Principal Paydown | G41: =+IFERROR(INDEX('Debt Schedule'!$F$12:$F$108,MATCH(Model!G4,'Debt Schedule'!$B$12:$B$108,0)),0) -> 0 | H41: =+IFERROR(INDEX('Debt Schedule'!$F$12:$F$108,MATCH(Model!H4,'Debt Schedule'!$B$12:$B$108,0)),0) -> -7740.5732 | I41: =+IFERROR(INDEX('Debt Schedule'!$F$12:$F$108,MATCH(Model!I4,'Debt Schedule'!$B$12:$B$108,0)),0) -> -7788.9518 | J41: =+IFERROR(INDEX('Debt Schedule'!$F$12:$F$108,MATCH(Model!J4,'Debt Schedule'!$B$12:$B$108,0)),0) -> -7837.6328 | K41: =+IFERROR(INDEX('Debt Schedule'!$F$12:$F$108,MATCH(Model!K4,'Debt Schedule'!$B$12:$B$108,0)),0) -> -7886.618 | L41: =+IFERROR(INDEX('Debt Schedule'!$F$12:$F$108,MATCH(Model!L4,'Debt Schedule'!$B$12:$B$108,0)),0) -> -7935.9093 | M41: =+IFERROR(INDEX('Debt Schedule'!$F$12:$F$108,MATCH(Model!M4,'Debt Schedule'!$B$12:$B$108,0)),0) -> -7985.5088 | N41: =+IFERROR(INDEX('Debt Schedule'!$F$12:$F$108,MATCH(Model!N4,'Debt Schedule'!$B$12:$B$108,0)),0) -> -8035.4182 | ... EI41: =+IFERROR(INDEX('Debt Schedule'!$F$12:$F$108,MATCH(Model!EI4,'Debt Schedule'!$B$12:$B$108,0)),0) -> 0
D42: Paydown | G42: =-MIN(G36,SUM(G39:G41)) -> 0 | H42: =-MIN(H36,SUM(H39:H41)) -> 0 | I42: =-MIN(I36,SUM(I39:I41)) -> 0 | J42: =-MIN(J36,SUM(J39:J41)) -> 0 | K42: =-MIN(K36,SUM(K39:K41)) -> 0 | L42: =-MIN(L36,SUM(L39:L41)) -> 0 | M42: =-MIN(M36,SUM(M39:M41)) -> 0 | N42: =-MIN(N36,SUM(N39:N41)) -> 0 | ... EI42: =-MIN(EI36,SUM(EI39:EI41)) -> 0 | EM42: x
D43: Ending Balance | G43: =SUM(G39:G42) -> 10430000 | H43: =SUM(H39:H42) -> 9862749.8 | I43: =SUM(I39:I42) -> 9862701.4 | J43: =SUM(J39:J42) -> 9862652.7 | K43: =SUM(K39:K42) -> 9862603.8 | L43: =SUM(L39:L42) -> 9862554.5 | M43: =SUM(M39:M42) -> 9862504.9 | N43: =SUM(N39:N42) -> 9862455 | ... EI43: =SUM(EI39:EI42) -> 0 | EM43: x
EM44: x
B45: =SUMIF(G65:EI65,"<0",G65:EI65) -> -6344243.8 | D45: Costs to Equity, Before Interest | G45: =SUM(G34:G36,G40:G42) -> -5340556.3 | H45: =SUM(H34:H36,H40:H42) -> -574262.38 | I45: =SUM(I34:I36,I40:I42) -> -23277.949 | J45: =SUM(J34:J36,J40:J42) -> -23278.251 | K45: =SUM(K34:K36,K40:K42) -> -23278.555 | L45: =SUM(L34:L36,L40:L42) -> -84528.862 | M45: =SUM(M34:M36,M40:M42) -> -54529.17 | N45: =SUM(N34:N36,N40:N42) -> -23279.48 | ... EI45: =SUM(EI34:EI36,EI40:EI42) -> 0 | EM45: x
EM46: x
D47: Plus: DSCR Loan Interest Expense | G47: =-G76 -> 0 | H47: =-H76 -> 65187.5 | I47: =-I76 -> 65139.121 | J47: =-J76 -> 65090.44 | K47: =-K76 -> 65041.455 | L47: =-L76 -> 64992.164 | M47: =-M76 -> 64942.564 | N47: =-N76 -> 64892.655 | ... EI47: =-EI76 -> 0 | EM47: x
D48: Less: Income Offset | G48: =-IF(Assumptions!$G$34="Yes",MIN(G26+G41+G42+G54,G47),MAX(0,MIN(G28+G41+G42,G47))) -> 0 | H48: =-IF(Assumptions!$G$34="Yes",MIN(H26+H41+H42+H54,H47),MAX(0,MIN(H28+H41+H42,H47))) -> -61904.978 | I48: =-IF(Assumptions!$G$34="Yes",MIN(I26+I41+I42+I54,I47),MAX(0,MIN(I28+I41+I42,I47))) -> -57628.034 | J48: =-IF(Assumptions!$G$34="Yes",MIN(J26+J41+J42+J54,J47),MAX(0,MIN(J28+J41+J42,J47))) -> -57733.427 | K48: =-IF(Assumptions!$G$34="Yes",MIN(K26+K41+K42+K54,K47),MAX(0,MIN(K28+K41+K42,K47))) -> -55295.336 | L48: =-IF(Assumptions!$G$34="Yes",MIN(L26+L41+L42+L54,L47),MAX(0,MIN(L28+L41+L42,L47))) -> -51488.322 | M48: =-IF(Assumptions!$G$34="Yes",MIN(M26+M41+M42+M54,M47),MAX(0,MIN(M28+M41+M42,M47))) -> -55582.242 | N48: =-IF(Assumptions!$G$34="Yes",MIN(N26+N41+N42+N54,N47),MAX(0,MIN(N28+N41+N42,N47))) -> -51514.913 | ... EI48: =-IF(Assumptions!$G$34="Yes",MIN(EI26+EI41+EI42+EI54,EI47),MAX(0,MIN(EI28+EI41+EI42,EI47))) -> 0 | EM48: x
B49: =MIN(SUM(G49:EI49),-Assumptions!R35) -> -101086.93 | D49: Interest Expense, net | G49: =-SUM(G47:G48) -> 0 | H49: =-SUM(H47:H48) -> -3282.5218 | I49: =-SUM(I47:I48) -> -7511.0879 | J49: =-SUM(J47:J48) -> -7357.0138 | K49: =-SUM(K47:K48) -> -9746.1191 | L49: =-SUM(L47:L48) -> -13503.842 | M49: =-SUM(M47:M48) -> -9360.3229 | N49: =-SUM(N47:N48) -> -13377.742 | ... EI49: =-SUM(EI47:EI48) -> 0 | EM49: x
EM50: x
B51: =-SUM(Assumptions!F5:F6) -> -6794409.5 | D51: Equity Draws | G51: =MAX(MIN(-G45+G41-G49,-$B$51-F52),0) -> 5340556.3 | H51: =MAX(MIN(-H45+H41-H49,-$B$51-G52),0) -> 569804.33 | I51: =MAX(MIN(-I45+I41-I49,-$B$51-H52),0) -> 23000.085 | J51: =MAX(MIN(-J45+J41-J49,-$B$51-I52),0) -> 22797.632 | K51: =MAX(MIN(-K45+K41-K49,-$B$51-J52),0) -> 25138.056 | L51: =MAX(MIN(-L45+L41-L49,-$B$51-K52),0) -> 90096.794 | M51: =MAX(MIN(-M45+M41-M49,-$B$51-L52),0) -> 55903.984 | N51: =MAX(MIN(-N45+N41-N49,-$B$51-M52),0) -> 28621.803 | ... EI51: =MAX(MIN(-EI45+EI41-EI49,-$B$51-EH52),0) -> 0 | EM51: x
D52: Cumulative Equity Drawn | G52: =+G51+F52 -> 5340556.3 | H52: =+H51+G52 -> 5910360.6 | I52: =+I51+H52 -> 5933360.7 | J52: =+J51+I52 -> 5956158.3 | K52: =+K51+J52 -> 5981296.4 | L52: =+L51+K52 -> 6071393.2 | M52: =+M51+L52 -> 6127297.2 | N52: =+N51+M52 -> 6155919 | ... EI52: =+EI51+EH52 -> 6603583.9 | EM52: x
EM53: x
D54: Perm Loan Draw | G54: =IF(AND(G4=Assumptions!$G$36,Assumptions!$G$34="Yes"),Assumptions!$L$40,0) -> 0 | H54: =IF(AND(H4=Assumptions!$G$36,Assumptions!$G$34="Yes"),Assumptions!$L$40,0) -> 0 | I54: =IF(AND(I4=Assumptions!$G$36,Assumptions!$G$34="Yes"),Assumptions!$L$40,0) -> 0 | J54: =IF(AND(J4=Assumptions!$G$36,Assumptions!$G$34="Yes"),Assumptions!$L$40,0) -> 0 | K54: =IF(AND(K4=Assumptions!$G$36,Assumptions!$G$34="Yes"),Assumptions!$L$40,0) -> 0 | L54: =IF(AND(L4=Assumptions!$G$36,Assumptions!$G$34="Yes"),Assumptions!$L$40,0) -> 0 | M54: =IF(AND(M4=Assumptions!$G$36,Assumptions!$G$34="Yes"),Assumptions!$L$40,0) -> 0 | N54: =IF(AND(N4=Assumptions!$G$36,Assumptions!$G$34="Yes"),Assumptions!$L$40,0) -> 0 | ... EI54: =IF(AND(EI4=Assumptions!$G$36,Assumptions!$G$34="Yes"),Assumptions!$L$40,0) -> 0 | EM54: x
D55: Cash Flow Before Perm Loan Interest | G55: =+G28-G47+G51+SUM(G40:G42) -> 0 | H55: =+H28-H47+H51+SUM(H40:H42) -> 0 | I55: =+I28-I47+I51+SUM(I40:I42) -> 9.094947e-13 | J55: =+J28-J47+J51+SUM(J40:J42) -> -9.094947e-13 | K55: =+K28-K47+K51+SUM(K40:K42) -> 1.8189894e-12 | L55: =+L28-L47+L51+SUM(L40:L42) -> 1.0913936e-11 | M55: =+M28-M47+M51+SUM(M40:M42) -> -9.094947e-13 | N55: =+N28-N47+N51+SUM(N40:N42) -> 1.8189894e-12 | ... EI55: =+EI28-EI47+EI51+SUM(EI40:EI42) -> 0 | EM55: x
EM56: x
D57: Permanent Loan | EM57: x
D58: Beginning Balance | G58: =+F63 -> 0 | H58: =+G63 -> 0 | I58: =+H63 -> 0 | J58: =+I63 -> 0 | K58: =+J63 -> 0 | L58: =+K63 -> 0 | M58: =+L63 -> 0 | N58: =+M63 -> 0 | ... EI58: =+EH63 -> 0 | EM58: x
D59: Draw | G59: =IF(AND(Assumptions!$G$34="Yes",Model!G4=Assumptions!$G$36),Assumptions!$L$37,0) -> 0 | H59: =IF(AND(Assumptions!$G$34="Yes",Model!H4=Assumptions!$G$36),Assumptions!$L$37,0) -> 0 | I59: =IF(AND(Assumptions!$G$34="Yes",Model!I4=Assumptions!$G$36),Assumptions!$L$37,0) -> 0 | J59: =IF(AND(Assumptions!$G$34="Yes",Model!J4=Assumptions!$G$36),Assumptions!$L$37,0) -> 0 | K59: =IF(AND(Assumptions!$G$34="Yes",Model!K4=Assumptions!$G$36),Assumptions!$L$37,0) -> 0 | L59: =IF(AND(Assumptions!$G$34="Yes",Model!L4=Assumptions!$G$36),Assumptions!$L$37,0) -> 0 | M59: =IF(AND(Assumptions!$G$34="Yes",Model!M4=Assumptions!$G$36),Assumptions!$L$37,0) -> 0 | N59: =IF(AND(Assumptions!$G$34="Yes",Model!N4=Assumptions!$G$36),Assumptions!$L$37,0) -> 0 | ... EI59: =IF(AND(Assumptions!$G$34="Yes",Model!EI4=Assumptions!$G$36),Assumptions!$L$37,0) -> 0 | EM59: x
D60: Principal Paydown | G60: =+IFERROR(INDEX('Debt Schedule'!$P$12:$P$108,MATCH(Model!G4,'Debt Schedule'!$M$12:$M$108,0)),0) -> 0 | H60: =+IFERROR(INDEX('Debt Schedule'!$P$12:$P$108,MATCH(Model!H4,'Debt Schedule'!$M$12:$M$108,0)),0) -> 0 | I60: =+IFERROR(INDEX('Debt Schedule'!$P$12:$P$108,MATCH(Model!I4,'Debt Schedule'!$M$12:$M$108,0)),0) -> 0 | J60: =+IFERROR(INDEX('Debt Schedule'!$P$12:$P$108,MATCH(Model!J4,'Debt Schedule'!$M$12:$M$108,0)),0) -> 0 | K60: =+IFERROR(INDEX('Debt Schedule'!$P$12:$P$108,MATCH(Model!K4,'Debt Schedule'!$M$12:$M$108,0)),0) -> 0 | L60: =+IFERROR(INDEX('Debt Schedule'!$P$12:$P$108,MATCH(Model!L4,'Debt Schedule'!$M$12:$M$108,0)),0) -> 0 | M60: =+IFERROR(INDEX('Debt Schedule'!$P$12:$P$108,MATCH(Model!M4,'Debt Schedule'!$M$12:$M$108,0)),0) -> 0 | N60: =+IFERROR(INDEX('Debt Schedule'!$P$12:$P$108,MATCH(Model!N4,'Debt Schedule'!$M$12:$M$108,0)),0) -> 0 | ... EI60: =+IFERROR(INDEX('Debt Schedule'!$P$12:$P$108,MATCH(Model!EI4,'Debt Schedule'!$M$12:$M$108,0)),0) -> 0 | EM60: x
D61: Paydown | G61: =IF(G4=Assumptions!$E$175,-MIN(G55,G58+G60),0) -> 0 | H61: =IF(H4=Assumptions!$E$175,-MIN(H55,H58+H60),0) -> 0 | I61: =IF(I4=Assumptions!$E$175,-MIN(I55,I58+I60),0) -> 0 | J61: =IF(J4=Assumptions!$E$175,-MIN(J55,J58+J60),0) -> 0 | K61: =IF(K4=Assumptions!$E$175,-MIN(K55,K58+K60),0) -> 0 | L61: =IF(L4=Assumptions!$E$175,-MIN(L55,L58+L60),0) -> 0 | M61: =IF(M4=Assumptions!$E$175,-MIN(M55,M58+M60),0) -> 0 | N61: =IF(N4=Assumptions!$E$175,-MIN(N55,N58+N60),0) -> 0 | ... EI61: =IF(EI4=Assumptions!$E$175,-MIN(EI55,EI58+EI60),0) -> 0 | EM61: x
D62: Interest Expense | G62: =+G80 -> 0 | H62: =+H80 -> 0 | I62: =+I80 -> 0 | J62: =+J80 -> 0 | K62: =+K80 -> 0 | L62: =+L80 -> 0 | M62: =+M80 -> 0 | N62: =+N80 -> 0 | ... EI62: =+EI80 -> 0 | EM62: x
D63: Ending Balance | G63: =SUM(G58:G61) -> 0 | H63: =SUM(H58:H61) -> 0 | I63: =SUM(I58:I61) -> 0 | J63: =SUM(J58:J61) -> 0 | K63: =SUM(K58:K61) -> 0 | L63: =SUM(L58:L61) -> 0 | M63: =SUM(M58:M61) -> 0 | N63: =SUM(N58:N61) -> 0 | ... EI63: =SUM(EI58:EI61) -> 0 | EM63: x
B65: =-SUMIFS(G65:EI65,G65:EI65,"<0") -> 6344243.8 | D65: Total Levered Project Cash Flows | G65: =SUM(-G51,G54:G55,-G62,G60:G61) -> -5340556.3 | H65: =SUM(-H51,H54:H55,-H62,H60:H61) -> -569804.33 | I65: =SUM(-I51,I54:I55,-I62,I60:I61) -> -23000.085 | J65: =SUM(-J51,J54:J55,-J62,J60:J61) -> -22797.632 | K65: =SUM(-K51,K54:K55,-K62,K60:K61) -> -25138.056 | L65: =SUM(-L51,L54:L55,-L62,L60:L61) -> -90096.794 | M65: =SUM(-M51,M54:M55,-M62,M60:M61) -> -55903.984 | N65: =SUM(-N51,N54:N55,-N62,N60:N61) -> -28621.803 | ... EI65: =SUM(-EI51,EI54:EI55,-EI62,EI60:EI61) -> 0 | EM65: x
B66: =+G66 -> -6794409.5 | D66: Equity In | G66: =SUM(B51:B51) -> -6794409.5 | EM66: x
B67: =+G67 -> 11183197 | D67: Profit | G67: =SUMIF(G65:EI65,">0",G65:EI65)+G66 -> 11183197 | EM67: x
D68: Levered IRR | G68: =XIRR(G65:EI65,$G$2:$EI$2) -> 0.30392409 | EM68: x
D69: Levered MOIC | G69: =-(G67-G66)/G66 -> 2.645941 | EM69: x
EM70: x
EM71: x
D72: 1-Month SOFR | G72: =IFERROR(INDEX('1-month Term SOFR'!$Q$12:$Q$132,MATCH(Model!G$2,'1-month Term SOFR'!$O$12:$O$132,0)),F72) -> 0.0412577 | H72: =IFERROR(INDEX('1-month Term SOFR'!$Q$12:$Q$132,MATCH(Model!H$2,'1-month Term SOFR'!$O$12:$O$132,0)),G72) -> 0.0403625 | I72: =IFERROR(INDEX('1-month Term SOFR'!$Q$12:$Q$132,MATCH(Model!I$2,'1-month Term SOFR'!$O$12:$O$132,0)),H72) -> 0.0395926 | J72: =IFERROR(INDEX('1-month Term SOFR'!$Q$12:$Q$132,MATCH(Model!J$2,'1-month Term SOFR'!$O$12:$O$132,0)),I72) -> 0.0381025 | K72: =IFERROR(INDEX('1-month Term SOFR'!$Q$12:$Q$132,MATCH(Model!K$2,'1-month Term SOFR'!$O$12:$O$132,0)),J72) -> 0.0378538 | L72: =IFERROR(INDEX('1-month Term SOFR'!$Q$12:$Q$132,MATCH(Model!L$2,'1-month Term SOFR'!$O$12:$O$132,0)),K72) -> 0.0378518 | M72: =IFERROR(INDEX('1-month Term SOFR'!$Q$12:$Q$132,MATCH(Model!M$2,'1-month Term SOFR'!$O$12:$O$132,0)),L72) -> 0.0367114 | N72: =IFERROR(INDEX('1-month Term SOFR'!$Q$12:$Q$132,MATCH(Model!N$2,'1-month Term SOFR'!$O$12:$O$132,0)),M72) -> 0.0364455 | ... EI72: =IFERROR(INDEX('1-month Term SOFR'!$Q$12:$Q$132,MATCH(Model!EI$2,'1-month Term SOFR'!$O$12:$O$132,0)),EH72) -> 0.0402355 | EM72: x
EM73: x
D74: Bridge Loan Interest Rate | EM74: x
D75: All-in Rate | G75: =Assumptions!$L$29 -> 0.075 | H75: =Assumptions!$L$29 -> 0.075 | I75: =Assumptions!$L$29 -> 0.075 | J75: =Assumptions!$L$29 -> 0.075 | K75: =Assumptions!$L$29 -> 0.075 | L75: =Assumptions!$L$29 -> 0.075 | M75: =Assumptions!$L$29 -> 0.075 | N75: =Assumptions!$L$29 -> 0.075 | ... EI75: =Assumptions!$L$29 -> 0.075 | EM75: x
D76: Interest Due | G76: =-IFERROR(INDEX('Debt Schedule'!$G$12:$G$108,MATCH(Model!G4,'Debt Schedule'!$B$12:$B$108,0)),0) -> 0 | H76: =-IFERROR(INDEX('Debt Schedule'!$G$12:$G$108,MATCH(Model!H4,'Debt Schedule'!$B$12:$B$108,0)),0) -> -65187.5 | I76: =-IFERROR(INDEX('Debt Schedule'!$G$12:$G$108,MATCH(Model!I4,'Debt Schedule'!$B$12:$B$108,0)),0) -> -65139.121 | J76: =-IFERROR(INDEX('Debt Schedule'!$G$12:$G$108,MATCH(Model!J4,'Debt Schedule'!$B$12:$B$108,0)),0) -> -65090.44 | K76: =-IFERROR(INDEX('Debt Schedule'!$G$12:$G$108,MATCH(Model!K4,'Debt Schedule'!$B$12:$B$108,0)),0) -> -65041.455 | L76: =-IFERROR(INDEX('Debt Schedule'!$G$12:$G$108,MATCH(Model!L4,'Debt Schedule'!$B$12:$B$108,0)),0) -> -64992.164 | M76: =-IFERROR(INDEX('Debt Schedule'!$G$12:$G$108,MATCH(Model!M4,'Debt Schedule'!$B$12:$B$108,0)),0) -> -64942.564 | N76: =-IFERROR(INDEX('Debt Schedule'!$G$12:$G$108,MATCH(Model!N4,'Debt Schedule'!$B$12:$B$108,0)),0) -> -64892.655 | ... EI76: =-IFERROR(INDEX('Debt Schedule'!$G$12:$G$108,MATCH(Model!EI4,'Debt Schedule'!$B$12:$B$108,0)),0) -> 0 | EM76: x
EM77: x
D78: Permanent Loan Interest Rate | EM78: x
D79: All-in Rate | G79: =+Assumptions!$G$37 -> 0.0570644 | H79: =+Assumptions!$G$37 -> 0.0570644 | I79: =+Assumptions!$G$37 -> 0.0570644 | J79: =+Assumptions!$G$37 -> 0.0570644 | K79: =+Assumptions!$G$37 -> 0.0570644 | L79: =+Assumptions!$G$37 -> 0.0570644 | M79: =+Assumptions!$G$37 -> 0.0570644 | N79: =+Assumptions!$G$37 -> 0.0570644 | ... EI79: =+Assumptions!$G$37 -> 0.0570644 | EM79: x
D80: Interest Due | G80: =-IFERROR(INDEX('Debt Schedule'!$Q$12:$Q$108,MATCH(Model!G4,'Debt Schedule'!$M$12:$M$108,0)),0) -> 0 | H80: =-IFERROR(INDEX('Debt Schedule'!$Q$12:$Q$108,MATCH(Model!H4,'Debt Schedule'!$M$12:$M$108,0)),0) -> 0 | I80: =-IFERROR(INDEX('Debt Schedule'!$Q$12:$Q$108,MATCH(Model!I4,'Debt Schedule'!$M$12:$M$108,0)),0) -> 0 | J80: =-IFERROR(INDEX('Debt Schedule'!$Q$12:$Q$108,MATCH(Model!J4,'Debt Schedule'!$M$12:$M$108,0)),0) -> 0 | K80: =-IFERROR(INDEX('Debt Schedule'!$Q$12:$Q$108,MATCH(Model!K4,'Debt Schedule'!$M$12:$M$108,0)),0) -> 0 | L80: =-IFERROR(INDEX('Debt Schedule'!$Q$12:$Q$108,MATCH(Model!L4,'Debt Schedule'!$M$12:$M$108,0)),0) -> 0 | M80: =-IFERROR(INDEX('Debt Schedule'!$Q$12:$Q$108,MATCH(Model!M4,'Debt Schedule'!$M$12:$M$108,0)),0) -> 0 | N80: =-IFERROR(INDEX('Debt Schedule'!$Q$12:$Q$108,MATCH(Model!N4,'Debt Schedule'!$M$12:$M$108,0)),0) -> 0 | ... EI80: =-IFERROR(INDEX('Debt Schedule'!$Q$12:$Q$108,MATCH(Model!EI4,'Debt Schedule'!$M$12:$M$108,0)),0) -> 0 | EM80: x
EM81: x
EM82: x
D83: Waterfall | EM83: x
F84: Allocation | H84: Waterfall | J84: LP | K84: GP | L84: Hurdle | EM84: x
D85: GP | F85: =+Assumptions!K3 -> 0.1 | H85: Preferred | J85: =+F86 -> 0.9 | K85: =+F85 -> 0.1 | L85: 0.1 | EM85: x
D86: LP | F86: =+Assumptions!K4 -> 0.9 | H86: Hurdle 1 | J86: =1-K86 -> 0.85 | K86: 0.15 | L86: 0.15 | EM86: x
D87: Total Equity | F87: =SUM(F85:F86) -> 1 | H87: Hurdle 2 | J87: =1-K87 -> 0.8 | K87: 0.2 | L87: 0.2 | EM87: x
H88: Hurdle 3 | J88: =1-K88 -> 0.7 | K88: 0.3 | L88: =+L87 -> 0.2 | EM88: x
EM89: x
EM90: x
D91: LP Net Returns | EM91: x
D92: Distributions | G92: =SUM(-G125,G141,G159,G167)*$F$86 -> 0 | H92: =SUM(-H125,H141,H159,H167)*$F$86 -> 0 | I92: =SUM(-I125,I141,I159,I167)*$F$86 -> 0 | J92: =SUM(-J125,J141,J159,J167)*$F$86 -> 0 | K92: =SUM(-K125,K141,K159,K167)*$F$86 -> 0 | L92: =SUM(-L125,L141,L159,L167)*$F$86 -> 0 | M92: =SUM(-M125,M141,M159,M167)*$F$86 -> 0 | N92: =SUM(-N125,N141,N159,N167)*$F$86 -> 0 | ... EI92: =SUM(-EI125,EI141,EI159,EI167)*$F$86 -> -725.71662 | EM92: x
D93: Contributions | G93: =-SUM(G120)*$F$86 -> -6114968.5 | H93: =-SUM(H120)*$F$86 -> 0 | I93: =-SUM(I120)*$F$86 -> 0 | J93: =-SUM(J120)*$F$86 -> 0 | K93: =-SUM(K120)*$F$86 -> 0 | L93: =-SUM(L120)*$F$86 -> 0 | M93: =-SUM(M120)*$F$86 -> 0 | N93: =-SUM(N120)*$F$86 -> 0 | ... EI93: =-SUM(EI120)*$F$86 -> 0 | EM93: x
D94: Net Cash Flows | G94: =SUM(G92:G93) -> -6114968.5 | H94: =SUM(H92:H93) -> 0 | I94: =SUM(I92:I93) -> 0 | J94: =SUM(J92:J93) -> 0 | K94: =SUM(K92:K93) -> 0 | L94: =SUM(L92:L93) -> 0 | M94: =SUM(M92:M93) -> 0 | N94: =SUM(N92:N93) -> 0 | ... EI94: =SUM(EI92:EI93) -> -725.71662 | EM94: x
D95: IRR | E95: =XIRR(G94:EI94,$G$2:$EI$2) -> 0.22809814 | EM95: x
D96: Equity Multiple | E96: =-SUM(G92:EI92)/SUM(G93:EI93) -> 2.2003834 | EM96: x
EM97: x
D98: GP Net Returns | EM98: x
D99: Distributions | G99: =SUM(G142,G160,G165)+(G92/$F$86*$F$85) -> 0 | H99: =SUM(H142,H160,H165)+(H92/$F$86*$F$85) -> 0 | I99: =SUM(I142,I160,I165)+(I92/$F$86*$F$85) -> 0 | J99: =SUM(J142,J160,J165)+(J92/$F$86*$F$85) -> 0 | K99: =SUM(K142,K160,K165)+(K92/$F$86*$F$85) -> 0 | L99: =SUM(L142,L160,L165)+(L92/$F$86*$F$85) -> 0 | M99: =SUM(M142,M160,M165)+(M92/$F$86*$F$85) -> 0 | N99: =SUM(N142,N160,N165)+(N92/$F$86*$F$85) -> 0 | ... EI99: =SUM(EI142,EI160,EI165)+(EI92/$F$86*$F$85) -> 725.71662 | EM99: x
D100: Contributions | G100: =-G120*$F$85 -> -679440.95 | H100: =-H120*$F$85 -> 0 | I100: =-I120*$F$85 -> 0 | J100: =-J120*$F$85 -> 0 | K100: =-K120*$F$85 -> 0 | L100: =-L120*$F$85 -> 0 | M100: =-M120*$F$85 -> 0 | N100: =-N120*$F$85 -> 0 | ... EI100: =-EI120*$F$85 -> 0 | EM100: x
D101: Net Cash Flows | G101: =SUM(G99:G100) -> -679440.95 | H101: =SUM(H99:H100) -> 0 | I101: =SUM(I99:I100) -> 0 | J101: =SUM(J99:J100) -> 0 | K101: =SUM(K99:K100) -> 0 | L101: =SUM(L99:L100) -> 0 | M101: =SUM(M99:M100) -> 0 | N101: =SUM(N99:N100) -> 0 | ... EI101: =SUM(EI99:EI100) -> 725.71662 | EM101: x
...

Sheet Assumptions
A1: 123 Main St. New York, NY
B2: Model Start | F2: 45838 | I2: Ownership Splits | N2: Offer | O2: Price | P2: Terms
I3: Sponsor Equity | K3: 0.1 | L3: =+F5 -> 679440.95 | N3: Ask | O3: 15000000
B4: Sources | F4: $ | G4: % | I4: LP Equity | K4: =1-K3 -> 0.9 | L4: =+F6 -> 6114968.5 | N4: Offer 1
B5: Sponsor Equity | F5: =+F8-SUM(F6:F7) -> 679440.95 | G5: =+F5/$F$8 -> 0.040770779 | I5: Total Equity | K5: =SUM(K3:K4) -> 1 | L5: =SUM(L3:L4) -> 6794409.5
B6: LP Equity | F6: =(F8-SUM(F7:F7))*K4 -> 6114968.5 | G6: =+F6/$F$8 -> 0.36693701
B7: =+B27 -> Acquisition Loan | F7: =+G31 -> 9870490.4 | G7: =+F7/$F$8 -> 0.59229221
B8: Total Sources | F8: =+F17 -> 16664900 | G8: =+F8/$F$8 -> 1 | I8: Levered IRR | K8: =+E184 -> 0.30392409
I9: Levered MOIC | K9: =+E185 -> 2.645941
B10: Uses | F10: $ | G10: %
B11: Acquisition of Property | F11: =+G22 -> 14900000 | G11: =+F11/$F$17 -> 0.89409478
B12: Closing Costs | F12: =+'Closing Costs'!E18 -> 646260.72 | G12: =+F12/$F$17 -> 0.038779754
B13: Legal and Setup Costs | F13: =+'Legal and Pre-Dev'!E12 -> 34650 | G13: =+F13/$F$17 -> 0.0020792204
B14: Reserves | F14: =+Reserves!E12 -> 386152.2 | G14: =+F14/$F$17 -> 0.023171588
B15: Hard Costs | F15: =+'Hard Costs'!E17 -> 596750 | G15: =+F15/$F$17 -> 0.035808796
B16: Interest Reserve | F16: =+L31 -> 101086.93 | G16: =+F16/$F$17 -> 0.0060658586
B17: Total Uses | F17: =SUM(F11:F16) -> 16664900 | G17: =+F17/$F$17 -> 1
B21: General Property Assumptions | I21: Going-in Cap Rate | L21: =('NOI Walk'!E51*12)/G22 -> 0.057099747
B22: Acquisition Price | E22: =+G22/E124 -> 191025.64 | F22: =+G22/O3-1 -> -0.0066666667 | G22: 14900000 | I22: Going-in Cash-on-Cash | L22: {=+INDEX(Model!65:65,,MATCH(1,Model!4:4,0))*12/L5} -> -1.0063644
B23: Closing on Property | G23: 0 | I23: Stabilized Yield on Cost | L23: {=INDEX('NOI Walk'!$E$64:$EF$64,,MATCH(Assumptions!G146+1,'NOI Walk'!$E$15:$EF$15,0))*12/F17} -> 0.089156529 | N23: Max DSCR Loan
B24: Buildable SF | G24: 55000 | I24: Re-leased Cash-on-Cash | L24: {=+INDEX(Model!65:65,,MATCH(G146+3,Model!4:4,0))*12/L5} -> 0.090822619 | N24: ="Stabilized Annualized NOI in Month "&1 -> Stabilized Annualized NOI in Month 1 | R24: {=INDEX('NOI Walk'!$E$64:$EF$64,,MATCH(1,'NOI Walk'!$E$15:$EF$15,0))*12} -> 835746.62
B25: Net Rentable SF | G25: =SUM(F46:F123)+'Retail Assumptions'!F19 -> 49950 | I25: Efficiency | L25: =+G25/G24 -> 0.90818182 | N25: Required DSCR Minimum | R25: 1
N26: Max Loan Size Based on DSCR | R26: =+R24/R25/L27 -> 9870490.4
B27: Acquisition Loan | I27: Loan Constant | L27: =IFERROR(PMT(L29,L30,-1),L29) -> 0.084671236
B28: Origination | G28: 0 | I28: Origination Fee | L28: 0.01 | N28: Acquisition Financing | R28: =+G22 -> 14900000
B29: LTC on Property | G29: =+G31/G22 -> 0.66244902 | I29: Rate | K29: =(L29-'1-month Term SOFR'!Q16)*10000 -> 346.375 | L29: 0.075 | N29: LTV Max | R29: 0.7
B30: LTC on Hard Costs | G30: 1 | I30: Amortization | L30: 30 | N30: Max Loan Size Based on LTC | R30: =+R29*R28 -> 10430000
B31: Max Loan Size | G31: =+R33 -> 9870490.4 | I31: Interest Reserve | L31: =-Model!B49 -> 101086.93 | N31: Plus: Hard Cost Advance | R31: =+G30*F15 -> 596750
B33: Permanent Loan | I33: Max Loan as Lesser of… | N33: Max DSCR Loan | R33: =MIN(R30+R31,R26) -> 9870490.4
B34: Permanent Loan Issued? | G34: Yes | I34: DSCR Min. | K34: 1.25 | L34: =+L38/K34/L39 -> 17202326
B35: Seasoning Period Post Stabilization | G35: =+G36-G146 -> 5 | I35: Debt Yield Min. | K35: 0.0875 | L35: =+L38/K35 -> 17127872 | N35: Lender's Minimum Required Interest Reserve | R35: 0
B36: Refinancing Month | G36: 36 | I36: LTV Max | J36: 0.06 | K36: 0.75 | L36: =+L38/J36*K36 -> 18733610
B37: Fixed Interest Rate | G37: {=G38/10000+INDEX(Model!$G$72:$EI$72,,MATCH(Assumptions!G36,Model!$G$4:$EI$4,0))} -> 0.0570644 | I37: Max Perm. Loan | L37: =MIN(L34:L36) -> 17127872
B38: SOFR Spread at Origination | G38: 200 | I38: ="Annualized NOI in Month "&G36 -> Annualized NOI in Month 36 | L38: {=INDEX('NOI Walk'!$E$64:$EF$64,,MATCH(Assumptions!G36,'NOI Walk'!$E$15:$EF$15,0))*12} -> 1498688.8
B39: Amortization | G39: 30 | I39: Loan Factor | L39: =+PMT(G37/12,G39*12,-1)*12 -> 0.069697032
B40: Origination Cost (Includes Title) | G40: 0.011 | I40: Perm Loan Proceeds net of fees | L40: =+L37*(1-G40) -> 16939466
I41: Proceeds from Cashout | L41: {=+INDEX(Model!G65:EI65,,MATCH(Assumptions!G36,Model!$G$4:$EI$4,0))} -> 7241526.2
G43: Unlevered ROI | H43: =((J124-I124)*12)/'Hard Costs'!E15 -> 1.7118172
B44: Rental Assumptions
A45: Unit Name | B45: Units | C45: Rent Type | D45: Vacate=1 Step-up=2 | E45: Layout | F45: Sq. Ft. | G45: Vacated | H45: Vacated | I45: Current Rent | J45: Pro Forma Rent | K45: Annual PF Rent | M45: Market Rent Assumptions | O45: Pro Forma $ Rent | P45: Pro Forma $ / SF | Q45: Avg. Current Rent | R45: Avg. Current $ / SF | S45: Avg. Pro Forma $ Rent | T45: Avg. Pro Forma $ / SF
A46: 1B | B46: 1 | C46: Fair Market | D46: 1 | E46: 2BR | F46: 825 | G46: 2 | H46: =+EOMONTH($F$2,G46) -> 45900 | I46: 1522.5 | J46: =+IFERROR(IF(OR(D46=1,D46=2),INDEX($O$46:$O$51,MATCH(E46,$M$46:$M$51,0)),I46),I46) -> 2600 | K46: =+J46*12 -> 31200 | M46: Studio | O46: 2000 | P46: 2.25 | Q46: =IFERROR(AVERAGEIF($E$46:$E$123,M46,$I$46:$I$123),0) -> 0 | R46: =IFERROR(SUMIF($E$46:$E$123,M46,$I$46:$I$123)/SUMIF($E$46:$E$123,M46,$F$46:$F$123),0) -> 0 | S46: =IFERROR(AVERAGEIF($E$46:$E$123,M46,$J$46:$J$123),0) -> 0 | T46: =IFERROR(SUMIF($E$46:$E$123,M46,$J$46:$J$123)/SUMIF($E$46:$E$123,M46,$F$46:$F$123),0) -> 0
A47: 2 | B47: =+B46+1 -> 2 | C47: Rent Control | D47: 1 | E47: 2BR | F47: 825 | G47: 2 | H47: =+EOMONTH($F$2,G47) -> 45900 | I47: 1764 | J47: =+IFERROR(IF(OR(D47=1,D47=2),INDEX($O$46:$O$51,MATCH(E47,$M$46:$M$51,0)),I47),I47) -> 2600 | K47: =+J47*12 -> 31200 | M47: 1BR | O47: 2200 | P47: 2 | Q47: =IFERROR(AVERAGEIF($E$46:$E$123,M47,$I$46:$I$123),0) -> 1544.0186 | R47: =IFERROR(SUMIF($E$46:$E$123,M47,$I$46:$I$123)/SUMIF($E$46:$E$123,M47,$F$46:$F$123),0) -> 2.4704298 | S47: =IFERROR(AVERAGEIF($E$46:$E$123,M47,$J$46:$J$123),0) -> 2097.5114 | T47: =IFERROR(SUMIF($E$46:$E$123,M47,$J$46:$J$123)/SUMIF($E$46:$E$123,M47,$F$46:$F$123),0) -> 3.3560182
A48: 3 | B48: =+B47+1 -> 3 | C48: Rent Stabilized | D48: 1 | E48: 1BR | F48: 625 | G48: 2 | H48: =+EOMONTH($F$2,G48) -> 45900 | I48: 1457.71 | J48: =+IFERROR(IF(OR(D48=1,D48=2),INDEX($O$46:$O$51,MATCH(E48,$M$46:$M$51,0)),I48),I48) -> 2200 | K48: =+J48*12 -> 26400 | M48: 2BR | O48: 2600 | P48: 1.9 | Q48: =IFERROR(AVERAGEIF($E$46:$E$123,M48,$I$46:$I$123),0) -> 1891.2167 | R48: =IFERROR(SUMIF($E$46:$E$123,M48,$I$46:$I$123)/SUMIF($E$46:$E$123,M48,$F$46:$F$123),0) -> 2.2923838 | S48: =IFERROR(AVERAGEIF($E$46:$E$123,M48,$J$46:$J$123),0) -> 2381.875 | T48: =IFERROR(SUMIF($E$46:$E$123,M48,$J$46:$J$123)/SUMIF($E$46:$E$123,M48,$F$46:$F$123),0) -> 2.8871212
A49: 4 | B49: =+B48+1 -> 4 | C49: Fair Market | D49: 0 | E49: 1BR | F49: 625 | G49: =+G46+1 -> 3 | H49: =+EOMONTH($F$2,G49) -> 45930 | I49: 1680 | J49: =+IFERROR(IF(OR(D49=1,D49=2),INDEX($O$46:$O$51,MATCH(E49,$M$46:$M$51,0)),I49),I49) -> 1680 | K49: =+J49*12 -> 20160 | M49: 3BR | O49: 3000 | P49: 1.85 | Q49: =IFERROR(AVERAGEIF($E$46:$E$123,M49,$I$46:$I$123),0) -> 0 | R49: =IFERROR(SUMIF($E$46:$E$123,M49,$I$46:$I$123)/SUMIF($E$46:$E$123,M49,$F$46:$F$123),0) -> 0 | S49: =IFERROR(AVERAGEIF($E$46:$E$123,M49,$J$46:$J$123),0) -> 0 | T49: =IFERROR(SUMIF($E$46:$E$123,M49,$J$46:$J$123)/SUMIF($E$46:$E$123,M49,$F$46:$F$123),0) -> 0
A50: 5 | B50: =+B49+1 -> 5 | C50: Fair Market | D50: 0 | E50: 1BR | F50: 625 | G50: =+G47+1 -> 3 | H50: =+EOMONTH($F$2,G50) -> 45930 | I50: 1451.66 | J50: =+IFERROR(IF(OR(D50=1,D50=2),INDEX($O$46:$O$51,MATCH(E50,$M$46:$M$51,0)),I50),I50) -> 1451.66 | K50: =+J50*12 -> 17419.92 | M50: 3BR / 2BA | O50: 3200 | P50: 1.8 | Q50: =IFERROR(AVERAGEIF($E$46:$E$123,M50,$I$46:$I$123),0) -> 0 | R50: =IFERROR(SUMIF($E$46:$E$123,M50,$I$46:$I$123)/SUMIF($E$46:$E$123,M50,$F$46:$F$123),0) -> 0 | S50: =IFERROR(AVERAGEIF($E$46:$E$123,M50,$J$46:$J$123),0) -> 0 | T50: =IFERROR(SUMIF($E$46:$E$123,M50,$J$46:$J$123)/SUMIF($E$46:$E$123,M50,$F$46:$F$123),0) -> 0
A51: 6 | B51: =+B50+1 -> 6 | C51: Fair Market | D51: 0 | E51: 1BR | F51: 625 | G51: =+G48+1 -> 3 | H51: =+EOMONTH($F$2,G51) -> 45930 | I51: 1627.5 | J51: =+IFERROR(IF(OR(D51=1,D51=2),INDEX($O$46:$O$51,MATCH(E51,$M$46:$M$51,0)),I51),I51) -> 1627.5 | K51: =+J51*12 -> 19530 | M51: 4BR | O51: 4000 | P51: 1.75 | Q51: =IFERROR(AVERAGEIF($E$46:$E$123,M51,$I$46:$I$123),0) -> 0 | R51: =IFERROR(SUMIF($E$46:$E$123,M51,$I$46:$I$123)/SUMIF($E$46:$E$123,M51,$F$46:$F$123),0) -> 0 | S51: =IFERROR(AVERAGEIF($E$46:$E$123,M51,$J$46:$J$123),0) -> 0 | T51: =IFERROR(SUMIF($E$46:$E$123,M51,$J$46:$J$123)/SUMIF($E$46:$E$123,M51,$F$46:$F$123),0) -> 0
A52: 7 | B52: =+B51+1 -> 7 | C52: Fair Market | D52: 2 | E52: 1BR | F52: 625 | G52: =+G49+1 -> 4 | H52: =+EOMONTH($F$2,G52) -> 45961 | I52: 1881 | J52: =+IFERROR(IF(OR(D52=1,D52=2),INDEX($O$46:$O$51,MATCH(E52,$M$46:$M$51,0)),I52),I52) -> 2200 | K52: =+J52*12 -> 26400 | M52: Underwriting PF Rent Roll | O52: =+K124+J134 -> 1983744.8
A53: 8 | B53: =+B52+1 -> 8 | C53: Fair Market | D53: 1 | E53: 1BR | F53: 625 | G53: =+G50+1 -> 4 | H53: =+EOMONTH($F$2,G53) -> 45961 | I53: 1417.5 | J53: =+IFERROR(IF(OR(D53=1,D53=2),INDEX($O$46:$O$51,MATCH(E53,$M$46:$M$51,0)),I53),I53) -> 2200 | K53: =+J53*12 -> 26400 | M53: Broker's PF Rent Roll | O53: =181800*12 -> 2181600
A54: 20 | B54: =+B53+1 -> 9 | C54: Fair Market | D54: 1 | E54: 1BR | F54: 625 | G54: =+G51+1 -> 4 | H54: =+EOMONTH($F$2,G54) -> 45961 | I54: 1650 | J54: =+IFERROR(IF(OR(D54=1,D54=2),INDEX($O$46:$O$51,MATCH(E54,$M$46:$M$51,0)),I54),I54) -> 2200 | K54: =+J54*12 -> 26400 | M54: Change in Rent Roll | O54: =+O52/O53-1 -> -0.090692684
A55: 21 | B55: =+B54+1 -> 10 | C55: Fair Market | D55: 1 | E55: 1BR | F55: 625 | G55: =+G52+1 -> 5 | H55: =+EOMONTH($F$2,G55) -> 45991 | I55: 1391.18 | J55: =+IFERROR(IF(OR(D55=1,D55=2),INDEX($O$46:$O$51,MATCH(E55,$M$46:$M$51,0)),I55),I55) -> 2200 | K55: =+J55*12 -> 26400
A56: 22 | B56: =+B55+1 -> 11 | C56: Fair Market | D56: 1 | E56: 1BR | F56: 625 | G56: =+G53+1 -> 5 | H56: =+EOMONTH($F$2,G56) -> 45991 | I56: 1391.25 | J56: =+IFERROR(IF(OR(D56=1,D56=2),INDEX($O$46:$O$51,MATCH(E56,$M$46:$M$51,0)),I56),I56) -> 2200 | K56: =+J56*12 -> 26400
A57: 23 | B57: =+B56+1 -> 12 | C57: Fair Market | D57: 1 | E57: 1BR | F57: 625 | G57: =+G54+1 -> 5 | H57: =+EOMONTH($F$2,G57) -> 45991 | I57: 1428 | J57: =+IFERROR(IF(OR(D57=1,D57=2),INDEX($O$46:$O$51,MATCH(E57,$M$46:$M$51,0)),I57),I57) -> 2200 | K57: =+J57*12 -> 26400
A58: 24 | B58: =+B57+1 -> 13 | C58: Fair Market | D58: 1 | E58: 1BR | F58: 625 | G58: =+G55+1 -> 6 | H58: =+EOMONTH($F$2,G58) -> 46022 | I58: 1391.25 | J58: =+IFERROR(IF(OR(D58=1,D58=2),INDEX($O$46:$O$51,MATCH(E58,$M$46:$M$51,0)),I58),I58) -> 2200 | K58: =+J58*12 -> 26400
A59: 25 | B59: =+B58+1 -> 14 | C59: Fair Market | D59: 1 | E59: 1BR | F59: 625 | G59: =+G56+1 -> 6 | H59: =+EOMONTH($F$2,G59) -> 46022 | I59: 1776.5 | J59: =+IFERROR(IF(OR(D59=1,D59=2),INDEX($O$46:$O$51,MATCH(E59,$M$46:$M$51,0)),I59),I59) -> 2200 | K59: =+J59*12 -> 26400
A60: 26 | B60: =+B59+1 -> 15 | C60: Fair Market | D60: 0 | E60: 1BR | F60: 625 | G60: =+G57+1 -> 6 | H60: =+EOMONTH($F$2,G60) -> 46022 | I60: 1365 | J60: =+IFERROR(IF(OR(D60=1,D60=2),INDEX($O$46:$O$51,MATCH(E60,$M$46:$M$51,0)),I60),I60) -> 1365 | K60: =+J60*12 -> 16380
A61: 27 | B61: =+B60+1 -> 16 | C61: Fair Market | D61: 1 | E61: 1BR | F61: 625 | G61: =+G58+1 -> 7 | H61: =+EOMONTH($F$2,G61) -> 46053 | I61: 1548.75 | J61: =+IFERROR(IF(OR(D61=1,D61=2),INDEX($O$46:$O$51,MATCH(E61,$M$46:$M$51,0)),I61),I61) -> 2200 | K61: =+J61*12 -> 26400
A62: 28 | B62: =+B61+1 -> 17 | C62: Fair Market | D62: 1 | E62: 1BR | F62: 625 | G62: =+G59+1 -> 7 | H62: =+EOMONTH($F$2,G62) -> 46053 | I62: 1417.5 | J62: =+IFERROR(IF(OR(D62=1,D62=2),INDEX($O$46:$O$51,MATCH(E62,$M$46:$M$51,0)),I62),I62) -> 2200 | K62: =+J62*12 -> 26400
A63: 29 | B63: =+B62+1 -> 18 | C63: Fair Market | D63: 1 | E63: 1BR | F63: 625 | G63: =+G60+1 -> 7 | H63: =+EOMONTH($F$2,G63) -> 46053 | I63: 1494.01 | J63: =+IFERROR(IF(OR(D63=1,D63=2),INDEX($O$46:$O$51,MATCH(E63,$M$46:$M$51,0)),I63),I63) -> 2200 | K63: =+J63*12 -> 26400
A64: 30 | B64: =+B63+1 -> 19 | C64: Fair Market | D64: 1 | E64: 1BR | F64: 625 | G64: =+G61+1 -> 8 | H64: =+EOMONTH($F$2,G64) -> 46081 | I64: 1548.75 | J64: =+IFERROR(IF(OR(D64=1,D64=2),INDEX($O$46:$O$51,MATCH(E64,$M$46:$M$51,0)),I64),I64) -> 2200 | K64: =+J64*12 -> 26400
A65: 31 | B65: =+B64+1 -> 20 | C65: Fair Market | D65: 1 | E65: 1BR | F65: 625 | G65: =+G62+1 -> 8 | H65: =+EOMONTH($F$2,G65) -> 46081 | I65: 1344 | J65: =+IFERROR(IF(OR(D65=1,D65=2),INDEX($O$46:$O$51,MATCH(E65,$M$46:$M$51,0)),I65),I65) -> 2200 | K65: =+J65*12 -> 26400
A66: 32 | B66: =+B65+1 -> 21 | C66: Fair Market | D66: 2 | E66: 1BR | F66: 625 | G66: =+G63+1 -> 8 | H66: =+EOMONTH($F$2,G66) -> 46081 | I66: 1700 | J66: =+IFERROR(IF(OR(D66=1,D66=2),INDEX($O$46:$O$51,MATCH(E66,$M$46:$M$51,0)),I66),I66) -> 2200 | K66: =+J66*12 -> 26400
... A83: 49 | B83: =+B82+1 -> 38 | C83: Fair Market | D83: 1 | E83: 1BR | F83: 625 | G83: =+G80+1 -> 14 | H83: =+EOMONTH($F$2,G83) -> 46265 | I83: 1700 | J83: =+IFERROR(IF(OR(D83=1,D83=2),INDEX($O$46:$O$51,MATCH(E83,$M$46:$M$51,0)),I83),I83) -> 2200 | K83: =+J83*12 -> 26400
A84: B | B84: =+B83+1 -> 39 | C84: Fair Market | D84: 0 | E84: 2BR | F84: 825 | G84: =+G81+1 -> 14 | H84: =+EOMONTH($F$2,G84) -> 46265 | I84: 1391.25 | J84: =+IFERROR(IF(OR(D84=1,D84=2),INDEX($O$46:$O$51,MATCH(E84,$M$46:$M$51,0)),I84),I84) -> 1391.25 | K84: =+J84*12 -> 16695
A85: 1 | B85: =+B84+1 -> 40 | C85: Fair Market | D85: 0 | E85: 2BR | F85: 825 | G85: =+G82+1 -> 15 | H85: =+EOMONTH($F$2,G85) -> 46295 | I85: 2500 | J85: =+IFERROR(IF(OR(D85=1,D85=2),INDEX($O$46:$O$51,MATCH(E85,$M$46:$M$51,0)),I85),I85) -> 2500 | K85: =+J85*12 -> 30000
A86: 2 | B86: =+B85+1 -> 41 | C86: Fair Market | D86: 1 | E86: 2BR | F86: 825 | G86: =+G83+1 -> 15 | H86: =+EOMONTH($F$2,G86) -> 46295 | I86: 2194.5 | J86: =+IFERROR(IF(OR(D86=1,D86=2),INDEX($O$46:$O$51,MATCH(E86,$M$46:$M$51,0)),I86),I86) -> 2600 | K86: =+J86*12 -> 31200
A87: 3 | B87: =+B86+1 -> 42 | C87: Fair Market | D87: 1 | E87: 1BR | F87: 625 | G87: =+G84+1 -> 15 | H87: =+EOMONTH($F$2,G87) -> 46295 | I87: 1724.25 | J87: =+IFERROR(IF(OR(D87=1,D87=2),INDEX($O$46:$O$51,MATCH(E87,$M$46:$M$51,0)),I87),I87) -> 2200 | K87: =+J87*12 -> 26400
A88: 4 | B88: =+B87+1 -> 43 | C88: Fair Market | D88: 2 | E88: 1BR | F88: 625 | G88: =+G85+1 -> 16 | H88: =+EOMONTH($F$2,G88) -> 46326 | I88: 1755.6 | J88: =+IFERROR(IF(OR(D88=1,D88=2),INDEX($O$46:$O$51,MATCH(E88,$M$46:$M$51,0)),I88),I88) -> 2200 | K88: =+J88*12 -> 26400
A89: 5 | B89: =+B88+1 -> 44 | C89: Fair Market | D89: 1 | E89: 1BR | F89: 625 | G89: =+G86+1 -> 16 | H89: =+EOMONTH($F$2,G89) -> 46326 | I89: 1417.5 | J89: =+IFERROR(IF(OR(D89=1,D89=2),INDEX($O$46:$O$51,MATCH(E89,$M$46:$M$51,0)),I89),I89) -> 2200 | K89: =+J89*12 -> 26400
A90: 6 | B90: =+B89+1 -> 45 | C90: Fair Market | D90: 1 | E90: 1BR | F90: 625 | G90: =+G87+1 -> 16 | H90: =+EOMONTH($F$2,G90) -> 46326 | I90: 1601.25 | J90: =+IFERROR(IF(OR(D90=1,D90=2),INDEX($O$46:$O$51,MATCH(E90,$M$46:$M$51,0)),I90),I90) -> 2200 | K90: =+J90*12 -> 26400
A91: 7 | B91: =+B90+1 -> 46 | C91: Fair Market | D91: 1 | E91: 1BR | F91: 625 | G91: =+G88+1 -> 17 | H91: =+EOMONTH($F$2,G91) -> 46356 | I91: 1732.5 | J91: =+IFERROR(IF(OR(D91=1,D91=2),INDEX($O$46:$O$51,MATCH(E91,$M$46:$M$51,0)),I91),I91) -> 2200 | K91: =+J91*12 -> 26400
A92: 8 | B92: =+B91+1 -> 47 | C92: Fair Market | D92: 1 | E92: 1BR | F92: 625 | G92: =+G89+1 -> 17 | H92: =+EOMONTH($F$2,G92) -> 46356 | I92: 1443.75 | J92: =+IFERROR(IF(OR(D92=1,D92=2),INDEX($O$46:$O$51,MATCH(E92,$M$46:$M$51,0)),I92),I92) -> 2200 | K92: =+J92*12 -> 26400
A93: 20 | B93: =+B92+1 -> 48 | C93: Fair Market | D93: 1 | E93: 1BR | F93: 625 | G93: =+G90+1 -> 17 | H93: =+EOMONTH($F$2,G93) -> 46356 | I93: 1417.5 | J93: =+IFERROR(IF(OR(D93=1,D93=2),INDEX($O$46:$O$51,MATCH(E93,$M$46:$M$51,0)),I93),I93) -> 2200 | K93: =+J93*12 -> 26400
A94: 21 | B94: =+B93+1 -> 49 | C94: Fair Market | D94: 1 | E94: 1BR | F94: 625 | G94: =+G91+1 -> 18 | H94: =+EOMONTH($F$2,G94) -> 46387 | I94: 1700 | J94: =+IFERROR(IF(OR(D94=1,D94=2),INDEX($O$46:$O$51,MATCH(E94,$M$46:$M$51,0)),I94),I94) -> 2200 | K94: =+J94*12 -> 26400
A95: 22 | B95: =+B94+1 -> 50 | C95: Fair Market | D95: 1 | E95: 1BR | F95: 625 | G95: =+G92+1 -> 18 | H95: =+EOMONTH($F$2,G95) -> 46387 | I95: 1819.13 | J95: =+IFERROR(IF(OR(D95=1,D95=2),INDEX($O$46:$O$51,MATCH(E95,$M$46:$M$51,0)),I95),I95) -> 2200 | K95: =+J95*12 -> 26400
A96: 23 | B96: =+B95+1 -> 51 | C96: Fair Market | D96: 1 | E96: 1BR | F96: 625 | G96: =+G93+1 -> 18 | H96: =+EOMONTH($F$2,G96) -> 46387 | I96: 1481.9 | J96: =+IFERROR(IF(OR(D96=1,D96=2),INDEX($O$46:$O$51,MATCH(E96,$M$46:$M$51,0)),I96),I96) -> 2200 | K96: =+J96*12 -> 26400
... A122: 49 | B122: =+B121+1 -> 77 | C122: Fair Market | D122: 0 | E122: 1BR | F122: 625 | G122: =+G119+1 -> 27 | H122: =+EOMONTH($F$2,G122) -> 46660 | I122: 1300 | J122: =+IFERROR(IF(OR(D122=1,D122=2),INDEX($O$46:$O$51,MATCH(E122,$M$46:$M$51,0)),I122),I122) -> 1300 | K122: =+J122*12 -> 15600
A123: B | B123: =+B122+1 -> 78 | C123: Fair Market | D123: 1 | E123: 2BR | F123: 825 | G123: =+G120+1 -> 27 | H123: =+EOMONTH($F$2,G123) -> 46660 | I123: 1975.05 | J123: =+IFERROR(IF(OR(D123=1,D123=2),INDEX($O$46:$O$51,MATCH(E123,$M$46:$M$51,0)),I123),I123) -> 2600 | K123: =+J123*12 -> 31200
B124: Total Rental Income | E124: =COUNTA(B46:B123) -> 78 | F124: =SUM(F46:F123)/E124 -> 640.38462 | I124: =SUM(I46:I123) -> 122516.64 | J124: =SUM(J46:J123) -> 165312.07 | K124: =SUM(K46:K123) -> 1983744.8
B126: Amenity Income | D126: Start | E126: Utilization x | F126: Units = | G126: Usage | H126: Monthly Fee | I126: Monthly | J126: Annual
B127: Parking | D127: 12 | E127: 0.95 | F127: 24 | G127: =ROUND(F127*E127,0) -> 23 | H127: 75 | I127: =+H127*G127 -> 1725 | J127: =+I127*12 -> 20700
B128: Storage | D128: 12 | E128: 0.95 | F128: 50 | G128: =ROUND(F128*E128,0) -> 48 | H128: 40 | I128: =+H128*G128 -> 1920 | J128: =+I128*12 -> 23040
B129: Laundry | D129: 1 | E129: 0.2 | F129: =+$E$124 -> 78 | G129: =ROUND(F129*E129,0) -> 16 | H129: 11 | I129: =+H129*G129 -> 176 | J129: =+I129*12 -> 2112
B130: Gym / Amenity Space | D130: 1 | E130: 0.5 | F130: =+$E$124 -> 78 | G130: =ROUND(F130*E130,0) -> 39 | H130: 100 | I130: =+H130*G130 -> 3900 | J130: =+I130*12 -> 46800
B131: Total Amenity Income | I131: =+SUM(I127:I130) -> 7721 | J131: =+SUM(J127:J130) -> 92652
B133: Retail | I133: =+I126 -> Monthly | J133: =+J126 -> Annual
B134: Effective Gross Retail Income | I134: =+J134/12 -> 0 | J134: =+'Retail Assumptions'!J49 -> 0
B136: Growth Rates
B137: Fair Market | E137: 0.025 | G137: Amenity Inflation | I137: 0.02
B138: Rent Control | E138: 0.01 | G138: Expense Inflation | I138: 0.02
B139: Rent Stabilized | E139: 0.02
B141: Leasing Assumptions | I141: Ongoing Lease-up
B142: Rehab Time | G142: 2 | I142: Free Month's Rent | K142: 0
B143: Lease-up Time | G143: 2 | I143: Broker Fee | K143: 1
B144: Max Months of Lease-Up | G144: =SUM(G142:G143) -> 4 | I144: Assumed Lease Term | K144: =12+K142 -> 12
B145: Units Leased per Month | G145: =+ROUND(E124/G144,0) -> 20 | I145: Annual Turnover | K145: 0.2
B146: Re-Stabilization Occurs | G146: =_xlfn.MAXIFS(G46:G123,D46:D123,1)+G143+G142 -> 31 | I146: Ongoing Lease-up Cost | K146: =+SUM(K142:K143)/K144*K145 -> 0.016666667
B147: Bad Debt | G147: 0.01
B148: Vacancy | G148: 0.05
B150: Operating Expenses | G150: Factor | H150: Statistic | I150: Monthly | J150: Annual | K150: Broker
B151: Property Taxes | G151: 3815.7179 | H151: =+$E$124 -> 78 | I151: =+J151/12 -> 24802.167 | J151: =+G151*H151 -> 297626 | K151: 280388
...

Sheet Rent Roll Model
B2: Rent Type | D2: Growth Rate | J2: Growth Rates by Rent Type
B3: =+Assumptions!B137 -> Fair Market | D3: =+Assumptions!E137 -> 0.025 | F3: =Assumptions!B146 -> Re-Stabilization Occurs | H3: =Assumptions!G146 -> 31 | J3: 1 | K3: =+J3*(1+$D3)^(1/12) -> 1.0020598 | L3: =+K3*(1+$D3)^(1/12) -> 1.0041239 | M3: =+L3*(1+$D3)^(1/12) -> 1.0061922 | N3: =+M3*(1+$D3)^(1/12) -> 1.0082648 | O3: =+N3*(1+$D3)^(1/12) -> 1.0103417 | P3: =+O3*(1+$D3)^(1/12) -> 1.0124228 | Q3: =+P3*(1+$D3)^(1/12) -> 1.0145083 | R3: =+Q3*(1+$D3)^(1/12) -> 1.016598 | ... EK3: =+EJ3*(1+$D3)^(1/12) -> 1.3093895
B4: =+Assumptions!B138 -> Rent Control | D4: =+Assumptions!E138 -> 0.01 | F4: =Assumptions!B148 -> Vacancy | H4: =Assumptions!G148 -> 0.05 | J4: 1 | K4: =+J4*(1+$D4)^(1/12) -> 1.0008295 | L4: =+K4*(1+$D4)^(1/12) -> 1.0016598 | M4: =+L4*(1+$D4)^(1/12) -> 1.0024907 | N4: =+M4*(1+$D4)^(1/12) -> 1.0033223 | O4: =+N4*(1+$D4)^(1/12) -> 1.0041546 | P4: =+O4*(1+$D4)^(1/12) -> 1.0049876 | Q4: =+P4*(1+$D4)^(1/12) -> 1.0058212 | R4: =+Q4*(1+$D4)^(1/12) -> 1.0066556 | ... EK4: =+EJ4*(1+$D4)^(1/12) -> 1.1147436
B5: =+Assumptions!B139 -> Rent Stabilized | D5: =+Assumptions!E139 -> 0.02 | J5: 1 | K5: =+J5*(1+$D5)^(1/12) -> 1.0016516 | L5: =+K5*(1+$D5)^(1/12) -> 1.0033059 | M5: =+L5*(1+$D5)^(1/12) -> 1.0049629 | N5: =+M5*(1+$D5)^(1/12) -> 1.0066227 | O5: =+N5*(1+$D5)^(1/12) -> 1.0082852 | P5: =+O5*(1+$D5)^(1/12) -> 1.0099505 | Q5: =+P5*(1+$D5)^(1/12) -> 1.0116185 | R5: =+Q5*(1+$D5)^(1/12) -> 1.0132893 | ... EK5: =+EJ5*(1+$D5)^(1/12) -> 1.2413242
J7: {=+INDEX(Model!$G$2:$EI$2,,MATCH(J8,Model!$G$4:$EI$4,0))} -> 45869 | K7: =EOMONTH(J7,1) -> 45900 | L7: =EOMONTH(K7,1) -> 45930 | M7: =EOMONTH(L7,1) -> 45961 | N7: =EOMONTH(M7,1) -> 45991 | O7: =EOMONTH(N7,1) -> 46022 | P7: =EOMONTH(O7,1) -> 46053 | Q7: =EOMONTH(P7,1) -> 46081 | R7: =EOMONTH(Q7,1) -> 46112 | ... EK7: =EOMONTH(EJ7,1) -> 49856
B8: =Assumptions!B45 -> Units | C8: =Assumptions!C45 -> Rent Type | D8: =Assumptions!D45 -> Vacate=1 Step-up=2 | E8: =Assumptions!G45 -> Vacated | F8: Re-Leased | G8: =Assumptions!I45 -> Current Rent | H8: =Assumptions!J45 -> Pro Forma Rent | J8: =+'NOI Walk'!E15 -> 1 | K8: =+'NOI Walk'!F15 -> 2 | L8: =+'NOI Walk'!G15 -> 3 | M8: =+'NOI Walk'!H15 -> 4 | N8: =+'NOI Walk'!I15 -> 5 | O8: =+'NOI Walk'!J15 -> 6 | P8: =+'NOI Walk'!K15 -> 7 | Q8: =+'NOI Walk'!L15 -> 8 | ... EK8: =+'NOI Walk'!EF15 -> 132
B9: =Assumptions!B46 -> 1 | C9: =Assumptions!C46 -> Fair Market | D9: =Assumptions!D46 -> 1 | E9: =Assumptions!G46 -> 2 | F9: =IF(D9=1,E9+SUM(Assumptions!$G$142:$G$143),'Rent Roll Model'!E9) -> 6 | G9: =Assumptions!I46 -> 1522.5 | H9: =Assumptions!J46 -> 2600 | J9: =IFERROR(IF($D9=0,$G9,IF(J$8<$E9,$G9,IF(J$8>=$F9,$H9,0)))*INDEX(J$3:J$5,MATCH($C9,$B$3:$B$5,0)),0) -> 1522.5 | K9: =IFERROR(IF($D9=0,$G9,IF(K$8<$E9,$G9,IF(K$8>=$F9,$H9,0)))*INDEX(K$3:K$5,MATCH($C9,$B$3:$B$5,0)),0) -> 0 | L9: =IFERROR(IF($D9=0,$G9,IF(L$8<$E9,$G9,IF(L$8>=$F9,$H9,0)))*INDEX(L$3:L$5,MATCH($C9,$B$3:$B$5,0)),0) -> 0 | M9: =IFERROR(IF($D9=0,$G9,IF(M$8<$E9,$G9,IF(M$8>=$F9,$H9,0)))*INDEX(M$3:M$5,MATCH($C9,$B$3:$B$5,0)),0) -> 0 | N9: =IFERROR(IF($D9=0,$G9,IF(N$8<$E9,$G9,IF(N$8>=$F9,$H9,0)))*INDEX(N$3:N$5,MATCH($C9,$B$3:$B$5,0)),0) -> 0 | O9: =IFERROR(IF($D9=0,$G9,IF(O$8<$E9,$G9,IF(O$8>=$F9,$H9,0)))*INDEX(O$3:O$5,MATCH($C9,$B$3:$B$5,0)),0) -> 2626.8884 | P9: =IFERROR(IF($D9=0,$G9,IF(P$8<$E9,$G9,IF(P$8>=$F9,$H9,0)))*INDEX(P$3:P$5,MATCH($C9,$B$3:$B$5,0)),0) -> 2632.2994 | Q9: =IFERROR(IF($D9=0,$G9,IF(Q$8<$E9,$G9,IF(Q$8>=$F9,$H9,0)))*INDEX(Q$3:Q$5,MATCH($C9,$B$3:$B$5,0)),0) -> 2637.7215 | ... EK9: =IFERROR(IF($D9=0,$G9,IF(EK$8<$E9,$G9,IF(EK$8>=$F9,$H9,0)))*INDEX(EK$3:EK$5,MATCH($C9,$B$3:$B$5,0)),0) -> 3404.4128
B10: =Assumptions!B47 -> 2 | C10: =Assumptions!C47 -> Rent Control | D10: =Assumptions!D47 -> 1 | E10: =Assumptions!G47 -> 2 | F10: =IF(D10=1,E10+SUM(Assumptions!$G$142:$G$143),'Rent Roll Model'!E10) -> 6 | G10: =Assumptions!I47 -> 1764 | H10: =Assumptions!J47 -> 2600 | J10: =IFERROR(IF($D10=0,$G10,IF(J$8<$E10,$G10,IF(J$8>=$F10,$H10,0)))*INDEX(J$3:J$5,MATCH($C10,$B$3:$B$5,0)),0) -> 1764 | K10: =IFERROR(IF($D10=0,$G10,IF(K$8<$E10,$G10,IF(K$8>=$F10,$H10,0)))*INDEX(K$3:K$5,MATCH($C10,$B$3:$B$5,0)),0) -> 0 | L10: =IFERROR(IF($D10=0,$G10,IF(L$8<$E10,$G10,IF(L$8>=$F10,$H10,0)))*INDEX(L$3:L$5,MATCH($C10,$B$3:$B$5,0)),0) -> 0 | M10: =IFERROR(IF($D10=0,$G10,IF(M$8<$E10,$G10,IF(M$8>=$F10,$H10,0)))*INDEX(M$3:M$5,MATCH($C10,$B$3:$B$5,0)),0) -> 0 | N10: =IFERROR(IF($D10=0,$G10,IF(N$8<$E10,$G10,IF(N$8>=$F10,$H10,0)))*INDEX(N$3:N$5,MATCH($C10,$B$3:$B$5,0)),0) -> 0 | O10: =IFERROR(IF($D10=0,$G10,IF(O$8<$E10,$G10,IF(O$8>=$F10,$H10,0)))*INDEX(O$3:O$5,MATCH($C10,$B$3:$B$5,0)),0) -> 2610.8019 | P10: =IFERROR(IF($D10=0,$G10,IF(P$8<$E10,$G10,IF(P$8>=$F10,$H10,0)))*INDEX(P$3:P$5,MATCH($C10,$B$3:$B$5,0)),0) -> 2612.9677 | Q10: =IFERROR(IF($D10=0,$G10,IF(Q$8<$E10,$G10,IF(Q$8>=$F10,$H10,0)))*INDEX(Q$3:Q$5,MATCH($C10,$B$3:$B$5,0)),0) -> 2615.1352 | ... EK10: =IFERROR(IF($D10=0,$G10,IF(EK$8<$E10,$G10,IF(EK$8>=$F10,$H10,0)))*INDEX(EK$3:EK$5,MATCH($C10,$B$3:$B$5,0)),0) -> 2898.3334
B11: =Assumptions!B48 -> 3 | C11: =Assumptions!C48 -> Rent Stabilized | D11: =Assumptions!D48 -> 1 | E11: =Assumptions!G48 -> 2 | F11: =IF(D11=1,E11+SUM(Assumptions!$G$142:$G$143),'Rent Roll Model'!E11) -> 6 | G11: =Assumptions!I48 -> 1457.71 | H11: =Assumptions!J48 -> 2200 | J11: =IFERROR(IF($D11=0,$G11,IF(J$8<$E11,$G11,IF(J$8>=$F11,$H11,0)))*INDEX(J$3:J$5,MATCH($C11,$B$3:$B$5,0)),0) -> 1457.71 | K11: =IFERROR(IF($D11=0,$G11,IF(K$8<$E11,$G11,IF(K$8>=$F11,$H11,0)))*INDEX(K$3:K$5,MATCH($C11,$B$3:$B$5,0)),0) -> 0 | L11: =IFERROR(IF($D11=0,$G11,IF(L$8<$E11,$G11,IF(L$8>=$F11,$H11,0)))*INDEX(L$3:L$5,MATCH($C11,$B$3:$B$5,0)),0) -> 0 | M11: =IFERROR(IF($D11=0,$G11,IF(M$8<$E11,$G11,IF(M$8>=$F11,$H11,0)))*INDEX(M$3:M$5,MATCH($C11,$B$3:$B$5,0)),0) -> 0 | N11: =IFERROR(IF($D11=0,$G11,IF(N$8<$E11,$G11,IF(N$8>=$F11,$H11,0)))*INDEX(N$3:N$5,MATCH($C11,$B$3:$B$5,0)),0) -> 0 | O11: =IFERROR(IF($D11=0,$G11,IF(O$8<$E11,$G11,IF(O$8>=$F11,$H11,0)))*INDEX(O$3:O$5,MATCH($C11,$B$3:$B$5,0)),0) -> 2218.2275 | P11: =IFERROR(IF($D11=0,$G11,IF(P$8<$E11,$G11,IF(P$8>=$F11,$H11,0)))*INDEX(P$3:P$5,MATCH($C11,$B$3:$B$5,0)),0) -> 2221.8911 | Q11: =IFERROR(IF($D11=0,$G11,IF(Q$8<$E11,$G11,IF(Q$8>=$F11,$H11,0)))*INDEX(Q$3:Q$5,MATCH($C11,$B$3:$B$5,0)),0) -> 2225.5607 | ... EK11: =IFERROR(IF($D11=0,$G11,IF(EK$8<$E11,$G11,IF(EK$8>=$F11,$H11,0)))*INDEX(EK$3:EK$5,MATCH($C11,$B$3:$B$5,0)),0) -> 2730.9132
B12: =Assumptions!B49 -> 4 | C12: =Assumptions!C49 -> Fair Market | D12: =Assumptions!D49 -> 0 | E12: =Assumptions!G49 -> 3 | F12: =IF(D12=1,E12+SUM(Assumptions!$G$142:$G$143),'Rent Roll Model'!E12) -> 3 | G12: =Assumptions!I49 -> 1680 | H12: =Assumptions!J49 -> 1680 | J12: =IFERROR(IF($D12=0,$G12,IF(J$8<$E12,$G12,IF(J$8>=$F12,$H12,0)))*INDEX(J$3:J$5,MATCH($C12,$B$3:$B$5,0)),0) -> 1680 | K12: =IFERROR(IF($D12=0,$G12,IF(K$8<$E12,$G12,IF(K$8>=$F12,$H12,0)))*INDEX(K$3:K$5,MATCH($C12,$B$3:$B$5,0)),0) -> 1683.4605 | L12: =IFERROR(IF($D12=0,$G12,IF(L$8<$E12,$G12,IF(L$8>=$F12,$H12,0)))*INDEX(L$3:L$5,MATCH($C12,$B$3:$B$5,0)),0) -> 1686.9282 | M12: =IFERROR(IF($D12=0,$G12,IF(M$8<$E12,$G12,IF(M$8>=$F12,$H12,0)))*INDEX(M$3:M$5,MATCH($C12,$B$3:$B$5,0)),0) -> 1690.403 | N12: =IFERROR(IF($D12=0,$G12,IF(N$8<$E12,$G12,IF(N$8>=$F12,$H12,0)))*INDEX(N$3:N$5,MATCH($C12,$B$3:$B$5,0)),0) -> 1693.8849 | O12: =IFERROR(IF($D12=0,$G12,IF(O$8<$E12,$G12,IF(O$8>=$F12,$H12,0)))*INDEX(O$3:O$5,MATCH($C12,$B$3:$B$5,0)),0) -> 1697.3741 | P12: =IFERROR(IF($D12=0,$G12,IF(P$8<$E12,$G12,IF(P$8>=$F12,$H12,0)))*INDEX(P$3:P$5,MATCH($C12,$B$3:$B$5,0)),0) -> 1700.8704 | Q12: =IFERROR(IF($D12=0,$G12,IF(Q$8<$E12,$G12,IF(Q$8>=$F12,$H12,0)))*INDEX(Q$3:Q$5,MATCH($C12,$B$3:$B$5,0)),0) -> 1704.3739 | ... EK12: =IFERROR(IF($D12=0,$G12,IF(EK$8<$E12,$G12,IF(EK$8>=$F12,$H12,0)))*INDEX(EK$3:EK$5,MATCH($C12,$B$3:$B$5,0)),0) -> 2199.7744
B13: =Assumptions!B50 -> 5 | C13: =Assumptions!C50 -> Fair Market | D13: =Assumptions!D50 -> 0 | E13: =Assumptions!G50 -> 3 | F13: =IF(D13=1,E13+SUM(Assumptions!$G$142:$G$143),'Rent Roll Model'!E13) -> 3 | G13: =Assumptions!I50 -> 1451.66 | H13: =Assumptions!J50 -> 1451.66 | J13: =IFERROR(IF($D13=0,$G13,IF(J$8<$E13,$G13,IF(J$8>=$F13,$H13,0)))*INDEX(J$3:J$5,MATCH($C13,$B$3:$B$5,0)),0) -> 1451.66 | K13: =IFERROR(IF($D13=0,$G13,IF(K$8<$E13,$G13,IF(K$8>=$F13,$H13,0)))*INDEX(K$3:K$5,MATCH($C13,$B$3:$B$5,0)),0) -> 1454.6502 | L13: =IFERROR(IF($D13=0,$G13,IF(L$8<$E13,$G13,IF(L$8>=$F13,$H13,0)))*INDEX(L$3:L$5,MATCH($C13,$B$3:$B$5,0)),0) -> 1457.6465 | M13: =IFERROR(IF($D13=0,$G13,IF(M$8<$E13,$G13,IF(M$8>=$F13,$H13,0)))*INDEX(M$3:M$5,MATCH($C13,$B$3:$B$5,0)),0) -> 1460.649 | N13: =IFERROR(IF($D13=0,$G13,IF(N$8<$E13,$G13,IF(N$8>=$F13,$H13,0)))*INDEX(N$3:N$5,MATCH($C13,$B$3:$B$5,0)),0) -> 1463.6577 | O13: =IFERROR(IF($D13=0,$G13,IF(O$8<$E13,$G13,IF(O$8>=$F13,$H13,0)))*INDEX(O$3:O$5,MATCH($C13,$B$3:$B$5,0)),0) -> 1466.6726 | P13: =IFERROR(IF($D13=0,$G13,IF(P$8<$E13,$G13,IF(P$8>=$F13,$H13,0)))*INDEX(P$3:P$5,MATCH($C13,$B$3:$B$5,0)),0) -> 1469.6937 | Q13: =IFERROR(IF($D13=0,$G13,IF(Q$8<$E13,$G13,IF(Q$8>=$F13,$H13,0)))*INDEX(Q$3:Q$5,MATCH($C13,$B$3:$B$5,0)),0) -> 1472.7211 | ... EK13: =IFERROR(IF($D13=0,$G13,IF(EK$8<$E13,$G13,IF(EK$8>=$F13,$H13,0)))*INDEX(EK$3:EK$5,MATCH($C13,$B$3:$B$5,0)),0) -> 1900.7884
B14: =Assumptions!B51 -> 6 | C14: =Assumptions!C51 -> Fair Market | D14: =Assumptions!D51 -> 0 | E14: =Assumptions!G51 -> 3 | F14: =IF(D14=1,E14+SUM(Assumptions!$G$142:$G$143),'Rent Roll Model'!E14) -> 3 | G14: =Assumptions!I51 -> 1627.5 | H14: =Assumptions!J51 -> 1627.5 | J14: =IFERROR(IF($D14=0,$G14,IF(J$8<$E14,$G14,IF(J$8>=$F14,$H14,0)))*INDEX(J$3:J$5,MATCH($C14,$B$3:$B$5,0)),0) -> 1627.5 | K14: =IFERROR(IF($D14=0,$G14,IF(K$8<$E14,$G14,IF(K$8>=$F14,$H14,0)))*INDEX(K$3:K$5,MATCH($C14,$B$3:$B$5,0)),0) -> 1630.8524 | L14: =IFERROR(IF($D14=0,$G14,IF(L$8<$E14,$G14,IF(L$8>=$F14,$H14,0)))*INDEX(L$3:L$5,MATCH($C14,$B$3:$B$5,0)),0) -> 1634.2117 | M14: =IFERROR(IF($D14=0,$G14,IF(M$8<$E14,$G14,IF(M$8>=$F14,$H14,0)))*INDEX(M$3:M$5,MATCH($C14,$B$3:$B$5,0)),0) -> 1637.5779 | N14: =IFERROR(IF($D14=0,$G14,IF(N$8<$E14,$G14,IF(N$8>=$F14,$H14,0)))*INDEX(N$3:N$5,MATCH($C14,$B$3:$B$5,0)),0) -> 1640.951 | O14: =IFERROR(IF($D14=0,$G14,IF(O$8<$E14,$G14,IF(O$8>=$F14,$H14,0)))*INDEX(O$3:O$5,MATCH($C14,$B$3:$B$5,0)),0) -> 1644.3311 | P14: =IFERROR(IF($D14=0,$G14,IF(P$8<$E14,$G14,IF(P$8>=$F14,$H14,0)))*INDEX(P$3:P$5,MATCH($C14,$B$3:$B$5,0)),0) -> 1647.7182 | Q14: =IFERROR(IF($D14=0,$G14,IF(Q$8<$E14,$G14,IF(Q$8>=$F14,$H14,0)))*INDEX(Q$3:Q$5,MATCH($C14,$B$3:$B$5,0)),0) -> 1651.1122 | ... EK14: =IFERROR(IF($D14=0,$G14,IF(EK$8<$E14,$G14,IF(EK$8>=$F14,$H14,0)))*INDEX(EK$3:EK$5,MATCH($C14,$B$3:$B$5,0)),0) -> 2131.0315
B15: =Assumptions!B52 -> 7 | C15: =Assumptions!C52 -> Fair Market | D15: =Assumptions!D52 -> 2 | E15: =Assumptions!G52 -> 4 | F15: =IF(D15=1,E15+SUM(Assumptions!$G$142:$G$143),'Rent Roll Model'!E15) -> 4 | G15: =Assumptions!I52 -> 1881 | H15: =Assumptions!J52 -> 2200 | J15: =IFERROR(IF($D15=0,$G15,IF(J$8<$E15,$G15,IF(J$8>=$F15,$H15,0)))*INDEX(J$3:J$5,MATCH($C15,$B$3:$B$5,0)),0) -> 1881 | K15: =IFERROR(IF($D15=0,$G15,IF(K$8<$E15,$G15,IF(K$8>=$F15,$H15,0)))*INDEX(K$3:K$5,MATCH($C15,$B$3:$B$5,0)),0) -> 1884.8746 | L15: =IFERROR(IF($D15=0,$G15,IF(L$8<$E15,$G15,IF(L$8>=$F15,$H15,0)))*INDEX(L$3:L$5,MATCH($C15,$B$3:$B$5,0)),0) -> 1888.7571 | M15: =IFERROR(IF($D15=0,$G15,IF(M$8<$E15,$G15,IF(M$8>=$F15,$H15,0)))*INDEX(M$3:M$5,MATCH($C15,$B$3:$B$5,0)),0) -> 2213.6229 | N15: =IFERROR(IF($D15=0,$G15,IF(N$8<$E15,$G15,IF(N$8>=$F15,$H15,0)))*INDEX(N$3:N$5,MATCH($C15,$B$3:$B$5,0)),0) -> 2218.1826 | O15: =IFERROR(IF($D15=0,$G15,IF(O$8<$E15,$G15,IF(O$8>=$F15,$H15,0)))*INDEX(O$3:O$5,MATCH($C15,$B$3:$B$5,0)),0) -> 2222.7517 | P15: =IFERROR(IF($D15=0,$G15,IF(P$8<$E15,$G15,IF(P$8>=$F15,$H15,0)))*INDEX(P$3:P$5,MATCH($C15,$B$3:$B$5,0)),0) -> 2227.3302 | Q15: =IFERROR(IF($D15=0,$G15,IF(Q$8<$E15,$G15,IF(Q$8>=$F15,$H15,0)))*INDEX(Q$3:Q$5,MATCH($C15,$B$3:$B$5,0)),0) -> 2231.9182 | ... EK15: =IFERROR(IF($D15=0,$G15,IF(EK$8<$E15,$G15,IF(EK$8>=$F15,$H15,0)))*INDEX(EK$3:EK$5,MATCH($C15,$B$3:$B$5,0)),0) -> 2880.657
B16: =Assumptions!B53 -> 8 | C16: =Assumptions!C53 -> Fair Market | D16: =Assumptions!D53 -> 1 | E16: =Assumptions!G53 -> 4 | F16: =IF(D16=1,E16+SUM(Assumptions!$G$142:$G$143),'Rent Roll Model'!E16) -> 8 | G16: =Assumptions!I53 -> 1417.5 | H16: =Assumptions!J53 -> 2200 | J16: =IFERROR(IF($D16=0,$G16,IF(J$8<$E16,$G16,IF(J$8>=$F16,$H16,0)))*INDEX(J$3:J$5,MATCH($C16,$B$3:$B$5,0)),0) -> 1417.5 | K16: =IFERROR(IF($D16=0,$G16,IF(K$8<$E16,$G16,IF(K$8>=$F16,$H16,0)))*INDEX(K$3:K$5,MATCH($C16,$B$3:$B$5,0)),0) -> 1420.4198 | L16: =IFERROR(IF($D16=0,$G16,IF(L$8<$E16,$G16,IF(L$8>=$F16,$H16,0)))*INDEX(L$3:L$5,MATCH($C16,$B$3:$B$5,0)),0) -> 1423.3457 | M16: =IFERROR(IF($D16=0,$G16,IF(M$8<$E16,$G16,IF(M$8>=$F16,$H16,0)))*INDEX(M$3:M$5,MATCH($C16,$B$3:$B$5,0)),0) -> 0 | N16: =IFERROR(IF($D16=0,$G16,IF(N$8<$E16,$G16,IF(N$8>=$F16,$H16,0)))*INDEX(N$3:N$5,MATCH($C16,$B$3:$B$5,0)),0) -> 0 | O16: =IFERROR(IF($D16=0,$G16,IF(O$8<$E16,$G16,IF(O$8>=$F16,$H16,0)))*INDEX(O$3:O$5,MATCH($C16,$B$3:$B$5,0)),0) -> 0 | P16: =IFERROR(IF($D16=0,$G16,IF(P$8<$E16,$G16,IF(P$8>=$F16,$H16,0)))*INDEX(P$3:P$5,MATCH($C16,$B$3:$B$5,0)),0) -> 0 | Q16: =IFERROR(IF($D16=0,$G16,IF(Q$8<$E16,$G16,IF(Q$8>=$F16,$H16,0)))*INDEX(Q$3:Q$5,MATCH($C16,$B$3:$B$5,0)),0) -> 2231.9182 | ... EK16: =IFERROR(IF($D16=0,$G16,IF(EK$8<$E16,$G16,IF(EK$8>=$F16,$H16,0)))*INDEX(EK$3:EK$5,MATCH($C16,$B$3:$B$5,0)),0) -> 2880.657
B17: =Assumptions!B54 -> 9 | C17: =Assumptions!C54 -> Fair Market | D17: =Assumptions!D54 -> 1 | E17: =Assumptions!G54 -> 4 | F17: =IF(D17=1,E17+SUM(Assumptions!$G$142:$G$143),'Rent Roll Model'!E17) -> 8 | G17: =Assumptions!I54 -> 1650 | H17: =Assumptions!J54 -> 2200 | J17: =IFERROR(IF($D17=0,$G17,IF(J$8<$E17,$G17,IF(J$8>=$F17,$H17,0)))*INDEX(J$3:J$5,MATCH($C17,$B$3:$B$5,0)),0) -> 1650 | K17: =IFERROR(IF($D17=0,$G17,IF(K$8<$E17,$G17,IF(K$8>=$F17,$H17,0)))*INDEX(K$3:K$5,MATCH($C17,$B$3:$B$5,0)),0) -> 1653.3987 | L17: =IFERROR(IF($D17=0,$G17,IF(L$8<$E17,$G17,IF(L$8>=$F17,$H17,0)))*INDEX(L$3:L$5,MATCH($C17,$B$3:$B$5,0)),0) -> 1656.8045 | M17: =IFERROR(IF($D17=0,$G17,IF(M$8<$E17,$G17,IF(M$8>=$F17,$H17,0)))*INDEX(M$3:M$5,MATCH($C17,$B$3:$B$5,0)),0) -> 0 | N17: =IFERROR(IF($D17=0,$G17,IF(N$8<$E17,$G17,IF(N$8>=$F17,$H17,0)))*INDEX(N$3:N$5,MATCH($C17,$B$3:$B$5,0)),0) -> 0 | O17: =IFERROR(IF($D17=0,$G17,IF(O$8<$E17,$G17,IF(O$8>=$F17,$H17,0)))*INDEX(O$3:O$5,MATCH($C17,$B$3:$B$5,0)),0) -> 0 | P17: =IFERROR(IF($D17=0,$G17,IF(P$8<$E17,$G17,IF(P$8>=$F17,$H17,0)))*INDEX(P$3:P$5,MATCH($C17,$B$3:$B$5,0)),0) -> 0 | Q17: =IFERROR(IF($D17=0,$G17,IF(Q$8<$E17,$G17,IF(Q$8>=$F17,$H17,0)))*INDEX(Q$3:Q$5,MATCH($C17,$B$3:$B$5,0)),0) -> 2231.9182 | ... EK17: =IFERROR(IF($D17=0,$G17,IF(EK$8<$E17,$G17,IF(EK$8>=$F17,$H17,0)))*INDEX(EK$3:EK$5,MATCH($C17,$B$3:$B$5,0)),0) -> 2880.657
B18: =Assumptions!B55 -> 10 | C18: =Assumptions!C55 -> Fair Market | D18: =Assumptions!D55 -> 1 | E18: =Assumptions!G55 -> 5 | F18: =IF(D18=1,E18+SUM(Assumptions!$G$142:$G$143),'Rent Roll Model'!E18) -> 9 | G18: =Assumptions!I55 -> 1391.18 | H18: =Assumptions!J55 -> 2200 | J18: =IFERROR(IF($D18=0,$G18,IF(J$8<$E18,$G18,IF(J$8>=$F18,$H18,0)))*INDEX(J$3:J$5,MATCH($C18,$B$3:$B$5,0)),0) -> 1391.18 | K18: =IFERROR(IF($D18=0,$G18,IF(K$8<$E18,$G18,IF(K$8>=$F18,$H18,0)))*INDEX(K$3:K$5,MATCH($C18,$B$3:$B$5,0)),0) -> 1394.0456 | L18: =IFERROR(IF($D18=0,$G18,IF(L$8<$E18,$G18,IF(L$8>=$F18,$H18,0)))*INDEX(L$3:L$5,MATCH($C18,$B$3:$B$5,0)),0) -> 1396.9171 | M18: =IFERROR(IF($D18=0,$G18,IF(M$8<$E18,$G18,IF(M$8>=$F18,$H18,0)))*INDEX(M$3:M$5,MATCH($C18,$B$3:$B$5,0)),0) -> 1399.7945 | N18: =IFERROR(IF($D18=0,$G18,IF(N$8<$E18,$G18,IF(N$8>=$F18,$H18,0)))*INDEX(N$3:N$5,MATCH($C18,$B$3:$B$5,0)),0) -> 0 | O18: =IFERROR(IF($D18=0,$G18,IF(O$8<$E18,$G18,IF(O$8>=$F18,$H18,0)))*INDEX(O$3:O$5,MATCH($C18,$B$3:$B$5,0)),0) -> 0 | P18: =IFERROR(IF($D18=0,$G18,IF(P$8<$E18,$G18,IF(P$8>=$F18,$H18,0)))*INDEX(P$3:P$5,MATCH($C18,$B$3:$B$5,0)),0) -> 0 | Q18: =IFERROR(IF($D18=0,$G18,IF(Q$8<$E18,$G18,IF(Q$8>=$F18,$H18,0)))*INDEX(Q$3:Q$5,MATCH($C18,$B$3:$B$5,0)),0) -> 0 | ... EK18: =IFERROR(IF($D18=0,$G18,IF(EK$8<$E18,$G18,IF(EK$8>=$F18,$H18,0)))*INDEX(EK$3:EK$5,MATCH($C18,$B$3:$B$5,0)),0) -> 2880.657
B19: =Assumptions!B56 -> 11 | C19: =Assumptions!C56 -> Fair Market | D19: =Assumptions!D56 -> 1 | E19: =Assumptions!G56 -> 5 | F19: =IF(D19=1,E19+SUM(Assumptions!$G$142:$G$143),'Rent Roll Model'!E19) -> 9 | G19: =Assumptions!I56 -> 1391.25 | H19: =Assumptions!J56 -> 2200 | J19: =IFERROR(IF($D19=0,$G19,IF(J$8<$E19,$G19,IF(J$8>=$F19,$H19,0)))*INDEX(J$3:J$5,MATCH($C19,$B$3:$B$5,0)),0) -> 1391.25 | K19: =IFERROR(IF($D19=0,$G19,IF(K$8<$E19,$G19,IF(K$8>=$F19,$H19,0)))*INDEX(K$3:K$5,MATCH($C19,$B$3:$B$5,0)),0) -> 1394.1157 | L19: =IFERROR(IF($D19=0,$G19,IF(L$8<$E19,$G19,IF(L$8>=$F19,$H19,0)))*INDEX(L$3:L$5,MATCH($C19,$B$3:$B$5,0)),0) -> 1396.9874 | M19: =IFERROR(IF($D19=0,$G19,IF(M$8<$E19,$G19,IF(M$8>=$F19,$H19,0)))*INDEX(M$3:M$5,MATCH($C19,$B$3:$B$5,0)),0) -> 1399.865 | N19: =IFERROR(IF($D19=0,$G19,IF(N$8<$E19,$G19,IF(N$8>=$F19,$H19,0)))*INDEX(N$3:N$5,MATCH($C19,$B$3:$B$5,0)),0) -> 0 | O19: =IFERROR(IF($D19=0,$G19,IF(O$8<$E19,$G19,IF(O$8>=$F19,$H19,0)))*INDEX(O$3:O$5,MATCH($C19,$B$3:$B$5,0)),0) -> 0 | P19: =IFERROR(IF($D19=0,$G19,IF(P$8<$E19,$G19,IF(P$8>=$F19,$H19,0)))*INDEX(P$3:P$5,MATCH($C19,$B$3:$B$5,0)),0) -> 0 | Q19: =IFERROR(IF($D19=0,$G19,IF(Q$8<$E19,$G19,IF(Q$8>=$F19,$H19,0)))*INDEX(Q$3:Q$5,MATCH($C19,$B$3:$B$5,0)),0) -> 0 | ... EK19: =IFERROR(IF($D19=0,$G19,IF(EK$8<$E19,$G19,IF(EK$8>=$F19,$H19,0)))*INDEX(EK$3:EK$5,MATCH($C19,$B$3:$B$5,0)),0) -> 2880.657
B20: =Assumptions!B57 -> 12 | C20: =Assumptions!C57 -> Fair Market | D20: =Assumptions!D57 -> 1 | E20: =Assumptions!G57 -> 5 | F20: =IF(D20=1,E20+SUM(Assumptions!$G$142:$G$143),'Rent Roll Model'!E20) -> 9 | G20: =Assumptions!I57 -> 1428 | H20: =Assumptions!J57 -> 2200 | J20: =IFERROR(IF($D20=0,$G20,IF(J$8<$E20,$G20,IF(J$8>=$F20,$H20,0)))*INDEX(J$3:J$5,MATCH($C20,$B$3:$B$5,0)),0) -> 1428 | K20: =IFERROR(IF($D20=0,$G20,IF(K$8<$E20,$G20,IF(K$8>=$F20,$H20,0)))*INDEX(K$3:K$5,MATCH($C20,$B$3:$B$5,0)),0) -> 1430.9414 | L20: =IFERROR(IF($D20=0,$G20,IF(L$8<$E20,$G20,IF(L$8>=$F20,$H20,0)))*INDEX(L$3:L$5,MATCH($C20,$B$3:$B$5,0)),0) -> 1433.889 | M20: =IFERROR(IF($D20=0,$G20,IF(M$8<$E20,$G20,IF(M$8>=$F20,$H20,0)))*INDEX(M$3:M$5,MATCH($C20,$B$3:$B$5,0)),0) -> 1436.8425 | N20: =IFERROR(IF($D20=0,$G20,IF(N$8<$E20,$G20,IF(N$8>=$F20,$H20,0)))*INDEX(N$3:N$5,MATCH($C20,$B$3:$B$5,0)),0) -> 0 | O20: =IFERROR(IF($D20=0,$G20,IF(O$8<$E20,$G20,IF(O$8>=$F20,$H20,0)))*INDEX(O$3:O$5,MATCH($C20,$B$3:$B$5,0)),0) -> 0 | P20: =IFERROR(IF($D20=0,$G20,IF(P$8<$E20,$G20,IF(P$8>=$F20,$H20,0)))*INDEX(P$3:P$5,MATCH($C20,$B$3:$B$5,0)),0) -> 0 | Q20: =IFERROR(IF($D20=0,$G20,IF(Q$8<$E20,$G20,IF(Q$8>=$F20,$H20,0)))*INDEX(Q$3:Q$5,MATCH($C20,$B$3:$B$5,0)),0) -> 0 | ... EK20: =IFERROR(IF($D20=0,$G20,IF(EK$8<$E20,$G20,IF(EK$8>=$F20,$H20,0)))*INDEX(EK$3:EK$5,MATCH($C20,$B$3:$B$5,0)),0) -> 2880.657
... B86: =Assumptions!B123 -> 78 | C86: =Assumptions!C123 -> Fair Market | D86: =Assumptions!D123 -> 1 | E86: =Assumptions!G123 -> 27 | F86: =IF(D86=1,E86+SUM(Assumptions!$G$142:$G$143),'Rent Roll Model'!E86) -> 31 | G86: =Assumptions!I123 -> 1975.05 | H86: =Assumptions!J123 -> 2600 | J86: =IFERROR(IF($D86=0,$G86,IF(J$8<$E86,$G86,IF(J$8>=$F86,$H86,0)))*INDEX(J$3:J$5,MATCH($C86,$B$3:$B$5,0)),0) -> 1975.05 | K86: =IFERROR(IF($D86=0,$G86,IF(K$8<$E86,$G86,IF(K$8>=$F86,$H86,0)))*INDEX(K$3:K$5,MATCH($C86,$B$3:$B$5,0)),0) -> 1979.1183 | L86: =IFERROR(IF($D86=0,$G86,IF(L$8<$E86,$G86,IF(L$8>=$F86,$H86,0)))*INDEX(L$3:L$5,MATCH($C86,$B$3:$B$5,0)),0) -> 1983.1949 | M86: =IFERROR(IF($D86=0,$G86,IF(M$8<$E86,$G86,IF(M$8>=$F86,$H86,0)))*INDEX(M$3:M$5,MATCH($C86,$B$3:$B$5,0)),0) -> 1987.28 | N86: =IFERROR(IF($D86=0,$G86,IF(N$8<$E86,$G86,IF(N$8>=$F86,$H86,0)))*INDEX(N$3:N$5,MATCH($C86,$B$3:$B$5,0)),0) -> 1991.3735 | O86: =IFERROR(IF($D86=0,$G86,IF(O$8<$E86,$G86,IF(O$8>=$F86,$H86,0)))*INDEX(O$3:O$5,MATCH($C86,$B$3:$B$5,0)),0) -> 1995.4754 | P86: =IFERROR(IF($D86=0,$G86,IF(P$8<$E86,$G86,IF(P$8>=$F86,$H86,0)))*INDEX(P$3:P$5,MATCH($C86,$B$3:$B$5,0)),0) -> 1999.5857 | Q86: =IFERROR(IF($D86=0,$G86,IF(Q$8<$E86,$G86,IF(Q$8>=$F86,$H86,0)))*INDEX(Q$3:Q$5,MATCH($C86,$B$3:$B$5,0)),0) -> 2003.7045 | ... EK86: =IFERROR(IF($D86=0,$G86,IF(EK$8<$E86,$G86,IF(EK$8>=$F86,$H86,0)))*INDEX(EK$3:EK$5,MATCH($C86,$B$3:$B$5,0)),0) -> 3404.4128
H87: Rent Roll | J87: =SUM(J8:J86) -> 122517.64 | K87: =SUM(K8:K86) -> 118017.02 | L87: =SUM(L8:L86) -> 118261.11 | M87: =SUM(M8:M86) -> 115740.19 | N87: =SUM(N8:N86) -> 111734.36 | O87: =SUM(O8:O86) -> 116220.91 | P87: =SUM(P8:P86) -> 111941.5 | Q87: =SUM(Q8:Q86) -> 114205.32 | ... EK87: =SUM(EK8:EK86) -> 215934.07
H89: Vacancy | J89: =-IF(J8<$H$3,COUNTIFS(J9:J86,0)*AVERAGEIFS(J9:J86,J9:J86,">0"),J87*$H$4) -> 0 | K89: =-IF(K8<$H$3,COUNTIFS(K9:K86,0)*AVERAGEIFS(K9:K86,K9:K86,">0"),K87*$H$4) -> -4720.6009 | L89: =-IF(L8<$H$3,COUNTIFS(L9:L86,0)*AVERAGEIFS(L9:L86,L9:L86,">0"),L87*$H$4) -> -4730.3245 | M89: =-IF(M8<$H$3,COUNTIFS(M9:M86,0)*AVERAGEIFS(M9:M86,M9:M86,">0"),M87*$H$4) -> -7927.1361 | N89: =-IF(N8<$H$3,COUNTIFS(N9:N86,0)*AVERAGEIFS(N9:N86,N9:N86,">0"),N87*$H$4) -> -12769.069 | O89: =-IF(O8<$H$3,COUNTIFS(O9:O86,0)*AVERAGEIFS(O9:O86,O9:O86,">0"),O87*$H$4) -> -11457.808 | P89: =-IF(P8<$H$3,COUNTIFS(P9:P86,0)*AVERAGEIFS(P9:P86,P9:P86,">0"),P87*$H$4) -> -16460.957 | Q89: =-IF(Q8<$H$3,COUNTIFS(Q9:Q86,0)*AVERAGEIFS(Q9:Q86,Q9:Q86,">0"),Q87*$H$4) -> -16793.724 | ... EK89: =-IF(EK8<$H$3,COUNTIFS(EK9:EK86,0)*AVERAGEIFS(EK9:EK86,EK9:EK86,">0"),EK87*$H$4) -> -10796.704

Sheet NOI Walk
S1: on Ask Price
B3: =+Assumptions!B45 -> Units | C3: =+Assumptions!E124 -> 78 | E3: Amenity Income | F3: Fee | G3: Utilization | I3: =Assumptions!B142 -> Rehab Time | K3: =Assumptions!G142 -> 2 | M3: =+Assumptions!B137 -> Fair Market | O3: =+Assumptions!E137 -> 0.025 | Q3: Year 1 NOI | R3: =SUMIFS($E$64:$EF$64,E15:EF15,"<=12") -> 775561.2 | S3: =+R3/Assumptions!$O$3 -> 0.05170408
B4: Current Rent / Unit | C4: =+Assumptions!I124/Assumptions!E124 -> 1570.7262 | E4: =+Assumptions!B127 -> Parking | F4: =+Assumptions!H127 -> 75 | G4: =+Assumptions!E127 -> 0.95 | I4: =Assumptions!B143 -> Lease-up Time | K4: =Assumptions!G143 -> 2 | M4: =+Assumptions!B138 -> Rent Control | O4: =+Assumptions!E138 -> 0.01 | Q4: Seller's NOI | R4: =+Assumptions!O53*(1-Assumptions!G148-Assumptions!G147)-Assumptions!K166 -> 1467910 | S4: =+R4/Assumptions!$O$3 -> 0.097860667
B5: Pro Forma Rent / Unit | C5: =+Assumptions!J124/Assumptions!E124 -> 2119.3855 | E5: =+Assumptions!B128 -> Storage | F5: =+Assumptions!H128 -> 40 | G5: =+Assumptions!E128 -> 0.95 | I5: =Assumptions!B146 -> Re-Stabilization Occurs | K5: =Assumptions!G146 -> 31 | M5: =+Assumptions!B139 -> Rent Stabilized | O5: =+Assumptions!E139 -> 0.02 | Q5: Change in NOI | R5: =+R3/R4-1 -> -0.47165616
B6: =Assumptions!B147 -> Bad Debt | C6: =Assumptions!G147 -> 0.01 | E6: =+Assumptions!B129 -> Laundry | F6: =+Assumptions!H129 -> 11 | G6: =+Assumptions!E129 -> 0.2 | I6: =+Assumptions!G138 -> Expense Inflation | K6: =+Assumptions!I138 -> 0.02 | M6: =+Assumptions!G137 -> Amenity Inflation | O6: =+Assumptions!I137 -> 0.02 | Q6: Stabilized NOI | R6: {=+INDEX('NOI Walk'!E64:EF64,,MATCH(Assumptions!G146,'NOI Walk'!E15:EF15,0))*12} -> 1482575.8 | S6: =+R6/Assumptions!$O$3 -> 0.098838384
B7: =+Assumptions!I146 -> Ongoing Lease-up Cost | C7: =+Assumptions!K146 -> 0.016666667 | E7: =+Assumptions!B130 -> Gym / Amenity Space | F7: =+Assumptions!H130 -> 100 | G7: =+Assumptions!E130 -> 0.5
B9: Rent Inflation Factor | E9: =(1+(MAX($O$3:$O$5)/12))^E15 -> 1.0020833 | F9: =(1+(MAX($O$3:$O$5)/12))^F15 -> 1.004171 | G9: =(1+(MAX($O$3:$O$5)/12))^G15 -> 1.006263 | H9: =(1+(MAX($O$3:$O$5)/12))^H15 -> 1.0083594 | I9: =(1+(MAX($O$3:$O$5)/12))^I15 -> 1.0104602 | J9: =(1+(MAX($O$3:$O$5)/12))^J15 -> 1.0125653 | K9: =(1+(MAX($O$3:$O$5)/12))^K15 -> 1.0146748 | L9: =(1+(MAX($O$3:$O$5)/12))^L15 -> 1.0167887 | ... EF9: =(1+(MAX($O$3:$O$5)/12))^EF15 -> 1.3161541
B10: Amenity Inflation Factor | E10: =(1+($O$6/12))^E15 -> 1.0016667 | F10: =(1+($O$6/12))^F15 -> 1.0033361 | G10: =(1+($O$6/12))^G15 -> 1.0050083 | H10: =(1+($O$6/12))^H15 -> 1.0066834 | I10: =(1+($O$6/12))^I15 -> 1.0083612 | J10: =(1+($O$6/12))^J15 -> 1.0100418 | K10: =(1+($O$6/12))^K15 -> 1.0117252 | L10: =(1+($O$6/12))^L15 -> 1.0134114 | ... EF10: =(1+($O$6/12))^EF15 -> 1.2458486
B11: Expenses Inflation Factor | E11: =(1+($K$6/12))^E15 -> 1.0016667 | F11: =(1+($K$6/12))^F15 -> 1.0033361 | G11: =(1+($K$6/12))^G15 -> 1.0050083 | H11: =(1+($K$6/12))^H15 -> 1.0066834 | I11: =(1+($K$6/12))^I15 -> 1.0083612 | J11: =(1+($K$6/12))^J15 -> 1.0100418 | K11: =(1+($K$6/12))^K15 -> 1.0117252 | L11: =(1+($K$6/12))^L15 -> 1.0134114 | ... EF11: =(1+($K$6/12))^EF15 -> 1.2458486
B12: Timeline | E12: =IF(E15<$K$5,"Lease-up",IF(E15=$K$5,"Stabilization","-")) -> Lease-up | F12: =IF(F15<$K$5,"Lease-up",IF(F15=$K$5,"Stabilization","-")) -> Lease-up | G12: =IF(G15<$K$5,"Lease-up",IF(G15=$K$5,"Stabilization","-")) -> Lease-up | H12: =IF(H15<$K$5,"Lease-up",IF(H15=$K$5,"Stabilization","-")) -> Lease-up | I12: =IF(I15<$K$5,"Lease-up",IF(I15=$K$5,"Stabilization","-")) -> Lease-up | J12: =IF(J15<$K$5,"Lease-up",IF(J15=$K$5,"Stabilization","-")) -> Lease-up | K12: =IF(K15<$K$5,"Lease-up",IF(K15=$K$5,"Stabilization","-")) -> Lease-up | L12: =IF(L15<$K$5,"Lease-up",IF(L15=$K$5,"Stabilization","-")) -> Lease-up | ... EF12: =IF(EF15<$K$5,"Lease-up",IF(EF15=$K$5,"Stabilization","-")) -> -
E13: =YEAR(Model!H2) -> 2025 | F13: =YEAR(Model!I2) -> 2025 | G13: =YEAR(Model!J2) -> 2025 | H13: =YEAR(Model!K2) -> 2025 | I13: =YEAR(Model!L2) -> 2025 | J13: =YEAR(Model!M2) -> 2025 | K13: =YEAR(Model!N2) -> 2026 | L13: =YEAR(Model!O2) -> 2026 | ... DS13: =YEAR(Model!DV2) -> 2035 | DT13: =YEAR(Model!#REF!) -> #REF! | DU13: =YEAR(Model!EJ2) -> 1900 | DV13: =YEAR(Model!EK2) -> 1900 | DW13: =YEAR(Model!EL2) -> 1900 | DX13: =YEAR(Model!EM2) -> #VALUE! | DY13: =YEAR(Model!EN2) -> 1900 | DZ13: =YEAR(Model!EO2) -> 1900 | EA13: =YEAR(Model!EP2) -> 1900 | EB13: =YEAR(Model!EQ2) -> 1900 | ... EF13: =YEAR(Model!EU2) -> 1900
E14: =+ROUNDUP(E15/12,0) -> 1 | F14: =+ROUNDUP(F15/12,0) -> 1 | G14: =+ROUNDUP(G15/12,0) -> 1 | H14: =+ROUNDUP(H15/12,0) -> 1 | I14: =+ROUNDUP(I15/12,0) -> 1 | J14: =+ROUNDUP(J15/12,0) -> 1 | K14: =+ROUNDUP(K15/12,0) -> 1 | L14: =+ROUNDUP(L15/12,0) -> 1 | ... EF14: =+ROUNDUP(EF15/12,0) -> 11
E15: 1 | F15: =+E15+1 -> 2 | G15: =+F15+1 -> 3 | H15: =+G15+1 -> 4 | I15: =+H15+1 -> 5 | J15: =+I15+1 -> 6 | K15: =+J15+1 -> 7 | L15: =+K15+1 -> 8 | M15: =+L15+1 -> 9 | ... EF15: =+EE15+1 -> 132
B16: Units Leased | E16: =+COUNTIF('Rent Roll Model'!J9:J86,">0") -> 78 | F16: =+COUNTIF('Rent Roll Model'!K9:K86,">0") -> 75 | G16: =+COUNTIF('Rent Roll Model'!L9:L86,">0") -> 75 | H16: =+COUNTIF('Rent Roll Model'!M9:M86,">0") -> 73 | I16: =+COUNTIF('Rent Roll Model'!N9:N86,">0") -> 70 | J16: =+COUNTIF('Rent Roll Model'!O9:O86,">0") -> 71 | K16: =+COUNTIF('Rent Roll Model'!P9:P86,">0") -> 68 | L16: =+COUNTIF('Rent Roll Model'!Q9:Q86,">0") -> 68 | ... EF16: =+COUNTIF('Rent Roll Model'!EK9:EK86,">0") -> 78
B17: Units Vacant | E17: =-COUNTIF('Rent Roll Model'!J9:J86,0) -> 0 | F17: =-COUNTIF('Rent Roll Model'!K9:K86,0) -> -3 | G17: =-COUNTIF('Rent Roll Model'!L9:L86,0) -> -3 | H17: =-COUNTIF('Rent Roll Model'!M9:M86,0) -> -5 | I17: =-COUNTIF('Rent Roll Model'!N9:N86,0) -> -8 | J17: =-COUNTIF('Rent Roll Model'!O9:O86,0) -> -7 | K17: =-COUNTIF('Rent Roll Model'!P9:P86,0) -> -10 | L17: =-COUNTIF('Rent Roll Model'!Q9:Q86,0) -> -10 | ... EF17: =-COUNTIF('Rent Roll Model'!EK9:EK86,0) -> 0
B18: New Leases Started | E18: =COUNTIFS('Rent Roll Model'!$F$9:$F$86,'NOI Walk'!E15,'Rent Roll Model'!$D$9:$D$86,1) -> 0 | F18: =COUNTIFS('Rent Roll Model'!$F$9:$F$86,'NOI Walk'!F15,'Rent Roll Model'!$D$9:$D$86,1) -> 0 | G18: =COUNTIFS('Rent Roll Model'!$F$9:$F$86,'NOI Walk'!G15,'Rent Roll Model'!$D$9:$D$86,1) -> 0 | H18: =COUNTIFS('Rent Roll Model'!$F$9:$F$86,'NOI Walk'!H15,'Rent Roll Model'!$D$9:$D$86,1) -> 0 | I18: =COUNTIFS('Rent Roll Model'!$F$9:$F$86,'NOI Walk'!I15,'Rent Roll Model'!$D$9:$D$86,1) -> 0 | J18: =COUNTIFS('Rent Roll Model'!$F$9:$F$86,'NOI Walk'!J15,'Rent Roll Model'!$D$9:$D$86,1) -> 3 | K18: =COUNTIFS('Rent Roll Model'!$F$9:$F$86,'NOI Walk'!K15,'Rent Roll Model'!$D$9:$D$86,1) -> 0 | L18: =COUNTIFS('Rent Roll Model'!$F$9:$F$86,'NOI Walk'!L15,'Rent Roll Model'!$D$9:$D$86,1) -> 2 | ... EF18: =COUNTIFS('Rent Roll Model'!$F$9:$F$86,'NOI Walk'!EF15,'Rent Roll Model'!$D$9:$D$86,1) -> 0
B20: Gross Potential Rent | E20: =+$C$5*$C$3*E9 -> 165656.47 | F20: =+$C$5*$C$3*F9 -> 166001.59 | G20: =+$C$5*$C$3*G9 -> 166347.42 | H20: =+$C$5*$C$3*H9 -> 166693.98 | I20: =+$C$5*$C$3*I9 -> 167041.26 | J20: =+$C$5*$C$3*J9 -> 167389.26 | K20: =+$C$5*$C$3*K9 -> 167737.99 | L20: =+$C$5*$C$3*L9 -> 168087.45 | ... EF20: =+$C$5*$C$3*EF9 -> 217576.16
B21: Loss-to-Lease | E21: =+E24-E22-E20 -> -43138.83 | F21: =+F24-F22-F20 -> -43263.965 | G21: =+G24-G22-G20 -> -43355.986 | H21: =+H24-H22-H20 -> -43026.659 | I21: =+I24-I22-I20 -> -42537.836 | J21: =+J24-J22-J20 -> -39710.548 | K21: =+K24-K22-K20 -> -39335.53 | L21: =+L24-L22-L20 -> -37088.4 | ... EF21: =+EF24-EF22-EF20 -> 9154.6119
B22: Vacancy | E22: =+'Rent Roll Model'!J89 -> 0 | F22: =+'Rent Roll Model'!K89 -> -4720.6009 | G22: =+'Rent Roll Model'!L89 -> -4730.3245 | H22: =+'Rent Roll Model'!M89 -> -7927.1361 | I22: =+'Rent Roll Model'!N89 -> -12769.069 | J22: =+'Rent Roll Model'!O89 -> -11457.808 | K22: =+'Rent Roll Model'!P89 -> -16460.957 | L22: =+'Rent Roll Model'!Q89 -> -16793.724 | ... EF22: =+'Rent Roll Model'!EK89 -> -10796.704
B23: Vacancy | E23: =-E22/(E20+E21) -> 0 | F23: =-F22/(F20+F21) -> 0.038460912 | G23: =-G22/(G20+G21) -> 0.0384606 | H23: =-H22/(H20+H21) -> 0.064100491 | I23: =-I22/(I20+I21) -> 0.10255998 | J23: =-J22/(J20+J21) -> 0.089739372 | K23: =-K22/(K20+K21) -> 0.12819814 | L23: =-L22/(L20+L21) -> 0.1281973 | ... EF23: =-EF22/(EF20+EF21) -> 0.047619048
B24: Rental Income | E24: =+'Rent Roll Model'!J87 -> 122517.64 | F24: =+'Rent Roll Model'!K87 -> 118017.02 | G24: =+'Rent Roll Model'!L87 -> 118261.11 | H24: =+'Rent Roll Model'!M87 -> 115740.19 | I24: =+'Rent Roll Model'!N87 -> 111734.36 | J24: =+'Rent Roll Model'!O87 -> 116220.91 | K24: =+'Rent Roll Model'!P87 -> 111941.5 | L24: =+'Rent Roll Model'!Q87 -> 114205.32 | ... EF24: =+'Rent Roll Model'!EK87 -> 215934.07
B25: =E4&" Income" -> Parking Income | E25: =IF(E$15<Assumptions!$D127,0,$F4*E$16*E$10*$G4) -> 0 | F25: =IF(F$15<Assumptions!$D127,0,$F4*F$16*F$10*$G4) -> 0 | G25: =IF(G$15<Assumptions!$D127,0,$F4*G$16*G$10*$G4) -> 0 | H25: =IF(H$15<Assumptions!$D127,0,$F4*H$16*H$10*$G4) -> 0 | I25: =IF(I$15<Assumptions!$D127,0,$F4*I$16*I$10*$G4) -> 0 | J25: =IF(J$15<Assumptions!$D127,0,$F4*J$16*J$10*$G4) -> 0 | K25: =IF(K$15<Assumptions!$D127,0,$F4*K$16*K$10*$G4) -> 0 | L25: =IF(L$15<Assumptions!$D127,0,$F4*L$16*L$10*$G4) -> 0 | ... EF25: =IF(EF$15<Assumptions!$D127,0,$F4*EF$16*EF$10*$G4) -> 6923.8034
B26: =E5&" Income" -> Storage Income | E26: =IF(E$15<Assumptions!$D128,0,$F5*E$16*E$10*$G5) -> 0 | F26: =IF(F$15<Assumptions!$D128,0,$F5*F$16*F$10*$G5) -> 0 | G26: =IF(G$15<Assumptions!$D128,0,$F5*G$16*G$10*$G5) -> 0 | H26: =IF(H$15<Assumptions!$D128,0,$F5*H$16*H$10*$G5) -> 0 | I26: =IF(I$15<Assumptions!$D128,0,$F5*I$16*I$10*$G5) -> 0 | J26: =IF(J$15<Assumptions!$D128,0,$F5*J$16*J$10*$G5) -> 0 | K26: =IF(K$15<Assumptions!$D128,0,$F5*K$16*K$10*$G5) -> 0 | L26: =IF(L$15<Assumptions!$D128,0,$F5*L$16*L$10*$G5) -> 0 | ... EF26: =IF(EF$15<Assumptions!$D128,0,$F5*EF$16*EF$10*$G5) -> 3692.6951
B27: =E6&" Income" -> Laundry Income | E27: =IF(E$15<Assumptions!$D129,0,$F6*E$16*E$10*$G6) -> 171.886 | F27: =IF(F$15<Assumptions!$D129,0,$F6*F$16*F$10*$G6) -> 165.55046 | G27: =IF(G$15<Assumptions!$D129,0,$F6*G$16*G$10*$G6) -> 165.82638 | H27: =IF(H$15<Assumptions!$D129,0,$F6*H$16*H$10*$G6) -> 161.67335 | I27: =IF(I$15<Assumptions!$D129,0,$F6*I$16*I$10*$G6) -> 155.28762 | J27: =IF(J$15<Assumptions!$D129,0,$F6*J$16*J$10*$G6) -> 157.76852 | K27: =IF(K$15<Assumptions!$D129,0,$F6*K$16*K$10*$G6) -> 151.35408 | L27: =IF(L$15<Assumptions!$D129,0,$F6*L$16*L$10*$G6) -> 151.60634 | ... EF27: =IF(EF$15<Assumptions!$D129,0,$F6*EF$16*EF$10*$G6) -> 213.78761
B28: =E7&" Income" -> Gym / Amenity Space Income | E28: =IF(E$15<Assumptions!$D130,0,$F7*Assumptions!$F$130*'NOI Walk'!E16/'NOI Walk'!$C$3*E$10*$G7) -> 3906.5 | F28: =IF(F$15<Assumptions!$D130,0,$F7*Assumptions!$F$130*'NOI Walk'!F16/'NOI Walk'!$C$3*F$10*$G7) -> 3762.5104 | G28: =IF(G$15<Assumptions!$D130,0,$F7*Assumptions!$F$130*'NOI Walk'!G16/'NOI Walk'!$C$3*G$10*$G7) -> 3768.7813 | H28: =IF(H$15<Assumptions!$D130,0,$F7*Assumptions!$F$130*'NOI Walk'!H16/'NOI Walk'!$C$3*H$10*$G7) -> 3674.3942 | I28: =IF(I$15<Assumptions!$D130,0,$F7*Assumptions!$F$130*'NOI Walk'!I16/'NOI Walk'!$C$3*I$10*$G7) -> 3529.2641 | J28: =IF(J$15<Assumptions!$D130,0,$F7*Assumptions!$F$130*'NOI Walk'!J16/'NOI Walk'!$C$3*J$10*$G7) -> 3585.6482 | K28: =IF(K$15<Assumptions!$D130,0,$F7*Assumptions!$F$130*'NOI Walk'!K16/'NOI Walk'!$C$3*K$10*$G7) -> 3439.8656 | L28: =IF(L$15<Assumptions!$D130,0,$F7*Assumptions!$F$130*'NOI Walk'!L16/'NOI Walk'!$C$3*L$10*$G7) -> 3445.5987 | ... EF28: =IF(EF$15<Assumptions!$D130,0,$F7*Assumptions!$F$130*'NOI Walk'!EF16/'NOI Walk'!$C$3*EF$10*$G7) -> 4858.8094
B29: Turnover Costs | E29: =-IF(E15<$K$5,0,(E24*$C$7)) -> 0 | F29: =-IF(F15<$K$5,0,(F24*$C$7)) -> 0 | G29: =-IF(G15<$K$5,0,(G24*$C$7)) -> 0 | H29: =-IF(H15<$K$5,0,(H24*$C$7)) -> 0 | I29: =-IF(I15<$K$5,0,(I24*$C$7)) -> 0 | J29: =-IF(J15<$K$5,0,(J24*$C$7)) -> 0 | K29: =-IF(K15<$K$5,0,(K24*$C$7)) -> 0 | L29: =-IF(L15<$K$5,0,(L24*$C$7)) -> 0 | ... EF29: =-IF(EF15<$K$5,0,(EF24*$C$7)) -> -3598.9012
B30: Bad Debt | E30: =-$C$6*SUM(E24:E28) -> -1265.9603 | F30: =-$C$6*SUM(F24:F28) -> -1219.4508 | G30: =-$C$6*SUM(G24:G28) -> -1221.9572 | H30: =-$C$6*SUM(H24:H28) -> -1195.7625 | I30: =-$C$6*SUM(I24:I28) -> -1154.1891 | J30: =-$C$6*SUM(J24:J28) -> -1199.6432 | K30: =-$C$6*SUM(K24:K28) -> -1155.3272 | L30: =-$C$6*SUM(L24:L28) -> -1178.0253 | ... EF30: =-$C$6*SUM(EF24:EF28) -> -2316.2317
B31: Effective Gross Income | E31: =SUM(E25:E30,E24) -> 125330.07 | F31: =SUM(F25:F30,F24) -> 120725.63 | G31: =SUM(G25:G30,G24) -> 120973.76 | H31: =SUM(H25:H30,H24) -> 118380.49 | I31: =SUM(I25:I30,I24) -> 114264.72 | J31: =SUM(J25:J30,J24) -> 118764.68 | K31: =SUM(K25:K30,K24) -> 114377.4 | L31: =SUM(L25:L30,L24) -> 116624.5 | ... EF31: =SUM(EF25:EF30,EF24) -> 225708.03
B33: Operating Expenses
B34: =Assumptions!B151 -> Property Taxes | E34: =Assumptions!$I151*E$11 -> 24843.504 | F34: =Assumptions!$I151*F$11 -> 24884.909 | G34: =Assumptions!$I151*G$11 -> 24926.384 | H34: =Assumptions!$I151*H$11 -> 24967.928 | I34: =Assumptions!$I151*I$11 -> 25009.541 | J34: =Assumptions!$I151*J$11 -> 25051.224 | K34: =Assumptions!$I151*K$11 -> 25092.976 | L34: =Assumptions!$I151*L$11 -> 25134.798 | ... EF34: =Assumptions!$I151*EF$11 -> 30899.744
B35: =Assumptions!B152 -> Insurance | E35: =+Assumptions!$I152*E$11 -> 5924.8583 | F35: =+Assumptions!$I152*F$11 -> 5934.7331 | G35: =+Assumptions!$I152*G$11 -> 5944.6243 | H35: =+Assumptions!$I152*H$11 -> 5954.532 | I35: =+Assumptions!$I152*I$11 -> 5964.4562 | J35: =+Assumptions!$I152*J$11 -> 5974.397 | K35: =+Assumptions!$I152*K$11 -> 5984.3543 | L35: =+Assumptions!$I152*L$11 -> 5994.3283 | ... EF35: =+Assumptions!$I152*EF$11 -> 7369.1942
B36: =Assumptions!B153 -> Water / Sewer | E36: =+Assumptions!$G$153/12*'NOI Walk'!E16*'NOI Walk'!E11 -> 3912.3431 | F36: =+Assumptions!$G$153/12*'NOI Walk'!F16*'NOI Walk'!F11 -> 3768.1381 | G36: =+Assumptions!$G$153/12*'NOI Walk'!G16*'NOI Walk'!G11 -> 3774.4183 | H36: =+Assumptions!$G$153/12*'NOI Walk'!H16*'NOI Walk'!H11 -> 3679.8901 | I36: =+Assumptions!$G$153/12*'NOI Walk'!I16*'NOI Walk'!I11 -> 3534.5429 | J36: =+Assumptions!$G$153/12*'NOI Walk'!J16*'NOI Walk'!J11 -> 3591.0114 | K36: =+Assumptions!$G$153/12*'NOI Walk'!K16*'NOI Walk'!K11 -> 3445.0106 | L36: =+Assumptions!$G$153/12*'NOI Walk'!L16*'NOI Walk'!L11 -> 3450.7523 | ... EF36: =+Assumptions!$G$153/12*'NOI Walk'!EF16*'NOI Walk'!EF11 -> 4866.0768
B37: =Assumptions!B154 -> Repairs & Maintenance | E37: =+Assumptions!$G$154/12*'NOI Walk'!E16*'NOI Walk'!E11 -> 3255.4167 | F37: =+Assumptions!$G$154/12*'NOI Walk'!F16*'NOI Walk'!F11 -> 3135.4253 | G37: =+Assumptions!$G$154/12*'NOI Walk'!G16*'NOI Walk'!G11 -> 3140.6511 | H37: =+Assumptions!$G$154/12*'NOI Walk'!H16*'NOI Walk'!H11 -> 3061.9952 | I37: =+Assumptions!$G$154/12*'NOI Walk'!I16*'NOI Walk'!I11 -> 2941.0534 | J37: =+Assumptions!$G$154/12*'NOI Walk'!J16*'NOI Walk'!J11 -> 2988.0402 | K37: =+Assumptions!$G$154/12*'NOI Walk'!K16*'NOI Walk'!K11 -> 2866.5546 | L37: =+Assumptions!$G$154/12*'NOI Walk'!L16*'NOI Walk'!L11 -> 2871.3322 | ... EF37: =+Assumptions!$G$154/12*'NOI Walk'!EF16*'NOI Walk'!EF11 -> 4049.0078
B38: =Assumptions!B155 -> Bank fees | E38: =+Assumptions!$I155*E$11 -> 162.77083 | F38: =+Assumptions!$I155*F$11 -> 163.04212 | G38: =+Assumptions!$I155*G$11 -> 163.31385 | H38: =+Assumptions!$I155*H$11 -> 163.58604 | I38: =+Assumptions!$I155*I$11 -> 163.85869 | J38: =+Assumptions!$I155*J$11 -> 164.13179 | K38: =+Assumptions!$I155*K$11 -> 164.40534 | L38: =+Assumptions!$I155*L$11 -> 164.67935 | ... EF38: =+Assumptions!$I155*EF$11 -> 202.45039
B39: =Assumptions!B156 -> Trash | E39: =+Assumptions!$I156*E$11 -> 200.33333 | F39: =+Assumptions!$I156*F$11 -> 200.66722 | G39: =+Assumptions!$I156*G$11 -> 201.00167 | H39: =+Assumptions!$I156*H$11 -> 201.33667 | I39: =+Assumptions!$I156*I$11 -> 201.67223 | J39: =+Assumptions!$I156*J$11 -> 202.00835 | K39: =+Assumptions!$I156*K$11 -> 202.34503 | L39: =+Assumptions!$I156*L$11 -> 202.68227 | ... EF39: =+Assumptions!$I156*EF$11 -> 249.16971
B40: =Assumptions!B157 -> Cleaning | E40: =+Assumptions!$I157*E$11 -> 976.625 | F40: =+Assumptions!$I157*F$11 -> 978.25271 | G40: =+Assumptions!$I157*G$11 -> 979.88313 | H40: =+Assumptions!$I157*H$11 -> 981.51627 | I40: =+Assumptions!$I157*I$11 -> 983.15213 | J40: =+Assumptions!$I157*J$11 -> 984.79072 | K40: =+Assumptions!$I157*K$11 -> 986.43203 | L40: =+Assumptions!$I157*L$11 -> 988.07609 | ... EF40: =+Assumptions!$I157*EF$11 -> 1214.7023
B41: =Assumptions!B158 -> Security, Internet | E41: =+Assumptions!$I158*E$11 -> 200.33333 | F41: =+Assumptions!$I158*F$11 -> 200.66722 | G41: =+Assumptions!$I158*G$11 -> 201.00167 | H41: =+Assumptions!$I158*H$11 -> 201.33667 | I41: =+Assumptions!$I158*I$11 -> 201.67223 | J41: =+Assumptions!$I158*J$11 -> 202.00835 | K41: =+Assumptions!$I158*K$11 -> 202.34503 | L41: =+Assumptions!$I158*L$11 -> 202.68227 | ... EF41: =+Assumptions!$I158*EF$11 -> 249.16971
B42: =Assumptions!B159 -> Pest Control | E42: =+Assumptions!$I159*E$11 -> 488.3125 | F42: =+Assumptions!$I159*F$11 -> 489.12635 | G42: =+Assumptions!$I159*G$11 -> 489.94156 | H42: =+Assumptions!$I159*H$11 -> 490.75813 | I42: =+Assumptions!$I159*I$11 -> 491.57606 | J42: =+Assumptions!$I159*J$11 -> 492.39536 | K42: =+Assumptions!$I159*K$11 -> 493.21602 | L42: =+Assumptions!$I159*L$11 -> 494.03804 | ... EF42: =+Assumptions!$I159*EF$11 -> 607.35117
B43: =Assumptions!B160 -> Super (Payroll) | E43: =+Assumptions!$I160*E$11 -> 3255.4167 | F43: =+Assumptions!$I160*F$11 -> 3260.8424 | G43: =+Assumptions!$I160*G$11 -> 3266.2771 | H43: =+Assumptions!$I160*H$11 -> 3271.7209 | I43: =+Assumptions!$I160*I$11 -> 3277.1738 | J43: =+Assumptions!$I160*J$11 -> 3282.6357 | K43: =+Assumptions!$I160*K$11 -> 3288.1068 | L43: =+Assumptions!$I160*L$11 -> 3293.587 | ... EF43: =+Assumptions!$I160*EF$11 -> 4049.0078
B44: =Assumptions!B161 -> Heat (Gas) | E44: =+Assumptions!$I161*E$11 -> 5624.6922 | F44: =+Assumptions!$I161*F$11 -> 5634.0667 | G44: =+Assumptions!$I161*G$11 -> 5643.4568 | H44: =+Assumptions!$I161*H$11 -> 5652.8626 | I44: =+Assumptions!$I161*I$11 -> 5662.284 | J44: =+Assumptions!$I161*J$11 -> 5671.7212 | K44: =+Assumptions!$I161*K$11 -> 5681.174 | L44: =+Assumptions!$I161*L$11 -> 5690.6427 | ... EF44: =+Assumptions!$I161*EF$11 -> 6995.8549
B45: =Assumptions!B162 -> Common Area Electric | E45: =+Assumptions!$I162*E$11 -> 282.47 | F45: =+Assumptions!$I162*F$11 -> 282.94078 | G45: =+Assumptions!$I162*G$11 -> 283.41235 | H45: =+Assumptions!$I162*H$11 -> 283.88471 | I45: =+Assumptions!$I162*I$11 -> 284.35785 | J45: =+Assumptions!$I162*J$11 -> 284.83178 | K45: =+Assumptions!$I162*K$11 -> 285.3065 | L45: =+Assumptions!$I162*L$11 -> 285.78201 | ... EF45: =+Assumptions!$I162*EF$11 -> 351.32929
B46: =Assumptions!B163 -> Landscaping / Snow Removal | E46: =+Assumptions!$I163*E$11 -> 1252.0833 | F46: =+Assumptions!$I163*F$11 -> 1254.1701 | G46: =+Assumptions!$I163*G$11 -> 1256.2604 | H46: =+Assumptions!$I163*H$11 -> 1258.3542 | I46: =+Assumptions!$I163*I$11 -> 1260.4514 | J46: =+Assumptions!$I163*J$11 -> 1262.5522 | K46: =+Assumptions!$I163*K$11 -> 1264.6565 | L46: =+Assumptions!$I163*L$11 -> 1266.7642 | ... EF46: =+Assumptions!$I163*EF$11 -> 1557.3107
B47: =Assumptions!B164 -> Property Management | E47: =+Assumptions!$G$164*E31 -> 3759.902 | F47: =+Assumptions!$G$164*F31 -> 3621.769 | G47: =+Assumptions!$G$164*G31 -> 3629.2129 | H47: =+Assumptions!$G$164*H31 -> 3551.4147 | I47: =+Assumptions!$G$164*I31 -> 3427.9415 | J47: =+Assumptions!$G$164*J31 -> 3562.9404 | K47: =+Assumptions!$G$164*K31 -> 3431.3219 | L47: =+Assumptions!$G$164*L31 -> 3498.735 | ... EF47: =+Assumptions!$G$164*EF31 -> 6771.241
B48: =Assumptions!B165 -> Accounting / Legal | E48: =+Assumptions!$I165*E$11 -> 292.15278 | F48: =+Assumptions!$I165*F$11 -> 292.6397 | G48: =+Assumptions!$I165*G$11 -> 293.12743 | H48: =+Assumptions!$I165*H$11 -> 293.61598 | I48: =+Assumptions!$I165*I$11 -> 294.10534 | J48: =+Assumptions!$I165*J$11 -> 294.59551 | K48: =+Assumptions!$I165*K$11 -> 295.08651 | L48: =+Assumptions!$I165*L$11 -> 295.57832 | ... EF48: =+Assumptions!$I165*EF$11 -> 363.3725
B49: =Assumptions!B166 -> Total Operating Expenses | E49: =SUM(E34:E48) -> 54431.214 | F49: =SUM(F34:F48) -> 54101.39 | G49: =SUM(G34:G48) -> 54192.967 | H49: =SUM(H34:H48) -> 54014.732 | I49: =SUM(I34:I48) -> 53697.839 | J49: =SUM(J34:J48) -> 54009.284 | K49: =SUM(K34:K48) -> 53683.291 | L49: =SUM(L34:L48) -> 53834.458 | ... EF49: =SUM(EF34:EF48) -> 69794.982
B51: Multifamily NOI | E51: =+E31-E49 -> 70898.852 | F51: =+F31-F49 -> 66624.242 | G51: =+G31-G49 -> 66780.797 | H51: =+H31-H49 -> 64365.759 | I51: =+I31-I49 -> 60566.879 | J51: =+J31-J49 -> 64755.397 | K51: =+K31-K49 -> 60694.106 | L51: =+L31-L49 -> 62790.043 | ... EF51: =+EF31-EF49 -> 155913.05
B52: NTM NOI | E52: =SUM(F51:Q51,F48:Q48) -> 801895.63 | F52: =SUM(G51:R51,G48:R48) -> 818076.18 | G52: =SUM(H51:S51,H48:S48) -> 836998.35 | H52: =SUM(I51:T51,I48:T48) -> 860332.89 | I52: =SUM(J51:U51,J48:U48) -> 887402.23 | J52: =SUM(K51:V51,K48:V48) -> 909813.35 | K52: =SUM(L51:W51,L48:W48) -> 936674.77 | L52: =SUM(M51:X51,M48:X48) -> 961466.33 | ... CJ52: =SUM(CK51:CV51,CK48:CV48) -> 1714971.6 | CK52: =SUM(CL51:EF51,CL48:EF48) -> 6992932.4 | CL52: =SUM(CM51:EG51,CM48:EG48) -> 6851401.5 | CM52: =SUM(CN51:EH51,CN48:EH48) -> 6709565.3 | CN52: =SUM(CO51:EI51,CO48:EI48) -> 6567423 | CO52: =SUM(CP51:EJ51,CP48:EJ48) -> 6424973.9 | CP52: =SUM(CQ51:EK51,CQ48:EK48) -> 6282217.4 | CQ52: =SUM(CR51:EL51,CR48:EL48) -> 6139153 | CR52: =SUM(CS51:EM51,CS48:EM48) -> 5995779.8 | ... EF52: =SUM(EG51:GA51,EG48:GA48) -> 0
B54: Capital Expenditures: Multifamily
B55: =+Assumptions!B169 -> Reserves | E55: =+Assumptions!$G$169*E31 -> 1253.3007 | F55: =+Assumptions!$G$169*F31 -> 1207.2563 | G55: =+Assumptions!$G$169*G31 -> 1209.7376 | H55: =+Assumptions!$G$169*H31 -> 1183.8049 | I55: =+Assumptions!$G$169*I31 -> 1142.6472 | J55: =+Assumptions!$G$169*J31 -> 1187.6468 | K55: =+Assumptions!$G$169*K31 -> 1143.774 | L55: =+Assumptions!$G$169*L31 -> 1166.245 | ... EF55: =+Assumptions!$G$169*EF31 -> 2257.0803
B56: Total Multifamily CapEx | E56: =SUM(E55:E55) -> 1253.3007 | F56: =SUM(F55:F55) -> 1207.2563 | G56: =SUM(G55:G55) -> 1209.7376 | H56: =SUM(H55:H55) -> 1183.8049 | I56: =SUM(I55:I55) -> 1142.6472 | J56: =SUM(J55:J55) -> 1187.6468 | K56: =SUM(K55:K55) -> 1143.774 | L56: =SUM(L55:L55) -> 1166.245 | ... EF56: =SUM(EF55:EF55) -> 2257.0803
B58: Retail NOI | E58: {=IFERROR(INDEX('Retail Assumptions'!$L$49:$EO$49,,MATCH(E15,'Retail Assumptions'!$L$5:$EO$5,0)),0)} -> 0 | F58: {=IFERROR(INDEX('Retail Assumptions'!$L$49:$EO$49,,MATCH(F15,'Retail Assumptions'!$L$5:$EO$5,0)),0)} -> 0 | G58: {=IFERROR(INDEX('Retail Assumptions'!$L$49:$EO$49,,MATCH(G15,'Retail Assumptions'!$L$5:$EO$5,0)),0)} -> 0 | H58: {=IFERROR(INDEX('Retail Assumptions'!$L$49:$EO$49,,MATCH(H15,'Retail Assumptions'!$L$5:$EO$5,0)),0)} -> 0 | I58: {=IFERROR(INDEX('Retail Assumptions'!$L$49:$EO$49,,MATCH(I15,'Retail Assumptions'!$L$5:$EO$5,0)),0)} -> 0 | J58: {=IFERROR(INDEX('Retail Assumptions'!$L$49:$EO$49,,MATCH(J15,'Retail Assumptions'!$L$5:$EO$5,0)),0)} -> 0 | K58: {=IFERROR(INDEX('Retail Assumptions'!$L$49:$EO$49,,MATCH(K15,'Retail Assumptions'!$L$5:$EO$5,0)),0)} -> 0 | L58: {=IFERROR(INDEX('Retail Assumptions'!$L$49:$EO$49,,MATCH(L15,'Retail Assumptions'!$L$5:$EO$5,0)),0)} -> 0 | ... EF58: {=IFERROR(INDEX('Retail Assumptions'!$L$49:$EO$49,,MATCH(EF15,'Retail Assumptions'!$L$5:$EO$5,0)),0)} -> 0
B59: NTM NOI | E59: =SUM(F58:Q58) -> 0 | F59: =SUM(G58:R58) -> 0 | G59: =SUM(H58:S58) -> 0 | H59: =SUM(I58:T58) -> 0 | I59: =SUM(J58:U58) -> 0 | J59: =SUM(K58:V58) -> 0 | K59: =SUM(L58:W58) -> 0 | L59: =SUM(M58:X58) -> 0 | ... CJ59: =SUM(CK58:CV58) -> 0 | CK59: =SUM(CL58:EF58) -> 0 | CL59: =SUM(CM58:EG58) -> 0 | CM59: =SUM(CN58:EH58) -> 0 | CN59: =SUM(CO58:EI58) -> 0 | CO59: =SUM(CP58:EJ58) -> 0 | CP59: =SUM(CQ58:EK58) -> 0 | CQ59: =SUM(CR58:EL58) -> 0 | CR59: =SUM(CS58:EM58) -> 0 | ... CU59: =SUM(CV58:EP58) -> 0 | CV59: =SUM(EG58:EQ58) -> 0 | CW59: =SUM(EG58:ER58) -> 0 | CX59: =SUM(EH58:ES58) -> 0 | CY59: =SUM(EI58:ET58) -> 0 | CZ59: =SUM(EJ58:EU58) -> 0 | DA59: =SUM(EK58:EV58) -> 0 | DB59: =SUM(EL58:EW58) -> 0 | DC59: =SUM(EM58:EX58) -> 0 | DD59: =SUM(EN58:EY58) -> 0 | ... EF59: =SUM(FP58:GA58) -> 0
B61: Capital Expenditures: Retail
B62: Total Retail Leasing Cost Reserves | E62: =(E58>0)*'Retail Assumptions'!$J$57/12*'NOI Walk'!E11 -> 0 | F62: =(F58>0)*'Retail Assumptions'!$J$57/12*'NOI Walk'!F11 -> 0 | G62: =(G58>0)*'Retail Assumptions'!$J$57/12*'NOI Walk'!G11 -> 0 | H62: =(H58>0)*'Retail Assumptions'!$J$57/12*'NOI Walk'!H11 -> 0 | I62: =(I58>0)*'Retail Assumptions'!$J$57/12*'NOI Walk'!I11 -> 0 | J62: =(J58>0)*'Retail Assumptions'!$J$57/12*'NOI Walk'!J11 -> 0 | K62: =(K58>0)*'Retail Assumptions'!$J$57/12*'NOI Walk'!K11 -> 0 | L62: =(L58>0)*'Retail Assumptions'!$J$57/12*'NOI Walk'!L11 -> 0 | ... EF62: =(EF58>0)*'Retail Assumptions'!$J$57/12*'NOI Walk'!EF11 -> 0
B64: Total Property NOI | E64: =+E58+E51-E56-E62 -> 69645.551 | F64: =+F58+F51-F56-F62 -> 65416.985 | G64: =+G58+G51-G56-G62 -> 65571.059 | H64: =+H58+H51-H56-H62 -> 63181.954 | I64: =+I58+I51-I56-I62 -> 59424.232 | J64: =+J58+J51-J56-J62 -> 63567.75 | K64: =+K58+K51-K56-K62 -> 59550.332 | L64: =+L58+L51-L56-L62 -> 61623.798 | ... EF64: =+EF58+EF51-EF56-EF62 -> 153655.97
B65: Total Property NTM NOI | E65: =SUM(F64:Q64) -> 783879.2 | F65: =SUM(G64:R64) -> 799882.39 | G65: =SUM(H64:S64) -> 818597.96 | H65: =SUM(I64:T64) -> 841678.48 | I65: =SUM(J64:U64) -> 868453.4 | J65: =SUM(K64:V64) -> 890620.02 | K65: =SUM(L64:W64) -> 917189.14 | L65: =SUM(M64:X64) -> 941710.7 | ... EF65: =SUM(EG64:ER64) -> 0

Sheet Debt Schedule
B2: =+Assumptions!B27 -> Acquisition Loan | M2: =Assumptions!B33 -> Permanent Loan
B3: =+Assumptions!B28 -> Origination | H3: =+Assumptions!G28 -> 0 | M3: =Assumptions!B35 -> Seasoning Period Post Stabilization | R3: =Assumptions!G35 -> 5
B4: =+Assumptions!I29 -> Rate | H4: =+Assumptions!L29 -> 0.075 | M4: =Assumptions!B36 -> Refinancing Month | R4: =Assumptions!G36 -> 36
B5: =+Assumptions!I30 -> Amortization | H5: =+Assumptions!L30 -> 30 | M5: =Assumptions!B37 -> Fixed Interest Rate | R5: =Assumptions!G37 -> 0.0570644
M6: =Assumptions!B39 -> Amortization | R6: =Assumptions!G39 -> 30
B7: Loan Constant | H7: =IF(H5=0,H4,PMT(H4/12,H5*12,-1)*12) -> 0.083905741 | M7: Loan Constant | R7: =PMT(R5/12,R6*12,-1)*12 -> 0.069697032
B8: Loan Size at Closing | H8: =+Assumptions!R30 -> 10430000 | M8: =Assumptions!I37 -> Max Perm. Loan | R8: =IF(Assumptions!G34="Yes",Assumptions!L37,0) -> 17127872
B11: Month | C11: Period | D11: Beg. Bal. | E11: Draws | F11: Principal | G11: Interest | H11: End. Bal. | M11: Month | N11: Period | O11: Beg. Bal. | P11: Principal | Q11: Interest | R11: End. Bal.
B12: =+Assumptions!G28 -> 0 | C12: 0 | H12: =+H8 -> 10430000 | M12: =+R4 -> 36 | N12: 0 | R12: =+R8 -> 17127872
B13: =+B12+1 -> 1 | C13: =+C12+1 -> 1 | D13: =IF(B13>Assumptions!$E$175,0,H12) -> 10430000 | E13: {=IFERROR(INDEX(Model!$G$40:$EI$40,,MATCH('Debt Schedule'!B13,Model!$G$4:$EI$4,0)),0)} -> -559509.63 | F13: =IF(AND(Assumptions!$G$34="Yes",'Debt Schedule'!B13>Assumptions!$G$36),0,IF(B13>Assumptions!$E$175,0,-IFERROR(PPMT($H$4/12,C13,$H$5*12,-$H$8),0))) -> -7740.5732 | G13: =IF(AND(Assumptions!$G$34="yes",'Debt Schedule'!B13>Assumptions!$G$36),0,IFERROR(IF(B13>Assumptions!$E$175,0,IPMT($H$4/12,C13,$H$5*12,-$H$8)),$H$4/12*D13)) -> 65187.5 | H13: =SUM(D13:F13) -> 9862749.8 | M13: =+M12+1 -> 37 | N13: =+N12+1 -> 1 | O13: =IF(M13>Assumptions!$E$175,0,R12) -> 17127872 | P13: =IF(M13>Assumptions!$E$175,0,-PPMT($R$5/12,N13,$R$6*12,-$R$8)) -> -18030.842 | Q13: =IF(M13>Assumptions!$E$175,0,-IPMT($R$5/12,N13,$R$6*12,-$R$8)) -> -81449.312 | R13: =+P13+O13 -> 17109841
B14: =+B13+1 -> 2 | C14: =+C13+1 -> 2 | D14: =IF(B14>Assumptions!$E$175,0,H13) -> 9862749.8 | E14: {=IFERROR(INDEX(Model!$G$40:$EI$40,,MATCH('Debt Schedule'!B14,Model!$G$4:$EI$4,0)),0)} -> 7740.5732 | F14: =IF(AND(Assumptions!$G$34="Yes",'Debt Schedule'!B14>Assumptions!$G$36),0,IF(B14>Assumptions!$E$175,0,-IFERROR(PPMT($H$4/12,C14,$H$5*12,-$H$8),0))) -> -7788.9518 | G14: =IF(AND(Assumptions!$G$34="yes",'Debt Schedule'!B14>Assumptions!$G$36),0,IFERROR(IF(B14>Assumptions!$E$175,0,IPMT($H$4/12,C14,$H$5*12,-$H$8)),$H$4/12*D14)) -> 65139.121 | H14: =SUM(D14:F14) -> 9862701.4 | M14: =+M13+1 -> 38 | N14: =+N13+1 -> 2 | O14: =IF(M14>Assumptions!$E$175,0,R13) -> 17109841 | P14: =IF(M14>Assumptions!$E$175,0,-PPMT($R$5/12,N14,$R$6*12,-$R$8)) -> -18116.585 | Q14: =IF(M14>Assumptions!$E$175,0,-IPMT($R$5/12,N14,$R$6*12,-$R$8)) -> -81363.569 | R14: =+P14+O14 -> 17091725
B15: =+B14+1 -> 3 | C15: =+C14+1 -> 3 | D15: =IF(B15>Assumptions!$E$175,0,H14) -> 9862701.4 | E15: {=IFERROR(INDEX(Model!$G$40:$EI$40,,MATCH('Debt Schedule'!B15,Model!$G$4:$EI$4,0)),0)} -> 7788.9518 | F15: =IF(AND(Assumptions!$G$34="Yes",'Debt Schedule'!B15>Assumptions!$G$36),0,IF(B15>Assumptions!$E$175,0,-IFERROR(PPMT($H$4/12,C15,$H$5*12,-$H$8),0))) -> -7837.6328 | G15: =IF(AND(Assumptions!$G$34="yes",'Debt Schedule'!B15>Assumptions!$G$36),0,IFERROR(IF(B15>Assumptions!$E$175,0,IPMT($H$4/12,C15,$H$5*12,-$H$8)),$H$4/12*D15)) -> 65090.44 | H15: =SUM(D15:F15) -> 9862652.7 | M15: =+M14+1 -> 39 | N15: =+N14+1 -> 3 | O15: =IF(M15>Assumptions!$E$175,0,R14) -> 17091725 | P15: =IF(M15>Assumptions!$E$175,0,-PPMT($R$5/12,N15,$R$6*12,-$R$8)) -> -18202.736 | Q15: =IF(M15>Assumptions!$E$175,0,-IPMT($R$5/12,N15,$R$6*12,-$R$8)) -> -81277.418 | R15: =+P15+O15 -> 17073522
B16: =+B15+1 -> 4 | C16: =+C15+1 -> 4 | D16: =IF(B16>Assumptions!$E$175,0,H15) -> 9862652.7 | E16: {=IFERROR(INDEX(Model!$G$40:$EI$40,,MATCH('Debt Schedule'!B16,Model!$G$4:$EI$4,0)),0)} -> 7837.6328 | F16: =IF(AND(Assumptions!$G$34="Yes",'Debt Schedule'!B16>Assumptions!$G$36),0,IF(B16>Assumptions!$E$175,0,-IFERROR(PPMT($H$4/12,C16,$H$5*12,-$H$8),0))) -> -7886.618 | G16: =IF(AND(Assumptions!$G$34="yes",'Debt Schedule'!B16>Assumptions!$G$36),0,IFERROR(IF(B16>Assumptions!$E$175,0,IPMT($H$4/12,C16,$H$5*12,-$H$8)),$H$4/12*D16)) -> 65041.455 | H16: =SUM(D16:F16) -> 9862603.8 | M16: =+M15+1 -> 40 | N16: =+N15+1 -> 4 | O16: =IF(M16>Assumptions!$E$175,0,R15) -> 17073522 | P16: =IF(M16>Assumptions!$E$175,0,-PPMT($R$5/12,N16,$R$6*12,-$R$8)) -> -18289.297 | Q16: =IF(M16>Assumptions!$E$175,0,-IPMT($R$5/12,N16,$R$6*12,-$R$8)) -> -81190.857 | R16: =+P16+O16 -> 17055233
B17: =+B16+1 -> 5 | C17: =+C16+1 -> 5 | D17: =IF(B17>Assumptions!$E$175,0,H16) -> 9862603.8 | E17: {=IFERROR(INDEX(Model!$G$40:$EI$40,,MATCH('Debt Schedule'!B17,Model!$G$4:$EI$4,0)),0)} -> 7886.618 | F17: =IF(AND(Assumptions!$G$34="Yes",'Debt Schedule'!B17>Assumptions!$G$36),0,IF(B17>Assumptions!$E$175,0,-IFERROR(PPMT($H$4/12,C17,$H$5*12,-$H$8),0))) -> -7935.9093 | G17: =IF(AND(Assumptions!$G$34="yes",'Debt Schedule'!B17>Assumptions!$G$36),0,IFERROR(IF(B17>Assumptions!$E$175,0,IPMT($H$4/12,C17,$H$5*12,-$H$8)),$H$4/12*D17)) -> 64992.164 | H17: =SUM(D17:F17) -> 9862554.5 | M17: =+M16+1 -> 41 | N17: =+N16+1 -> 5 | O17: =IF(M17>Assumptions!$E$175,0,R16) -> 17055233 | P17: =IF(M17>Assumptions!$E$175,0,-PPMT($R$5/12,N17,$R$6*12,-$R$8)) -> -18376.269 | Q17: =IF(M17>Assumptions!$E$175,0,-IPMT($R$5/12,N17,$R$6*12,-$R$8)) -> -81103.885 | R17: =+P17+O17 -> 17036856
B18: =+B17+1 -> 6 | C18: =+C17+1 -> 6 | D18: =IF(B18>Assumptions!$E$175,0,H17) -> 9862554.5 | E18: {=IFERROR(INDEX(Model!$G$40:$EI$40,,MATCH('Debt Schedule'!B18,Model!$G$4:$EI$4,0)),0)} -> 7935.9093 | F18: =IF(AND(Assumptions!$G$34="Yes",'Debt Schedule'!B18>Assumptions!$G$36),0,IF(B18>Assumptions!$E$175,0,-IFERROR(PPMT($H$4/12,C18,$H$5*12,-$H$8),0))) -> -7985.5088 | G18: =IF(AND(Assumptions!$G$34="yes",'Debt Schedule'!B18>Assumptions!$G$36),0,IFERROR(IF(B18>Assumptions!$E$175,0,IPMT($H$4/12,C18,$H$5*12,-$H$8)),$H$4/12*D18)) -> 64942.564 | H18: =SUM(D18:F18) -> 9862504.9 | M18: =+M17+1 -> 42 | N18: =+N17+1 -> 6 | O18: =IF(M18>Assumptions!$E$175,0,R17) -> 17036856 | P18: =IF(M18>Assumptions!$E$175,0,-PPMT($R$5/12,N18,$R$6*12,-$R$8)) -> -18463.655 | Q18: =IF(M18>Assumptions!$E$175,0,-IPMT($R$5/12,N18,$R$6*12,-$R$8)) -> -81016.499 | R18: =+P18+O18 -> 17018393
B19: =+B18+1 -> 7 | C19: =+C18+1 -> 7 | D19: =IF(B19>Assumptions!$E$175,0,H18) -> 9862504.9 | E19: {=IFERROR(INDEX(Model!$G$40:$EI$40,,MATCH('Debt Schedule'!B19,Model!$G$4:$EI$4,0)),0)} -> 7985.5088 | F19: =IF(AND(Assumptions!$G$34="Yes",'Debt Schedule'!B19>Assumptions!$G$36),0,IF(B19>Assumptions!$E$175,0,-IFERROR(PPMT($H$4/12,C19,$H$5*12,-$H$8),0))) -> -8035.4182 | G19: =IF(AND(Assumptions!$G$34="yes",'Debt Schedule'!B19>Assumptions!$G$36),0,IFERROR(IF(B19>Assumptions!$E$175,0,IPMT($H$4/12,C19,$H$5*12,-$H$8)),$H$4/12*D19)) -> 64892.655 | H19: =SUM(D19:F19) -> 9862455 | M19: =+M18+1 -> 43 | N19: =+N18+1 -> 7 | O19: =IF(M19>Assumptions!$E$175,0,R18) -> 17018393 | P19: =IF(M19>Assumptions!$E$175,0,-PPMT($R$5/12,N19,$R$6*12,-$R$8)) -> -18551.457 | Q19: =IF(M19>Assumptions!$E$175,0,-IPMT($R$5/12,N19,$R$6*12,-$R$8)) -> -80928.698 | R19: =+P19+O19 -> 16999841
B20: =+B19+1 -> 8 | C20: =+C19+1 -> 8 | D20: =IF(B20>Assumptions!$E$175,0,H19) -> 9862455 | E20: {=IFERROR(INDEX(Model!$G$40:$EI$40,,MATCH('Debt Schedule'!B20,Model!$G$4:$EI$4,0)),0)} -> 8035.4182 | F20: =IF(AND(Assumptions!$G$34="Yes",'Debt Schedule'!B20>Assumptions!$G$36),0,IF(B20>Assumptions!$E$175,0,-IFERROR(PPMT($H$4/12,C20,$H$5*12,-$H$8),0))) -> -8085.6396 | G20: =IF(AND(Assumptions!$G$34="yes",'Debt Schedule'!B20>Assumptions!$G$36),0,IFERROR(IF(B20>Assumptions!$E$175,0,IPMT($H$4/12,C20,$H$5*12,-$H$8)),$H$4/12*D20)) -> 64842.434 | H20: =SUM(D20:F20) -> 9862404.7 | M20: =+M19+1 -> 44 | N20: =+N19+1 -> 8 | O20: =IF(M20>Assumptions!$E$175,0,R19) -> 16999841 | P20: =IF(M20>Assumptions!$E$175,0,-PPMT($R$5/12,N20,$R$6*12,-$R$8)) -> -18639.676 | Q20: =IF(M20>Assumptions!$E$175,0,-IPMT($R$5/12,N20,$R$6*12,-$R$8)) -> -80840.479 | R20: =+P20+O20 -> 16981202
B21: =+B20+1 -> 9 | C21: =+C20+1 -> 9 | D21: =IF(B21>Assumptions!$E$175,0,H20) -> 9862404.7 | E21: {=IFERROR(INDEX(Model!$G$40:$EI$40,,MATCH('Debt Schedule'!B21,Model!$G$4:$EI$4,0)),0)} -> 8085.6396 | F21: =IF(AND(Assumptions!$G$34="Yes",'Debt Schedule'!B21>Assumptions!$G$36),0,IF(B21>Assumptions!$E$175,0,-IFERROR(PPMT($H$4/12,C21,$H$5*12,-$H$8),0))) -> -8136.1748 | G21: =IF(AND(Assumptions!$G$34="yes",'Debt Schedule'!B21>Assumptions!$G$36),0,IFERROR(IF(B21>Assumptions!$E$175,0,IPMT($H$4/12,C21,$H$5*12,-$H$8)),$H$4/12*D21)) -> 64791.898 | H21: =SUM(D21:F21) -> 9862354.2 | M21: =+M20+1 -> 45 | N21: =+N20+1 -> 9 | O21: =IF(M21>Assumptions!$E$175,0,R20) -> 16981202 | P21: =IF(M21>Assumptions!$E$175,0,-PPMT($R$5/12,N21,$R$6*12,-$R$8)) -> -18728.314 | Q21: =IF(M21>Assumptions!$E$175,0,-IPMT($R$5/12,N21,$R$6*12,-$R$8)) -> -80751.84 | R21: =+P21+O21 -> 16962473
B22: =+B21+1 -> 10 | C22: =+C21+1 -> 10 | D22: =IF(B22>Assumptions!$E$175,0,H21) -> 9862354.2 | E22: {=IFERROR(INDEX(Model!$G$40:$EI$40,,MATCH('Debt Schedule'!B22,Model!$G$4:$EI$4,0)),0)} -> 8136.1748 | F22: =IF(AND(Assumptions!$G$34="Yes",'Debt Schedule'!B22>Assumptions!$G$36),0,IF(B22>Assumptions!$E$175,0,-IFERROR(PPMT($H$4/12,C22,$H$5*12,-$H$8),0))) -> -8187.0259 | G22: =IF(AND(Assumptions!$G$34="yes",'Debt Schedule'!B22>Assumptions!$G$36),0,IFERROR(IF(B22>Assumptions!$E$175,0,IPMT($H$4/12,C22,$H$5*12,-$H$8)),$H$4/12*D22)) -> 64741.047 | H22: =SUM(D22:F22) -> 9862303.3 | M22: =+M21+1 -> 46 | N22: =+N21+1 -> 10 | O22: =IF(M22>Assumptions!$E$175,0,R21) -> 16962473 | P22: =IF(M22>Assumptions!$E$175,0,-PPMT($R$5/12,N22,$R$6*12,-$R$8)) -> -18817.374 | Q22: =IF(M22>Assumptions!$E$175,0,-IPMT($R$5/12,N22,$R$6*12,-$R$8)) -> -80662.78 | R22: =+P22+O22 -> 16943656
B23: =+B22+1 -> 11 | C23: =+C22+1 -> 11 | D23: =IF(B23>Assumptions!$E$175,0,H22) -> 9862303.3 | E23: {=IFERROR(INDEX(Model!$G$40:$EI$40,,MATCH('Debt Schedule'!B23,Model!$G$4:$EI$4,0)),0)} -> 8187.0259 | F23: =IF(AND(Assumptions!$G$34="Yes",'Debt Schedule'!B23>Assumptions!$G$36),0,IF(B23>Assumptions!$E$175,0,-IFERROR(PPMT($H$4/12,C23,$H$5*12,-$H$8),0))) -> -8238.1948 | G23: =IF(AND(Assumptions!$G$34="yes",'Debt Schedule'!B23>Assumptions!$G$36),0,IFERROR(IF(B23>Assumptions!$E$175,0,IPMT($H$4/12,C23,$H$5*12,-$H$8)),$H$4/12*D23)) -> 64689.878 | H23: =SUM(D23:F23) -> 9862252.2 | M23: =+M22+1 -> 47 | N23: =+N22+1 -> 11 | O23: =IF(M23>Assumptions!$E$175,0,R22) -> 16943656 | P23: =IF(M23>Assumptions!$E$175,0,-PPMT($R$5/12,N23,$R$6*12,-$R$8)) -> -18906.858 | Q23: =IF(M23>Assumptions!$E$175,0,-IPMT($R$5/12,N23,$R$6*12,-$R$8)) -> -80573.297 | R23: =+P23+O23 -> 16924749
B24: =+B23+1 -> 12 | C24: =+C23+1 -> 12 | D24: =IF(B24>Assumptions!$E$175,0,H23) -> 9862252.2 | E24: {=IFERROR(INDEX(Model!$G$40:$EI$40,,MATCH('Debt Schedule'!B24,Model!$G$4:$EI$4,0)),0)} -> 8238.1948 | F24: =IF(AND(Assumptions!$G$34="Yes",'Debt Schedule'!B24>Assumptions!$G$36),0,IF(B24>Assumptions!$E$175,0,-IFERROR(PPMT($H$4/12,C24,$H$5*12,-$H$8),0))) -> -8289.6835 | G24: =IF(AND(Assumptions!$G$34="yes",'Debt Schedule'!B24>Assumptions!$G$36),0,IFERROR(IF(B24>Assumptions!$E$175,0,IPMT($H$4/12,C24,$H$5*12,-$H$8)),$H$4/12*D24)) -> 64638.39 | H24: =SUM(D24:F24) -> 9862200.7 | M24: =+M23+1 -> 48 | N24: =+N23+1 -> 12 | O24: =IF(M24>Assumptions!$E$175,0,R23) -> 16924749 | P24: =IF(M24>Assumptions!$E$175,0,-PPMT($R$5/12,N24,$R$6*12,-$R$8)) -> -18996.767 | Q24: =IF(M24>Assumptions!$E$175,0,-IPMT($R$5/12,N24,$R$6*12,-$R$8)) -> -80483.388 | R24: =+P24+O24 -> 16905752
... B108: =+B107+1 -> 96 | C108: =+C107+1 -> 96 | D108: =IF(B108>Assumptions!$E$175,0,H107) -> 0 | E108: {=IFERROR(INDEX(Model!$G$40:$EI$40,,MATCH('Debt Schedule'!B108,Model!$G$4:$EI$4,0)),0)} -> 0 | F108: =IF(AND(Assumptions!$G$34="Yes",'Debt Schedule'!B108>Assumptions!$G$36),0,IF(B108>Assumptions!$E$175,0,-IFERROR(PPMT($H$4/12,C108,$H$5*12,-$H$8),0))) -> 0 | G108: =IF(AND(Assumptions!$G$34="yes",'Debt Schedule'!B108>Assumptions!$G$36),0,IFERROR(IF(B108>Assumptions!$E$175,0,IPMT($H$4/12,C108,$H$5*12,-$H$8)),$H$4/12*D108)) -> 0 | H108: =SUM(D108:F108) -> 0 | M108: =+M107+1 -> 132 | N108: =+N107+1 -> 96 | O108: =IF(M108>Assumptions!$E$175,0,R107) -> 0 | P108: =IF(M108>Assumptions!$E$175,0,-PPMT($R$5/12,N108,$R$6*12,-$R$8)) -> 0 | Q108: =IF(M108>Assumptions!$E$175,0,-IPMT($R$5/12,N108,$R$6*12,-$R$8)) -> 0 | R108: =+P108+O108 -> 0

Sheet Retail Assumptions
L3: =+EOMONTH(Assumptions!F2,'Retail Assumptions'!L5) -> 45838 | M3: =+EOMONTH(L3,1) -> 45869 | N3: =+EOMONTH(M3,1) -> 45900 | O3: =+EOMONTH(N3,1) -> 45930 | P3: =+EOMONTH(O3,1) -> 45961 | Q3: =+EOMONTH(P3,1) -> 45991 | R3: =+EOMONTH(Q3,1) -> 46022 | S3: =+EOMONTH(R3,1) -> 46053 | T3: =+EOMONTH(S3,1) -> 46081 | ... EO3: =+EOMONTH(EN3,1) -> 49887
B4: Base Retail Income | L4: =ROUNDUP(L5/12,0) -> 0 | M4: =ROUNDUP(M5/12,0) -> 1 | N4: =ROUNDUP(N5/12,0) -> 1 | O4: =ROUNDUP(O5/12,0) -> 1 | P4: =ROUNDUP(P5/12,0) -> 1 | Q4: =ROUNDUP(Q5/12,0) -> 1 | R4: =ROUNDUP(R5/12,0) -> 1 | S4: =ROUNDUP(S5/12,0) -> 1 | ... EO4: =ROUNDUP(EO5/12,0) -> 12
B5: Suite | C5: Tenant | E5: Lease Start | F5: SF | G5: Rent Start | H5: Annual Bumps | I5: Rent / SF / Yr. | J5: Annual Rent (Yr. 1) | L5: =+G19 -> 0 | M5: =+L5+1 -> 1 | N5: =+M5+1 -> 2 | O5: =+N5+1 -> 3 | P5: =+O5+1 -> 4 | Q5: =+P5+1 -> 5 | R5: =+Q5+1 -> 6 | S5: =+R5+1 -> 7 | T5: =+S5+1 -> 8 | ... EO5: =+EN5+1 -> 133
B6: 100 | C6: Commercial Tenant | E6: 1 | F6: 0 | G6: 1 | H6: 0.01 | I6: 0 | J6: =+I6*F6 -> 0 | L6: =($G6<=L$5)*($J6/12)*(1+$H6)^(ROUNDUP(MAX(L$5-$G6+1,0)/12,0)-1) -> 0 | M6: =($G6<=M$5)*($J6/12)*(1+$H6)^(ROUNDUP(MAX(M$5-$G6+1,0)/12,0)-1) -> 0 | N6: =($G6<=N$5)*($J6/12)*(1+$H6)^(ROUNDUP(MAX(N$5-$G6+1,0)/12,0)-1) -> 0 | O6: =($G6<=O$5)*($J6/12)*(1+$H6)^(ROUNDUP(MAX(O$5-$G6+1,0)/12,0)-1) -> 0 | P6: =($G6<=P$5)*($J6/12)*(1+$H6)^(ROUNDUP(MAX(P$5-$G6+1,0)/12,0)-1) -> 0 | Q6: =($G6<=Q$5)*($J6/12)*(1+$H6)^(ROUNDUP(MAX(Q$5-$G6+1,0)/12,0)-1) -> 0 | R6: =($G6<=R$5)*($J6/12)*(1+$H6)^(ROUNDUP(MAX(R$5-$G6+1,0)/12,0)-1) -> 0 | S6: =($G6<=S$5)*($J6/12)*(1+$H6)^(ROUNDUP(MAX(S$5-$G6+1,0)/12,0)-1) -> 0 | ... EO6: =($G6<=EO$5)*($J6/12)*(1+$H6)^(ROUNDUP(MAX(EO$5-$G6+1,0)/12,0)-1) -> 0
B7: =+B6+100 -> 200 | C7: [Retail Tenant] | E7: 1 | F7: 0 | G7: 0 | H7: 0.01 | I7: 0 | J7: =+I7*F7 -> 0 | L7: =($G7<=L$5)*($J7/12)*(1+$H7)^(ROUNDUP(MAX(L$5-$G7+1,0)/12,0)-1) -> 0 | M7: =($G7<=M$5)*($J7/12)*(1+$H7)^(ROUNDUP(MAX(M$5-$G7+1,0)/12,0)-1) -> 0 | N7: =($G7<=N$5)*($J7/12)*(1+$H7)^(ROUNDUP(MAX(N$5-$G7+1,0)/12,0)-1) -> 0 | O7: =($G7<=O$5)*($J7/12)*(1+$H7)^(ROUNDUP(MAX(O$5-$G7+1,0)/12,0)-1) -> 0 | P7: =($G7<=P$5)*($J7/12)*(1+$H7)^(ROUNDUP(MAX(P$5-$G7+1,0)/12,0)-1) -> 0 | Q7: =($G7<=Q$5)*($J7/12)*(1+$H7)^(ROUNDUP(MAX(Q$5-$G7+1,0)/12,0)-1) -> 0 | R7: =($G7<=R$5)*($J7/12)*(1+$H7)^(ROUNDUP(MAX(R$5-$G7+1,0)/12,0)-1) -> 0 | S7: =($G7<=S$5)*($J7/12)*(1+$H7)^(ROUNDUP(MAX(S$5-$G7+1,0)/12,0)-1) -> 0 | ... EO7: =($G7<=EO$5)*($J7/12)*(1+$H7)^(ROUNDUP(MAX(EO$5-$G7+1,0)/12,0)-1) -> 0
B8: =+B7+100 -> 300 | C8: [Retail Tenant] | E8: 1 | F8: 0 | G8: 0 | H8: 0.01 | I8: 0 | J8: =+I8*F8 -> 0 | L8: =($G8<=L$5)*($J8/12)*(1+$H8)^(ROUNDUP(MAX(L$5-$G8+1,0)/12,0)-1) -> 0 | M8: =($G8<=M$5)*($J8/12)*(1+$H8)^(ROUNDUP(MAX(M$5-$G8+1,0)/12,0)-1) -> 0 | N8: =($G8<=N$5)*($J8/12)*(1+$H8)^(ROUNDUP(MAX(N$5-$G8+1,0)/12,0)-1) -> 0 | O8: =($G8<=O$5)*($J8/12)*(1+$H8)^(ROUNDUP(MAX(O$5-$G8+1,0)/12,0)-1) -> 0 | P8: =($G8<=P$5)*($J8/12)*(1+$H8)^(ROUNDUP(MAX(P$5-$G8+1,0)/12,0)-1) -> 0 | Q8: =($G8<=Q$5)*($J8/12)*(1+$H8)^(ROUNDUP(MAX(Q$5-$G8+1,0)/12,0)-1) -> 0 | R8: =($G8<=R$5)*($J8/12)*(1+$H8)^(ROUNDUP(MAX(R$5-$G8+1,0)/12,0)-1) -> 0 | S8: =($G8<=S$5)*($J8/12)*(1+$H8)^(ROUNDUP(MAX(S$5-$G8+1,0)/12,0)-1) -> 0 | ... EO8: =($G8<=EO$5)*($J8/12)*(1+$H8)^(ROUNDUP(MAX(EO$5-$G8+1,0)/12,0)-1) -> 0
B9: =+B8+100 -> 400 | C9: [Retail Tenant] | E9: 1 | F9: 0 | G9: 0 | H9: 0.01 | I9: 0 | J9: =+I9*F9 -> 0 | L9: =($G9<=L$5)*($J9/12)*(1+$H9)^(ROUNDUP(MAX(L$5-$G9+1,0)/12,0)-1) -> 0 | M9: =($G9<=M$5)*($J9/12)*(1+$H9)^(ROUNDUP(MAX(M$5-$G9+1,0)/12,0)-1) -> 0 | N9: =($G9<=N$5)*($J9/12)*(1+$H9)^(ROUNDUP(MAX(N$5-$G9+1,0)/12,0)-1) -> 0 | O9: =($G9<=O$5)*($J9/12)*(1+$H9)^(ROUNDUP(MAX(O$5-$G9+1,0)/12,0)-1) -> 0 | P9: =($G9<=P$5)*($J9/12)*(1+$H9)^(ROUNDUP(MAX(P$5-$G9+1,0)/12,0)-1) -> 0 | Q9: =($G9<=Q$5)*($J9/12)*(1+$H9)^(ROUNDUP(MAX(Q$5-$G9+1,0)/12,0)-1) -> 0 | R9: =($G9<=R$5)*($J9/12)*(1+$H9)^(ROUNDUP(MAX(R$5-$G9+1,0)/12,0)-1) -> 0 | S9: =($G9<=S$5)*($J9/12)*(1+$H9)^(ROUNDUP(MAX(S$5-$G9+1,0)/12,0)-1) -> 0 | ... EO9: =($G9<=EO$5)*($J9/12)*(1+$H9)^(ROUNDUP(MAX(EO$5-$G9+1,0)/12,0)-1) -> 0
B10: =+B9+100 -> 500 | C10: [Retail Tenant] | E10: 1 | F10: 0 | G10: 0 | H10: 0.01 | I10: 0 | J10: =+I10*F10 -> 0 | L10: =($G10<=L$5)*($J10/12)*(1+$H10)^(ROUNDUP(MAX(L$5-$G10+1,0)/12,0)-1) -> 0 | M10: =($G10<=M$5)*($J10/12)*(1+$H10)^(ROUNDUP(MAX(M$5-$G10+1,0)/12,0)-1) -> 0 | N10: =($G10<=N$5)*($J10/12)*(1+$H10)^(ROUNDUP(MAX(N$5-$G10+1,0)/12,0)-1) -> 0 | O10: =($G10<=O$5)*($J10/12)*(1+$H10)^(ROUNDUP(MAX(O$5-$G10+1,0)/12,0)-1) -> 0 | P10: =($G10<=P$5)*($J10/12)*(1+$H10)^(ROUNDUP(MAX(P$5-$G10+1,0)/12,0)-1) -> 0 | Q10: =($G10<=Q$5)*($J10/12)*(1+$H10)^(ROUNDUP(MAX(Q$5-$G10+1,0)/12,0)-1) -> 0 | R10: =($G10<=R$5)*($J10/12)*(1+$H10)^(ROUNDUP(MAX(R$5-$G10+1,0)/12,0)-1) -> 0 | S10: =($G10<=S$5)*($J10/12)*(1+$H10)^(ROUNDUP(MAX(S$5-$G10+1,0)/12,0)-1) -> 0 | ... EO10: =($G10<=EO$5)*($J10/12)*(1+$H10)^(ROUNDUP(MAX(EO$5-$G10+1,0)/12,0)-1) -> 0
B11: =+B10+100 -> 600 | C11: [Retail Tenant] | E11: 1 | F11: 0 | G11: 0 | H11: 0.01 | I11: 0 | J11: =+I11*F11 -> 0 | L11: =($G11<=L$5)*($J11/12)*(1+$H11)^(ROUNDUP(MAX(L$5-$G11+1,0)/12,0)-1) -> 0 | M11: =($G11<=M$5)*($J11/12)*(1+$H11)^(ROUNDUP(MAX(M$5-$G11+1,0)/12,0)-1) -> 0 | N11: =($G11<=N$5)*($J11/12)*(1+$H11)^(ROUNDUP(MAX(N$5-$G11+1,0)/12,0)-1) -> 0 | O11: =($G11<=O$5)*($J11/12)*(1+$H11)^(ROUNDUP(MAX(O$5-$G11+1,0)/12,0)-1) -> 0 | P11: =($G11<=P$5)*($J11/12)*(1+$H11)^(ROUNDUP(MAX(P$5-$G11+1,0)/12,0)-1) -> 0 | Q11: =($G11<=Q$5)*($J11/12)*(1+$H11)^(ROUNDUP(MAX(Q$5-$G11+1,0)/12,0)-1) -> 0 | R11: =($G11<=R$5)*($J11/12)*(1+$H11)^(ROUNDUP(MAX(R$5-$G11+1,0)/12,0)-1) -> 0 | S11: =($G11<=S$5)*($J11/12)*(1+$H11)^(ROUNDUP(MAX(S$5-$G11+1,0)/12,0)-1) -> 0 | ... EO11: =($G11<=EO$5)*($J11/12)*(1+$H11)^(ROUNDUP(MAX(EO$5-$G11+1,0)/12,0)-1) -> 0
B12: =+B11+100 -> 700 | C12: [Retail Tenant] | E12: 1 | F12: 0 | G12: 0 | H12: 0.01 | I12: 0 | J12: =+I12*F12 -> 0 | L12: =($G12<=L$5)*($J12/12)*(1+$H12)^(ROUNDUP(MAX(L$5-$G12+1,0)/12,0)-1) -> 0 | M12: =($G12<=M$5)*($J12/12)*(1+$H12)^(ROUNDUP(MAX(M$5-$G12+1,0)/12,0)-1) -> 0 | N12: =($G12<=N$5)*($J12/12)*(1+$H12)^(ROUNDUP(MAX(N$5-$G12+1,0)/12,0)-1) -> 0 | O12: =($G12<=O$5)*($J12/12)*(1+$H12)^(ROUNDUP(MAX(O$5-$G12+1,0)/12,0)-1) -> 0 | P12: =($G12<=P$5)*($J12/12)*(1+$H12)^(ROUNDUP(MAX(P$5-$G12+1,0)/12,0)-1) -> 0 | Q12: =($G12<=Q$5)*($J12/12)*(1+$H12)^(ROUNDUP(MAX(Q$5-$G12+1,0)/12,0)-1) -> 0 | R12: =($G12<=R$5)*($J12/12)*(1+$H12)^(ROUNDUP(MAX(R$5-$G12+1,0)/12,0)-1) -> 0 | S12: =($G12<=S$5)*($J12/12)*(1+$H12)^(ROUNDUP(MAX(S$5-$G12+1,0)/12,0)-1) -> 0 | ... EO12: =($G12<=EO$5)*($J12/12)*(1+$H12)^(ROUNDUP(MAX(EO$5-$G12+1,0)/12,0)-1) -> 0
B13: =+B12+100 -> 800 | C13: [Retail Tenant] | E13: 1 | F13: 0 | G13: 0 | H13: 0.01 | I13: 0 | J13: =+I13*F13 -> 0 | L13: =($G13<=L$5)*($J13/12)*(1+$H13)^(ROUNDUP(MAX(L$5-$G13+1,0)/12,0)-1) -> 0 | M13: =($G13<=M$5)*($J13/12)*(1+$H13)^(ROUNDUP(MAX(M$5-$G13+1,0)/12,0)-1) -> 0 | N13: =($G13<=N$5)*($J13/12)*(1+$H13)^(ROUNDUP(MAX(N$5-$G13+1,0)/12,0)-1) -> 0 | O13: =($G13<=O$5)*($J13/12)*(1+$H13)^(ROUNDUP(MAX(O$5-$G13+1,0)/12,0)-1) -> 0 | P13: =($G13<=P$5)*($J13/12)*(1+$H13)^(ROUNDUP(MAX(P$5-$G13+1,0)/12,0)-1) -> 0 | Q13: =($G13<=Q$5)*($J13/12)*(1+$H13)^(ROUNDUP(MAX(Q$5-$G13+1,0)/12,0)-1) -> 0 | R13: =($G13<=R$5)*($J13/12)*(1+$H13)^(ROUNDUP(MAX(R$5-$G13+1,0)/12,0)-1) -> 0 | S13: =($G13<=S$5)*($J13/12)*(1+$H13)^(ROUNDUP(MAX(S$5-$G13+1,0)/12,0)-1) -> 0 | ... EO13: =($G13<=EO$5)*($J13/12)*(1+$H13)^(ROUNDUP(MAX(EO$5-$G13+1,0)/12,0)-1) -> 0
B14: =+B13+100 -> 900 | C14: [Retail Tenant] | E14: 1 | F14: 0 | G14: 0 | H14: 0.01 | I14: 0 | J14: =+I14*F14 -> 0 | L14: =($G14<=L$5)*($J14/12)*(1+$H14)^(ROUNDUP(MAX(L$5-$G14+1,0)/12,0)-1) -> 0 | M14: =($G14<=M$5)*($J14/12)*(1+$H14)^(ROUNDUP(MAX(M$5-$G14+1,0)/12,0)-1) -> 0 | N14: =($G14<=N$5)*($J14/12)*(1+$H14)^(ROUNDUP(MAX(N$5-$G14+1,0)/12,0)-1) -> 0 | O14: =($G14<=O$5)*($J14/12)*(1+$H14)^(ROUNDUP(MAX(O$5-$G14+1,0)/12,0)-1) -> 0 | P14: =($G14<=P$5)*($J14/12)*(1+$H14)^(ROUNDUP(MAX(P$5-$G14+1,0)/12,0)-1) -> 0 | Q14: =($G14<=Q$5)*($J14/12)*(1+$H14)^(ROUNDUP(MAX(Q$5-$G14+1,0)/12,0)-1) -> 0 | R14: =($G14<=R$5)*($J14/12)*(1+$H14)^(ROUNDUP(MAX(R$5-$G14+1,0)/12,0)-1) -> 0 | S14: =($G14<=S$5)*($J14/12)*(1+$H14)^(ROUNDUP(MAX(S$5-$G14+1,0)/12,0)-1) -> 0 | ... EO14: =($G14<=EO$5)*($J14/12)*(1+$H14)^(ROUNDUP(MAX(EO$5-$G14+1,0)/12,0)-1) -> 0
B15: =+B14+100 -> 1000 | C15: [Retail Tenant] | E15: 1 | F15: 0 | G15: 0 | H15: 0.01 | I15: 0 | J15: =+I15*F15 -> 0 | L15: =($G15<=L$5)*($J15/12)*(1+$H15)^(ROUNDUP(MAX(L$5-$G15+1,0)/12,0)-1) -> 0 | M15: =($G15<=M$5)*($J15/12)*(1+$H15)^(ROUNDUP(MAX(M$5-$G15+1,0)/12,0)-1) -> 0 | N15: =($G15<=N$5)*($J15/12)*(1+$H15)^(ROUNDUP(MAX(N$5-$G15+1,0)/12,0)-1) -> 0 | O15: =($G15<=O$5)*($J15/12)*(1+$H15)^(ROUNDUP(MAX(O$5-$G15+1,0)/12,0)-1) -> 0 | P15: =($G15<=P$5)*($J15/12)*(1+$H15)^(ROUNDUP(MAX(P$5-$G15+1,0)/12,0)-1) -> 0 | Q15: =($G15<=Q$5)*($J15/12)*(1+$H15)^(ROUNDUP(MAX(Q$5-$G15+1,0)/12,0)-1) -> 0 | R15: =($G15<=R$5)*($J15/12)*(1+$H15)^(ROUNDUP(MAX(R$5-$G15+1,0)/12,0)-1) -> 0 | S15: =($G15<=S$5)*($J15/12)*(1+$H15)^(ROUNDUP(MAX(S$5-$G15+1,0)/12,0)-1) -> 0 | ... EO15: =($G15<=EO$5)*($J15/12)*(1+$H15)^(ROUNDUP(MAX(EO$5-$G15+1,0)/12,0)-1) -> 0
B16: =+B15+100 -> 1100 | C16: [Retail Tenant] | E16: 1 | F16: 0 | G16: 0 | H16: 0.01 | I16: 0 | J16: =+I16*F16 -> 0 | L16: =($G16<=L$5)*($J16/12)*(1+$H16)^(ROUNDUP(MAX(L$5-$G16+1,0)/12,0)-1) -> 0 | M16: =($G16<=M$5)*($J16/12)*(1+$H16)^(ROUNDUP(MAX(M$5-$G16+1,0)/12,0)-1) -> 0 | N16: =($G16<=N$5)*($J16/12)*(1+$H16)^(ROUNDUP(MAX(N$5-$G16+1,0)/12,0)-1) -> 0 | O16: =($G16<=O$5)*($J16/12)*(1+$H16)^(ROUNDUP(MAX(O$5-$G16+1,0)/12,0)-1) -> 0 | P16: =($G16<=P$5)*($J16/12)*(1+$H16)^(ROUNDUP(MAX(P$5-$G16+1,0)/12,0)-1) -> 0 | Q16: =($G16<=Q$5)*($J16/12)*(1+$H16)^(ROUNDUP(MAX(Q$5-$G16+1,0)/12,0)-1) -> 0 | R16: =($G16<=R$5)*($J16/12)*(1+$H16)^(ROUNDUP(MAX(R$5-$G16+1,0)/12,0)-1) -> 0 | S16: =($G16<=S$5)*($J16/12)*(1+$H16)^(ROUNDUP(MAX(S$5-$G16+1,0)/12,0)-1) -> 0 | ... EO16: =($G16<=EO$5)*($J16/12)*(1+$H16)^(ROUNDUP(MAX(EO$5-$G16+1,0)/12,0)-1) -> 0
B17: =+B16+100 -> 1200 | C17: [Retail Tenant] | E17: 1 | F17: 0 | G17: 0 | H17: 0.01 | I17: 0 | J17: =+I17*F17 -> 0 | L17: =($G17<=L$5)*($J17/12)*(1+$H17)^(ROUNDUP(MAX(L$5-$G17+1,0)/12,0)-1) -> 0 | M17: =($G17<=M$5)*($J17/12)*(1+$H17)^(ROUNDUP(MAX(M$5-$G17+1,0)/12,0)-1) -> 0 | N17: =($G17<=N$5)*($J17/12)*(1+$H17)^(ROUNDUP(MAX(N$5-$G17+1,0)/12,0)-1) -> 0 | O17: =($G17<=O$5)*($J17/12)*(1+$H17)^(ROUNDUP(MAX(O$5-$G17+1,0)/12,0)-1) -> 0 | P17: =($G17<=P$5)*($J17/12)*(1+$H17)^(ROUNDUP(MAX(P$5-$G17+1,0)/12,0)-1) -> 0 | Q17: =($G17<=Q$5)*($J17/12)*(1+$H17)^(ROUNDUP(MAX(Q$5-$G17+1,0)/12,0)-1) -> 0 | R17: =($G17<=R$5)*($J17/12)*(1+$H17)^(ROUNDUP(MAX(R$5-$G17+1,0)/12,0)-1) -> 0 | S17: =($G17<=S$5)*($J17/12)*(1+$H17)^(ROUNDUP(MAX(S$5-$G17+1,0)/12,0)-1) -> 0 | ... EO17: =($G17<=EO$5)*($J17/12)*(1+$H17)^(ROUNDUP(MAX(EO$5-$G17+1,0)/12,0)-1) -> 0
B18: =+B17+100 -> 1300 | C18: [Retail Tenant] | E18: 1 | F18: 0 | G18: 0 | H18: 0.01 | I18: 0 | J18: =+I18*F18 -> 0 | L18: =($G18<=L$5)*($J18/12)*(1+$H18)^(ROUNDUP(MAX(L$5-$G18+1,0)/12,0)-1) -> 0 | M18: =($G18<=M$5)*($J18/12)*(1+$H18)^(ROUNDUP(MAX(M$5-$G18+1,0)/12,0)-1) -> 0 | N18: =($G18<=N$5)*($J18/12)*(1+$H18)^(ROUNDUP(MAX(N$5-$G18+1,0)/12,0)-1) -> 0 | O18: =($G18<=O$5)*($J18/12)*(1+$H18)^(ROUNDUP(MAX(O$5-$G18+1,0)/12,0)-1) -> 0 | P18: =($G18<=P$5)*($J18/12)*(1+$H18)^(ROUNDUP(MAX(P$5-$G18+1,0)/12,0)-1) -> 0 | Q18: =($G18<=Q$5)*($J18/12)*(1+$H18)^(ROUNDUP(MAX(Q$5-$G18+1,0)/12,0)-1) -> 0 | R18: =($G18<=R$5)*($J18/12)*(1+$H18)^(ROUNDUP(MAX(R$5-$G18+1,0)/12,0)-1) -> 0 | S18: =($G18<=S$5)*($J18/12)*(1+$H18)^(ROUNDUP(MAX(S$5-$G18+1,0)/12,0)-1) -> 0 | ... EO18: =($G18<=EO$5)*($J18/12)*(1+$H18)^(ROUNDUP(MAX(EO$5-$G18+1,0)/12,0)-1) -> 0
B19: Total Base Retail Income | E19: =MIN(E6:E18) -> 1 | F19: =SUM(F6:F18) -> 0 | G19: =MIN(G6:G18) -> 0 | H19: =IFERROR(SUMPRODUCT(H6:H18,J6:J18)/J19,0) -> 0 | I19: =IFERROR(SUMPRODUCT(I6:I18,F6:F18)/F19,0) -> 0 | J19: =SUM(J6:J18) -> 0 | L19: =SUM(L6:L18) -> 0 | M19: =SUM(M6:M18) -> 0 | N19: =SUM(N6:N18) -> 0 | O19: =SUM(O6:O18) -> 0 | P19: =SUM(P6:P18) -> 0 | Q19: =SUM(Q6:Q18) -> 0 | R19: =SUM(R6:R18) -> 0 | S19: =SUM(S6:S18) -> 0 | ... EO19: =SUM(EO6:EO18) -> 0
K20: Occ. | L20: =IFERROR(SUMIF($E$6:$E$18,"<="&L5,$F$6:$F$18)/$F$19,0) -> 0 | M20: =IFERROR(SUMIF($E$6:$E$18,"<="&M5,$F$6:$F$18)/$F$19,0) -> 0 | N20: =IFERROR(SUMIF($E$6:$E$18,"<="&N5,$F$6:$F$18)/$F$19,0) -> 0 | O20: =IFERROR(SUMIF($E$6:$E$18,"<="&O5,$F$6:$F$18)/$F$19,0) -> 0 | P20: =IFERROR(SUMIF($E$6:$E$18,"<="&P5,$F$6:$F$18)/$F$19,0) -> 0 | Q20: =IFERROR(SUMIF($E$6:$E$18,"<="&Q5,$F$6:$F$18)/$F$19,0) -> 0 | R20: =IFERROR(SUMIF($E$6:$E$18,"<="&R5,$F$6:$F$18)/$F$19,0) -> 0 | S20: =IFERROR(SUMIF($E$6:$E$18,"<="&S5,$F$6:$F$18)/$F$19,0) -> 0 | ... EO20: =IFERROR(SUMIF($E$6:$E$18,"<="&EO5,$F$6:$F$18)/$F$19,0) -> 0
B21: Recovery Income
B22: =+B5 -> Suite | C22: =+C5 -> Tenant | F22: Recovery Start | H22: Pro Rata Share | I22: Rec. / SF / Yr. | J22: Annual Recovery
B23: =+B6 -> 100 | C23: =+C6 -> Commercial Tenant | F23: 1 | H23: =IFERROR(F6/$F$19,0) -> 0 | I23: =IFERROR(J23/F6,0) -> 0 | J23: =+H23*$J$47 -> 0 | L23: =IFERROR((L$5>=$F23)*$H23*L$47,0) -> 0 | M23: =IFERROR((M$5>=$F23)*$H23*M$47,0) -> 0 | N23: =IFERROR((N$5>=$F23)*$H23*N$47,0) -> 0 | O23: =IFERROR((O$5>=$F23)*$H23*O$47,0) -> 0 | P23: =IFERROR((P$5>=$F23)*$H23*P$47,0) -> 0 | Q23: =IFERROR((Q$5>=$F23)*$H23*Q$47,0) -> 0 | R23: =IFERROR((R$5>=$F23)*$H23*R$47,0) -> 0 | S23: =IFERROR((S$5>=$F23)*$H23*S$47,0) -> 0 | ... EO23: =IFERROR((EO$5>=$F23)*$H23*EO$47,0) -> 0
B24: =+B7 -> 200 | C24: =+C7 -> [Retail Tenant] | F24: 24 | H24: =IFERROR(F7/$F$19,0) -> 0 | I24: =IFERROR(J24/F7,0) -> 0 | J24: =+H24*$J$47 -> 0 | L24: =IFERROR((L$5>=$F24)*$H24*L$47,0) -> 0 | M24: =IFERROR((M$5>=$F24)*$H24*M$47,0) -> 0 | N24: =IFERROR((N$5>=$F24)*$H24*N$47,0) -> 0 | O24: =IFERROR((O$5>=$F24)*$H24*O$47,0) -> 0 | P24: =IFERROR((P$5>=$F24)*$H24*P$47,0) -> 0 | Q24: =IFERROR((Q$5>=$F24)*$H24*Q$47,0) -> 0 | R24: =IFERROR((R$5>=$F24)*$H24*R$47,0) -> 0 | S24: =IFERROR((S$5>=$F24)*$H24*S$47,0) -> 0 | ... EO24: =IFERROR((EO$5>=$F24)*$H24*EO$47,0) -> 0
B25: =+B8 -> 300 | C25: =+C8 -> [Retail Tenant] | F25: 1 | H25: =IFERROR(F8/$F$19,0) -> 0 | I25: =IFERROR(J25/F8,0) -> 0 | J25: =+H25*$J$47 -> 0 | L25: =IFERROR((L$5>=$F25)*$H25*L$47,0) -> 0 | M25: =IFERROR((M$5>=$F25)*$H25*M$47,0) -> 0 | N25: =IFERROR((N$5>=$F25)*$H25*N$47,0) -> 0 | O25: =IFERROR((O$5>=$F25)*$H25*O$47,0) -> 0 | P25: =IFERROR((P$5>=$F25)*$H25*P$47,0) -> 0 | Q25: =IFERROR((Q$5>=$F25)*$H25*Q$47,0) -> 0 | R25: =IFERROR((R$5>=$F25)*$H25*R$47,0) -> 0 | S25: =IFERROR((S$5>=$F25)*$H25*S$47,0) -> 0 | ... EO25: =IFERROR((EO$5>=$F25)*$H25*EO$47,0) -> 0
B26: =+B9 -> 400 | C26: =+C9 -> [Retail Tenant] | F26: 1 | H26: =IFERROR(F9/$F$19,0) -> 0 | I26: =IFERROR(J26/F9,0) -> 0 | J26: =+H26*$J$47 -> 0 | L26: =IFERROR((L$5>=$F26)*$H26*L$47,0) -> 0 | M26: =IFERROR((M$5>=$F26)*$H26*M$47,0) -> 0 | N26: =IFERROR((N$5>=$F26)*$H26*N$47,0) -> 0 | O26: =IFERROR((O$5>=$F26)*$H26*O$47,0) -> 0 | P26: =IFERROR((P$5>=$F26)*$H26*P$47,0) -> 0 | Q26: =IFERROR((Q$5>=$F26)*$H26*Q$47,0) -> 0 | R26: =IFERROR((R$5>=$F26)*$H26*R$47,0) -> 0 | S26: =IFERROR((S$5>=$F26)*$H26*S$47,0) -> 0 | ... EO26: =IFERROR((EO$5>=$F26)*$H26*EO$47,0) -> 0
B27: =+B10 -> 500 | C27: =+C10 -> [Retail Tenant] | F27: 1 | H27: =IFERROR(F10/$F$19,0) -> 0 | I27: =IFERROR(J27/F10,0) -> 0 | J27: =+H27*$J$47 -> 0 | L27: =IFERROR((L$5>=$F27)*$H27*L$47,0) -> 0 | M27: =IFERROR((M$5>=$F27)*$H27*M$47,0) -> 0 | N27: =IFERROR((N$5>=$F27)*$H27*N$47,0) -> 0 | O27: =IFERROR((O$5>=$F27)*$H27*O$47,0) -> 0 | P27: =IFERROR((P$5>=$F27)*$H27*P$47,0) -> 0 | Q27: =IFERROR((Q$5>=$F27)*$H27*Q$47,0) -> 0 | R27: =IFERROR((R$5>=$F27)*$H27*R$47,0) -> 0 | S27: =IFERROR((S$5>=$F27)*$H27*S$47,0) -> 0 | ... EO27: =IFERROR((EO$5>=$F27)*$H27*EO$47,0) -> 0
B28: =+B11 -> 600 | C28: =+C11 -> [Retail Tenant] | F28: 1 | H28: =IFERROR(F11/$F$19,0) -> 0 | I28: =IFERROR(J28/F11,0) -> 0 | J28: =+H28*$J$47 -> 0 | L28: =IFERROR((L$5>=$F28)*$H28*L$47,0) -> 0 | M28: =IFERROR((M$5>=$F28)*$H28*M$47,0) -> 0 | N28: =IFERROR((N$5>=$F28)*$H28*N$47,0) -> 0 | O28: =IFERROR((O$5>=$F28)*$H28*O$47,0) -> 0 | P28: =IFERROR((P$5>=$F28)*$H28*P$47,0) -> 0 | Q28: =IFERROR((Q$5>=$F28)*$H28*Q$47,0) -> 0 | R28: =IFERROR((R$5>=$F28)*$H28*R$47,0) -> 0 | S28: =IFERROR((S$5>=$F28)*$H28*S$47,0) -> 0 | ... EO28: =IFERROR((EO$5>=$F28)*$H28*EO$47,0) -> 0
B29: =+B12 -> 700 | C29: =+C12 -> [Retail Tenant] | F29: 24 | H29: =IFERROR(F12/$F$19,0) -> 0 | I29: =IFERROR(J29/F12,0) -> 0 | J29: =+H29*$J$47 -> 0 | L29: =IFERROR((L$5>=$F29)*$H29*L$47,0) -> 0 | M29: =IFERROR((M$5>=$F29)*$H29*M$47,0) -> 0 | N29: =IFERROR((N$5>=$F29)*$H29*N$47,0) -> 0 | O29: =IFERROR((O$5>=$F29)*$H29*O$47,0) -> 0 | P29: =IFERROR((P$5>=$F29)*$H29*P$47,0) -> 0 | Q29: =IFERROR((Q$5>=$F29)*$H29*Q$47,0) -> 0 | R29: =IFERROR((R$5>=$F29)*$H29*R$47,0) -> 0 | S29: =IFERROR((S$5>=$F29)*$H29*S$47,0) -> 0 | ... EO29: =IFERROR((EO$5>=$F29)*$H29*EO$47,0) -> 0
B30: =+B13 -> 800 | C30: =+C13 -> [Retail Tenant] | F30: 36 | H30: =IFERROR(F13/$F$19,0) -> 0 | I30: =IFERROR(J30/F13,0) -> 0 | J30: =+H30*$J$47 -> 0 | L30: =IFERROR((L$5>=$F30)*$H30*L$47,0) -> 0 | M30: =IFERROR((M$5>=$F30)*$H30*M$47,0) -> 0 | N30: =IFERROR((N$5>=$F30)*$H30*N$47,0) -> 0 | O30: =IFERROR((O$5>=$F30)*$H30*O$47,0) -> 0 | P30: =IFERROR((P$5>=$F30)*$H30*P$47,0) -> 0 | Q30: =IFERROR((Q$5>=$F30)*$H30*Q$47,0) -> 0 | R30: =IFERROR((R$5>=$F30)*$H30*R$47,0) -> 0 | S30: =IFERROR((S$5>=$F30)*$H30*S$47,0) -> 0 | ... EO30: =IFERROR((EO$5>=$F30)*$H30*EO$47,0) -> 0
B31: =+B14 -> 900 | C31: =+C14 -> [Retail Tenant] | F31: 36 | H31: =IFERROR(F14/$F$19,0) -> 0 | I31: =IFERROR(J31/F14,0) -> 0 | J31: =+H31*$J$47 -> 0 | L31: =IFERROR((L$5>=$F31)*$H31*L$47,0) -> 0 | M31: =IFERROR((M$5>=$F31)*$H31*M$47,0) -> 0 | N31: =IFERROR((N$5>=$F31)*$H31*N$47,0) -> 0 | O31: =IFERROR((O$5>=$F31)*$H31*O$47,0) -> 0 | P31: =IFERROR((P$5>=$F31)*$H31*P$47,0) -> 0 | Q31: =IFERROR((Q$5>=$F31)*$H31*Q$47,0) -> 0 | R31: =IFERROR((R$5>=$F31)*$H31*R$47,0) -> 0 | S31: =IFERROR((S$5>=$F31)*$H31*S$47,0) -> 0 | ... EO31: =IFERROR((EO$5>=$F31)*$H31*EO$47,0) -> 0
B32: =+B15 -> 1000 | C32: =+C15 -> [Retail Tenant] | F32: 1 | H32: =IFERROR(F15/$F$19,0) -> 0 | I32: =IFERROR(J32/F15,0) -> 0 | J32: =+H32*$J$47 -> 0 | L32: =IFERROR((L$5>=$F32)*$H32*L$47,0) -> 0 | M32: =IFERROR((M$5>=$F32)*$H32*M$47,0) -> 0 | N32: =IFERROR((N$5>=$F32)*$H32*N$47,0) -> 0 | O32: =IFERROR((O$5>=$F32)*$H32*O$47,0) -> 0 | P32: =IFERROR((P$5>=$F32)*$H32*P$47,0) -> 0 | Q32: =IFERROR((Q$5>=$F32)*$H32*Q$47,0) -> 0 | R32: =IFERROR((R$5>=$F32)*$H32*R$47,0) -> 0 | S32: =IFERROR((S$5>=$F32)*$H32*S$47,0) -> 0 | ... EO32: =IFERROR((EO$5>=$F32)*$H32*EO$47,0) -> 0
B33: =+B16 -> 1100 | C33: =+C16 -> [Retail Tenant] | F33: 1 | H33: =IFERROR(F16/$F$19,0) -> 0 | I33: =IFERROR(J33/F16,0) -> 0 | J33: =+H33*$J$47 -> 0 | L33: =IFERROR((L$5>=$F33)*$H33*L$47,0) -> 0 | M33: =IFERROR((M$5>=$F33)*$H33*M$47,0) -> 0 | N33: =IFERROR((N$5>=$F33)*$H33*N$47,0) -> 0 | O33: =IFERROR((O$5>=$F33)*$H33*O$47,0) -> 0 | P33: =IFERROR((P$5>=$F33)*$H33*P$47,0) -> 0 | Q33: =IFERROR((Q$5>=$F33)*$H33*Q$47,0) -> 0 | R33: =IFERROR((R$5>=$F33)*$H33*R$47,0) -> 0 | S33: =IFERROR((S$5>=$F33)*$H33*S$47,0) -> 0 | ... EO33: =IFERROR((EO$5>=$F33)*$H33*EO$47,0) -> 0
B34: =+B17 -> 1200 | C34: =+C17 -> [Retail Tenant] | F34: 1 | H34: =IFERROR(F17/$F$19,0) -> 0 | I34: =IFERROR(J34/F17,0) -> 0 | J34: =+H34*$J$47 -> 0 | L34: =IFERROR((L$5>=$F34)*$H34*L$47,0) -> 0 | M34: =IFERROR((M$5>=$F34)*$H34*M$47,0) -> 0 | N34: =IFERROR((N$5>=$F34)*$H34*N$47,0) -> 0 | O34: =IFERROR((O$5>=$F34)*$H34*O$47,0) -> 0 | P34: =IFERROR((P$5>=$F34)*$H34*P$47,0) -> 0 | Q34: =IFERROR((Q$5>=$F34)*$H34*Q$47,0) -> 0 | R34: =IFERROR((R$5>=$F34)*$H34*R$47,0) -> 0 | S34: =IFERROR((S$5>=$F34)*$H34*S$47,0) -> 0 | ... EO34: =IFERROR((EO$5>=$F34)*$H34*EO$47,0) -> 0
B35: =+B18 -> 1300 | C35: =+C18 -> [Retail Tenant] | F35: 1 | H35: =IFERROR(F18/$F$19,0) -> 0 | I35: =IFERROR(J35/F18,0) -> 0 | J35: =+H35*$J$47 -> 0 | L35: =IFERROR((L$5>=$F35)*$H35*L$47,0) -> 0 | M35: =IFERROR((M$5>=$F35)*$H35*M$47,0) -> 0 | N35: =IFERROR((N$5>=$F35)*$H35*N$47,0) -> 0 | O35: =IFERROR((O$5>=$F35)*$H35*O$47,0) -> 0 | P35: =IFERROR((P$5>=$F35)*$H35*P$47,0) -> 0 | Q35: =IFERROR((Q$5>=$F35)*$H35*Q$47,0) -> 0 | R35: =IFERROR((R$5>=$F35)*$H35*R$47,0) -> 0 | S35: =IFERROR((S$5>=$F35)*$H35*S$47,0) -> 0 | ... EO35: =IFERROR((EO$5>=$F35)*$H35*EO$47,0) -> 0
B36: Total Recovery Income | F36: =MIN(F23:F35) -> 1 | I36: =IFERROR(J36/F19,0) -> 0 | J36: =SUM(J23:J35) -> 0 | L36: =SUM(L23:L35) -> 0 | M36: =SUM(M23:M35) -> 0 | N36: =SUM(N23:N35) -> 0 | O36: =SUM(O23:O35) -> 0 | P36: =SUM(P23:P35) -> 0 | Q36: =SUM(Q23:Q35) -> 0 | R36: =SUM(R23:R35) -> 0 | S36: =SUM(S23:S35) -> 0 | ... EO36: =SUM(EO23:EO35) -> 0
B38: Gross Potential Retail Income | I38: =IFERROR(J38/F19,0) -> 0 | J38: =+J36+J19 -> 0 | L38: =+L36+L19 -> 0 | M38: =+M36+M19 -> 0 | N38: =+N36+N19 -> 0 | O38: =+O36+O19 -> 0 | P38: =+P36+P19 -> 0 | Q38: =+Q36+Q19 -> 0 | R38: =+R36+R19 -> 0 | S38: =+S36+S19 -> 0 | ... EO38: =+EO36+EO19 -> 0
B39: Less: Vacancy and Bad Debt | G39: 0.05 | I39: =IFERROR(J39/$F$19,0) -> 0 | J39: =+SUM(J36,J19)*G39 -> 0 | L39: =-$G$39*L38 -> 0 | M39: =-$G$39*M38 -> 0 | N39: =-$G$39*N38 -> 0 | O39: =-$G$39*O38 -> 0 | P39: =-$G$39*P38 -> 0 | Q39: =-$G$39*Q38 -> 0 | R39: =-$G$39*R38 -> 0 | S39: =-$G$39*S38 -> 0 | ... EO39: =-$G$39*EO38 -> 0
B40: Gross Potential Retail Income | I40: =IFERROR(J40/F19,0) -> 0 | J40: =+J38-J39 -> 0 | L40: =SUM(L38:L39) -> 0 | M40: =SUM(M38:M39) -> 0 | N40: =SUM(N38:N39) -> 0 | O40: =SUM(O38:O39) -> 0 | P40: =SUM(P38:P39) -> 0 | Q40: =SUM(Q38:Q39) -> 0 | R40: =SUM(R38:R39) -> 0 | S40: =SUM(S38:S39) -> 0 | ... EO40: =SUM(EO38:EO39) -> 0
B42: Retail Operating Expenses | G42: Expense Growth | I42: Per SF / Yr. | J42: Annual
B43: CAM | G43: =+Assumptions!$I$138 -> 0.02 | I43: 0 | J43: =+$F$19*I43 -> 0 | L43: =IFERROR($J43/12*L$20*(1+$G43)^(ROUNDUP(L$5/12,0)-1),0) -> 0 | M43: =IFERROR($J43/12*M$20*(1+$G43)^(ROUNDUP(M$5/12,0)-1),0) -> 0 | N43: =IFERROR($J43/12*N$20*(1+$G43)^(ROUNDUP(N$5/12,0)-1),0) -> 0 | O43: =IFERROR($J43/12*O$20*(1+$G43)^(ROUNDUP(O$5/12,0)-1),0) -> 0 | P43: =IFERROR($J43/12*P$20*(1+$G43)^(ROUNDUP(P$5/12,0)-1),0) -> 0 | Q43: =IFERROR($J43/12*Q$20*(1+$G43)^(ROUNDUP(Q$5/12,0)-1),0) -> 0 | R43: =IFERROR($J43/12*R$20*(1+$G43)^(ROUNDUP(R$5/12,0)-1),0) -> 0 | S43: =IFERROR($J43/12*S$20*(1+$G43)^(ROUNDUP(S$5/12,0)-1),0) -> 0 | ... EO43: =IFERROR($J43/12*EO$20*(1+$G43)^(ROUNDUP(EO$5/12,0)-1),0) -> 0
B44: Management Fee | G44: =+Assumptions!$I$138 -> 0.02 | I44: 0 | J44: =+$F$19*I44 -> 0 | L44: =IFERROR($J44/12*L$20*(1+$G44)^(ROUNDUP(L$5/12,0)-1),0) -> 0 | M44: =IFERROR($J44/12*M$20*(1+$G44)^(ROUNDUP(M$5/12,0)-1),0) -> 0 | N44: =IFERROR($J44/12*N$20*(1+$G44)^(ROUNDUP(N$5/12,0)-1),0) -> 0 | O44: =IFERROR($J44/12*O$20*(1+$G44)^(ROUNDUP(O$5/12,0)-1),0) -> 0 | P44: =IFERROR($J44/12*P$20*(1+$G44)^(ROUNDUP(P$5/12,0)-1),0) -> 0 | Q44: =IFERROR($J44/12*Q$20*(1+$G44)^(ROUNDUP(Q$5/12,0)-1),0) -> 0 | R44: =IFERROR($J44/12*R$20*(1+$G44)^(ROUNDUP(R$5/12,0)-1),0) -> 0 | S44: =IFERROR($J44/12*S$20*(1+$G44)^(ROUNDUP(S$5/12,0)-1),0) -> 0 | ... EO44: =IFERROR($J44/12*EO$20*(1+$G44)^(ROUNDUP(EO$5/12,0)-1),0) -> 0
B45: Insurance | G45: =+Assumptions!$I$138 -> 0.02 | I45: 0 | J45: =+$F$19*I45 -> 0 | L45: =IFERROR($J45/12*L$20*(1+$G45)^(ROUNDUP(L$5/12,0)-1),0) -> 0 | M45: =IFERROR($J45/12*M$20*(1+$G45)^(ROUNDUP(M$5/12,0)-1),0) -> 0 | N45: =IFERROR($J45/12*N$20*(1+$G45)^(ROUNDUP(N$5/12,0)-1),0) -> 0 | O45: =IFERROR($J45/12*O$20*(1+$G45)^(ROUNDUP(O$5/12,0)-1),0) -> 0 | P45: =IFERROR($J45/12*P$20*(1+$G45)^(ROUNDUP(P$5/12,0)-1),0) -> 0 | Q45: =IFERROR($J45/12*Q$20*(1+$G45)^(ROUNDUP(Q$5/12,0)-1),0) -> 0 | R45: =IFERROR($J45/12*R$20*(1+$G45)^(ROUNDUP(R$5/12,0)-1),0) -> 0 | S45: =IFERROR($J45/12*S$20*(1+$G45)^(ROUNDUP(S$5/12,0)-1),0) -> 0 | ... EO45: =IFERROR($J45/12*EO$20*(1+$G45)^(ROUNDUP(EO$5/12,0)-1),0) -> 0
B46: Property Taxes | G46: =+Assumptions!$I$138 -> 0.02 | I46: 0 | J46: =+$F$19*I46 -> 0 | L46: =IFERROR($J46/12*L$20*(1+$G46)^(ROUNDUP(L$5/12,0)-1),0) -> 0 | M46: =IFERROR($J46/12*M$20*(1+$G46)^(ROUNDUP(M$5/12,0)-1),0) -> 0 | N46: =IFERROR($J46/12*N$20*(1+$G46)^(ROUNDUP(N$5/12,0)-1),0) -> 0 | O46: =IFERROR($J46/12*O$20*(1+$G46)^(ROUNDUP(O$5/12,0)-1),0) -> 0 | P46: =IFERROR($J46/12*P$20*(1+$G46)^(ROUNDUP(P$5/12,0)-1),0) -> 0 | Q46: =IFERROR($J46/12*Q$20*(1+$G46)^(ROUNDUP(Q$5/12,0)-1),0) -> 0 | R46: =IFERROR($J46/12*R$20*(1+$G46)^(ROUNDUP(R$5/12,0)-1),0) -> 0 | S46: =IFERROR($J46/12*S$20*(1+$G46)^(ROUNDUP(S$5/12,0)-1),0) -> 0 | ... EO46: =IFERROR($J46/12*EO$20*(1+$G46)^(ROUNDUP(EO$5/12,0)-1),0) -> 0
B47: Total Retail Operating Expenses | I47: =IFERROR(J47/F19,0) -> 0 | J47: =SUM(J43:J46) -> 0 | L47: =SUM(L43:L46) -> 0 | M47: =SUM(M43:M46) -> 0 | N47: =SUM(N43:N46) -> 0 | O47: =SUM(O43:O46) -> 0 | P47: =SUM(P43:P46) -> 0 | Q47: =SUM(Q43:Q46) -> 0 | R47: =SUM(R43:R46) -> 0 | S47: =SUM(S43:S46) -> 0 | ... EO47: =SUM(EO43:EO46) -> 0
B49: Effective Gross Retail Income | I49: =IFERROR(J49/$F$19,0) -> 0 | J49: =+SUM(J19,J36)-SUM(J39,J47) -> 0 | L49: =+L40-L47 -> 0 | M49: =+M40-M47 -> 0 | N49: =+N40-N47 -> 0 | O49: =+O40-O47 -> 0 | P49: =+P40-P47 -> 0 | Q49: =+Q40-Q47 -> 0 | R49: =+R40-R47 -> 0 | S49: =+S40-S47 -> 0 | ... EO49: =+EO40-EO47 -> 0
B51: Leasing Assumptions | D51: New Lease | E51: Renewal Lease | I51: New Lease | J51: Renewal Lease
B52: Renewal Probability | D52: =1-E52 -> 0.3 | E52: 0.7 | G52: Tenant Improvements | I52: =+$F$19*D52*D54 -> 0 | J52: =+$F$19*E52*E54 -> 0
B53: Retail Rent | D53: 25 | E53: 15 | G53: Leasing Commissions | I53: =+D52*$F$19*D53*D56*D55 -> 0 | J53: =+E52*$F$19*E53*E56*E55 -> 0
B54: TI's | D54: 20 | E54: 5 | G54: Total Leasing Costs | I54: =SUM(I52:I53) -> 0 | J54: =SUM(J52:J53) -> 0
B55: Leasing Commissions | D55: 0.07 | E55: 0.04 | G55: Annualized Leasing Costs | I55: =+I54/D56 -> 0 | J55: =+J54/E56 -> 0
B56: Lease Term | D56: 7 | E56: 5
G57: Total Leasing Cost Reserves | I57: =IFERROR(J57/F19,0) -> 0 | J57: =+J55+I55 -> 0

Sheet Closing Costs
B4: =+Assumptions!B12 -> Closing Costs | G4: Beg. Mo. | H4: End. Mo. | J4: =+Model!G4 -> 0 | K4: =+Model!H4 -> 1 | L4: =+Model!I4 -> 2 | M4: =+Model!J4 -> 3 | N4: =+Model!K4 -> 4 | O4: =+Model!L4 -> 5 | P4: =+Model!M4 -> 6 | Q4: =+Model!N4 -> 7 | ... EL4: =+Model!EI4 -> 132
B5: Acquisition Fee | D5: 0.02 | E5: =+Assumptions!$G$22*D5 -> 298000 | G5: 0 | H5: 0 | J5: =IF(AND($G5=J$4,$H5=J$4),$E5,IF($G5>J$4,0,IF($H5<J$4,0,$E5/($H5-$G5+1)))) -> 298000 | K5: =IF(AND($G5=K$4,$H5=K$4),$E5,IF($G5>K$4,0,IF($H5<K$4,0,$E5/($H5-$G5+1)))) -> 0 | L5: =IF(AND($G5=L$4,$H5=L$4),$E5,IF($G5>L$4,0,IF($H5<L$4,0,$E5/($H5-$G5+1)))) -> 0 | M5: =IF(AND($G5=M$4,$H5=M$4),$E5,IF($G5>M$4,0,IF($H5<M$4,0,$E5/($H5-$G5+1)))) -> 0 | N5: =IF(AND($G5=N$4,$H5=N$4),$E5,IF($G5>N$4,0,IF($H5<N$4,0,$E5/($H5-$G5+1)))) -> 0 | O5: =IF(AND($G5=O$4,$H5=O$4),$E5,IF($G5>O$4,0,IF($H5<O$4,0,$E5/($H5-$G5+1)))) -> 0 | P5: =IF(AND($G5=P$4,$H5=P$4),$E5,IF($G5>P$4,0,IF($H5<P$4,0,$E5/($H5-$G5+1)))) -> 0 | Q5: =IF(AND($G5=Q$4,$H5=Q$4),$E5,IF($G5>Q$4,0,IF($H5<Q$4,0,$E5/($H5-$G5+1)))) -> 0 | ... EL5: =IF(AND($G5=EL$4,$H5=EL$4),$E5,IF($G5>EL$4,0,IF($H5<EL$4,0,$E5/($H5-$G5+1)))) -> 0
B6: Financing Fees: Acquisition Loan | D6: =+Assumptions!L28 -> 0.01 | E6: =+D6*Assumptions!G31 -> 98704.904 | G6: =+Assumptions!$G$28 -> 0 | H6: =+Assumptions!$G$28 -> 0 | J6: =IF(AND($G6=J$4,$H6=J$4),$E6,IF($G6>J$4,0,IF($H6<J$4,0,$E6/($H6-$G6+1)))) -> 98704.904 | K6: =IF(AND($G6=K$4,$H6=K$4),$E6,IF($G6>K$4,0,IF($H6<K$4,0,$E6/($H6-$G6+1)))) -> 0 | L6: =IF(AND($G6=L$4,$H6=L$4),$E6,IF($G6>L$4,0,IF($H6<L$4,0,$E6/($H6-$G6+1)))) -> 0 | M6: =IF(AND($G6=M$4,$H6=M$4),$E6,IF($G6>M$4,0,IF($H6<M$4,0,$E6/($H6-$G6+1)))) -> 0 | N6: =IF(AND($G6=N$4,$H6=N$4),$E6,IF($G6>N$4,0,IF($H6<N$4,0,$E6/($H6-$G6+1)))) -> 0 | O6: =IF(AND($G6=O$4,$H6=O$4),$E6,IF($G6>O$4,0,IF($H6<O$4,0,$E6/($H6-$G6+1)))) -> 0 | P6: =IF(AND($G6=P$4,$H6=P$4),$E6,IF($G6>P$4,0,IF($H6<P$4,0,$E6/($H6-$G6+1)))) -> 0 | Q6: =IF(AND($G6=Q$4,$H6=Q$4),$E6,IF($G6>Q$4,0,IF($H6<Q$4,0,$E6/($H6-$G6+1)))) -> 0 | ... EL6: =IF(AND($G6=EL$4,$H6=EL$4),$E6,IF($G6>EL$4,0,IF($H6<EL$4,0,$E6/($H6-$G6+1)))) -> 0
B7: Title Insurance | D7: 0.0035 | E7: =+Assumptions!$G$22*D7 -> 52150 | G7: 0 | H7: 0 | J7: =IF(AND($G7=J$4,$H7=J$4),$E7,IF($G7>J$4,0,IF($H7<J$4,0,$E7/($H7-$G7+1)))) -> 52150 | K7: =IF(AND($G7=K$4,$H7=K$4),$E7,IF($G7>K$4,0,IF($H7<K$4,0,$E7/($H7-$G7+1)))) -> 0 | L7: =IF(AND($G7=L$4,$H7=L$4),$E7,IF($G7>L$4,0,IF($H7<L$4,0,$E7/($H7-$G7+1)))) -> 0 | M7: =IF(AND($G7=M$4,$H7=M$4),$E7,IF($G7>M$4,0,IF($H7<M$4,0,$E7/($H7-$G7+1)))) -> 0 | N7: =IF(AND($G7=N$4,$H7=N$4),$E7,IF($G7>N$4,0,IF($H7<N$4,0,$E7/($H7-$G7+1)))) -> 0 | O7: =IF(AND($G7=O$4,$H7=O$4),$E7,IF($G7>O$4,0,IF($H7<O$4,0,$E7/($H7-$G7+1)))) -> 0 | P7: =IF(AND($G7=P$4,$H7=P$4),$E7,IF($G7>P$4,0,IF($H7<P$4,0,$E7/($H7-$G7+1)))) -> 0 | Q7: =IF(AND($G7=Q$4,$H7=Q$4),$E7,IF($G7>Q$4,0,IF($H7<Q$4,0,$E7/($H7-$G7+1)))) -> 0 | ... EL7: =IF(AND($G7=EL$4,$H7=EL$4),$E7,IF($G7>EL$4,0,IF($H7<EL$4,0,$E7/($H7-$G7+1)))) -> 0
B8: Appraisal | E8: 5000 | G8: 0 | H8: 0 | J8: =IF(AND($G8=J$4,$H8=J$4),$E8,IF($G8>J$4,0,IF($H8<J$4,0,$E8/($H8-$G8+1)))) -> 5000 | K8: =IF(AND($G8=K$4,$H8=K$4),$E8,IF($G8>K$4,0,IF($H8<K$4,0,$E8/($H8-$G8+1)))) -> 0 | L8: =IF(AND($G8=L$4,$H8=L$4),$E8,IF($G8>L$4,0,IF($H8<L$4,0,$E8/($H8-$G8+1)))) -> 0 | M8: =IF(AND($G8=M$4,$H8=M$4),$E8,IF($G8>M$4,0,IF($H8<M$4,0,$E8/($H8-$G8+1)))) -> 0 | N8: =IF(AND($G8=N$4,$H8=N$4),$E8,IF($G8>N$4,0,IF($H8<N$4,0,$E8/($H8-$G8+1)))) -> 0 | O8: =IF(AND($G8=O$4,$H8=O$4),$E8,IF($G8>O$4,0,IF($H8<O$4,0,$E8/($H8-$G8+1)))) -> 0 | P8: =IF(AND($G8=P$4,$H8=P$4),$E8,IF($G8>P$4,0,IF($H8<P$4,0,$E8/($H8-$G8+1)))) -> 0 | Q8: =IF(AND($G8=Q$4,$H8=Q$4),$E8,IF($G8>Q$4,0,IF($H8<Q$4,0,$E8/($H8-$G8+1)))) -> 0 | ... EL8: =IF(AND($G8=EL$4,$H8=EL$4),$E8,IF($G8>EL$4,0,IF($H8<EL$4,0,$E8/($H8-$G8+1)))) -> 0
B9: Inspection | E9: 3000 | G9: 0 | H9: 0 | J9: =IF(AND($G9=J$4,$H9=J$4),$E9,IF($G9>J$4,0,IF($H9<J$4,0,$E9/($H9-$G9+1)))) -> 3000 | K9: =IF(AND($G9=K$4,$H9=K$4),$E9,IF($G9>K$4,0,IF($H9<K$4,0,$E9/($H9-$G9+1)))) -> 0 | L9: =IF(AND($G9=L$4,$H9=L$4),$E9,IF($G9>L$4,0,IF($H9<L$4,0,$E9/($H9-$G9+1)))) -> 0 | M9: =IF(AND($G9=M$4,$H9=M$4),$E9,IF($G9>M$4,0,IF($H9<M$4,0,$E9/($H9-$G9+1)))) -> 0 | N9: =IF(AND($G9=N$4,$H9=N$4),$E9,IF($G9>N$4,0,IF($H9<N$4,0,$E9/($H9-$G9+1)))) -> 0 | O9: =IF(AND($G9=O$4,$H9=O$4),$E9,IF($G9>O$4,0,IF($H9<O$4,0,$E9/($H9-$G9+1)))) -> 0 | P9: =IF(AND($G9=P$4,$H9=P$4),$E9,IF($G9>P$4,0,IF($H9<P$4,0,$E9/($H9-$G9+1)))) -> 0 | Q9: =IF(AND($G9=Q$4,$H9=Q$4),$E9,IF($G9>Q$4,0,IF($H9<Q$4,0,$E9/($H9-$G9+1)))) -> 0 | ... EL9: =IF(AND($G9=EL$4,$H9=EL$4),$E9,IF($G9>EL$4,0,IF($H9<EL$4,0,$E9/($H9-$G9+1)))) -> 0
B10: Application Fee | E10: 5000 | G10: 0 | H10: 0 | J10: =IF(AND($G10=J$4,$H10=J$4),$E10,IF($G10>J$4,0,IF($H10<J$4,0,$E10/($H10-$G10+1)))) -> 5000 | K10: =IF(AND($G10=K$4,$H10=K$4),$E10,IF($G10>K$4,0,IF($H10<K$4,0,$E10/($H10-$G10+1)))) -> 0 | L10: =IF(AND($G10=L$4,$H10=L$4),$E10,IF($G10>L$4,0,IF($H10<L$4,0,$E10/($H10-$G10+1)))) -> 0 | M10: =IF(AND($G10=M$4,$H10=M$4),$E10,IF($G10>M$4,0,IF($H10<M$4,0,$E10/($H10-$G10+1)))) -> 0 | N10: =IF(AND($G10=N$4,$H10=N$4),$E10,IF($G10>N$4,0,IF($H10<N$4,0,$E10/($H10-$G10+1)))) -> 0 | O10: =IF(AND($G10=O$4,$H10=O$4),$E10,IF($G10>O$4,0,IF($H10<O$4,0,$E10/($H10-$G10+1)))) -> 0 | P10: =IF(AND($G10=P$4,$H10=P$4),$E10,IF($G10>P$4,0,IF($H10<P$4,0,$E10/($H10-$G10+1)))) -> 0 | Q10: =IF(AND($G10=Q$4,$H10=Q$4),$E10,IF($G10>Q$4,0,IF($H10<Q$4,0,$E10/($H10-$G10+1)))) -> 0 | ... EL10: =IF(AND($G10=EL$4,$H10=EL$4),$E10,IF($G10>EL$4,0,IF($H10<EL$4,0,$E10/($H10-$G10+1)))) -> 0
B11: Legal Closing Costs | E11: 5000 | G11: 0 | H11: 0 | J11: =IF(AND($G11=J$4,$H11=J$4),$E11,IF($G11>J$4,0,IF($H11<J$4,0,$E11/($H11-$G11+1)))) -> 5000 | K11: =IF(AND($G11=K$4,$H11=K$4),$E11,IF($G11>K$4,0,IF($H11<K$4,0,$E11/($H11-$G11+1)))) -> 0 | L11: =IF(AND($G11=L$4,$H11=L$4),$E11,IF($G11>L$4,0,IF($H11<L$4,0,$E11/($H11-$G11+1)))) -> 0 | M11: =IF(AND($G11=M$4,$H11=M$4),$E11,IF($G11>M$4,0,IF($H11<M$4,0,$E11/($H11-$G11+1)))) -> 0 | N11: =IF(AND($G11=N$4,$H11=N$4),$E11,IF($G11>N$4,0,IF($H11<N$4,0,$E11/($H11-$G11+1)))) -> 0 | O11: =IF(AND($G11=O$4,$H11=O$4),$E11,IF($G11>O$4,0,IF($H11<O$4,0,$E11/($H11-$G11+1)))) -> 0 | P11: =IF(AND($G11=P$4,$H11=P$4),$E11,IF($G11>P$4,0,IF($H11<P$4,0,$E11/($H11-$G11+1)))) -> 0 | Q11: =IF(AND($G11=Q$4,$H11=Q$4),$E11,IF($G11>Q$4,0,IF($H11<Q$4,0,$E11/($H11-$G11+1)))) -> 0 | ... EL11: =IF(AND($G11=EL$4,$H11=EL$4),$E11,IF($G11>EL$4,0,IF($H11<EL$4,0,$E11/($H11-$G11+1)))) -> 0
B12: Transfer Fees | E12: 750 | G12: 0 | H12: 0 | J12: =IF(AND($G12=J$4,$H12=J$4),$E12,IF($G12>J$4,0,IF($H12<J$4,0,$E12/($H12-$G12+1)))) -> 750 | K12: =IF(AND($G12=K$4,$H12=K$4),$E12,IF($G12>K$4,0,IF($H12<K$4,0,$E12/($H12-$G12+1)))) -> 0 | L12: =IF(AND($G12=L$4,$H12=L$4),$E12,IF($G12>L$4,0,IF($H12<L$4,0,$E12/($H12-$G12+1)))) -> 0 | M12: =IF(AND($G12=M$4,$H12=M$4),$E12,IF($G12>M$4,0,IF($H12<M$4,0,$E12/($H12-$G12+1)))) -> 0 | N12: =IF(AND($G12=N$4,$H12=N$4),$E12,IF($G12>N$4,0,IF($H12<N$4,0,$E12/($H12-$G12+1)))) -> 0 | O12: =IF(AND($G12=O$4,$H12=O$4),$E12,IF($G12>O$4,0,IF($H12<O$4,0,$E12/($H12-$G12+1)))) -> 0 | P12: =IF(AND($G12=P$4,$H12=P$4),$E12,IF($G12>P$4,0,IF($H12<P$4,0,$E12/($H12-$G12+1)))) -> 0 | Q12: =IF(AND($G12=Q$4,$H12=Q$4),$E12,IF($G12>Q$4,0,IF($H12<Q$4,0,$E12/($H12-$G12+1)))) -> 0 | ... EL12: =IF(AND($G12=EL$4,$H12=EL$4),$E12,IF($G12>EL$4,0,IF($H12<EL$4,0,$E12/($H12-$G12+1)))) -> 0
B13: Loan Processing Fees | E13: 1995 | G13: 0 | H13: 0 | J13: =IF(AND($G13=J$4,$H13=J$4),$E13,IF($G13>J$4,0,IF($H13<J$4,0,$E13/($H13-$G13+1)))) -> 1995 | K13: =IF(AND($G13=K$4,$H13=K$4),$E13,IF($G13>K$4,0,IF($H13<K$4,0,$E13/($H13-$G13+1)))) -> 0 | L13: =IF(AND($G13=L$4,$H13=L$4),$E13,IF($G13>L$4,0,IF($H13<L$4,0,$E13/($H13-$G13+1)))) -> 0 | M13: =IF(AND($G13=M$4,$H13=M$4),$E13,IF($G13>M$4,0,IF($H13<M$4,0,$E13/($H13-$G13+1)))) -> 0 | N13: =IF(AND($G13=N$4,$H13=N$4),$E13,IF($G13>N$4,0,IF($H13<N$4,0,$E13/($H13-$G13+1)))) -> 0 | O13: =IF(AND($G13=O$4,$H13=O$4),$E13,IF($G13>O$4,0,IF($H13<O$4,0,$E13/($H13-$G13+1)))) -> 0 | P13: =IF(AND($G13=P$4,$H13=P$4),$E13,IF($G13>P$4,0,IF($H13<P$4,0,$E13/($H13-$G13+1)))) -> 0 | Q13: =IF(AND($G13=Q$4,$H13=Q$4),$E13,IF($G13>Q$4,0,IF($H13<Q$4,0,$E13/($H13-$G13+1)))) -> 0 | ... EL13: =IF(AND($G13=EL$4,$H13=EL$4),$E13,IF($G13>EL$4,0,IF($H13<EL$4,0,$E13/($H13-$G13+1)))) -> 0
B14: Filing and Recording Fees | E14: 500 | G14: 0 | H14: 0 | J14: =IF(AND($G14=J$4,$H14=J$4),$E14,IF($G14>J$4,0,IF($H14<J$4,0,$E14/($H14-$G14+1)))) -> 500 | K14: =IF(AND($G14=K$4,$H14=K$4),$E14,IF($G14>K$4,0,IF($H14<K$4,0,$E14/($H14-$G14+1)))) -> 0 | L14: =IF(AND($G14=L$4,$H14=L$4),$E14,IF($G14>L$4,0,IF($H14<L$4,0,$E14/($H14-$G14+1)))) -> 0 | M14: =IF(AND($G14=M$4,$H14=M$4),$E14,IF($G14>M$4,0,IF($H14<M$4,0,$E14/($H14-$G14+1)))) -> 0 | N14: =IF(AND($G14=N$4,$H14=N$4),$E14,IF($G14>N$4,0,IF($H14<N$4,0,$E14/($H14-$G14+1)))) -> 0 | O14: =IF(AND($G14=O$4,$H14=O$4),$E14,IF($G14>O$4,0,IF($H14<O$4,0,$E14/($H14-$G14+1)))) -> 0 | P14: =IF(AND($G14=P$4,$H14=P$4),$E14,IF($G14>P$4,0,IF($H14<P$4,0,$E14/($H14-$G14+1)))) -> 0 | Q14: =IF(AND($G14=Q$4,$H14=Q$4),$E14,IF($G14>Q$4,0,IF($H14<Q$4,0,$E14/($H14-$G14+1)))) -> 0 | ... EL14: =IF(AND($G14=EL$4,$H14=EL$4),$E14,IF($G14>EL$4,0,IF($H14<EL$4,0,$E14/($H14-$G14+1)))) -> 0
B15: Escrow / Prepaid: Insurance | E15: =+Assumptions!J152 -> 70980 | G15: 0 | H15: 0 | J15: =IF(AND($G15=J$4,$H15=J$4),$E15,IF($G15>J$4,0,IF($H15<J$4,0,$E15/($H15-$G15+1)))) -> 70980 | K15: =IF(AND($G15=K$4,$H15=K$4),$E15,IF($G15>K$4,0,IF($H15<K$4,0,$E15/($H15-$G15+1)))) -> 0 | L15: =IF(AND($G15=L$4,$H15=L$4),$E15,IF($G15>L$4,0,IF($H15<L$4,0,$E15/($H15-$G15+1)))) -> 0 | M15: =IF(AND($G15=M$4,$H15=M$4),$E15,IF($G15>M$4,0,IF($H15<M$4,0,$E15/($H15-$G15+1)))) -> 0 | N15: =IF(AND($G15=N$4,$H15=N$4),$E15,IF($G15>N$4,0,IF($H15<N$4,0,$E15/($H15-$G15+1)))) -> 0 | O15: =IF(AND($G15=O$4,$H15=O$4),$E15,IF($G15>O$4,0,IF($H15<O$4,0,$E15/($H15-$G15+1)))) -> 0 | P15: =IF(AND($G15=P$4,$H15=P$4),$E15,IF($G15>P$4,0,IF($H15<P$4,0,$E15/($H15-$G15+1)))) -> 0 | Q15: =IF(AND($G15=Q$4,$H15=Q$4),$E15,IF($G15>Q$4,0,IF($H15<Q$4,0,$E15/($H15-$G15+1)))) -> 0 | ... EL15: =IF(AND($G15=EL$4,$H15=EL$4),$E15,IF($G15>EL$4,0,IF($H15<EL$4,0,$E15/($H15-$G15+1)))) -> 0
B16: Escrow / Prepaid: Property Taxes | E16: =+Assumptions!J151/4 -> 74406.5 | G16: 0 | H16: 0 | J16: =IF(AND($G16=J$4,$H16=J$4),$E16,IF($G16>J$4,0,IF($H16<J$4,0,$E16/($H16-$G16+1)))) -> 74406.5 | K16: =IF(AND($G16=K$4,$H16=K$4),$E16,IF($G16>K$4,0,IF($H16<K$4,0,$E16/($H16-$G16+1)))) -> 0 | L16: =IF(AND($G16=L$4,$H16=L$4),$E16,IF($G16>L$4,0,IF($H16<L$4,0,$E16/($H16-$G16+1)))) -> 0 | M16: =IF(AND($G16=M$4,$H16=M$4),$E16,IF($G16>M$4,0,IF($H16<M$4,0,$E16/($H16-$G16+1)))) -> 0 | N16: =IF(AND($G16=N$4,$H16=N$4),$E16,IF($G16>N$4,0,IF($H16<N$4,0,$E16/($H16-$G16+1)))) -> 0 | O16: =IF(AND($G16=O$4,$H16=O$4),$E16,IF($G16>O$4,0,IF($H16<O$4,0,$E16/($H16-$G16+1)))) -> 0 | P16: =IF(AND($G16=P$4,$H16=P$4),$E16,IF($G16>P$4,0,IF($H16<P$4,0,$E16/($H16-$G16+1)))) -> 0 | Q16: =IF(AND($G16=Q$4,$H16=Q$4),$E16,IF($G16>Q$4,0,IF($H16<Q$4,0,$E16/($H16-$G16+1)))) -> 0 | ... EL16: =IF(AND($G16=EL$4,$H16=EL$4),$E16,IF($G16>EL$4,0,IF($H16<EL$4,0,$E16/($H16-$G16+1)))) -> 0
B17: Contingency | D17: 0.05 | E17: =+D17*SUM(E5:E16) -> 30774.32 | G17: =+H17 -> 0 | H17: =MAX(H5:H14) -> 0 | J17: =IF(AND($G17=J$4,$H17=J$4),$E17,IF($G17>J$4,0,IF($H17<J$4,0,$E17/($H17-$G17+1)))) -> 30774.32 | K17: =IF(AND($G17=K$4,$H17=K$4),$E17,IF($G17>K$4,0,IF($H17<K$4,0,$E17/($H17-$G17+1)))) -> 0 | L17: =IF(AND($G17=L$4,$H17=L$4),$E17,IF($G17>L$4,0,IF($H17<L$4,0,$E17/($H17-$G17+1)))) -> 0 | M17: =IF(AND($G17=M$4,$H17=M$4),$E17,IF($G17>M$4,0,IF($H17<M$4,0,$E17/($H17-$G17+1)))) -> 0 | N17: =IF(AND($G17=N$4,$H17=N$4),$E17,IF($G17>N$4,0,IF($H17<N$4,0,$E17/($H17-$G17+1)))) -> 0 | O17: =IF(AND($G17=O$4,$H17=O$4),$E17,IF($G17>O$4,0,IF($H17<O$4,0,$E17/($H17-$G17+1)))) -> 0 | P17: =IF(AND($G17=P$4,$H17=P$4),$E17,IF($G17>P$4,0,IF($H17<P$4,0,$E17/($H17-$G17+1)))) -> 0 | Q17: =IF(AND($G17=Q$4,$H17=Q$4),$E17,IF($G17>Q$4,0,IF($H17<Q$4,0,$E17/($H17-$G17+1)))) -> 0 | ... EL17: =IF(AND($G17=EL$4,$H17=EL$4),$E17,IF($G17>EL$4,0,IF($H17<EL$4,0,$E17/($H17-$G17+1)))) -> 0
B18: Total Closing Costs | E18: =SUM(E5:E17) -> 646260.72 | J18: =SUM(J5:J17) -> 646260.72 | K18: =SUM(K5:K17) -> 0 | L18: =SUM(L5:L17) -> 0 | M18: =SUM(M5:M17) -> 0 | N18: =SUM(N5:N17) -> 0 | O18: =SUM(O5:O17) -> 0 | P18: =SUM(P5:P17) -> 0 | Q18: =SUM(Q5:Q17) -> 0 | ... EL18: =SUM(EL5:EL17) -> 0

Sheet Legal and Pre-Dev
B4: =Assumptions!$B$13 -> Legal and Setup Costs | G4: Beg. Mo. | H4: End. Mo. | J4: =+Model!G4 -> 0 | K4: =+Model!H4 -> 1 | L4: =+Model!I4 -> 2 | M4: =+Model!J4 -> 3 | N4: =+Model!K4 -> 4 | O4: =+Model!L4 -> 5 | P4: =+Model!M4 -> 6 | Q4: =+Model!N4 -> 7 | ... EL4: =+Model!EI4 -> 132
B5: Business Formation, Partnership Legal | E5: 15000 | G5: 0 | H5: 0 | J5: =IF(AND($G5=J$4,$H5=J$4),$E5,IF($G5>J$4,0,IF($H5<J$4,0,$E5/($H5-$G5+1)))) -> 15000 | K5: =IF(AND($G5=K$4,$H5=K$4),$E5,IF($G5>K$4,0,IF($H5<K$4,0,$E5/($H5-$G5+1)))) -> 0 | L5: =IF(AND($G5=L$4,$H5=L$4),$E5,IF($G5>L$4,0,IF($H5<L$4,0,$E5/($H5-$G5+1)))) -> 0 | M5: =IF(AND($G5=M$4,$H5=M$4),$E5,IF($G5>M$4,0,IF($H5<M$4,0,$E5/($H5-$G5+1)))) -> 0 | N5: =IF(AND($G5=N$4,$H5=N$4),$E5,IF($G5>N$4,0,IF($H5<N$4,0,$E5/($H5-$G5+1)))) -> 0 | O5: =IF(AND($G5=O$4,$H5=O$4),$E5,IF($G5>O$4,0,IF($H5<O$4,0,$E5/($H5-$G5+1)))) -> 0 | P5: =IF(AND($G5=P$4,$H5=P$4),$E5,IF($G5>P$4,0,IF($H5<P$4,0,$E5/($H5-$G5+1)))) -> 0 | Q5: =IF(AND($G5=Q$4,$H5=Q$4),$E5,IF($G5>Q$4,0,IF($H5<Q$4,0,$E5/($H5-$G5+1)))) -> 0 | ... EL5: =IF(AND($G5=EL$4,$H5=EL$4),$E5,IF($G5>EL$4,0,IF($H5<EL$4,0,$E5/($H5-$G5+1)))) -> 0
B6: Fees, Permits | E6: 500 | G6: 0 | H6: 0 | J6: =IF(AND($G6=J$4,$H6=J$4),$E6,IF($G6>J$4,0,IF($H6<J$4,0,$E6/($H6-$G6+1)))) -> 500 | K6: =IF(AND($G6=K$4,$H6=K$4),$E6,IF($G6>K$4,0,IF($H6<K$4,0,$E6/($H6-$G6+1)))) -> 0 | L6: =IF(AND($G6=L$4,$H6=L$4),$E6,IF($G6>L$4,0,IF($H6<L$4,0,$E6/($H6-$G6+1)))) -> 0 | M6: =IF(AND($G6=M$4,$H6=M$4),$E6,IF($G6>M$4,0,IF($H6<M$4,0,$E6/($H6-$G6+1)))) -> 0 | N6: =IF(AND($G6=N$4,$H6=N$4),$E6,IF($G6>N$4,0,IF($H6<N$4,0,$E6/($H6-$G6+1)))) -> 0 | O6: =IF(AND($G6=O$4,$H6=O$4),$E6,IF($G6>O$4,0,IF($H6<O$4,0,$E6/($H6-$G6+1)))) -> 0 | P6: =IF(AND($G6=P$4,$H6=P$4),$E6,IF($G6>P$4,0,IF($H6<P$4,0,$E6/($H6-$G6+1)))) -> 0 | Q6: =IF(AND($G6=Q$4,$H6=Q$4),$E6,IF($G6>Q$4,0,IF($H6<Q$4,0,$E6/($H6-$G6+1)))) -> 0 | ... EL6: =IF(AND($G6=EL$4,$H6=EL$4),$E6,IF($G6>EL$4,0,IF($H6<EL$4,0,$E6/($H6-$G6+1)))) -> 0
B7: Environmental Testing (Tank Sweep) | E7: 1000 | G7: 0 | H7: 0 | J7: =IF(AND($G7=J$4,$H7=J$4),$E7,IF($G7>J$4,0,IF($H7<J$4,0,$E7/($H7-$G7+1)))) -> 1000 | K7: =IF(AND($G7=K$4,$H7=K$4),$E7,IF($G7>K$4,0,IF($H7<K$4,0,$E7/($H7-$G7+1)))) -> 0 | L7: =IF(AND($G7=L$4,$H7=L$4),$E7,IF($G7>L$4,0,IF($H7<L$4,0,$E7/($H7-$G7+1)))) -> 0 | M7: =IF(AND($G7=M$4,$H7=M$4),$E7,IF($G7>M$4,0,IF($H7<M$4,0,$E7/($H7-$G7+1)))) -> 0 | N7: =IF(AND($G7=N$4,$H7=N$4),$E7,IF($G7>N$4,0,IF($H7<N$4,0,$E7/($H7-$G7+1)))) -> 0 | O7: =IF(AND($G7=O$4,$H7=O$4),$E7,IF($G7>O$4,0,IF($H7<O$4,0,$E7/($H7-$G7+1)))) -> 0 | P7: =IF(AND($G7=P$4,$H7=P$4),$E7,IF($G7>P$4,0,IF($H7<P$4,0,$E7/($H7-$G7+1)))) -> 0 | Q7: =IF(AND($G7=Q$4,$H7=Q$4),$E7,IF($G7>Q$4,0,IF($H7<Q$4,0,$E7/($H7-$G7+1)))) -> 0 | ... EL7: =IF(AND($G7=EL$4,$H7=EL$4),$E7,IF($G7>EL$4,0,IF($H7<EL$4,0,$E7/($H7-$G7+1)))) -> 0
B8: Lender's Legal for Financing | E8: 2500 | G8: 0 | H8: 0 | J8: =IF(AND($G8=J$4,$H8=J$4),$E8,IF($G8>J$4,0,IF($H8<J$4,0,$E8/($H8-$G8+1)))) -> 2500 | K8: =IF(AND($G8=K$4,$H8=K$4),$E8,IF($G8>K$4,0,IF($H8<K$4,0,$E8/($H8-$G8+1)))) -> 0 | L8: =IF(AND($G8=L$4,$H8=L$4),$E8,IF($G8>L$4,0,IF($H8<L$4,0,$E8/($H8-$G8+1)))) -> 0 | M8: =IF(AND($G8=M$4,$H8=M$4),$E8,IF($G8>M$4,0,IF($H8<M$4,0,$E8/($H8-$G8+1)))) -> 0 | N8: =IF(AND($G8=N$4,$H8=N$4),$E8,IF($G8>N$4,0,IF($H8<N$4,0,$E8/($H8-$G8+1)))) -> 0 | O8: =IF(AND($G8=O$4,$H8=O$4),$E8,IF($G8>O$4,0,IF($H8<O$4,0,$E8/($H8-$G8+1)))) -> 0 | P8: =IF(AND($G8=P$4,$H8=P$4),$E8,IF($G8>P$4,0,IF($H8<P$4,0,$E8/($H8-$G8+1)))) -> 0 | Q8: =IF(AND($G8=Q$4,$H8=Q$4),$E8,IF($G8>Q$4,0,IF($H8<Q$4,0,$E8/($H8-$G8+1)))) -> 0 | ... EL8: =IF(AND($G8=EL$4,$H8=EL$4),$E8,IF($G8>EL$4,0,IF($H8<EL$4,0,$E8/($H8-$G8+1)))) -> 0
B9: Borrower's Legal for Financing | E9: 2500 | G9: 0 | H9: 0 | J9: =IF(AND($G9=J$4,$H9=J$4),$E9,IF($G9>J$4,0,IF($H9<J$4,0,$E9/($H9-$G9+1)))) -> 2500 | K9: =IF(AND($G9=K$4,$H9=K$4),$E9,IF($G9>K$4,0,IF($H9<K$4,0,$E9/($H9-$G9+1)))) -> 0 | L9: =IF(AND($G9=L$4,$H9=L$4),$E9,IF($G9>L$4,0,IF($H9<L$4,0,$E9/($H9-$G9+1)))) -> 0 | M9: =IF(AND($G9=M$4,$H9=M$4),$E9,IF($G9>M$4,0,IF($H9<M$4,0,$E9/($H9-$G9+1)))) -> 0 | N9: =IF(AND($G9=N$4,$H9=N$4),$E9,IF($G9>N$4,0,IF($H9<N$4,0,$E9/($H9-$G9+1)))) -> 0 | O9: =IF(AND($G9=O$4,$H9=O$4),$E9,IF($G9>O$4,0,IF($H9<O$4,0,$E9/($H9-$G9+1)))) -> 0 | P9: =IF(AND($G9=P$4,$H9=P$4),$E9,IF($G9>P$4,0,IF($H9<P$4,0,$E9/($H9-$G9+1)))) -> 0 | Q9: =IF(AND($G9=Q$4,$H9=Q$4),$E9,IF($G9>Q$4,0,IF($H9<Q$4,0,$E9/($H9-$G9+1)))) -> 0 | ... EL9: =IF(AND($G9=EL$4,$H9=EL$4),$E9,IF($G9>EL$4,0,IF($H9<EL$4,0,$E9/($H9-$G9+1)))) -> 0
B10: Cost Segregation Study | E10: 10000 | G10: 0 | H10: 0 | J10: =IF(AND($G10=J$4,$H10=J$4),$E10,IF($G10>J$4,0,IF($H10<J$4,0,$E10/($H10-$G10+1)))) -> 10000 | K10: =IF(AND($G10=K$4,$H10=K$4),$E10,IF($G10>K$4,0,IF($H10<K$4,0,$E10/($H10-$G10+1)))) -> 0 | L10: =IF(AND($G10=L$4,$H10=L$4),$E10,IF($G10>L$4,0,IF($H10<L$4,0,$E10/($H10-$G10+1)))) -> 0 | M10: =IF(AND($G10=M$4,$H10=M$4),$E10,IF($G10>M$4,0,IF($H10<M$4,0,$E10/($H10-$G10+1)))) -> 0 | N10: =IF(AND($G10=N$4,$H10=N$4),$E10,IF($G10>N$4,0,IF($H10<N$4,0,$E10/($H10-$G10+1)))) -> 0 | O10: =IF(AND($G10=O$4,$H10=O$4),$E10,IF($G10>O$4,0,IF($H10<O$4,0,$E10/($H10-$G10+1)))) -> 0 | P10: =IF(AND($G10=P$4,$H10=P$4),$E10,IF($G10>P$4,0,IF($H10<P$4,0,$E10/($H10-$G10+1)))) -> 0 | Q10: =IF(AND($G10=Q$4,$H10=Q$4),$E10,IF($G10>Q$4,0,IF($H10<Q$4,0,$E10/($H10-$G10+1)))) -> 0 | ... EL10: =IF(AND($G10=EL$4,$H10=EL$4),$E10,IF($G10>EL$4,0,IF($H10<EL$4,0,$E10/($H10-$G10+1)))) -> 0
B11: Contingency | D11: 0.1 | E11: =+D11*SUM(E5:E10) -> 3150 | G11: =+H11 -> 0 | H11: =MAX(H5:H10) -> 0 | J11: =IF(AND($G11=J$4,$H11=J$4),$E11,IF($G11>J$4,0,IF($H11<J$4,0,$E11/($H11-$G11+1)))) -> 3150 | K11: =IF(AND($G11=K$4,$H11=K$4),$E11,IF($G11>K$4,0,IF($H11<K$4,0,$E11/($H11-$G11+1)))) -> 0 | L11: =IF(AND($G11=L$4,$H11=L$4),$E11,IF($G11>L$4,0,IF($H11<L$4,0,$E11/($H11-$G11+1)))) -> 0 | M11: =IF(AND($G11=M$4,$H11=M$4),$E11,IF($G11>M$4,0,IF($H11<M$4,0,$E11/($H11-$G11+1)))) -> 0 | N11: =IF(AND($G11=N$4,$H11=N$4),$E11,IF($G11>N$4,0,IF($H11<N$4,0,$E11/($H11-$G11+1)))) -> 0 | O11: =IF(AND($G11=O$4,$H11=O$4),$E11,IF($G11>O$4,0,IF($H11<O$4,0,$E11/($H11-$G11+1)))) -> 0 | P11: =IF(AND($G11=P$4,$H11=P$4),$E11,IF($G11>P$4,0,IF($H11<P$4,0,$E11/($H11-$G11+1)))) -> 0 | Q11: =IF(AND($G11=Q$4,$H11=Q$4),$E11,IF($G11>Q$4,0,IF($H11<Q$4,0,$E11/($H11-$G11+1)))) -> 0 | ... EL11: =IF(AND($G11=EL$4,$H11=EL$4),$E11,IF($G11>EL$4,0,IF($H11<EL$4,0,$E11/($H11-$G11+1)))) -> 0
B12: Total Legal and Pre-Development Costs | E12: =SUM(E5:E11) -> 34650 | J12: =SUM(J5:J11) -> 34650 | K12: =SUM(K5:K11) -> 0 | L12: =SUM(L5:L11) -> 0 | M12: =SUM(M5:M11) -> 0 | N12: =SUM(N5:N11) -> 0 | O12: =SUM(O5:O11) -> 0 | P12: =SUM(P5:P11) -> 0 | Q12: =SUM(Q5:Q11) -> 0 | ... EL12: =SUM(EL5:EL11) -> 0

Sheet Reserves
B4: =Assumptions!$B$14 -> Reserves | G4: Beg. Mo. | H4: End. Mo. | J4: =+Model!G4 -> 0 | K4: =+Model!H4 -> 1 | L4: =+Model!I4 -> 2 | M4: =+Model!J4 -> 3 | N4: =+Model!K4 -> 4 | O4: =+Model!L4 -> 5 | P4: =+Model!M4 -> 6 | Q4: =+Model!N4 -> 7 | ... EL4: =+Model!EI4 -> 132
B5: Loan Draws | E5: 0 | G5: 0 | H5: 0 | J5: =IF(AND($G5=J$4,$H5=J$4),$E5,IF($G5>J$4,0,IF($H5<J$4,0,$E5/($H5-$G5+1)))) -> 0 | K5: =IF(AND($G5=K$4,$H5=K$4),$E5,IF($G5>K$4,0,IF($H5<K$4,0,$E5/($H5-$G5+1)))) -> 0 | L5: =IF(AND($G5=L$4,$H5=L$4),$E5,IF($G5>L$4,0,IF($H5<L$4,0,$E5/($H5-$G5+1)))) -> 0 | M5: =IF(AND($G5=M$4,$H5=M$4),$E5,IF($G5>M$4,0,IF($H5<M$4,0,$E5/($H5-$G5+1)))) -> 0 | N5: =IF(AND($G5=N$4,$H5=N$4),$E5,IF($G5>N$4,0,IF($H5<N$4,0,$E5/($H5-$G5+1)))) -> 0 | O5: =IF(AND($G5=O$4,$H5=O$4),$E5,IF($G5>O$4,0,IF($H5<O$4,0,$E5/($H5-$G5+1)))) -> 0 | P5: =IF(AND($G5=P$4,$H5=P$4),$E5,IF($G5>P$4,0,IF($H5<P$4,0,$E5/($H5-$G5+1)))) -> 0 | Q5: =IF(AND($G5=Q$4,$H5=Q$4),$E5,IF($G5>Q$4,0,IF($H5<Q$4,0,$E5/($H5-$G5+1)))) -> 0 | ... EL5: =IF(AND($G5=EL$4,$H5=EL$4),$E5,IF($G5>EL$4,0,IF($H5<EL$4,0,$E5/($H5-$G5+1)))) -> 0
B6: Cash Reserve: Debt Service | E6: =+Assumptions!G31*Assumptions!L27/12 -> 69645.551 | G6: 0 | H6: 0 | J6: =IF(AND($G6=J$4,$H6=J$4),$E6,IF($G6>J$4,0,IF($H6<J$4,0,$E6/($H6-$G6+1)))) -> 69645.551 | K6: =IF(AND($G6=K$4,$H6=K$4),$E6,IF($G6>K$4,0,IF($H6<K$4,0,$E6/($H6-$G6+1)))) -> 0 | L6: =IF(AND($G6=L$4,$H6=L$4),$E6,IF($G6>L$4,0,IF($H6<L$4,0,$E6/($H6-$G6+1)))) -> 0 | M6: =IF(AND($G6=M$4,$H6=M$4),$E6,IF($G6>M$4,0,IF($H6<M$4,0,$E6/($H6-$G6+1)))) -> 0 | N6: =IF(AND($G6=N$4,$H6=N$4),$E6,IF($G6>N$4,0,IF($H6<N$4,0,$E6/($H6-$G6+1)))) -> 0 | O6: =IF(AND($G6=O$4,$H6=O$4),$E6,IF($G6>O$4,0,IF($H6<O$4,0,$E6/($H6-$G6+1)))) -> 0 | P6: =IF(AND($G6=P$4,$H6=P$4),$E6,IF($G6>P$4,0,IF($H6<P$4,0,$E6/($H6-$G6+1)))) -> 0 | Q6: =IF(AND($G6=Q$4,$H6=Q$4),$E6,IF($G6>Q$4,0,IF($H6<Q$4,0,$E6/($H6-$G6+1)))) -> 0 | ... EL6: =IF(AND($G6=EL$4,$H6=EL$4),$E6,IF($G6>EL$4,0,IF($H6<EL$4,0,$E6/($H6-$G6+1)))) -> 0
B7: Cash Reserve: Mechanicals | E7: 25000 | G7: 0 | H7: 0 | J7: =IF(AND($G7=J$4,$H7=J$4),$E7,IF($G7>J$4,0,IF($H7<J$4,0,$E7/($H7-$G7+1)))) -> 25000 | K7: =IF(AND($G7=K$4,$H7=K$4),$E7,IF($G7>K$4,0,IF($H7<K$4,0,$E7/($H7-$G7+1)))) -> 0 | L7: =IF(AND($G7=L$4,$H7=L$4),$E7,IF($G7>L$4,0,IF($H7<L$4,0,$E7/($H7-$G7+1)))) -> 0 | M7: =IF(AND($G7=M$4,$H7=M$4),$E7,IF($G7>M$4,0,IF($H7<M$4,0,$E7/($H7-$G7+1)))) -> 0 | N7: =IF(AND($G7=N$4,$H7=N$4),$E7,IF($G7>N$4,0,IF($H7<N$4,0,$E7/($H7-$G7+1)))) -> 0 | O7: =IF(AND($G7=O$4,$H7=O$4),$E7,IF($G7>O$4,0,IF($H7<O$4,0,$E7/($H7-$G7+1)))) -> 0 | P7: =IF(AND($G7=P$4,$H7=P$4),$E7,IF($G7>P$4,0,IF($H7<P$4,0,$E7/($H7-$G7+1)))) -> 0 | Q7: =IF(AND($G7=Q$4,$H7=Q$4),$E7,IF($G7>Q$4,0,IF($H7<Q$4,0,$E7/($H7-$G7+1)))) -> 0 | ... EL7: =IF(AND($G7=EL$4,$H7=EL$4),$E7,IF($G7>EL$4,0,IF($H7<EL$4,0,$E7/($H7-$G7+1)))) -> 0
B8: Cash Reserve: Roof | E8: 25000 | G8: 0 | H8: 0 | J8: =IF(AND($G8=J$4,$H8=J$4),$E8,IF($G8>J$4,0,IF($H8<J$4,0,$E8/($H8-$G8+1)))) -> 25000 | K8: =IF(AND($G8=K$4,$H8=K$4),$E8,IF($G8>K$4,0,IF($H8<K$4,0,$E8/($H8-$G8+1)))) -> 0 | L8: =IF(AND($G8=L$4,$H8=L$4),$E8,IF($G8>L$4,0,IF($H8<L$4,0,$E8/($H8-$G8+1)))) -> 0 | M8: =IF(AND($G8=M$4,$H8=M$4),$E8,IF($G8>M$4,0,IF($H8<M$4,0,$E8/($H8-$G8+1)))) -> 0 | N8: =IF(AND($G8=N$4,$H8=N$4),$E8,IF($G8>N$4,0,IF($H8<N$4,0,$E8/($H8-$G8+1)))) -> 0 | O8: =IF(AND($G8=O$4,$H8=O$4),$E8,IF($G8>O$4,0,IF($H8<O$4,0,$E8/($H8-$G8+1)))) -> 0 | P8: =IF(AND($G8=P$4,$H8=P$4),$E8,IF($G8>P$4,0,IF($H8<P$4,0,$E8/($H8-$G8+1)))) -> 0 | Q8: =IF(AND($G8=Q$4,$H8=Q$4),$E8,IF($G8>Q$4,0,IF($H8<Q$4,0,$E8/($H8-$G8+1)))) -> 0 | ... EL8: =IF(AND($G8=EL$4,$H8=EL$4),$E8,IF($G8>EL$4,0,IF($H8<EL$4,0,$E8/($H8-$G8+1)))) -> 0
B9: Cash Reserve: Cash for Keys | C9: 20 | D9: 5000 | E9: =+D9*C9 -> 100000 | G9: 1 | H9: 33 | J9: =IF(AND($G9=J$4,$H9=J$4),$E9,IF($G9>J$4,0,IF($H9<J$4,0,$E9/($H9-$G9+1)))) -> 0 | K9: =IF(AND($G9=K$4,$H9=K$4),$E9,IF($G9>K$4,0,IF($H9<K$4,0,$E9/($H9-$G9+1)))) -> 3030.303 | L9: =IF(AND($G9=L$4,$H9=L$4),$E9,IF($G9>L$4,0,IF($H9<L$4,0,$E9/($H9-$G9+1)))) -> 3030.303 | M9: =IF(AND($G9=M$4,$H9=M$4),$E9,IF($G9>M$4,0,IF($H9<M$4,0,$E9/($H9-$G9+1)))) -> 3030.303 | N9: =IF(AND($G9=N$4,$H9=N$4),$E9,IF($G9>N$4,0,IF($H9<N$4,0,$E9/($H9-$G9+1)))) -> 3030.303 | O9: =IF(AND($G9=O$4,$H9=O$4),$E9,IF($G9>O$4,0,IF($H9<O$4,0,$E9/($H9-$G9+1)))) -> 3030.303 | P9: =IF(AND($G9=P$4,$H9=P$4),$E9,IF($G9>P$4,0,IF($H9<P$4,0,$E9/($H9-$G9+1)))) -> 3030.303 | Q9: =IF(AND($G9=Q$4,$H9=Q$4),$E9,IF($G9>Q$4,0,IF($H9<Q$4,0,$E9/($H9-$G9+1)))) -> 3030.303 | ... EL9: =IF(AND($G9=EL$4,$H9=EL$4),$E9,IF($G9>EL$4,0,IF($H9<EL$4,0,$E9/($H9-$G9+1)))) -> 0
B10: Leasing Cost Reserves | C10: =IFERROR(SUMIFS(Assumptions!$D$46:$D$123,Assumptions!$D$46:$D$123,1),0) -> 62 | D10: =+Assumptions!J124/Assumptions!E124 -> 2119.3855 | E10: =+D10*C10 -> 131401.9 | G10: 1 | H10: 33 | J10: =IF(AND($G10=J$4,$H10=J$4),$E10,IF($G10>J$4,0,IF($H10<J$4,0,$E10/($H10-$G10+1)))) -> 0 | K10: =IF(AND($G10=K$4,$H10=K$4),$E10,IF($G10>K$4,0,IF($H10<K$4,0,$E10/($H10-$G10+1)))) -> 3981.8758 | L10: =IF(AND($G10=L$4,$H10=L$4),$E10,IF($G10>L$4,0,IF($H10<L$4,0,$E10/($H10-$G10+1)))) -> 3981.8758 | M10: =IF(AND($G10=M$4,$H10=M$4),$E10,IF($G10>M$4,0,IF($H10<M$4,0,$E10/($H10-$G10+1)))) -> 3981.8758 | N10: =IF(AND($G10=N$4,$H10=N$4),$E10,IF($G10>N$4,0,IF($H10<N$4,0,$E10/($H10-$G10+1)))) -> 3981.8758 | O10: =IF(AND($G10=O$4,$H10=O$4),$E10,IF($G10>O$4,0,IF($H10<O$4,0,$E10/($H10-$G10+1)))) -> 3981.8758 | P10: =IF(AND($G10=P$4,$H10=P$4),$E10,IF($G10>P$4,0,IF($H10<P$4,0,$E10/($H10-$G10+1)))) -> 3981.8758 | Q10: =IF(AND($G10=Q$4,$H10=Q$4),$E10,IF($G10>Q$4,0,IF($H10<Q$4,0,$E10/($H10-$G10+1)))) -> 3981.8758 | ... EL10: =IF(AND($G10=EL$4,$H10=EL$4),$E10,IF($G10>EL$4,0,IF($H10<EL$4,0,$E10/($H10-$G10+1)))) -> 0
B11: Contingency | D11: 0.1 | E11: =+D11*SUM(E5:E10) -> 35104.745 | G11: =+H11 -> 33 | H11: =MAX(H5:H10) -> 33 | J11: =IF(AND($G11=J$4,$H11=J$4),$E11,IF($G11>J$4,0,IF($H11<J$4,0,$E11/($H11-$G11+1)))) -> 0 | K11: =IF(AND($G11=K$4,$H11=K$4),$E11,IF($G11>K$4,0,IF($H11<K$4,0,$E11/($H11-$G11+1)))) -> 0 | L11: =IF(AND($G11=L$4,$H11=L$4),$E11,IF($G11>L$4,0,IF($H11<L$4,0,$E11/($H11-$G11+1)))) -> 0 | M11: =IF(AND($G11=M$4,$H11=M$4),$E11,IF($G11>M$4,0,IF($H11<M$4,0,$E11/($H11-$G11+1)))) -> 0 | N11: =IF(AND($G11=N$4,$H11=N$4),$E11,IF($G11>N$4,0,IF($H11<N$4,0,$E11/($H11-$G11+1)))) -> 0 | O11: =IF(AND($G11=O$4,$H11=O$4),$E11,IF($G11>O$4,0,IF($H11<O$4,0,$E11/($H11-$G11+1)))) -> 0 | P11: =IF(AND($G11=P$4,$H11=P$4),$E11,IF($G11>P$4,0,IF($H11<P$4,0,$E11/($H11-$G11+1)))) -> 0 | Q11: =IF(AND($G11=Q$4,$H11=Q$4),$E11,IF($G11>Q$4,0,IF($H11<Q$4,0,$E11/($H11-$G11+1)))) -> 0 | ... EL11: =IF(AND($G11=EL$4,$H11=EL$4),$E11,IF($G11>EL$4,0,IF($H11<EL$4,0,$E11/($H11-$G11+1)))) -> 0
B12: Total Reserves | E12: =SUM(E5:E11) -> 386152.2 | J12: =SUM(J5:J11) -> 119645.55 | K12: =SUM(K5:K11) -> 7012.1788 | L12: =SUM(L5:L11) -> 7012.1788 | M12: =SUM(M5:M11) -> 7012.1788 | N12: =SUM(N5:N11) -> 7012.1788 | O12: =SUM(O5:O11) -> 7012.1788 | P12: =SUM(P5:P11) -> 7012.1788 | Q12: =SUM(Q5:Q11) -> 7012.1788 | ... EL12: =SUM(EL5:EL11) -> 0

Sheet Hard Costs
B4: =+Assumptions!B15 -> Hard Costs | D4: =+Assumptions!G24 -> 55000 | G4: Beg. Mo. | H4: End. Mo. | J4: =+Model!G4 -> 0 | K4: =+Model!H4 -> 1 | L4: =+Model!I4 -> 2 | M4: =+Model!J4 -> 3 | N4: =+Model!K4 -> 4 | O4: =+Model!L4 -> 5 | P4: =+Model!M4 -> 6 | Q4: =+Model!N4 -> 7 | ... EL4: =+Model!EI4 -> 132
B5: Demo | E5: 20000 | G5: 0 | H5: 0 | J5: =IF(AND($G5=J$4,$H5=J$4),$E5,IF($G5>J$4,0,IF($H5<J$4,0,$E5/($H5-$G5+1)))) -> 20000 | K5: =IF(AND($G5=K$4,$H5=K$4),$E5,IF($G5>K$4,0,IF($H5<K$4,0,$E5/($H5-$G5+1)))) -> 0 | L5: =IF(AND($G5=L$4,$H5=L$4),$E5,IF($G5>L$4,0,IF($H5<L$4,0,$E5/($H5-$G5+1)))) -> 0 | M5: =IF(AND($G5=M$4,$H5=M$4),$E5,IF($G5>M$4,0,IF($H5<M$4,0,$E5/($H5-$G5+1)))) -> 0 | N5: =IF(AND($G5=N$4,$H5=N$4),$E5,IF($G5>N$4,0,IF($H5<N$4,0,$E5/($H5-$G5+1)))) -> 0 | O5: =IF(AND($G5=O$4,$H5=O$4),$E5,IF($G5>O$4,0,IF($H5<O$4,0,$E5/($H5-$G5+1)))) -> 0 | P5: =IF(AND($G5=P$4,$H5=P$4),$E5,IF($G5>P$4,0,IF($H5<P$4,0,$E5/($H5-$G5+1)))) -> 0 | Q5: =IF(AND($G5=Q$4,$H5=Q$4),$E5,IF($G5>Q$4,0,IF($H5<Q$4,0,$E5/($H5-$G5+1)))) -> 0 | ... EL5: =IF(AND($G5=EL$4,$H5=EL$4),$E5,IF($G5>EL$4,0,IF($H5<EL$4,0,$E5/($H5-$G5+1)))) -> 0
B6: Dumpsters and Permits | E6: 10000 | G6: 2 | H6: 11 | J6: =IF(AND($G6=J$4,$H6=J$4),$E6,IF($G6>J$4,0,IF($H6<J$4,0,$E6/($H6-$G6+1)))) -> 0 | K6: =IF(AND($G6=K$4,$H6=K$4),$E6,IF($G6>K$4,0,IF($H6<K$4,0,$E6/($H6-$G6+1)))) -> 0 | L6: =IF(AND($G6=L$4,$H6=L$4),$E6,IF($G6>L$4,0,IF($H6<L$4,0,$E6/($H6-$G6+1)))) -> 1000 | M6: =IF(AND($G6=M$4,$H6=M$4),$E6,IF($G6>M$4,0,IF($H6<M$4,0,$E6/($H6-$G6+1)))) -> 1000 | N6: =IF(AND($G6=N$4,$H6=N$4),$E6,IF($G6>N$4,0,IF($H6<N$4,0,$E6/($H6-$G6+1)))) -> 1000 | O6: =IF(AND($G6=O$4,$H6=O$4),$E6,IF($G6>O$4,0,IF($H6<O$4,0,$E6/($H6-$G6+1)))) -> 1000 | P6: =IF(AND($G6=P$4,$H6=P$4),$E6,IF($G6>P$4,0,IF($H6<P$4,0,$E6/($H6-$G6+1)))) -> 1000 | Q6: =IF(AND($G6=Q$4,$H6=Q$4),$E6,IF($G6>Q$4,0,IF($H6<Q$4,0,$E6/($H6-$G6+1)))) -> 1000 | ... EL6: =IF(AND($G6=EL$4,$H6=EL$4),$E6,IF($G6>EL$4,0,IF($H6<EL$4,0,$E6/($H6-$G6+1)))) -> 0
B7: Storage Buildout | C7: 50 | D7: 1250 | E7: =+D7*C7 -> 62500 | G7: 5 | H7: 6 | J7: =IF(AND($G7=J$4,$H7=J$4),$E7,IF($G7>J$4,0,IF($H7<J$4,0,$E7/($H7-$G7+1)))) -> 0 | K7: =IF(AND($G7=K$4,$H7=K$4),$E7,IF($G7>K$4,0,IF($H7<K$4,0,$E7/($H7-$G7+1)))) -> 0 | L7: =IF(AND($G7=L$4,$H7=L$4),$E7,IF($G7>L$4,0,IF($H7<L$4,0,$E7/($H7-$G7+1)))) -> 0 | M7: =IF(AND($G7=M$4,$H7=M$4),$E7,IF($G7>M$4,0,IF($H7<M$4,0,$E7/($H7-$G7+1)))) -> 0 | N7: =IF(AND($G7=N$4,$H7=N$4),$E7,IF($G7>N$4,0,IF($H7<N$4,0,$E7/($H7-$G7+1)))) -> 0 | O7: =IF(AND($G7=O$4,$H7=O$4),$E7,IF($G7>O$4,0,IF($H7<O$4,0,$E7/($H7-$G7+1)))) -> 31250 | P7: =IF(AND($G7=P$4,$H7=P$4),$E7,IF($G7>P$4,0,IF($H7<P$4,0,$E7/($H7-$G7+1)))) -> 31250 | Q7: =IF(AND($G7=Q$4,$H7=Q$4),$E7,IF($G7>Q$4,0,IF($H7<Q$4,0,$E7/($H7-$G7+1)))) -> 0 | ... EL7: =IF(AND($G7=EL$4,$H7=EL$4),$E7,IF($G7>EL$4,0,IF($H7<EL$4,0,$E7/($H7-$G7+1)))) -> 0
B8: Green Card Repairs | E8: 20000 | G8: 0 | H8: 0 | J8: =IF(AND($G8=J$4,$H8=J$4),$E8,IF($G8>J$4,0,IF($H8<J$4,0,$E8/($H8-$G8+1)))) -> 20000 | K8: =IF(AND($G8=K$4,$H8=K$4),$E8,IF($G8>K$4,0,IF($H8<K$4,0,$E8/($H8-$G8+1)))) -> 0 | L8: =IF(AND($G8=L$4,$H8=L$4),$E8,IF($G8>L$4,0,IF($H8<L$4,0,$E8/($H8-$G8+1)))) -> 0 | M8: =IF(AND($G8=M$4,$H8=M$4),$E8,IF($G8>M$4,0,IF($H8<M$4,0,$E8/($H8-$G8+1)))) -> 0 | N8: =IF(AND($G8=N$4,$H8=N$4),$E8,IF($G8>N$4,0,IF($H8<N$4,0,$E8/($H8-$G8+1)))) -> 0 | O8: =IF(AND($G8=O$4,$H8=O$4),$E8,IF($G8>O$4,0,IF($H8<O$4,0,$E8/($H8-$G8+1)))) -> 0 | P8: =IF(AND($G8=P$4,$H8=P$4),$E8,IF($G8>P$4,0,IF($H8<P$4,0,$E8/($H8-$G8+1)))) -> 0 | Q8: =IF(AND($G8=Q$4,$H8=Q$4),$E8,IF($G8>Q$4,0,IF($H8<Q$4,0,$E8/($H8-$G8+1)))) -> 0 | ... EL8: =IF(AND($G8=EL$4,$H8=EL$4),$E8,IF($G8>EL$4,0,IF($H8<EL$4,0,$E8/($H8-$G8+1)))) -> 0
B9: Mechancial repairs | E9: 10000 | G9: 0 | H9: 0 | J9: =IF(AND($G9=J$4,$H9=J$4),$E9,IF($G9>J$4,0,IF($H9<J$4,0,$E9/($H9-$G9+1)))) -> 10000 | K9: =IF(AND($G9=K$4,$H9=K$4),$E9,IF($G9>K$4,0,IF($H9<K$4,0,$E9/($H9-$G9+1)))) -> 0 | L9: =IF(AND($G9=L$4,$H9=L$4),$E9,IF($G9>L$4,0,IF($H9<L$4,0,$E9/($H9-$G9+1)))) -> 0 | M9: =IF(AND($G9=M$4,$H9=M$4),$E9,IF($G9>M$4,0,IF($H9<M$4,0,$E9/($H9-$G9+1)))) -> 0 | N9: =IF(AND($G9=N$4,$H9=N$4),$E9,IF($G9>N$4,0,IF($H9<N$4,0,$E9/($H9-$G9+1)))) -> 0 | O9: =IF(AND($G9=O$4,$H9=O$4),$E9,IF($G9>O$4,0,IF($H9<O$4,0,$E9/($H9-$G9+1)))) -> 0 | P9: =IF(AND($G9=P$4,$H9=P$4),$E9,IF($G9>P$4,0,IF($H9<P$4,0,$E9/($H9-$G9+1)))) -> 0 | Q9: =IF(AND($G9=Q$4,$H9=Q$4),$E9,IF($G9>Q$4,0,IF($H9<Q$4,0,$E9/($H9-$G9+1)))) -> 0 | ... EL9: =IF(AND($G9=EL$4,$H9=EL$4),$E9,IF($G9>EL$4,0,IF($H9<EL$4,0,$E9/($H9-$G9+1)))) -> 0
B10: Common Area Refresh | E10: 20000 | G10: 10 | H10: 10 | J10: =IF(AND($G10=J$4,$H10=J$4),$E10,IF($G10>J$4,0,IF($H10<J$4,0,$E10/($H10-$G10+1)))) -> 0 | K10: =IF(AND($G10=K$4,$H10=K$4),$E10,IF($G10>K$4,0,IF($H10<K$4,0,$E10/($H10-$G10+1)))) -> 0 | L10: =IF(AND($G10=L$4,$H10=L$4),$E10,IF($G10>L$4,0,IF($H10<L$4,0,$E10/($H10-$G10+1)))) -> 0 | M10: =IF(AND($G10=M$4,$H10=M$4),$E10,IF($G10>M$4,0,IF($H10<M$4,0,$E10/($H10-$G10+1)))) -> 0 | N10: =IF(AND($G10=N$4,$H10=N$4),$E10,IF($G10>N$4,0,IF($H10<N$4,0,$E10/($H10-$G10+1)))) -> 0 | O10: =IF(AND($G10=O$4,$H10=O$4),$E10,IF($G10>O$4,0,IF($H10<O$4,0,$E10/($H10-$G10+1)))) -> 0 | P10: =IF(AND($G10=P$4,$H10=P$4),$E10,IF($G10>P$4,0,IF($H10<P$4,0,$E10/($H10-$G10+1)))) -> 0 | Q10: =IF(AND($G10=Q$4,$H10=Q$4),$E10,IF($G10>Q$4,0,IF($H10<Q$4,0,$E10/($H10-$G10+1)))) -> 0 | ... EL10: =IF(AND($G10=EL$4,$H10=EL$4),$E10,IF($G10>EL$4,0,IF($H10<EL$4,0,$E10/($H10-$G10+1)))) -> 0
B11: Exterior Façade | E11: 30000 | G11: 5 | H11: 5 | J11: =IF(AND($G11=J$4,$H11=J$4),$E11,IF($G11>J$4,0,IF($H11<J$4,0,$E11/($H11-$G11+1)))) -> 0 | K11: =IF(AND($G11=K$4,$H11=K$4),$E11,IF($G11>K$4,0,IF($H11<K$4,0,$E11/($H11-$G11+1)))) -> 0 | L11: =IF(AND($G11=L$4,$H11=L$4),$E11,IF($G11>L$4,0,IF($H11<L$4,0,$E11/($H11-$G11+1)))) -> 0 | M11: =IF(AND($G11=M$4,$H11=M$4),$E11,IF($G11>M$4,0,IF($H11<M$4,0,$E11/($H11-$G11+1)))) -> 0 | N11: =IF(AND($G11=N$4,$H11=N$4),$E11,IF($G11>N$4,0,IF($H11<N$4,0,$E11/($H11-$G11+1)))) -> 0 | O11: =IF(AND($G11=O$4,$H11=O$4),$E11,IF($G11>O$4,0,IF($H11<O$4,0,$E11/($H11-$G11+1)))) -> 30000 | P11: =IF(AND($G11=P$4,$H11=P$4),$E11,IF($G11>P$4,0,IF($H11<P$4,0,$E11/($H11-$G11+1)))) -> 0 | Q11: =IF(AND($G11=Q$4,$H11=Q$4),$E11,IF($G11>Q$4,0,IF($H11<Q$4,0,$E11/($H11-$G11+1)))) -> 0 | ... EL11: =IF(AND($G11=EL$4,$H11=EL$4),$E11,IF($G11>EL$4,0,IF($H11<EL$4,0,$E11/($H11-$G11+1)))) -> 0
B12: Roof repair | E12: 10000 | G12: 0 | H12: 0 | J12: =IF(AND($G12=J$4,$H12=J$4),$E12,IF($G12>J$4,0,IF($H12<J$4,0,$E12/($H12-$G12+1)))) -> 10000 | K12: =IF(AND($G12=K$4,$H12=K$4),$E12,IF($G12>K$4,0,IF($H12<K$4,0,$E12/($H12-$G12+1)))) -> 0 | L12: =IF(AND($G12=L$4,$H12=L$4),$E12,IF($G12>L$4,0,IF($H12<L$4,0,$E12/($H12-$G12+1)))) -> 0 | M12: =IF(AND($G12=M$4,$H12=M$4),$E12,IF($G12>M$4,0,IF($H12<M$4,0,$E12/($H12-$G12+1)))) -> 0 | N12: =IF(AND($G12=N$4,$H12=N$4),$E12,IF($G12>N$4,0,IF($H12<N$4,0,$E12/($H12-$G12+1)))) -> 0 | O12: =IF(AND($G12=O$4,$H12=O$4),$E12,IF($G12>O$4,0,IF($H12<O$4,0,$E12/($H12-$G12+1)))) -> 0 | P12: =IF(AND($G12=P$4,$H12=P$4),$E12,IF($G12>P$4,0,IF($H12<P$4,0,$E12/($H12-$G12+1)))) -> 0 | Q12: =IF(AND($G12=Q$4,$H12=Q$4),$E12,IF($G12>Q$4,0,IF($H12<Q$4,0,$E12/($H12-$G12+1)))) -> 0 | ... EL12: =IF(AND($G12=EL$4,$H12=EL$4),$E12,IF($G12>EL$4,0,IF($H12<EL$4,0,$E12/($H12-$G12+1)))) -> 0
B13: Parking lot seal cracks | E13: 10000 | G13: 0 | H13: 0 | J13: =IF(AND($G13=J$4,$H13=J$4),$E13,IF($G13>J$4,0,IF($H13<J$4,0,$E13/($H13-$G13+1)))) -> 10000 | K13: =IF(AND($G13=K$4,$H13=K$4),$E13,IF($G13>K$4,0,IF($H13<K$4,0,$E13/($H13-$G13+1)))) -> 0 | L13: =IF(AND($G13=L$4,$H13=L$4),$E13,IF($G13>L$4,0,IF($H13<L$4,0,$E13/($H13-$G13+1)))) -> 0 | M13: =IF(AND($G13=M$4,$H13=M$4),$E13,IF($G13>M$4,0,IF($H13<M$4,0,$E13/($H13-$G13+1)))) -> 0 | N13: =IF(AND($G13=N$4,$H13=N$4),$E13,IF($G13>N$4,0,IF($H13<N$4,0,$E13/($H13-$G13+1)))) -> 0 | O13: =IF(AND($G13=O$4,$H13=O$4),$E13,IF($G13>O$4,0,IF($H13<O$4,0,$E13/($H13-$G13+1)))) -> 0 | P13: =IF(AND($G13=P$4,$H13=P$4),$E13,IF($G13>P$4,0,IF($H13<P$4,0,$E13/($H13-$G13+1)))) -> 0 | Q13: =IF(AND($G13=Q$4,$H13=Q$4),$E13,IF($G13>Q$4,0,IF($H13<Q$4,0,$E13/($H13-$G13+1)))) -> 0 | ... EL13: =IF(AND($G13=EL$4,$H13=EL$4),$E13,IF($G13>EL$4,0,IF($H13<EL$4,0,$E13/($H13-$G13+1)))) -> 0
B14: Unit Rehabs | C14: 5 | D14: 10000 | E14: =+D14*C14 -> 50000 | G14: 2 | H14: 24 | J14: =IF(AND($G14=J$4,$H14=J$4),$E14,IF($G14>J$4,0,IF($H14<J$4,0,$E14/($H14-$G14+1)))) -> 0 | K14: =IF(AND($G14=K$4,$H14=K$4),$E14,IF($G14>K$4,0,IF($H14<K$4,0,$E14/($H14-$G14+1)))) -> 0 | L14: =IF(AND($G14=L$4,$H14=L$4),$E14,IF($G14>L$4,0,IF($H14<L$4,0,$E14/($H14-$G14+1)))) -> 2173.913 | M14: =IF(AND($G14=M$4,$H14=M$4),$E14,IF($G14>M$4,0,IF($H14<M$4,0,$E14/($H14-$G14+1)))) -> 2173.913 | N14: =IF(AND($G14=N$4,$H14=N$4),$E14,IF($G14>N$4,0,IF($H14<N$4,0,$E14/($H14-$G14+1)))) -> 2173.913 | O14: =IF(AND($G14=O$4,$H14=O$4),$E14,IF($G14>O$4,0,IF($H14<O$4,0,$E14/($H14-$G14+1)))) -> 2173.913 | P14: =IF(AND($G14=P$4,$H14=P$4),$E14,IF($G14>P$4,0,IF($H14<P$4,0,$E14/($H14-$G14+1)))) -> 2173.913 | Q14: =IF(AND($G14=Q$4,$H14=Q$4),$E14,IF($G14>Q$4,0,IF($H14<Q$4,0,$E14/($H14-$G14+1)))) -> 2173.913 | ... EL14: =IF(AND($G14=EL$4,$H14=EL$4),$E14,IF($G14>EL$4,0,IF($H14<EL$4,0,$E14/($H14-$G14+1)))) -> 0
