Workbook
Name Financial_Summary: #REF!
Name IQ_CH: 110000
Name IQ_CQ: 5000
Name IQ_CY: 10000
Name IQ_DAILY: 500000
Name IQ_FH: 100000
Name IQ_FQ: 500
Name IQ_FY: 1000
Name IQ_LTM: 2000
Name IQ_MONTH: 15000
Name IQ_NTM: 6000
Name IQ_WEEK: 50000
Name IQ_YTD: 3000

Sheet Diligence and Notes
B3: Notes
B4: 1 | C4: Sold for $11.5mm in 2018.
B5: 2
B6: 3
B8: Diligence Questions
B9: 1 | C9: Please confirm there are no elevators.
B10: 2 | C10: What are Super's responsibilities?
B11: 3 | C11: How many units have been renovated since acquiring?
B12: 4 | C12: Please share gross Sq Ft of property and approx Sq Ft of the units.
B13: 5 | C13: What is the age of the mechanicals?
B14: 6 | C14: What is approx. age of the roof?
B15: 7 | C15: Please share rent comps.

Sheet Underwriting Assumptions
C3: Underwriting Assumptions
J4: Monthly | K4: Annual | M4: Notes
C5: Pro Forma Rent Roll | J5: =+K5/12 -> 189600 | K5: =+Assumptions!J124 -> 2275200 | M5: Current Rent Roll
C6: ="Plus: "&Assumptions!B131 -> Plus: Total Amenity Income | J6: =+K6/12 -> 10648 | K6: =+Assumptions!J131 -> 127776 | M6: Laundry Currently
C7: Less: Vacancy, Turnover, Bad Debt | G7: =-Assumptions!G146-Assumptions!G145-Assumptions!P144 -> -0.066666667 | J7: =+$G$7*J5 -> -12640 | K7: =+$G$7*K5 -> -151680 | M7: 5% Vacancy + 20% Turnover
C8: Effective Gross Income | J8: =SUM(J5:J7) -> 187608 | K8: =SUM(K5:K7) -> 2251296
C10: =Assumptions!B148 -> Operating Expenses | H10: =Assumptions!G148 -> Factor | I10: =Assumptions!H148 -> Statistic | J10: =Assumptions!I148 -> Monthly | K10: =Assumptions!J148 -> Annual
C11: =Assumptions!B149 -> Property Taxes | H11: =Assumptions!G149 -> 3815.7179 | I11: =Assumptions!H149 -> 78 | J11: =Assumptions!I149 -> 24802.167 | K11: =Assumptions!J149 -> 297626 | M11: Broker
C12: =Assumptions!B150 -> Insurance | H12: =Assumptions!G150 -> 1200 | I12: =Assumptions!H150 -> 78 | J12: =Assumptions!I150 -> 7800 | K12: =Assumptions!J150 -> 93600 | M12: Estimate
C13: =Assumptions!B151 -> Water / Sewer | H13: =Assumptions!G151 -> 600.89744 | I13: =Assumptions!H151 -> 78 | J13: =Assumptions!I151 -> 3905.8333 | K13: =Assumptions!J151 -> 46870 | M13: Estimate
C14: =Assumptions!B152 -> Repairs & Maintenance | H14: =Assumptions!G152 -> 500 | I14: =Assumptions!H152 -> 78 | J14: =Assumptions!I152 -> 3250 | K14: =Assumptions!J152 -> 39000 | M14: Estimate
C15: =Assumptions!B153 -> Elevator Contract | J15: =Assumptions!I153 -> 0 | K15: =Assumptions!J153 -> 0 | M15: Estimate
C16: =Assumptions!B154 -> Trash | J16: =Assumptions!I154 -> 200 | K16: =Assumptions!J154 -> 2400 | M16: Estimate (NEW)
C17: =Assumptions!B156 -> Security, Internet | J17: =Assumptions!I156 -> 200 | K17: =Assumptions!J156 -> 2400 | M17: Estimate (NEW)
C18: =Assumptions!B157 -> Pest Control | H18: =Assumptions!G157 -> 50 | I18: =Assumptions!H157 -> 78 | J18: =Assumptions!I157 -> 325 | K18: =Assumptions!J157 -> 3900 | M18: Estimate (NEW)
C19: =Assumptions!B160 -> Common Area Electric | H19: =Assumptions!G160 -> 0.67009901 | I19: =Assumptions!H160 -> 5050 | J19: =Assumptions!I160 -> 282 | K19: =Assumptions!J160 -> 3384 | M19: Broker
C20: =Assumptions!B161 -> Landscaping / Snow Removal | J20: =Assumptions!I161 -> 500 | K20: =Assumptions!J161 -> 6000 | M20: Estimate
C21: =Assumptions!B162 -> Property Management | H21: =Assumptions!G162 -> 0.03 | I21: =Assumptions!H162 -> 2242777.6 | J21: =Assumptions!I162 -> 5606.944 | K21: =Assumptions!J162 -> 67283.328 | M21: PCG PM Fee
C22: =Assumptions!B163 -> Accounting / Legal | J22: =Assumptions!I163 -> 208.33333 | K22: =Assumptions!J163 -> 2500 | M22: Estimate (NEW)
C23: =+Assumptions!B164 -> Total Operating Expenses | J23: =Assumptions!I164 -> 56920.611 | K23: =Assumptions!J164 -> 683047.33
C24: Operating Expense Margin | K24: =+K23/K8 -> 0.30340183
C26: Net Operating Income | J26: =+J8-J23 -> 130687.39 | K26: =+K8-K23 -> 1568248.7
C27: ="Implied Stabilized Cap Rate at "&TEXT(Assumptions!G23,"$#,##0")&" Purchase" -> Implied Stabilized Cap Rate at $15,000,000 Purchase | K27: =+K26/Assumptions!G23 -> 0.10454991

Sheet NOI
C3: Net Operating Income Summary
G4: 1 | H4: =+G4+1 -> 2 | I4: =+H4+1 -> 3 | J4: =+I4+1 -> 4 | K4: =+J4+1 -> 5
C5: ='NOI Walk'!B22 -> Gross Potential Rent | G5: =+SUMIFS('NOI Walk'!$H22:$CZ22,'NOI Walk'!$H$15:$CZ$15,NOI!G$4) -> 2306246.6 | H5: =+SUMIFS('NOI Walk'!$H22:$CZ22,'NOI Walk'!$H$15:$CZ$15,NOI!H$4) -> 2364568 | I5: =+SUMIFS('NOI Walk'!$H22:$CZ22,'NOI Walk'!$H$15:$CZ$15,NOI!I$4) -> 2424364.3 | J5: =+SUMIFS('NOI Walk'!$H22:$CZ22,'NOI Walk'!$H$15:$CZ$15,NOI!J$4) -> 2485672.7 | K5: =+SUMIFS('NOI Walk'!$H22:$CZ22,'NOI Walk'!$H$15:$CZ$15,NOI!K$4) -> 2548531.5
C6: Loss-to-Lease | G6: =+SUMIFS('NOI Walk'!$H23:$CZ23,'NOI Walk'!$H$15:$CZ$15,NOI!G$4) -> -721212.05 | H6: =+SUMIFS('NOI Walk'!$H23:$CZ23,'NOI Walk'!$H$15:$CZ$15,NOI!H$4) -> -369245.48 | I6: =+SUMIFS('NOI Walk'!$H23:$CZ23,'NOI Walk'!$H$15:$CZ$15,NOI!I$4) -> -40882.296 | J6: =+SUMIFS('NOI Walk'!$H23:$CZ23,'NOI Walk'!$H$15:$CZ$15,NOI!J$4) -> 0 | K6: =+SUMIFS('NOI Walk'!$H23:$CZ23,'NOI Walk'!$H$15:$CZ$15,NOI!K$4) -> 0
C7: Vacancy | G7: =+SUMIFS('NOI Walk'!$H26:$CZ26,'NOI Walk'!$H$15:$CZ$15,NOI!G$4) -> -143581.91 | H7: =+SUMIFS('NOI Walk'!$H26:$CZ26,'NOI Walk'!$H$15:$CZ$15,NOI!H$4) -> -176301.68 | I7: =+SUMIFS('NOI Walk'!$H26:$CZ26,'NOI Walk'!$H$15:$CZ$15,NOI!I$4) -> -130841.15 | J7: =+SUMIFS('NOI Walk'!$H26:$CZ26,'NOI Walk'!$H$15:$CZ$15,NOI!J$4) -> -124283.64 | K7: =+SUMIFS('NOI Walk'!$H26:$CZ26,'NOI Walk'!$H$15:$CZ$15,NOI!K$4) -> -127426.58
C8: ='NOI Walk'!B27 -> Vacancy | G8: =-G7/G5 -> 0.06225783 | H8: =-H7/H5 -> 0.074559786 | I8: =-I7/I5 -> 0.05396926 | J8: =-J7/J5 -> 0.05 | K8: =-K7/K5 -> 0.05
C9: Rental Income | G9: =+SUMIFS('NOI Walk'!$H24:$CZ24,'NOI Walk'!$H$15:$CZ$15,NOI!G$4)+SUMIFS('NOI Walk'!$H25:$CZ25,'NOI Walk'!$H$15:$CZ$15,NOI!G$4) -> 1441452.6 | H9: =+SUMIFS('NOI Walk'!$H24:$CZ24,'NOI Walk'!$H$15:$CZ$15,NOI!H$4)+SUMIFS('NOI Walk'!$H25:$CZ25,'NOI Walk'!$H$15:$CZ$15,NOI!H$4) -> 1819020.8 | I9: =+SUMIFS('NOI Walk'!$H24:$CZ24,'NOI Walk'!$H$15:$CZ$15,NOI!I$4)+SUMIFS('NOI Walk'!$H25:$CZ25,'NOI Walk'!$H$15:$CZ$15,NOI!I$4) -> 2323719.1 | J9: =+SUMIFS('NOI Walk'!$H24:$CZ24,'NOI Walk'!$H$15:$CZ$15,NOI!J$4)+SUMIFS('NOI Walk'!$H25:$CZ25,'NOI Walk'!$H$15:$CZ$15,NOI!J$4) -> 2485672.7 | K9: =+SUMIFS('NOI Walk'!$H24:$CZ24,'NOI Walk'!$H$15:$CZ$15,NOI!K$4)+SUMIFS('NOI Walk'!$H25:$CZ25,'NOI Walk'!$H$15:$CZ$15,NOI!K$4) -> 2548531.5
C10: ='NOI Walk'!B28 -> Parking Income | G10: =+SUMIFS('NOI Walk'!$H28:$CZ28,'NOI Walk'!$H$15:$CZ$15,NOI!G$4) -> 57717.568 | H10: =+SUMIFS('NOI Walk'!$H28:$CZ28,'NOI Walk'!$H$15:$CZ$15,NOI!H$4) -> 57639.59 | I10: =+SUMIFS('NOI Walk'!$H28:$CZ28,'NOI Walk'!$H$15:$CZ$15,NOI!I$4) -> 63932.971 | J10: =+SUMIFS('NOI Walk'!$H28:$CZ28,'NOI Walk'!$H$15:$CZ$15,NOI!J$4) -> 67814.68 | K10: =+SUMIFS('NOI Walk'!$H28:$CZ28,'NOI Walk'!$H$15:$CZ$15,NOI!K$4) -> 69183.476
C11: ='NOI Walk'!B29 -> Storage Income | G11: =+SUMIFS('NOI Walk'!$H29:$CZ29,'NOI Walk'!$H$15:$CZ$15,NOI!G$4) -> 11031.665 | H11: =+SUMIFS('NOI Walk'!$H29:$CZ29,'NOI Walk'!$H$15:$CZ$15,NOI!H$4) -> 19213.197 | I11: =+SUMIFS('NOI Walk'!$H29:$CZ29,'NOI Walk'!$H$15:$CZ$15,NOI!I$4) -> 21310.99 | J11: =+SUMIFS('NOI Walk'!$H29:$CZ29,'NOI Walk'!$H$15:$CZ$15,NOI!J$4) -> 22604.893 | K11: =+SUMIFS('NOI Walk'!$H29:$CZ29,'NOI Walk'!$H$15:$CZ$15,NOI!K$4) -> 23061.159
C12: ='NOI Walk'!B30 -> Laundry Income | G12: =+SUMIFS('NOI Walk'!$H30:$CZ30,'NOI Walk'!$H$15:$CZ$15,NOI!G$4) -> 9405.826 | H12: =+SUMIFS('NOI Walk'!$H30:$CZ30,'NOI Walk'!$H$15:$CZ$15,NOI!H$4) -> 9393.1184 | I12: =+SUMIFS('NOI Walk'!$H30:$CZ30,'NOI Walk'!$H$15:$CZ$15,NOI!I$4) -> 10418.706 | J12: =+SUMIFS('NOI Walk'!$H30:$CZ30,'NOI Walk'!$H$15:$CZ$15,NOI!J$4) -> 11051.281 | K12: =+SUMIFS('NOI Walk'!$H30:$CZ30,'NOI Walk'!$H$15:$CZ$15,NOI!K$4) -> 11274.344
C13: ='NOI Walk'!B31 -> Parking Income | G13: =+SUMIFS('NOI Walk'!$H31:$CZ31,'NOI Walk'!$H$15:$CZ$15,NOI!G$4) -> 76956.758 | H13: =+SUMIFS('NOI Walk'!$H31:$CZ31,'NOI Walk'!$H$15:$CZ$15,NOI!H$4) -> 76852.787 | I13: =+SUMIFS('NOI Walk'!$H31:$CZ31,'NOI Walk'!$H$15:$CZ$15,NOI!I$4) -> 85243.961 | J13: =+SUMIFS('NOI Walk'!$H31:$CZ31,'NOI Walk'!$H$15:$CZ$15,NOI!J$4) -> 90419.573 | K13: =+SUMIFS('NOI Walk'!$H31:$CZ31,'NOI Walk'!$H$15:$CZ$15,NOI!K$4) -> 92244.634
C14: ='NOI Walk'!B32 -> Turnover Costs | G14: =+SUMIFS('NOI Walk'!$H32:$CZ32,'NOI Walk'!$H$15:$CZ$15,NOI!G$4) -> 0 | H14: =+SUMIFS('NOI Walk'!$H32:$CZ32,'NOI Walk'!$H$15:$CZ$15,NOI!H$4) -> 0 | I14: =+SUMIFS('NOI Walk'!$H32:$CZ32,'NOI Walk'!$H$15:$CZ$15,NOI!I$4) -> 0 | J14: =+SUMIFS('NOI Walk'!$H32:$CZ32,'NOI Walk'!$H$15:$CZ$15,NOI!J$4) -> 0 | K14: =+SUMIFS('NOI Walk'!$H32:$CZ32,'NOI Walk'!$H$15:$CZ$15,NOI!K$4) -> 0
C15: ='NOI Walk'!B34 -> Effective Gross Income | G15: =+SUMIFS('NOI Walk'!$H34:$CZ34,'NOI Walk'!$H$15:$CZ$15,NOI!G$4) -> 1596564.4 | H15: =+SUMIFS('NOI Walk'!$H34:$CZ34,'NOI Walk'!$H$15:$CZ$15,NOI!H$4) -> 1982119.5 | I15: =+SUMIFS('NOI Walk'!$H34:$CZ34,'NOI Walk'!$H$15:$CZ$15,NOI!I$4) -> 2504625.7 | J15: =+SUMIFS('NOI Walk'!$H34:$CZ34,'NOI Walk'!$H$15:$CZ$15,NOI!J$4) -> 2677563.1 | K15: =+SUMIFS('NOI Walk'!$H34:$CZ34,'NOI Walk'!$H$15:$CZ$15,NOI!K$4) -> 2744295.1
C17: ='NOI Walk'!B36 -> Operating Expenses
C18: ='NOI Walk'!B37 -> Property Taxes | G18: =+SUMIFS('NOI Walk'!$H37:$CZ37,'NOI Walk'!$H$15:$CZ$15,NOI!G$4) -> 300870.07 | H18: =+SUMIFS('NOI Walk'!$H37:$CZ37,'NOI Walk'!$H$15:$CZ$15,NOI!H$4) -> 306942.94 | I18: =+SUMIFS('NOI Walk'!$H37:$CZ37,'NOI Walk'!$H$15:$CZ$15,NOI!I$4) -> 313138.38 | J18: =+SUMIFS('NOI Walk'!$H37:$CZ37,'NOI Walk'!$H$15:$CZ$15,NOI!J$4) -> 319458.88 | K18: =+SUMIFS('NOI Walk'!$H37:$CZ37,'NOI Walk'!$H$15:$CZ$15,NOI!K$4) -> 325906.95
C19: ='NOI Walk'!B38 -> Insurance | G19: =+SUMIFS('NOI Walk'!$H38:$CZ38,'NOI Walk'!$H$15:$CZ$15,NOI!G$4) -> 94620.223 | H19: =+SUMIFS('NOI Walk'!$H38:$CZ38,'NOI Walk'!$H$15:$CZ$15,NOI!H$4) -> 96530.071 | I19: =+SUMIFS('NOI Walk'!$H38:$CZ38,'NOI Walk'!$H$15:$CZ$15,NOI!I$4) -> 98478.468 | J19: =+SUMIFS('NOI Walk'!$H38:$CZ38,'NOI Walk'!$H$15:$CZ$15,NOI!J$4) -> 100466.19 | K19: =+SUMIFS('NOI Walk'!$H38:$CZ38,'NOI Walk'!$H$15:$CZ$15,NOI!K$4) -> 102494.04
C20: ='NOI Walk'!B39 -> Water / Sewer | G20: =+SUMIFS('NOI Walk'!$H39:$CZ39,'NOI Walk'!$H$15:$CZ$15,NOI!G$4) -> 42817.702 | H20: =+SUMIFS('NOI Walk'!$H39:$CZ39,'NOI Walk'!$H$15:$CZ$15,NOI!H$4) -> 42759.854 | I20: =+SUMIFS('NOI Walk'!$H39:$CZ39,'NOI Walk'!$H$15:$CZ$15,NOI!I$4) -> 47428.59 | J20: =+SUMIFS('NOI Walk'!$H39:$CZ39,'NOI Walk'!$H$15:$CZ$15,NOI!J$4) -> 50308.231 | K20: =+SUMIFS('NOI Walk'!$H39:$CZ39,'NOI Walk'!$H$15:$CZ$15,NOI!K$4) -> 51323.67
C21: ='NOI Walk'!B40 -> Repairs & Maintenance | G21: =+SUMIFS('NOI Walk'!$H40:$CZ40,'NOI Walk'!$H$15:$CZ$15,NOI!G$4) -> 35628.129 | H21: =+SUMIFS('NOI Walk'!$H40:$CZ40,'NOI Walk'!$H$15:$CZ$15,NOI!H$4) -> 35579.994 | I21: =+SUMIFS('NOI Walk'!$H40:$CZ40,'NOI Walk'!$H$15:$CZ$15,NOI!I$4) -> 39464.797 | J21: =+SUMIFS('NOI Walk'!$H40:$CZ40,'NOI Walk'!$H$15:$CZ$15,NOI!J$4) -> 41860.914 | K21: =+SUMIFS('NOI Walk'!$H40:$CZ40,'NOI Walk'!$H$15:$CZ$15,NOI!K$4) -> 42705.849
C22: ='NOI Walk'!B41 -> Elevator Contract | G22: =+SUMIFS('NOI Walk'!$H41:$CZ41,'NOI Walk'!$H$15:$CZ$15,NOI!G$4) -> 0 | H22: =+SUMIFS('NOI Walk'!$H41:$CZ41,'NOI Walk'!$H$15:$CZ$15,NOI!H$4) -> 0 | I22: =+SUMIFS('NOI Walk'!$H41:$CZ41,'NOI Walk'!$H$15:$CZ$15,NOI!I$4) -> 0 | J22: =+SUMIFS('NOI Walk'!$H41:$CZ41,'NOI Walk'!$H$15:$CZ$15,NOI!J$4) -> 0 | K22: =+SUMIFS('NOI Walk'!$H41:$CZ41,'NOI Walk'!$H$15:$CZ$15,NOI!K$4) -> 0
C23: ='NOI Walk'!B42 -> Trash | G23: =+SUMIFS('NOI Walk'!$H42:$CZ42,'NOI Walk'!$H$15:$CZ$15,NOI!G$4) -> 2426.1596 | H23: =+SUMIFS('NOI Walk'!$H42:$CZ42,'NOI Walk'!$H$15:$CZ$15,NOI!H$4) -> 2475.13 | I23: =+SUMIFS('NOI Walk'!$H42:$CZ42,'NOI Walk'!$H$15:$CZ$15,NOI!I$4) -> 2525.0889 | J23: =+SUMIFS('NOI Walk'!$H42:$CZ42,'NOI Walk'!$H$15:$CZ$15,NOI!J$4) -> 2576.0562 | K23: =+SUMIFS('NOI Walk'!$H42:$CZ42,'NOI Walk'!$H$15:$CZ$15,NOI!K$4) -> 2628.0523
C24: ='NOI Walk'!B43 -> Cleaning | G24: =+SUMIFS('NOI Walk'!$H43:$CZ43,'NOI Walk'!$H$15:$CZ$15,NOI!G$4) -> 11827.528 | H24: =+SUMIFS('NOI Walk'!$H43:$CZ43,'NOI Walk'!$H$15:$CZ$15,NOI!H$4) -> 12066.259 | I24: =+SUMIFS('NOI Walk'!$H43:$CZ43,'NOI Walk'!$H$15:$CZ$15,NOI!I$4) -> 12309.809 | J24: =+SUMIFS('NOI Walk'!$H43:$CZ43,'NOI Walk'!$H$15:$CZ$15,NOI!J$4) -> 12558.274 | K24: =+SUMIFS('NOI Walk'!$H43:$CZ43,'NOI Walk'!$H$15:$CZ$15,NOI!K$4) -> 12811.755
C25: ='NOI Walk'!B44 -> Security, Internet | G25: =+SUMIFS('NOI Walk'!$H44:$CZ44,'NOI Walk'!$H$15:$CZ$15,NOI!G$4) -> 2426.1596 | H25: =+SUMIFS('NOI Walk'!$H44:$CZ44,'NOI Walk'!$H$15:$CZ$15,NOI!H$4) -> 2475.13 | I25: =+SUMIFS('NOI Walk'!$H44:$CZ44,'NOI Walk'!$H$15:$CZ$15,NOI!I$4) -> 2525.0889 | J25: =+SUMIFS('NOI Walk'!$H44:$CZ44,'NOI Walk'!$H$15:$CZ$15,NOI!J$4) -> 2576.0562 | K25: =+SUMIFS('NOI Walk'!$H44:$CZ44,'NOI Walk'!$H$15:$CZ$15,NOI!K$4) -> 2628.0523
C26: ='NOI Walk'!B45 -> Pest Control | G26: =+SUMIFS('NOI Walk'!$H45:$CZ45,'NOI Walk'!$H$15:$CZ$15,NOI!G$4) -> 3942.5093 | H26: =+SUMIFS('NOI Walk'!$H45:$CZ45,'NOI Walk'!$H$15:$CZ$15,NOI!H$4) -> 4022.0863 | I26: =+SUMIFS('NOI Walk'!$H45:$CZ45,'NOI Walk'!$H$15:$CZ$15,NOI!I$4) -> 4103.2695 | J26: =+SUMIFS('NOI Walk'!$H45:$CZ45,'NOI Walk'!$H$15:$CZ$15,NOI!J$4) -> 4186.0914 | K26: =+SUMIFS('NOI Walk'!$H45:$CZ45,'NOI Walk'!$H$15:$CZ$15,NOI!K$4) -> 4270.5849
C27: ='NOI Walk'!B46 -> Super (Payroll) | G27: =+SUMIFS('NOI Walk'!$H46:$CZ46,'NOI Walk'!$H$15:$CZ$15,NOI!G$4) -> 39425.093 | H27: =+SUMIFS('NOI Walk'!$H46:$CZ46,'NOI Walk'!$H$15:$CZ$15,NOI!H$4) -> 40220.863 | I27: =+SUMIFS('NOI Walk'!$H46:$CZ46,'NOI Walk'!$H$15:$CZ$15,NOI!I$4) -> 41032.695 | J27: =+SUMIFS('NOI Walk'!$H46:$CZ46,'NOI Walk'!$H$15:$CZ$15,NOI!J$4) -> 41860.914 | K27: =+SUMIFS('NOI Walk'!$H46:$CZ46,'NOI Walk'!$H$15:$CZ$15,NOI!K$4) -> 42705.849
C28: ='NOI Walk'!B47 -> Heat (Gas) | G28: =+SUMIFS('NOI Walk'!$H47:$CZ47,'NOI Walk'!$H$15:$CZ$15,NOI!G$4) -> 68118.473 | H28: =+SUMIFS('NOI Walk'!$H47:$CZ47,'NOI Walk'!$H$15:$CZ$15,NOI!H$4) -> 69493.401 | I28: =+SUMIFS('NOI Walk'!$H47:$CZ47,'NOI Walk'!$H$15:$CZ$15,NOI!I$4) -> 70896.08 | J28: =+SUMIFS('NOI Walk'!$H47:$CZ47,'NOI Walk'!$H$15:$CZ$15,NOI!J$4) -> 72327.072 | K28: =+SUMIFS('NOI Walk'!$H47:$CZ47,'NOI Walk'!$H$15:$CZ$15,NOI!K$4) -> 73786.947
C29: ='NOI Walk'!B48 -> Common Area Electric | G29: =+SUMIFS('NOI Walk'!$H48:$CZ48,'NOI Walk'!$H$15:$CZ$15,NOI!G$4) -> 3420.885 | H29: =+SUMIFS('NOI Walk'!$H48:$CZ48,'NOI Walk'!$H$15:$CZ$15,NOI!H$4) -> 3489.9333 | I29: =+SUMIFS('NOI Walk'!$H48:$CZ48,'NOI Walk'!$H$15:$CZ$15,NOI!I$4) -> 3560.3754 | J29: =+SUMIFS('NOI Walk'!$H48:$CZ48,'NOI Walk'!$H$15:$CZ$15,NOI!J$4) -> 3632.2393 | K29: =+SUMIFS('NOI Walk'!$H48:$CZ48,'NOI Walk'!$H$15:$CZ$15,NOI!K$4) -> 3705.5537
... C35: ='NOI Walk'!B54 -> Multifamily NOI | G35: =+SUMIFS('NOI Walk'!$H54:$CZ54,'NOI Walk'!$H$15:$CZ$15,NOI!G$4) -> 934551.93 | H35: =+SUMIFS('NOI Walk'!$H54:$CZ54,'NOI Walk'!$H$15:$CZ$15,NOI!H$4) -> 1297834.2 | I35: =+SUMIFS('NOI Walk'!$H54:$CZ54,'NOI Walk'!$H$15:$CZ$15,NOI!I$4) -> 1785081.3 | J35: =+SUMIFS('NOI Walk'!$H54:$CZ54,'NOI Walk'!$H$15:$CZ$15,NOI!J$4) -> 1936301.8 | K35: =+SUMIFS('NOI Walk'!$H54:$CZ54,'NOI Walk'!$H$15:$CZ$15,NOI!K$4) -> 1987691.3
C36: ='NOI Walk'!B58 -> Reserves | G36: =-SUMIFS('NOI Walk'!$H59:$CZ59,'NOI Walk'!$H$15:$CZ$15,NOI!G$4) -> -15965.644 | H36: =-SUMIFS('NOI Walk'!$H59:$CZ59,'NOI Walk'!$H$15:$CZ$15,NOI!H$4) -> -19821.195 | I36: =-SUMIFS('NOI Walk'!$H59:$CZ59,'NOI Walk'!$H$15:$CZ$15,NOI!I$4) -> -25046.257 | J36: =-SUMIFS('NOI Walk'!$H59:$CZ59,'NOI Walk'!$H$15:$CZ$15,NOI!J$4) -> -26775.631 | K36: =-SUMIFS('NOI Walk'!$H59:$CZ59,'NOI Walk'!$H$15:$CZ$15,NOI!K$4) -> -27442.951
C37: Total Property NOI, net of reserves | G37: =SUM(G35:G36) -> 918586.29 | H37: =SUM(H35:H36) -> 1278013 | I37: =SUM(I35:I36) -> 1760035 | J37: =SUM(J35:J36) -> 1909526.2 | K37: =SUM(K35:K36) -> 1960248.4
C38: Yield on Cost | G38: =+G37/Assumptions!$F$17 -> 0.046535877 | H38: =+H37/Assumptions!$F$17 -> 0.064744551 | I38: =+I37/Assumptions!$F$17 -> 0.089163942 | J38: =+J37/Assumptions!$F$17 -> 0.096737211 | K38: =+K37/Assumptions!$F$17 -> 0.099306814

Sheet Cash Flow and Exit
B2: CASH FLOW
F3: 0 | G3: =+F3+1 -> 1 | H3: =+G3+1 -> 2 | I3: =+H3+1 -> 3 | J3: =+I3+1 -> 4 | K3: =+J3+1 -> 5
F5: Closing | G5: =+G3 -> 1 | H5: =+H3 -> 2 | I5: =+I3 -> 3 | J5: =+J3 -> 4 | K5: =+K3 -> 5
B6: Net Operating Income, After Reserves | F6: =+SUMIFS(Model!$G30:$DW30,Model!$G$3:$DW$3,'Cash Flow and Exit'!F$3) -> 0 | G6: =+SUMIFS(Model!$G30:$DW30,Model!$G$3:$DW$3,'Cash Flow and Exit'!G$3) -> 918586.29 | H6: =+SUMIFS(Model!$G30:$DW30,Model!$G$3:$DW$3,'Cash Flow and Exit'!H$3) -> 1278013 | I6: =+SUMIFS(Model!$G30:$DW30,Model!$G$3:$DW$3,'Cash Flow and Exit'!I$3) -> 1760035 | J6: =+SUMIFS(Model!$G30:$DW30,Model!$G$3:$DW$3,'Cash Flow and Exit'!J$3) -> 1909526.2 | K6: =+SUMIFS(Model!$G30:$DW30,Model!$G$3:$DW$3,'Cash Flow and Exit'!K$3) -> 1960248.4
B8: Acquisition Loan Draw | F8: =+SUMIFS(Model!$G44:$DW44,Model!$G$3:$DW$3,'Cash Flow and Exit'!F$3) -> 11250000 | G8: =+SUMIFS(Model!$G44:$DW44,Model!$G$3:$DW$3,'Cash Flow and Exit'!G$3) -> 0 | H8: =+SUMIFS(Model!$G44:$DW44,Model!$G$3:$DW$3,'Cash Flow and Exit'!H$3) -> 0 | I8: =+SUMIFS(Model!$G44:$DW44,Model!$G$3:$DW$3,'Cash Flow and Exit'!I$3) -> 0 | J8: =+SUMIFS(Model!$G44:$DW44,Model!$G$3:$DW$3,'Cash Flow and Exit'!J$3) -> 0 | K8: =+SUMIFS(Model!$G44:$DW44,Model!$G$3:$DW$3,'Cash Flow and Exit'!K$3) -> 0
B9: Acqusition Loan Debt Service | F9: =-SUMIFS(Model!$G45:$DW45,Model!$G$3:$DW$3,'Cash Flow and Exit'!F$3)+SUMIFS(Model!$G51:$DW51,Model!$G$3:$DW$3,'Cash Flow and Exit'!F$3) -> 0 | G9: =-SUMIFS(Model!$G45:$DW45,Model!$G$3:$DW$3,'Cash Flow and Exit'!G$3)+SUMIFS(Model!$G51:$DW51,Model!$G$3:$DW$3,'Cash Flow and Exit'!G$3) -> 1184721.6 | H9: =-SUMIFS(Model!$G45:$DW45,Model!$G$3:$DW$3,'Cash Flow and Exit'!H$3)+SUMIFS(Model!$G51:$DW51,Model!$G$3:$DW$3,'Cash Flow and Exit'!H$3) -> 1184721.6 | I9: =-SUMIFS(Model!$G45:$DW45,Model!$G$3:$DW$3,'Cash Flow and Exit'!I$3)+SUMIFS(Model!$G51:$DW51,Model!$G$3:$DW$3,'Cash Flow and Exit'!I$3) -> 888541.21 | J9: =-SUMIFS(Model!$G45:$DW45,Model!$G$3:$DW$3,'Cash Flow and Exit'!J$3)+SUMIFS(Model!$G51:$DW51,Model!$G$3:$DW$3,'Cash Flow and Exit'!J$3) -> 0 | K9: =-SUMIFS(Model!$G45:$DW45,Model!$G$3:$DW$3,'Cash Flow and Exit'!K$3)+SUMIFS(Model!$G51:$DW51,Model!$G$3:$DW$3,'Cash Flow and Exit'!K$3) -> 0
B10: Acqusition Loan Paydown | F10: =+SUMIFS(Model!$G46:$DW46,Model!$G$3:$DW$3,'Cash Flow and Exit'!F$3) -> 0 | G10: =+SUMIFS(Model!$G46:$DW46,Model!$G$3:$DW$3,'Cash Flow and Exit'!G$3) -> 0 | H10: =+SUMIFS(Model!$G46:$DW46,Model!$G$3:$DW$3,'Cash Flow and Exit'!H$3) -> 0 | I10: =+SUMIFS(Model!$G46:$DW46,Model!$G$3:$DW$3,'Cash Flow and Exit'!I$3) -> -11061858 | J10: =+SUMIFS(Model!$G46:$DW46,Model!$G$3:$DW$3,'Cash Flow and Exit'!J$3) -> 0 | K10: =+SUMIFS(Model!$G46:$DW46,Model!$G$3:$DW$3,'Cash Flow and Exit'!K$3) -> 0
B12: Refi Loan Draw | F12: =+SUMIFS(Model!$G63:$DW63,Model!$G$3:$DW$3,'Cash Flow and Exit'!F$3) -> 0 | G12: =+SUMIFS(Model!$G63:$DW63,Model!$G$3:$DW$3,'Cash Flow and Exit'!G$3) -> 0 | H12: =+SUMIFS(Model!$G63:$DW63,Model!$G$3:$DW$3,'Cash Flow and Exit'!H$3) -> 0 | I12: =+SUMIFS(Model!$G63:$DW63,Model!$G$3:$DW$3,'Cash Flow and Exit'!I$3) -> 20678404 | J12: =+SUMIFS(Model!$G63:$DW63,Model!$G$3:$DW$3,'Cash Flow and Exit'!J$3) -> 0 | K12: =+SUMIFS(Model!$G63:$DW63,Model!$G$3:$DW$3,'Cash Flow and Exit'!K$3) -> 0
B13: Refi Loan Debt Service | F13: =-SUMIFS(Model!$G64:$DW64,Model!$G$3:$DW$3,'Cash Flow and Exit'!F$3)-SUMIFS(Model!$G66:$DW66,Model!$G$3:$DW$3,'Cash Flow and Exit'!F$3) -> 0 | G13: =-SUMIFS(Model!$G64:$DW64,Model!$G$3:$DW$3,'Cash Flow and Exit'!G$3)-SUMIFS(Model!$G66:$DW66,Model!$G$3:$DW$3,'Cash Flow and Exit'!G$3) -> 0 | H13: =-SUMIFS(Model!$G64:$DW64,Model!$G$3:$DW$3,'Cash Flow and Exit'!H$3)-SUMIFS(Model!$G66:$DW66,Model!$G$3:$DW$3,'Cash Flow and Exit'!H$3) -> 0 | I13: =-SUMIFS(Model!$G64:$DW64,Model!$G$3:$DW$3,'Cash Flow and Exit'!I$3)-SUMIFS(Model!$G66:$DW66,Model!$G$3:$DW$3,'Cash Flow and Exit'!I$3) -> -259453.77 | J13: =-SUMIFS(Model!$G64:$DW64,Model!$G$3:$DW$3,'Cash Flow and Exit'!J$3)-SUMIFS(Model!$G66:$DW66,Model!$G$3:$DW$3,'Cash Flow and Exit'!J$3) -> -1018899.8 | K13: =-SUMIFS(Model!$G64:$DW64,Model!$G$3:$DW$3,'Cash Flow and Exit'!K$3)-SUMIFS(Model!$G66:$DW66,Model!$G$3:$DW$3,'Cash Flow and Exit'!K$3) -> -987196.75
B14: Refi Loan Paydown | F14: =+SUMIFS(Model!$G65:$DW65,Model!$G$3:$DW$3,'Cash Flow and Exit'!F$3) -> 0 | G14: =+SUMIFS(Model!$G65:$DW65,Model!$G$3:$DW$3,'Cash Flow and Exit'!G$3) -> 0 | H14: =+SUMIFS(Model!$G65:$DW65,Model!$G$3:$DW$3,'Cash Flow and Exit'!H$3) -> 0 | I14: =+SUMIFS(Model!$G65:$DW65,Model!$G$3:$DW$3,'Cash Flow and Exit'!I$3) -> 0 | J14: =+SUMIFS(Model!$G65:$DW65,Model!$G$3:$DW$3,'Cash Flow and Exit'!J$3) -> 0 | K14: =+SUMIFS(Model!$G65:$DW65,Model!$G$3:$DW$3,'Cash Flow and Exit'!K$3) -> -20104331
B16: Exit Proceeds | F16: =+SUMIFS(Model!$G22:$DW22,Model!$G$3:$DW$3,'Cash Flow and Exit'!F$3) -> 0 | G16: =+SUMIFS(Model!$G22:$DW22,Model!$G$3:$DW$3,'Cash Flow and Exit'!G$3) -> 0 | H16: =+SUMIFS(Model!$G22:$DW22,Model!$G$3:$DW$3,'Cash Flow and Exit'!H$3) -> 0 | I16: =+SUMIFS(Model!$G22:$DW22,Model!$G$3:$DW$3,'Cash Flow and Exit'!I$3) -> 0 | J16: =+SUMIFS(Model!$G22:$DW22,Model!$G$3:$DW$3,'Cash Flow and Exit'!J$3) -> 0 | K16: =+SUMIFS(Model!$G22:$DW22,Model!$G$3:$DW$3,'Cash Flow and Exit'!K$3) -> 32998037
B18: Levered Cash Flow | F18: =+SUMIFS(Model!$G69:$DW69,Model!$G$3:$DW$3,'Cash Flow and Exit'!F$3) -> -5651390.8 | G18: =+SUMIFS(Model!$G69:$DW69,Model!$G$3:$DW$3,'Cash Flow and Exit'!G$3) -> -1429309.2 | H18: =+SUMIFS(Model!$G69:$DW69,Model!$G$3:$DW$3,'Cash Flow and Exit'!H$3) -> -1300834.7 | I18: =+SUMIFS(Model!$G69:$DW69,Model!$G$3:$DW$3,'Cash Flow and Exit'!I$3) -> 9901956.3 | J18: =+SUMIFS(Model!$G69:$DW69,Model!$G$3:$DW$3,'Cash Flow and Exit'!J$3) -> 392327.05 | K18: =+SUMIFS(Model!$G69:$DW69,Model!$G$3:$DW$3,'Cash Flow and Exit'!K$3) -> 13336756
B19: Cash-on-Cash | G19: =-G18/$F$18 -> -0.25291283 | H19: =-H18/$F$18 -> -0.23017957 | I19: =-I18/$F$18 -> 1.7521273 | J19: =-J18/$F$18 -> 0.069421328 | K19: =-K18/$F$18 -> 2.3599068
B21: Total Equity Invested | E21: =-Model!$G$70 -> 8489313.8 | H21: Unlevered Returns | K21: =+TEXT(Model!F35,"0.0%")&" / "&TEXT(Model!F36,"0.00x") -> 18.5% / 2.26x
B22: Totel Equity Returned | E22: =+E23+E21 -> 23631039 | H22: Levered Gross Returns | K22: =+TEXT(Model!G72,"0.0%")&" / "&TEXT(Model!G73,"0.00x") -> 33.9% / 2.78x
B23: Gross Profit | E23: =+Model!G71 -> 15141725 | H23: Levered Net Returns | K23: =+TEXT(Model!E99,"0.0%")&" / "&TEXT(Model!E100,"0.00x") -> 23.7% / 2.21x
M24: =+Assumptions!B173 -> Multifamily
M25: =+Assumptions!B174 -> Exit (June 30, 2030) | P25: =+Assumptions!E174 -> 60
M26: =+Assumptions!B175 -> NTM NOI in Month 60 | P26: =+Assumptions!E175 -> 2043222.1
M27: =+Assumptions!B176 -> Applied Exit Cap Rate | P27: =+Assumptions!E176 -> 0.06
M28: =+Assumptions!B177 -> Implied Asset Value | P28: =+Assumptions!E177 -> 34053702
M29: =+Assumptions!B178 -> Less: Selling Costs | P29: =+Assumptions!E178 -> 0.031
M30: =+Assumptions!B179 -> Less: Selling Costs | P30: =+Assumptions!E179 -> -1055664.8
M31: =+Assumptions!B180 -> Net Reversion Proceeds | P31: =+Assumptions!E180 -> 32998037
M32: =+Assumptions!B181 -> $ / Unit | P32: =+Assumptions!E181 -> 436585.92
Q34: Exit Cap Rate | R34: Implied Valuation | S34: $ / Unit | T34: $ / SF | U34: Gross Returns
Q35: 0.08 | R35: =+$P$26/Q35 -> 25540276 | S35: =+R35/Assumptions!$D$124 -> 327439.44 | T35: =+R35/Assumptions!$G$25 -> 464.36866 | U35: =+TEXT(Assumptions!G190,"0.0%")&" / "&TEXT(Assumptions!G200,"0.0x") -> 61.6% / 3.6x
Q36: =+Q35-0.25% -> 0.0775 | R36: =+$P$26/Q36 -> 26364156 | S36: =+R36/Assumptions!$D$124 -> 338002 | T36: =+R36/Assumptions!$G$25 -> 479.3483 | U36: =+TEXT(Assumptions!G191,"0.0%")&" / "&TEXT(Assumptions!G201,"0.0x") -> 62.6% / 3.7x
Q37: =+Q36-0.25% -> 0.075 | R37: =+$P$26/Q37 -> 27242961 | S37: =+R37/Assumptions!$D$124 -> 349268.74 | T37: =+R37/Assumptions!$G$25 -> 495.32657 | U37: =+TEXT(Assumptions!G192,"0.0%")&" / "&TEXT(Assumptions!G202,"0.0x") -> 63.6% / 3.9x
Q38: =+Q37-0.25% -> 0.0725 | R38: =+$P$26/Q38 -> 28182374 | S38: =+R38/Assumptions!$D$124 -> 361312.49 | T38: =+R38/Assumptions!$G$25 -> 512.4068 | U38: =+TEXT(Assumptions!G193,"0.0%")&" / "&TEXT(Assumptions!G203,"0.0x") -> 64.6% / 4.0x
Q39: =+Q38-0.25% -> 0.07 | R39: =+$P$26/Q39 -> 29188887 | S39: =+R39/Assumptions!$D$124 -> 374216.5 | T39: =+R39/Assumptions!$G$25 -> 530.70704 | U39: =+TEXT(Assumptions!G194,"0.0%")&" / "&TEXT(Assumptions!G204,"0.0x") -> 65.7% / 4.2x

Sheet Model
EM1: x
G2: =+Assumptions!F2 -> 45838 | H2: =+EOMONTH(G2,1) -> 45869 | I2: =+EOMONTH(H2,1) -> 45900 | J2: =+EOMONTH(I2,1) -> 45930 | K2: =+EOMONTH(J2,1) -> 45961 | L2: =+EOMONTH(K2,1) -> 45991 | M2: =+EOMONTH(L2,1) -> 46022 | N2: =+EOMONTH(M2,1) -> 46053 | O2: =+EOMONTH(N2,1) -> 46081 | ... EI2: =+EOMONTH(EH2,1) -> 49856 | EM2: x
G3: =ROUNDUP(G4/12,0) -> 0 | H3: =ROUNDUP(H4/12,0) -> 1 | I3: =ROUNDUP(I4/12,0) -> 1 | J3: =ROUNDUP(J4/12,0) -> 1 | K3: =ROUNDUP(K4/12,0) -> 1 | L3: =ROUNDUP(L4/12,0) -> 1 | M3: =ROUNDUP(M4/12,0) -> 1 | N3: =ROUNDUP(N4/12,0) -> 1 | ... EI3: =ROUNDUP(EI4/12,0) -> 11 | EM3: x
G4: 0 | H4: =+G4+1 -> 1 | I4: =+H4+1 -> 2 | J4: =+I4+1 -> 3 | K4: =+J4+1 -> 4 | L4: =+K4+1 -> 5 | M4: =+L4+1 -> 6 | N4: =+M4+1 -> 7 | O4: =+N4+1 -> 8 | ... EI4: =+EH4+1 -> 132 | EM4: x
B5: =SUM(G5:EI5) -> 15000000 | D5: Acquisition of Property | G5: =+IF(G4=Assumptions!$G$24,Assumptions!$G$23,0) -> 15000000 | H5: =+IF(H4=Assumptions!$G$24,Assumptions!$G$23,0) -> 0 | I5: =+IF(I4=Assumptions!$G$24,Assumptions!$G$23,0) -> 0 | J5: =+IF(J4=Assumptions!$G$24,Assumptions!$G$23,0) -> 0 | K5: =+IF(K4=Assumptions!$G$24,Assumptions!$G$23,0) -> 0 | L5: =+IF(L4=Assumptions!$G$24,Assumptions!$G$23,0) -> 0 | M5: =+IF(M4=Assumptions!$G$24,Assumptions!$G$23,0) -> 0 | N5: =+IF(N4=Assumptions!$G$24,Assumptions!$G$23,0) -> 0 | ... EI5: =+IF(EI4=Assumptions!$G$24,Assumptions!$G$23,0) -> 0 | EM5: x
B6: =SUM(G6:EI6) -> 1062339.1 | D6: =+'Closing Costs'!B4 -> Closing Costs | G6: {=INDEX('Closing Costs'!$J$19:$EL$19,,MATCH(Model!G$4,'Closing Costs'!$J$4:$EL$4,0))} -> 1062339.1 | H6: {=INDEX('Closing Costs'!$J$19:$EL$19,,MATCH(Model!H$4,'Closing Costs'!$J$4:$EL$4,0))} -> 0 | I6: {=INDEX('Closing Costs'!$J$19:$EL$19,,MATCH(Model!I$4,'Closing Costs'!$J$4:$EL$4,0))} -> 0 | J6: {=INDEX('Closing Costs'!$J$19:$EL$19,,MATCH(Model!J$4,'Closing Costs'!$J$4:$EL$4,0))} -> 0 | K6: {=INDEX('Closing Costs'!$J$19:$EL$19,,MATCH(Model!K$4,'Closing Costs'!$J$4:$EL$4,0))} -> 0 | L6: {=INDEX('Closing Costs'!$J$19:$EL$19,,MATCH(Model!L$4,'Closing Costs'!$J$4:$EL$4,0))} -> 0 | M6: {=INDEX('Closing Costs'!$J$19:$EL$19,,MATCH(Model!M$4,'Closing Costs'!$J$4:$EL$4,0))} -> 0 | N6: {=INDEX('Closing Costs'!$J$19:$EL$19,,MATCH(Model!N$4,'Closing Costs'!$J$4:$EL$4,0))} -> 0 | ... EI6: {=INDEX('Closing Costs'!$J$19:$EL$19,,MATCH(Model!EI$4,'Closing Costs'!$J$4:$EL$4,0))} -> 0 | EM6: x
B7: =SUM(G7:EI7) -> 29925 | D7: =+'Legal and Pre-Dev'!B4 -> Legal and Pre-Development Costs | G7: {=INDEX('Legal and Pre-Dev'!$J$12:$EL$12,,MATCH(Model!G$4,'Legal and Pre-Dev'!$J$4:$EL$4,0))} -> 29925 | H7: {=INDEX('Legal and Pre-Dev'!$J$12:$EL$12,,MATCH(Model!H$4,'Legal and Pre-Dev'!$J$4:$EL$4,0))} -> 0 | I7: {=INDEX('Legal and Pre-Dev'!$J$12:$EL$12,,MATCH(Model!I$4,'Legal and Pre-Dev'!$J$4:$EL$4,0))} -> 0 | J7: {=INDEX('Legal and Pre-Dev'!$J$12:$EL$12,,MATCH(Model!J$4,'Legal and Pre-Dev'!$J$4:$EL$4,0))} -> 0 | K7: {=INDEX('Legal and Pre-Dev'!$J$12:$EL$12,,MATCH(Model!K$4,'Legal and Pre-Dev'!$J$4:$EL$4,0))} -> 0 | L7: {=INDEX('Legal and Pre-Dev'!$J$12:$EL$12,,MATCH(Model!L$4,'Legal and Pre-Dev'!$J$4:$EL$4,0))} -> 0 | M7: {=INDEX('Legal and Pre-Dev'!$J$12:$EL$12,,MATCH(Model!M$4,'Legal and Pre-Dev'!$J$4:$EL$4,0))} -> 0 | N7: {=INDEX('Legal and Pre-Dev'!$J$12:$EL$12,,MATCH(Model!N$4,'Legal and Pre-Dev'!$J$4:$EL$4,0))} -> 0 | ... EI7: {=INDEX('Legal and Pre-Dev'!$J$12:$EL$12,,MATCH(Model!EI$4,'Legal and Pre-Dev'!$J$4:$EL$4,0))} -> 0 | EM7: x
B8: =SUM(G8:EI8) -> 789126.76 | D8: =+Reserves!B4 -> Reserves | G8: {=INDEX(Reserves!$J$12:$EL$12,,MATCH(Model!G$4,Reserves!$J$4:$EL$4,0))} -> 789126.76 | H8: {=INDEX(Reserves!$J$12:$EL$12,,MATCH(Model!H$4,Reserves!$J$4:$EL$4,0))} -> 0 | I8: {=INDEX(Reserves!$J$12:$EL$12,,MATCH(Model!I$4,Reserves!$J$4:$EL$4,0))} -> 0 | J8: {=INDEX(Reserves!$J$12:$EL$12,,MATCH(Model!J$4,Reserves!$J$4:$EL$4,0))} -> 0 | K8: {=INDEX(Reserves!$J$12:$EL$12,,MATCH(Model!K$4,Reserves!$J$4:$EL$4,0))} -> 0 | L8: {=INDEX(Reserves!$J$12:$EL$12,,MATCH(Model!L$4,Reserves!$J$4:$EL$4,0))} -> 0 | M8: {=INDEX(Reserves!$J$12:$EL$12,,MATCH(Model!M$4,Reserves!$J$4:$EL$4,0))} -> 0 | N8: {=INDEX(Reserves!$J$12:$EL$12,,MATCH(Model!N$4,Reserves!$J$4:$EL$4,0))} -> 0 | ... EI8: {=INDEX(Reserves!$J$12:$EL$12,,MATCH(Model!EI$4,Reserves!$J$4:$EL$4,0))} -> 0 | EM8: x
B9: =SUM(G9:EI9) -> 2577300 | D9: =+'Hard Costs'!B4 -> Hard Costs | G9: {=INDEX('Hard Costs'!$J$16:$EL$16,,MATCH(Model!G$4,'Hard Costs'!$J$4:$EL$4,0))} -> 20000 | H9: {=INDEX('Hard Costs'!$J$16:$EL$16,,MATCH(Model!H$4,'Hard Costs'!$J$4:$EL$4,0))} -> 0 | I9: {=INDEX('Hard Costs'!$J$16:$EL$16,,MATCH(Model!I$4,'Hard Costs'!$J$4:$EL$4,0))} -> 97652.174 | J9: {=INDEX('Hard Costs'!$J$16:$EL$16,,MATCH(Model!J$4,'Hard Costs'!$J$4:$EL$4,0))} -> 97652.174 | K9: {=INDEX('Hard Costs'!$J$16:$EL$16,,MATCH(Model!K$4,'Hard Costs'!$J$4:$EL$4,0))} -> 97652.174 | L9: {=INDEX('Hard Costs'!$J$16:$EL$16,,MATCH(Model!L$4,'Hard Costs'!$J$4:$EL$4,0))} -> 145152.17 | M9: {=INDEX('Hard Costs'!$J$16:$EL$16,,MATCH(Model!M$4,'Hard Costs'!$J$4:$EL$4,0))} -> 135152.17 | N9: {=INDEX('Hard Costs'!$J$16:$EL$16,,MATCH(Model!N$4,'Hard Costs'!$J$4:$EL$4,0))} -> 97652.174 | ... EI9: {=INDEX('Hard Costs'!$J$16:$EL$16,,MATCH(Model!EI$4,'Hard Costs'!$J$4:$EL$4,0))} -> 0 | EM9: x
B10: =SUM(G10:EI10) -> -19458691 | D10: Total Project Costs | G10: =-SUM(G5:G9) -> -16901391 | H10: =-SUM(H5:H9) -> 0 | I10: =-SUM(I5:I9) -> -97652.174 | J10: =-SUM(J5:J9) -> -97652.174 | K10: =-SUM(K5:K9) -> -97652.174 | L10: =-SUM(L5:L9) -> -145152.17 | M10: =-SUM(M5:M9) -> -135152.17 | N10: =-SUM(N5:N9) -> -97652.174 | ... EI10: =-SUM(EI5:EI9) -> 0 | EM10: x
EM11: x
D12: Condo Sales | EM12: x
D13: Less: Selling Costs | EM13: x
D14: Condo Proceeds, net | EM14: x
EM15: x
D16: Retail Sale | G16: =IF(G$4=Assumptions!$J$174,Assumptions!$J$177,0) -> 0 | H16: =IF(H$4=Assumptions!$J$174,Assumptions!$J$177,0) -> 0 | I16: =IF(I$4=Assumptions!$J$174,Assumptions!$J$177,0) -> 0 | J16: =IF(J$4=Assumptions!$J$174,Assumptions!$J$177,0) -> 0 | K16: =IF(K$4=Assumptions!$J$174,Assumptions!$J$177,0) -> 0 | L16: =IF(L$4=Assumptions!$J$174,Assumptions!$J$177,0) -> 0 | M16: =IF(M$4=Assumptions!$J$174,Assumptions!$J$177,0) -> 0 | N16: =IF(N$4=Assumptions!$J$174,Assumptions!$J$177,0) -> 0 | ... EI16: =IF(EI$4=Assumptions!$J$174,Assumptions!$J$177,0) -> 0 | EM16: x
D17: Less: Selling Costs | G17: =IF(G$4=Assumptions!$J$174,Assumptions!$J$179,0) -> 0 | H17: =IF(H$4=Assumptions!$J$174,Assumptions!$J$179,0) -> 0 | I17: =IF(I$4=Assumptions!$J$174,Assumptions!$J$179,0) -> 0 | J17: =IF(J$4=Assumptions!$J$174,Assumptions!$J$179,0) -> 0 | K17: =IF(K$4=Assumptions!$J$174,Assumptions!$J$179,0) -> 0 | L17: =IF(L$4=Assumptions!$J$174,Assumptions!$J$179,0) -> 0 | M17: =IF(M$4=Assumptions!$J$174,Assumptions!$J$179,0) -> 0 | N17: =IF(N$4=Assumptions!$J$174,Assumptions!$J$179,0) -> 0 | ... EI17: =IF(EI$4=Assumptions!$J$174,Assumptions!$J$179,0) -> 0 | EM17: x
D18: Retail Proceeds, net | G18: =IF(G$4=Assumptions!$J$174,Assumptions!$J$180,0) -> 0 | H18: =IF(H$4=Assumptions!$J$174,Assumptions!$J$180,0) -> 0 | I18: =IF(I$4=Assumptions!$J$174,Assumptions!$J$180,0) -> 0 | J18: =IF(J$4=Assumptions!$J$174,Assumptions!$J$180,0) -> 0 | K18: =IF(K$4=Assumptions!$J$174,Assumptions!$J$180,0) -> 0 | L18: =IF(L$4=Assumptions!$J$174,Assumptions!$J$180,0) -> 0 | M18: =IF(M$4=Assumptions!$J$174,Assumptions!$J$180,0) -> 0 | N18: =IF(N$4=Assumptions!$J$174,Assumptions!$J$180,0) -> 0 | ... EI18: =IF(EI$4=Assumptions!$J$174,Assumptions!$J$180,0) -> 0 | EM18: x
EM19: x
D20: Multifamily Sale | G20: =IF(G4=Assumptions!$E$174,Assumptions!$E$177,0) -> 0 | H20: =IF(H4=Assumptions!$E$174,Assumptions!$E$177,0) -> 0 | I20: =IF(I4=Assumptions!$E$174,Assumptions!$E$177,0) -> 0 | J20: =IF(J4=Assumptions!$E$174,Assumptions!$E$177,0) -> 0 | K20: =IF(K4=Assumptions!$E$174,Assumptions!$E$177,0) -> 0 | L20: =IF(L4=Assumptions!$E$174,Assumptions!$E$177,0) -> 0 | M20: =IF(M4=Assumptions!$E$174,Assumptions!$E$177,0) -> 0 | N20: =IF(N4=Assumptions!$E$174,Assumptions!$E$177,0) -> 0 | ... EI20: =IF(EI4=Assumptions!$E$174,Assumptions!$E$177,0) -> 0 | EM20: x
D21: Less: Selling Costs | G21: =IF(G4=Assumptions!$E$174,Assumptions!$E$179,0) -> 0 | H21: =IF(H4=Assumptions!$E$174,Assumptions!$E$179,0) -> 0 | I21: =IF(I4=Assumptions!$E$174,Assumptions!$E$179,0) -> 0 | J21: =IF(J4=Assumptions!$E$174,Assumptions!$E$179,0) -> 0 | K21: =IF(K4=Assumptions!$E$174,Assumptions!$E$179,0) -> 0 | L21: =IF(L4=Assumptions!$E$174,Assumptions!$E$179,0) -> 0 | M21: =IF(M4=Assumptions!$E$174,Assumptions!$E$179,0) -> 0 | N21: =IF(N4=Assumptions!$E$174,Assumptions!$E$179,0) -> 0 | ... EI21: =IF(EI4=Assumptions!$E$174,Assumptions!$E$179,0) -> 0 | EM21: x
D22: Multifamily Proceeds, net | G22: =IF(G4=Assumptions!$E$174,Assumptions!$E$180,0) -> 0 | H22: =IF(H4=Assumptions!$E$174,Assumptions!$E$180,0) -> 0 | I22: =IF(I4=Assumptions!$E$174,Assumptions!$E$180,0) -> 0 | J22: =IF(J4=Assumptions!$E$174,Assumptions!$E$180,0) -> 0 | K22: =IF(K4=Assumptions!$E$174,Assumptions!$E$180,0) -> 0 | L22: =IF(L4=Assumptions!$E$174,Assumptions!$E$180,0) -> 0 | M22: =IF(M4=Assumptions!$E$174,Assumptions!$E$180,0) -> 0 | N22: =IF(N4=Assumptions!$E$174,Assumptions!$E$180,0) -> 0 | ... EI22: =IF(EI4=Assumptions!$E$174,Assumptions!$E$180,0) -> 0 | EM22: x
EM23: x
D24: Retail Income | G24: {=IFERROR(INDEX('NOI Walk'!$H$61:$EI$61,,MATCH(Model!G$4,'NOI Walk'!$H$16:$EI$16,0)),0)} -> 0 | H24: {=IFERROR(INDEX('NOI Walk'!$H$61:$EI$61,,MATCH(Model!H$4,'NOI Walk'!$H$16:$EI$16,0)),0)} -> 0 | I24: {=IFERROR(INDEX('NOI Walk'!$H$61:$EI$61,,MATCH(Model!I$4,'NOI Walk'!$H$16:$EI$16,0)),0)} -> 0 | J24: {=IFERROR(INDEX('NOI Walk'!$H$61:$EI$61,,MATCH(Model!J$4,'NOI Walk'!$H$16:$EI$16,0)),0)} -> 0 | K24: {=IFERROR(INDEX('NOI Walk'!$H$61:$EI$61,,MATCH(Model!K$4,'NOI Walk'!$H$16:$EI$16,0)),0)} -> 0 | L24: {=IFERROR(INDEX('NOI Walk'!$H$61:$EI$61,,MATCH(Model!L$4,'NOI Walk'!$H$16:$EI$16,0)),0)} -> 0 | M24: {=IFERROR(INDEX('NOI Walk'!$H$61:$EI$61,,MATCH(Model!M$4,'NOI Walk'!$H$16:$EI$16,0)),0)} -> 0 | N24: {=IFERROR(INDEX('NOI Walk'!$H$61:$EI$61,,MATCH(Model!N$4,'NOI Walk'!$H$16:$EI$16,0)),0)} -> 0 | ... EI24: {=IFERROR(INDEX('NOI Walk'!$H$61:$EI$61,,MATCH(Model!EI$4,'NOI Walk'!$H$16:$EI$16,0)),0)} -> 0 | EM24: x
D25: Less: Leasing Cost Reserves | G25: {=-IFERROR(INDEX('NOI Walk'!$H$65:$EI$65,,MATCH(Model!G$4,'NOI Walk'!$H$16:$EI$16,0)),0)} -> 0 | H25: {=-IFERROR(INDEX('NOI Walk'!$H$65:$EI$65,,MATCH(Model!H$4,'NOI Walk'!$H$16:$EI$16,0)),0)} -> 0 | I25: {=-IFERROR(INDEX('NOI Walk'!$H$65:$EI$65,,MATCH(Model!I$4,'NOI Walk'!$H$16:$EI$16,0)),0)} -> 0 | J25: {=-IFERROR(INDEX('NOI Walk'!$H$65:$EI$65,,MATCH(Model!J$4,'NOI Walk'!$H$16:$EI$16,0)),0)} -> 0 | K25: {=-IFERROR(INDEX('NOI Walk'!$H$65:$EI$65,,MATCH(Model!K$4,'NOI Walk'!$H$16:$EI$16,0)),0)} -> 0 | L25: {=-IFERROR(INDEX('NOI Walk'!$H$65:$EI$65,,MATCH(Model!L$4,'NOI Walk'!$H$16:$EI$16,0)),0)} -> 0 | M25: {=-IFERROR(INDEX('NOI Walk'!$H$65:$EI$65,,MATCH(Model!M$4,'NOI Walk'!$H$16:$EI$16,0)),0)} -> 0 | N25: {=-IFERROR(INDEX('NOI Walk'!$H$65:$EI$65,,MATCH(Model!N$4,'NOI Walk'!$H$16:$EI$16,0)),0)} -> 0 | ... EI25: {=-IFERROR(INDEX('NOI Walk'!$H$65:$EI$65,,MATCH(Model!EI$4,'NOI Walk'!$H$16:$EI$16,0)),0)} -> 0 | EM25: x
D26: Retail Cash Flow | G26: =SUM(G24:G25) -> 0 | H26: =SUM(H24:H25) -> 0 | I26: =SUM(I24:I25) -> 0 | J26: =SUM(J24:J25) -> 0 | K26: =SUM(K24:K25) -> 0 | L26: =SUM(L24:L25) -> 0 | M26: =SUM(M24:M25) -> 0 | N26: =SUM(N24:N25) -> 0 | ... EI26: =SUM(EI24:EI25) -> 0 | EM26: x
EM27: x
D28: Multifamily NOI | G28: {=IFERROR(INDEX('NOI Walk'!$H$54:$EI$54,,MATCH(Model!G$4,'NOI Walk'!$H$16:$EI$16,0)),0)} -> 0 | H28: {=IFERROR(INDEX('NOI Walk'!$H$54:$EI$54,,MATCH(Model!H$4,'NOI Walk'!$H$16:$EI$16,0)),0)} -> 80459.495 | I28: {=IFERROR(INDEX('NOI Walk'!$H$54:$EI$54,,MATCH(Model!I$4,'NOI Walk'!$H$16:$EI$16,0)),0)} -> 75837.508 | J28: {=IFERROR(INDEX('NOI Walk'!$H$54:$EI$54,,MATCH(Model!J$4,'NOI Walk'!$H$16:$EI$16,0)),0)} -> 71196.087 | K28: {=IFERROR(INDEX('NOI Walk'!$H$54:$EI$54,,MATCH(Model!K$4,'NOI Walk'!$H$16:$EI$16,0)),0)} -> 66535.171 | L28: {=IFERROR(INDEX('NOI Walk'!$H$54:$EI$54,,MATCH(Model!L$4,'NOI Walk'!$H$16:$EI$16,0)),0)} -> 69219.137 | M28: {=IFERROR(INDEX('NOI Walk'!$H$54:$EI$54,,MATCH(Model!M$4,'NOI Walk'!$H$16:$EI$16,0)),0)} -> 73435.037 | N28: {=IFERROR(INDEX('NOI Walk'!$H$54:$EI$54,,MATCH(Model!N$4,'NOI Walk'!$H$16:$EI$16,0)),0)} -> 76143.347 | ... EI28: {=IFERROR(INDEX('NOI Walk'!$H$54:$EI$54,,MATCH(Model!EI$4,'NOI Walk'!$H$16:$EI$16,0)),0)} -> 196131.31 | EM28: x
D29: Less: CapEx | G29: {=-IFERROR(INDEX('NOI Walk'!$H$59:$EI$59,,MATCH(Model!G$4,'NOI Walk'!$H$16:$EI$16,0)),0)} -> 0 | H29: {=-IFERROR(INDEX('NOI Walk'!$H$59:$EI$59,,MATCH(Model!H$4,'NOI Walk'!$H$16:$EI$16,0)),0)} -> -1359.3679 | I29: {=-IFERROR(INDEX('NOI Walk'!$H$59:$EI$59,,MATCH(Model!I$4,'NOI Walk'!$H$16:$EI$16,0)),0)} -> -1309.7548 | J29: {=-IFERROR(INDEX('NOI Walk'!$H$59:$EI$59,,MATCH(Model!J$4,'NOI Walk'!$H$16:$EI$16,0)),0)} -> -1259.9334 | K29: {=-IFERROR(INDEX('NOI Walk'!$H$59:$EI$59,,MATCH(Model!K$4,'NOI Walk'!$H$16:$EI$16,0)),0)} -> -1209.903 | L29: {=-IFERROR(INDEX('NOI Walk'!$H$59:$EI$59,,MATCH(Model!L$4,'NOI Walk'!$H$16:$EI$16,0)),0)} -> -1238.4461 | M29: {=-IFERROR(INDEX('NOI Walk'!$H$59:$EI$59,,MATCH(Model!M$4,'NOI Walk'!$H$16:$EI$16,0)),0)} -> -1282.7837 | N29: {=-IFERROR(INDEX('NOI Walk'!$H$59:$EI$59,,MATCH(Model!N$4,'NOI Walk'!$H$16:$EI$16,0)),0)} -> -1311.5806 | ... EI29: {=-IFERROR(INDEX('NOI Walk'!$H$59:$EI$59,,MATCH(Model!EI$4,'NOI Walk'!$H$16:$EI$16,0)),0)} -> -2681.0347 | EM29: x
D30: Multifamily Cash Flow | G30: =SUM(G28:G29) -> 0 | H30: =SUM(H28:H29) -> 79100.127 | I30: =SUM(I28:I29) -> 74527.753 | J30: =SUM(J28:J29) -> 69936.153 | K30: =SUM(K28:K29) -> 65325.268 | L30: =SUM(L28:L29) -> 67980.691 | M30: =SUM(M28:M29) -> 72152.254 | N30: =SUM(N28:N29) -> 74831.767 | ... EI30: =SUM(EI28:EI29) -> 193450.28 | EM30: x
EM31: x
D32: Total Unlevered Cash Flow | G32: =IF(G4>Assumptions!$E$174,0,SUM(G30,G26,G10,G22,G18)) -> -16901391 | H32: =IF(H4>Assumptions!$E$174,0,SUM(H30,H26,H10,H22,H18)) -> 79100.127 | I32: =IF(I4>Assumptions!$E$174,0,SUM(I30,I26,I10,I22,I18)) -> -23124.421 | J32: =IF(J4>Assumptions!$E$174,0,SUM(J30,J26,J10,J22,J18)) -> -27716.02 | K32: =IF(K4>Assumptions!$E$174,0,SUM(K30,K26,K10,K22,K18)) -> -32326.906 | L32: =IF(L4>Assumptions!$E$174,0,SUM(L30,L26,L10,L22,L18)) -> -77171.483 | M32: =IF(M4>Assumptions!$E$174,0,SUM(M30,M26,M10,M22,M18)) -> -62999.92 | N32: =IF(N4>Assumptions!$E$174,0,SUM(N30,N26,N10,N22,N18)) -> -22820.407 | ... EI32: =IF(EI4>Assumptions!$E$174,0,SUM(EI30,EI26,EI10,EI22,EI18)) -> 0 | EM32: x
D33: Equity In | F33: =SUM(G33:EI33) -> -19458691 | G33: =+MIN(G10,0) -> -16901391 | H33: =+MIN(H10,0) -> 0 | I33: =+MIN(I10,0) -> -97652.174 | J33: =+MIN(J10,0) -> -97652.174 | K33: =+MIN(K10,0) -> -97652.174 | L33: =+MIN(L10,0) -> -145152.17 | M33: =+MIN(M10,0) -> -135152.17 | N33: =+MIN(N10,0) -> -97652.174 | ... EI33: =+MIN(EI10,0) -> 0 | EM33: x
D34: Profit | F34: =+SUM(G32:OFFSET(G32,,Assumptions!$E$174)) -> 21365755 | EM34: x
D35: Unlevered IRR | F35: =XIRR(G32:EI32,$G$2:$EI$2) -> 0.18511292 | EM35: x
D36: Unlevered MOIC | F36: =-(F34-G33)/G33 -> 2.2641418 | EM36: x
EM37: x
D38: Financable Costs | G38: =-G5-G9 -> -15020000 | H38: =-H5-H9 -> 0 | I38: =-I5-I9 -> -97652.174 | J38: =-J5-J9 -> -97652.174 | K38: =-K5-K9 -> -97652.174 | L38: =-L5-L9 -> -145152.17 | M38: =-M5-M9 -> -135152.17 | N38: =-N5-N9 -> -97652.174 | ... S38: =-S5-S9 -> -96652.174 | T38: =+T33 -> -96652.174 | U38: =+U33 -> -96652.174 | V38: =+V33 -> -96652.174 | W38: =+W33 -> -96652.174 | X38: =+X33 -> -96652.174 | Y38: =+Y33 -> -96652.174 | Z38: =+Z33 -> -96652.174 | AA38: =+AA33 -> -96652.174 | ... EI38: =+EI33 -> 0 | EM38: x
D39: Remaining Costs | G39: =+G33-G38 -> -1881390.8 | H39: =+H33-H38 -> 0 | I39: =+I33-I38 -> 0 | J39: =+J33-J38 -> 0 | K39: =+K33-K38 -> 0 | L39: =+L33-L38 -> 0 | M39: =+M33-M38 -> 0 | N39: =+N33-N38 -> 0 | ... EI39: =+EI33-EI38 -> 0 | EM39: x
D40: Cash Available for DSCR Loan Paydown | G40: =+G58 -> 0 | H40: =+H58 -> 0 | I40: =+I58 -> 0 | J40: =+J58 -> 0 | K40: =+K58 -> 0 | L40: =+L58 -> 0 | M40: =+M58 -> 0 | N40: =+N58 -> 0 | ... BN40: =+BN58 -> 0 | BO40: =IF(AND(Assumptions!$G$34="No",Model!BO4=Assumptions!$E$174),BO32,BO58) -> 0 | BP40: =+BP58 -> 0 | BQ40: =+BQ58 -> 0 | BR40: =+BR58 -> 0 | BS40: =+BS58 -> 0 | BT40: =+BT58 -> 0 | BU40: =+BU58 -> 0 | BV40: =+BV58 -> 0 | BW40: =+BW58 -> 0 | ... EI40: =+EI58 -> 0 | EM40: x
EM41: x
B42: =+Assumptions!G31 -> 11250000 | D42: Bridge Loan | EM42: x
D43: Beginning Balance | H43: =+G47 -> 11250000 | I43: =+H47 -> 11245023 | J43: =+I47 -> 11240005 | K43: =+J47 -> 11234945 | L43: =+K47 -> 11229843 | M43: =+L47 -> 11224698 | N43: =+M47 -> 11219510 | O43: =+N47 -> 11214279 | ... EI43: =+EH47 -> 0 | EM43: x
D44: Draw | G44: =IF(G4=Assumptions!$G$24,Assumptions!$R$30,MIN(G5*Assumptions!$G$29+G9*Assumptions!$G$30,Assumptions!$G$31-G43)) -> 11250000 | H44: =IF(H4=Assumptions!$G$24,Assumptions!$R$30,MIN(H5*Assumptions!$G$29+H9*Assumptions!$G$30,Assumptions!$G$31-H43)) -> 0 | I44: =IF(I4=Assumptions!$G$24,Assumptions!$R$30,MIN(I5*Assumptions!$G$29+I9*Assumptions!$G$30,Assumptions!$G$31-I43)) -> 0 | J44: =IF(J4=Assumptions!$G$24,Assumptions!$R$30,MIN(J5*Assumptions!$G$29+J9*Assumptions!$G$30,Assumptions!$G$31-J43)) -> 0 | K44: =IF(K4=Assumptions!$G$24,Assumptions!$R$30,MIN(K5*Assumptions!$G$29+K9*Assumptions!$G$30,Assumptions!$G$31-K43)) -> 0 | L44: =IF(L4=Assumptions!$G$24,Assumptions!$R$30,MIN(L5*Assumptions!$G$29+L9*Assumptions!$G$30,Assumptions!$G$31-L43)) -> 0 | M44: =IF(M4=Assumptions!$G$24,Assumptions!$R$30,MIN(M5*Assumptions!$G$29+M9*Assumptions!$G$30,Assumptions!$G$31-M43)) -> 0 | N44: =IF(N4=Assumptions!$G$24,Assumptions!$R$30,MIN(N5*Assumptions!$G$29+N9*Assumptions!$G$30,Assumptions!$G$31-N43)) -> 0 | ... EI44: =IF(EI4=Assumptions!$G$24,Assumptions!$R$30,MIN(EI5*Assumptions!$G$29+EI9*Assumptions!$G$30,Assumptions!$G$31-EI43)) -> 0 | EM44: x
D45: Principal Paydown | G45: =+IFERROR(INDEX('Debt Schedule'!$F$12:$F$108,MATCH(Model!G4,'Debt Schedule'!$B$12:$B$108,0)),0) -> 0 | H45: =+IFERROR(INDEX('Debt Schedule'!$F$12:$F$108,MATCH(Model!H4,'Debt Schedule'!$B$12:$B$108,0)),0) -> -4976.8016 | I45: =+IFERROR(INDEX('Debt Schedule'!$F$12:$F$108,MATCH(Model!I4,'Debt Schedule'!$B$12:$B$108,0)),0) -> -5018.275 | J45: =+IFERROR(INDEX('Debt Schedule'!$F$12:$F$108,MATCH(Model!J4,'Debt Schedule'!$B$12:$B$108,0)),0) -> -5060.0939 | K45: =+IFERROR(INDEX('Debt Schedule'!$F$12:$F$108,MATCH(Model!K4,'Debt Schedule'!$B$12:$B$108,0)),0) -> -5102.2614 | L45: =+IFERROR(INDEX('Debt Schedule'!$F$12:$F$108,MATCH(Model!L4,'Debt Schedule'!$B$12:$B$108,0)),0) -> -5144.7802 | M45: =+IFERROR(INDEX('Debt Schedule'!$F$12:$F$108,MATCH(Model!M4,'Debt Schedule'!$B$12:$B$108,0)),0) -> -5187.6534 | N45: =+IFERROR(INDEX('Debt Schedule'!$F$12:$F$108,MATCH(Model!N4,'Debt Schedule'!$B$12:$B$108,0)),0) -> -5230.8838 | ... EI45: =+IFERROR(INDEX('Debt Schedule'!$F$12:$F$108,MATCH(Model!EI4,'Debt Schedule'!$B$12:$B$108,0)),0) -> 0
D46: Paydown | G46: =-MIN(G40,SUM(G43:G45)) -> 0 | H46: =-MIN(H40,SUM(H43:H45)) -> 0 | I46: =-MIN(I40,SUM(I43:I45)) -> 0 | J46: =-MIN(J40,SUM(J43:J45)) -> 0 | K46: =-MIN(K40,SUM(K43:K45)) -> 0 | L46: =-MIN(L40,SUM(L43:L45)) -> 0 | M46: =-MIN(M40,SUM(M43:M45)) -> 0 | N46: =-MIN(N40,SUM(N43:N45)) -> 0 | ... EI46: =-MIN(EI40,SUM(EI43:EI45)) -> 0 | EM46: x
D47: Ending Balance | G47: =SUM(G43:G46) -> 11250000 | H47: =SUM(H43:H46) -> 11245023 | I47: =SUM(I43:I46) -> 11240005 | J47: =SUM(J43:J46) -> 11234945 | K47: =SUM(K43:K46) -> 11229843 | L47: =SUM(L43:L46) -> 11224698 | M47: =SUM(M43:M46) -> 11219510 | N47: =SUM(N43:N46) -> 11214279 | ... EI47: =SUM(EI43:EI46) -> 0 | EM47: x
EM48: x
B49: =SUM(G49:R49) -> -6774996.4 | D49: Costs to Equity, Before Interest | G49: =SUM(G38:G40,G44:G46) -> -5651390.8 | H49: =SUM(H38:H40,H44:H46) -> -4976.8016 | I49: =SUM(I38:I40,I44:I46) -> -102670.45 | J49: =SUM(J38:J40,J44:J46) -> -102712.27 | K49: =SUM(K38:K40,K44:K46) -> -102754.44 | L49: =SUM(L38:L40,L44:L46) -> -150296.95 | M49: =SUM(M38:M40,M44:M46) -> -140339.83 | N49: =SUM(N38:N40,N44:N46) -> -102883.06 | ... EI49: =SUM(EI38:EI40,EI44:EI46) -> 0 | EM49: x
EM50: x
D51: Plus: DSCR Loan Interest Expense | G51: =-G80 -> 0 | H51: =-H80 -> 93750 | I51: =-I80 -> 93708.527 | J51: =-J80 -> 93666.708 | K51: =-K80 -> 93624.54 | L51: =-L80 -> 93582.021 | M51: =-M80 -> 93539.148 | N51: =-N80 -> 93495.918 | ... EI51: =-EI80 -> 0 | EM51: x
D52: Less: Income Offset | G52: =-MIN(G30+G45+G46+G58,G51) -> 0 | H52: =-MIN(H30+H45+H46+H58,H51) -> -74123.325 | I52: =-MIN(I30+I45+I46+I58,I51) -> -69509.478 | J52: =-MIN(J30+J45+J46+J58,J51) -> -64876.06 | K52: =-MIN(K30+K45+K46+K58,K51) -> -60223.006 | L52: =-MIN(L30+L45+L46+L58,L51) -> -62835.91 | M52: =-MIN(M30+M45+M46+M58,M51) -> -66964.6 | N52: =-MIN(N30+N45+N46+N58,N51) -> -69600.883 | ... EI52: =-MIN(EI30+EI45+EI46+EI58,EI51) -> 0 | EM52: x
B53: =SUM(G53:EI53) -> -280622.96 | D53: Interest Expense, net | G53: =-SUM(G51:G52) -> 0 | H53: =-SUM(H51:H52) -> -19626.675 | I53: =-SUM(I51:I52) -> -24199.048 | J53: =-SUM(J51:J52) -> -28790.648 | K53: =-SUM(K51:K52) -> -33401.534 | L53: =-SUM(L51:L52) -> -30746.111 | M53: =-SUM(M51:M52) -> -26574.548 | N53: =-SUM(N51:N52) -> -23895.035 | ... EI53: =-SUM(EI51:EI52) -> 0 | EM53: x
EM54: x
B55: =-SUM(Assumptions!F5:F6) -> -8489313.8 | D55: Equity Draws | G55: =MAX(MIN(-G49+G45-G53,-$B$55-F56),0) -> 5651390.8 | H55: =MAX(MIN(-H49+H45-H53,-$B$55-G56),0) -> 19626.675 | I55: =MAX(MIN(-I49+I45-I53,-$B$55-H56),0) -> 121851.22 | J55: =MAX(MIN(-J49+J45-J53,-$B$55-I56),0) -> 126442.82 | K55: =MAX(MIN(-K49+K45-K53,-$B$55-J56),0) -> 131053.71 | L55: =MAX(MIN(-L49+L45-L53,-$B$55-K56),0) -> 175898.28 | M55: =MAX(MIN(-M49+M45-M53,-$B$55-L56),0) -> 161726.72 | N55: =MAX(MIN(-N49+N45-N53,-$B$55-M56),0) -> 121547.21 | ... EI55: =MAX(MIN(-EI49+EI45-EI53,-$B$55-EH56),0) -> 0 | EM55: x
D56: Cumulative Equity Drawn | G56: =+G55+F56 -> 5651390.8 | H56: =+H55+G56 -> 5671017.5 | I56: =+I55+H56 -> 5792868.7 | J56: =+J55+I56 -> 5919311.6 | K56: =+K55+J56 -> 6050365.3 | L56: =+L55+K56 -> 6226263.5 | M56: =+M55+L56 -> 6387990.3 | N56: =+N55+M56 -> 6509537.5 | ... EI56: =+EI55+EH56 -> 8489313.8 | EM56: x
EM57: x
D58: Perm Loan Draw | G58: =IF(AND(G4=Assumptions!$G$36,Assumptions!$G$34="Yes"),Assumptions!$L$40,0) -> 0 | H58: =IF(AND(H4=Assumptions!$G$36,Assumptions!$G$34="Yes"),Assumptions!$L$40,0) -> 0 | I58: =IF(AND(I4=Assumptions!$G$36,Assumptions!$G$34="Yes"),Assumptions!$L$40,0) -> 0 | J58: =IF(AND(J4=Assumptions!$G$36,Assumptions!$G$34="Yes"),Assumptions!$L$40,0) -> 0 | K58: =IF(AND(K4=Assumptions!$G$36,Assumptions!$G$34="Yes"),Assumptions!$L$40,0) -> 0 | L58: =IF(AND(L4=Assumptions!$G$36,Assumptions!$G$34="Yes"),Assumptions!$L$40,0) -> 0 | M58: =IF(AND(M4=Assumptions!$G$36,Assumptions!$G$34="Yes"),Assumptions!$L$40,0) -> 0 | N58: =IF(AND(N4=Assumptions!$G$36,Assumptions!$G$34="Yes"),Assumptions!$L$40,0) -> 0 | ... EI58: =IF(AND(EI4=Assumptions!$G$36,Assumptions!$G$34="Yes"),Assumptions!$L$40,0) -> 0 | EM58: x
D59: Cash Flow Before Perm Loan Interest | G59: =+G32-G51+G55+SUM(G44:G46) -> 0 | H59: =+H32-H51+H55+SUM(H44:H46) -> 0 | I59: =+I32-I51+I55+SUM(I44:I46) -> 0 | J59: =+J32-J51+J55+SUM(J44:J46) -> 0 | K59: =+K32-K51+K55+SUM(K44:K46) -> 9.094947e-12 | L59: =+L32-L51+L55+SUM(L44:L46) -> 0 | M59: =+M32-M51+M55+SUM(M44:M46) -> 0 | N59: =+N32-N51+N55+SUM(N44:N46) -> 0 | ... EI59: =+EI32-EI51+EI55+SUM(EI44:EI46) -> 0 | EM59: x
EM60: x
D61: Permanent Loan | EM61: x
D62: Beginning Balance | G62: =+F67 -> 0 | H62: =+G67 -> 0 | I62: =+H67 -> 0 | J62: =+I67 -> 0 | K62: =+J67 -> 0 | L62: =+K67 -> 0 | M62: =+L67 -> 0 | N62: =+M67 -> 0 | ... EI62: =+EH67 -> 0 | EM62: x
D63: Draw | G63: =IF(AND(Assumptions!$G$34="Yes",Model!G4=Assumptions!$G$36),Assumptions!$L$37,0) -> 0 | H63: =IF(AND(Assumptions!$G$34="Yes",Model!H4=Assumptions!$G$36),Assumptions!$L$37,0) -> 0 | I63: =IF(AND(Assumptions!$G$34="Yes",Model!I4=Assumptions!$G$36),Assumptions!$L$37,0) -> 0 | J63: =IF(AND(Assumptions!$G$34="Yes",Model!J4=Assumptions!$G$36),Assumptions!$L$37,0) -> 0 | K63: =IF(AND(Assumptions!$G$34="Yes",Model!K4=Assumptions!$G$36),Assumptions!$L$37,0) -> 0 | L63: =IF(AND(Assumptions!$G$34="Yes",Model!L4=Assumptions!$G$36),Assumptions!$L$37,0) -> 0 | M63: =IF(AND(Assumptions!$G$34="Yes",Model!M4=Assumptions!$G$36),Assumptions!$L$37,0) -> 0 | N63: =IF(AND(Assumptions!$G$34="Yes",Model!N4=Assumptions!$G$36),Assumptions!$L$37,0) -> 0 | ... EI63: =IF(AND(Assumptions!$G$34="Yes",Model!EI4=Assumptions!$G$36),Assumptions!$L$37,0) -> 0 | EM63: x
D64: Principal Paydown | G64: =+IFERROR(INDEX('Debt Schedule'!$P$12:$P$108,MATCH(Model!G4,'Debt Schedule'!$M$12:$M$108,0)),0) -> 0 | H64: =+IFERROR(INDEX('Debt Schedule'!$P$12:$P$108,MATCH(Model!H4,'Debt Schedule'!$M$12:$M$108,0)),0) -> 0 | I64: =+IFERROR(INDEX('Debt Schedule'!$P$12:$P$108,MATCH(Model!I4,'Debt Schedule'!$M$12:$M$108,0)),0) -> 0 | J64: =+IFERROR(INDEX('Debt Schedule'!$P$12:$P$108,MATCH(Model!J4,'Debt Schedule'!$M$12:$M$108,0)),0) -> 0 | K64: =+IFERROR(INDEX('Debt Schedule'!$P$12:$P$108,MATCH(Model!K4,'Debt Schedule'!$M$12:$M$108,0)),0) -> 0 | L64: =+IFERROR(INDEX('Debt Schedule'!$P$12:$P$108,MATCH(Model!L4,'Debt Schedule'!$M$12:$M$108,0)),0) -> 0 | M64: =+IFERROR(INDEX('Debt Schedule'!$P$12:$P$108,MATCH(Model!M4,'Debt Schedule'!$M$12:$M$108,0)),0) -> 0 | N64: =+IFERROR(INDEX('Debt Schedule'!$P$12:$P$108,MATCH(Model!N4,'Debt Schedule'!$M$12:$M$108,0)),0) -> 0 | ... EI64: =+IFERROR(INDEX('Debt Schedule'!$P$12:$P$108,MATCH(Model!EI4,'Debt Schedule'!$M$12:$M$108,0)),0) -> 0 | EM64: x
D65: Paydown | G65: =IF(G4=Assumptions!$E$174,-MIN(G59,G62+G64),0) -> 0 | H65: =IF(H4=Assumptions!$E$174,-MIN(H59,H62+H64),0) -> 0 | I65: =IF(I4=Assumptions!$E$174,-MIN(I59,I62+I64),0) -> 0 | J65: =IF(J4=Assumptions!$E$174,-MIN(J59,J62+J64),0) -> 0 | K65: =IF(K4=Assumptions!$E$174,-MIN(K59,K62+K64),0) -> 0 | L65: =IF(L4=Assumptions!$E$174,-MIN(L59,L62+L64),0) -> 0 | M65: =IF(M4=Assumptions!$E$174,-MIN(M59,M62+M64),0) -> 0 | N65: =IF(N4=Assumptions!$E$174,-MIN(N59,N62+N64),0) -> 0 | ... EI65: =IF(EI4=Assumptions!$E$174,-MIN(EI59,EI62+EI64),0) -> 0 | EM65: x
D66: Interest Expense | G66: =+G84 -> 0 | H66: =+H84 -> 0 | I66: =+I84 -> 0 | J66: =+J84 -> 0 | K66: =+K84 -> 0 | L66: =+L84 -> 0 | M66: =+M84 -> 0 | N66: =+N84 -> 0 | ... EI66: =+EI84 -> 0 | EM66: x
D67: Ending Balance | G67: =SUM(G62:G65) -> 0 | H67: =SUM(H62:H65) -> 0 | I67: =SUM(I62:I65) -> 0 | J67: =SUM(J62:J65) -> 0 | K67: =SUM(K62:K65) -> 0 | L67: =SUM(L62:L65) -> 0 | M67: =SUM(M62:M65) -> 0 | N67: =SUM(N62:N65) -> 0 | ... EI67: =SUM(EI62:EI65) -> 0 | EM67: x
B69: =-SUM(G69:S69) -> 7080700.1 | D69: Total Levered Project Cash Flows | G69: =SUM(-G55,G58:G59,-G66,G64:G65) -> -5651390.8 | H69: =SUM(-H55,H58:H59,-H66,H64:H65) -> -19626.675 | I69: =SUM(-I55,I58:I59,-I66,I64:I65) -> -121851.22 | J69: =SUM(-J55,J58:J59,-J66,J64:J65) -> -126442.82 | K69: =SUM(-K55,K58:K59,-K66,K64:K65) -> -131053.71 | L69: =SUM(-L55,L58:L59,-L66,L64:L65) -> -175898.28 | M69: =SUM(-M55,M58:M59,-M66,M64:M65) -> -161726.72 | N69: =SUM(-N55,N58:N59,-N66,N64:N65) -> -121547.21 | ... EI69: =SUM(-EI55,EI58:EI59,-EI66,EI64:EI65) -> 0 | EM69: x
D70: Equity In | G70: =SUM(B55:B55) -> -8489313.8 | EM70: x
D71: Profit | G71: =SUMIF(G69:EI69,">0",G69:EI69)+G70 -> 15141725 | EM71: x
D72: Levered IRR | G72: =XIRR(G69:EI69,$G$2:$EI$2) -> 0.33942088 | EM72: x
D73: Levered MOIC | G73: =-(G71-G70)/G70 -> 2.7836218 | EM73: x
EM74: x
EM75: x
D76: 1-Month SOFR | G76: =IFERROR(INDEX('1-month Term SOFR'!$Q$12:$Q$132,MATCH(Model!G$2,'1-month Term SOFR'!$O$12:$O$132,0)),F76) -> 0.0412577 | H76: =IFERROR(INDEX('1-month Term SOFR'!$Q$12:$Q$132,MATCH(Model!H$2,'1-month Term SOFR'!$O$12:$O$132,0)),G76) -> 0.0403625 | I76: =IFERROR(INDEX('1-month Term SOFR'!$Q$12:$Q$132,MATCH(Model!I$2,'1-month Term SOFR'!$O$12:$O$132,0)),H76) -> 0.0395926 | J76: =IFERROR(INDEX('1-month Term SOFR'!$Q$12:$Q$132,MATCH(Model!J$2,'1-month Term SOFR'!$O$12:$O$132,0)),I76) -> 0.0381025 | K76: =IFERROR(INDEX('1-month Term SOFR'!$Q$12:$Q$132,MATCH(Model!K$2,'1-month Term SOFR'!$O$12:$O$132,0)),J76) -> 0.0378538 | L76: =IFERROR(INDEX('1-month Term SOFR'!$Q$12:$Q$132,MATCH(Model!L$2,'1-month Term SOFR'!$O$12:$O$132,0)),K76) -> 0.0378518 | M76: =IFERROR(INDEX('1-month Term SOFR'!$Q$12:$Q$132,MATCH(Model!M$2,'1-month Term SOFR'!$O$12:$O$132,0)),L76) -> 0.0367114 | N76: =IFERROR(INDEX('1-month Term SOFR'!$Q$12:$Q$132,MATCH(Model!N$2,'1-month Term SOFR'!$O$12:$O$132,0)),M76) -> 0.0364455 | ... EI76: =IFERROR(INDEX('1-month Term SOFR'!$Q$12:$Q$132,MATCH(Model!EI$2,'1-month Term SOFR'!$O$12:$O$132,0)),EH76) -> 0.0402355 | EM76: x
EM77: x
D78: Bridge Loan Interest Rate | EM78: x
D79: All-in Rate | G79: =Assumptions!$L$29 -> 0.1 | H79: =Assumptions!$L$29 -> 0.1 | I79: =Assumptions!$L$29 -> 0.1 | J79: =Assumptions!$L$29 -> 0.1 | K79: =Assumptions!$L$29 -> 0.1 | L79: =Assumptions!$L$29 -> 0.1 | M79: =Assumptions!$L$29 -> 0.1 | N79: =Assumptions!$L$29 -> 0.1 | ... EI79: =Assumptions!$L$29 -> 0.1 | EM79: x
D80: Interest Due | G80: =-IFERROR(INDEX('Debt Schedule'!$G$12:$G$108,MATCH(Model!G4,'Debt Schedule'!$B$12:$B$108,0)),0) -> 0 | H80: =-IFERROR(INDEX('Debt Schedule'!$G$12:$G$108,MATCH(Model!H4,'Debt Schedule'!$B$12:$B$108,0)),0) -> -93750 | I80: =-IFERROR(INDEX('Debt Schedule'!$G$12:$G$108,MATCH(Model!I4,'Debt Schedule'!$B$12:$B$108,0)),0) -> -93708.527 | J80: =-IFERROR(INDEX('Debt Schedule'!$G$12:$G$108,MATCH(Model!J4,'Debt Schedule'!$B$12:$B$108,0)),0) -> -93666.708 | K80: =-IFERROR(INDEX('Debt Schedule'!$G$12:$G$108,MATCH(Model!K4,'Debt Schedule'!$B$12:$B$108,0)),0) -> -93624.54 | L80: =-IFERROR(INDEX('Debt Schedule'!$G$12:$G$108,MATCH(Model!L4,'Debt Schedule'!$B$12:$B$108,0)),0) -> -93582.021 | M80: =-IFERROR(INDEX('Debt Schedule'!$G$12:$G$108,MATCH(Model!M4,'Debt Schedule'!$B$12:$B$108,0)),0) -> -93539.148 | N80: =-IFERROR(INDEX('Debt Schedule'!$G$12:$G$108,MATCH(Model!N4,'Debt Schedule'!$B$12:$B$108,0)),0) -> -93495.918 | ... EI80: =-IFERROR(INDEX('Debt Schedule'!$G$12:$G$108,MATCH(Model!EI4,'Debt Schedule'!$B$12:$B$108,0)),0) -> 0 | EM80: x
EM81: x
D82: Permanent Loan Interest Rate | EM82: x
D83: All-in Rate | G83: =+Assumptions!$G$37 -> 0.0618393 | H83: =+Assumptions!$G$37 -> 0.0618393 | I83: =+Assumptions!$G$37 -> 0.0618393 | J83: =+Assumptions!$G$37 -> 0.0618393 | K83: =+Assumptions!$G$37 -> 0.0618393 | L83: =+Assumptions!$G$37 -> 0.0618393 | M83: =+Assumptions!$G$37 -> 0.0618393 | N83: =+Assumptions!$G$37 -> 0.0618393 | ... EI83: =+Assumptions!$G$37 -> 0.0618393 | EM83: x
D84: Interest Due | G84: =-IFERROR(INDEX('Debt Schedule'!$Q$12:$Q$108,MATCH(Model!G4,'Debt Schedule'!$M$12:$M$108,0)),0) -> 0 | H84: =-IFERROR(INDEX('Debt Schedule'!$Q$12:$Q$108,MATCH(Model!H4,'Debt Schedule'!$M$12:$M$108,0)),0) -> 0 | I84: =-IFERROR(INDEX('Debt Schedule'!$Q$12:$Q$108,MATCH(Model!I4,'Debt Schedule'!$M$12:$M$108,0)),0) -> 0 | J84: =-IFERROR(INDEX('Debt Schedule'!$Q$12:$Q$108,MATCH(Model!J4,'Debt Schedule'!$M$12:$M$108,0)),0) -> 0 | K84: =-IFERROR(INDEX('Debt Schedule'!$Q$12:$Q$108,MATCH(Model!K4,'Debt Schedule'!$M$12:$M$108,0)),0) -> 0 | L84: =-IFERROR(INDEX('Debt Schedule'!$Q$12:$Q$108,MATCH(Model!L4,'Debt Schedule'!$M$12:$M$108,0)),0) -> 0 | M84: =-IFERROR(INDEX('Debt Schedule'!$Q$12:$Q$108,MATCH(Model!M4,'Debt Schedule'!$M$12:$M$108,0)),0) -> 0 | N84: =-IFERROR(INDEX('Debt Schedule'!$Q$12:$Q$108,MATCH(Model!N4,'Debt Schedule'!$M$12:$M$108,0)),0) -> 0 | ... EI84: =-IFERROR(INDEX('Debt Schedule'!$Q$12:$Q$108,MATCH(Model!EI4,'Debt Schedule'!$M$12:$M$108,0)),0) -> 0 | EM84: x
EM85: x
EM86: x
D87: Waterfall | EM87: x
F88: Allocation | J88: LP | K88: GP | L88: Hurdle | EM88: x
D89: GP | F89: =+Assumptions!K3 -> 0.1 | H89: Preferred | J89: =+F90 -> 0.9 | K89: =+F89 -> 0.1 | L89: 0.1 | EM89: x
D90: LP | F90: =+Assumptions!K4 -> 0.9 | H90: Hurdle 1 | J90: =1-K90 -> 0.85 | K90: 0.15 | L90: 0.15 | EM90: x
D91: Total Equity | F91: =SUM(F89:F90) -> 1 | H91: Hurdle 2 | J91: =1-K91 -> 0.8 | K91: 0.2 | L91: 0.2 | EM91: x
H92: Hurdle 3 | J92: =1-K92 -> 0.7 | K92: 0.3 | L92: =+L91 -> 0.2 | EM92: x
EM93: x
EM94: x
D95: LP Net Returns | EM95: x
B96: =SUM(G96:EI96) -> 16914109 | D96: Distributions | G96: =SUM(-G129,G145,G163,G171)*$F$90 -> 0 | H96: =SUM(-H129,H145,H163,H171)*$F$90 -> 0 | I96: =SUM(-I129,I145,I163,I171)*$F$90 -> 0 | J96: =SUM(-J129,J145,J163,J171)*$F$90 -> 0 | K96: =SUM(-K129,K145,K163,K171)*$F$90 -> 0 | L96: =SUM(-L129,L145,L163,L171)*$F$90 -> 0 | M96: =SUM(-M129,M145,M163,M171)*$F$90 -> 0 | N96: =SUM(-N129,N145,N163,N171)*$F$90 -> 0 | ... EI96: =SUM(-EI129,EI145,EI163,EI171)*$F$90 -> -861.99689 | EM96: x
B97: =SUM(G97:EI97) -> -7640382.4 | D97: Contributions | G97: =-SUM(G124)*$F$90 -> -7640382.4 | H97: =-SUM(H124)*$F$90 -> 0 | I97: =-SUM(I124)*$F$90 -> 0 | J97: =-SUM(J124)*$F$90 -> 0 | K97: =-SUM(K124)*$F$90 -> 0 | L97: =-SUM(L124)*$F$90 -> 0 | M97: =-SUM(M124)*$F$90 -> 0 | N97: =-SUM(N124)*$F$90 -> 0 | ... EI97: =-SUM(EI124)*$F$90 -> 0 | EM97: x
D98: Net Cash Flows | G98: =SUM(G96:G97) -> -7640382.4 | H98: =SUM(H96:H97) -> 0 | I98: =SUM(I96:I97) -> 0 | J98: =SUM(J96:J97) -> 0 | K98: =SUM(K96:K97) -> 0 | L98: =SUM(L96:L97) -> 0 | M98: =SUM(M96:M97) -> 0 | N98: =SUM(N96:N97) -> 0 | ... EI98: =SUM(EI96:EI97) -> -861.99689 | EM98: x
D99: IRR | E99: =XIRR(G98:EI98,$G$2:$EI$2) -> 0.23664005 | EM99: x
D100: Equity Multiple | E100: =-SUM(G96:EI96)/SUM(G97:EI97) -> 2.2137778 | EM100: x
EM101: x
...

Sheet Assumptions
A1: 265-275 Beech St. Hackensack, NJ
B2: Model Start | F2: 45838 | I2: Ownership Splits | N2: Offer | O2: Price | P2: Terms
I3: Sponsor Equity | K3: 0.1 | L3: =+F5 -> 848931.38 | N3: Ask | O3: =+G22 -> 15000000
B4: Sources | F4: $ | G4: % | I4: LP Equity | K4: =1-K3 -> 0.9 | L4: =+F6 -> 7640382.4 | N4: Offer 1
B5: Sponsor Equity | F5: =+F8-SUM(F6:F7) -> 848931.38 | G5: =+F5/$F$8 -> 0.043007137 | I5: Total Equity | K5: =SUM(K3:K4) -> 1 | L5: =SUM(L3:L4) -> 8489313.8
B6: LP Equity | F6: =(F8-SUM(F7:F7))*K4 -> 7640382.4 | G6: =+F6/$F$8 -> 0.38706424
B7: =+B27 -> Acquisition Loan | F7: =+G31 -> 11250000 | G7: =+F7/$F$8 -> 0.56992863
A8: =F8=SUM(F5:F7) -> TRUE | B8: Total Sources | F8: =+F17 -> 19739314 | G8: =+F8/$F$8 -> 1 | I8: Levered IRR | K8: =+E183 -> 0.33942088
I9: Levered MOIC | K9: =+E184 -> 2.7836218
B10: Uses | F10: $ | G10: %
B11: Acquisition of Property | F11: =+G23 -> 15000000 | G11: =+F11/$F$17 -> 0.75990484
B12: Closing Costs | F12: =+'Closing Costs'!E19 -> 1062339.1 | G12: =+F12/$F$17 -> 0.05381844
B13: Legal and Pre-Development | F13: =+'Legal and Pre-Dev'!E12 -> 29925 | G13: =+F13/$F$17 -> 0.0015160101
B14: Reserves | F14: =+Reserves!E12 -> 789126.76 | G14: =+F14/$F$17 -> 0.039977416
B15: Hard Costs | F15: =+'Hard Costs'!E16 -> 2577300 | G15: =+F15/$F$17 -> 0.13056685
B16: Interest Reserve | F16: =+L31 -> 280622.96 | G16: =+F16/$F$17 -> 0.01421645
A17: =F17=SUM(F11:F16) -> TRUE | B17: Total Uses | F17: =SUM(F11:F16) -> 19739314 | G17: =+F17/$F$17 -> 1
I20: Re-leased Cash-on-Cash | L20: {=+INDEX(Model!69:69,,MATCH(G144+3,Model!4:4,0))*12/L5} -> 13.381843
B21: General Property Assumptions | I21: Going-in Cap | L21: =('NOI Walk'!H54*12)/G23 -> 0.064367596
B22: Ask | G22: 15000000 | I22: Going-in Cash-on-Cash | L22: {=+INDEX(Model!69:69,,MATCH(1,Model!4:4,0))*12/L5} -> -0.027743125
B23: Acquisition Price | E23: =+G23/D124 -> 192307.69 | F23: =+G23/O3-1 -> 0 | G23: 15000000 | I23: Net Rentable SF | L23: =SUM(E46:E123)+'Retail Assumptions'!F19 -> 49950 | N23: ="Max "&B27 -> Max Acquisition Loan
B24: Closing on Property | G24: 0 | I24: Efficiency | L24: =+L23/G25 -> 0.90818182 | N24: ="Stabilized Annualized NOI in Month "&1 -> Stabilized Annualized NOI in Month 1 | R24: {=INDEX('NOI Walk'!$H$67:$EI$67,,MATCH(1,'NOI Walk'!$H$16:$EI$16,0))*12} -> 965513.94
B25: Buildable SF | G25: 55000 | I25: Stabilized Yield on Cost | L25: {=INDEX('NOI Walk'!$H$67:$EI$67,,MATCH(Assumptions!G144+1,'NOI Walk'!$H$16:$EI$16,0))*12/F17} -> 0.095658551 | N25: Required DSCR Minimum | R25: 0.25
N26: Max Loan Size Based on DSCR | R26: =+R24/R25/L27 -> 36407269
B27: Acquisition Loan | I27: Loan Constant | L27: =IFERROR(PMT(L29,L30,-1),L29) -> 0.10607925
B28: Origination | G28: 0 | I28: Origination Fee | L28: 0.02 | N28: Acquisition Financing | R28: =+G23 -> 15000000
B29: LTC on Property | G29: =+G31/G23 -> 0.75 | I29: Rate | K29: =(L29-'1-month Term SOFR'!Q16)*10000 -> 596.375 | L29: 0.1 | N29: LTV Max | R29: 0.75
B30: LTC on Hard Costs | G30: 0 | I30: Amortization | L30: 30 | N30: Max Loan Size Based on LTC | R30: =+R29*R28 -> 11250000
B31: Max Loan Size | G31: =+R33 -> 11250000 | I31: Interest Reserve | L31: =-Model!B53 -> 280622.96 | N31: Plus: Hard Cost Advance | R31: =+G30*F15 -> 0
B33: Permanent Loan | I33: Max Loan as Lesser of… | N33: =+N23 -> Max Acquisition Loan | R33: =MIN(R30+R31,R26) -> 11250000
B34: Permanent Loan Issued? | G34: Yes | I34: DSCR Min. | K34: 1.25 | L34: =+L38/K34/L39 -> 20678404
B35: Seasoning Period Post Stabilization | G35: =+G36-G144 -> 3 | I35: Debt Yield Min. | K35: 0.09 | L35: =+L38/K35 -> 21072210
B36: Refinancing Month | G36: 33 | I36: LTV Max | J36: 0.06 | K36: 0.75 | L36: =+L38/J36*K36 -> 23706236
B37: Fixed Interest Rate | G37: {=G38/10000+INDEX(Model!$G$76:$EI$76,,MATCH(Assumptions!G36,Model!$G$4:$EI$4,0))} -> 0.0618393 | I37: Max Perm. Loan | L37: =MIN(L34:L36) -> 20678404
B38: SOFR Spread at Origination | G38: 250 | I38: ="Annualized NOI in Month "&G36 -> Annualized NOI in Month 33 | L38: {=INDEX('NOI Walk'!$H$67:$EI$67,,MATCH(Assumptions!G36,'NOI Walk'!$H$16:$EI$16,0))*12} -> 1896498.9
B39: Amortization | G39: 30 | I39: Loan Factor | L39: =+PMT(G37/12,G39*12,-1)*12 -> 0.073371188
B40: Origination Cost | G40: 0.01 | I40: Perm Loan Proceeds net of fees | L40: =+L37*(1-G40) -> 20471620
I41: Proceeds from Cashout | L41: {=+INDEX(Model!G69:EI69,,MATCH(Assumptions!G36,Model!$G$4:$EI$4,0))} -> 9466888.8
G43: Unlevered ROI | H43: =((I124-H124)*12)/'Hard Costs'!E14 -> 0.3621234
B44: Rental Assumptions
B45: Units | C45: Vacate 1=Yes | D45: Layout | E45: Sq. Ft. | F45: Vacated | G45: Vacated | H45: Current Rent | I45: PF Rent | J45: Annual PF Rent | L45: Market Rent Assumptions | N45: PF $ Rent | O45: PF $ / SF | P45: Current $ / SF | Q45: Avg. Current | R45: Avg. PF
A46: 1 | B46: 1 | C46: 1 | D46: 2BR | E46: 825 | F46: 2 | G46: =+EOMONTH($F$2,F46) -> 45900 | H46: 1522.5 | I46: =+IFERROR(IF(OR(C46=1,C46=2),INDEX($N$46:$N$51,MATCH(D46,$L$46:$L$51,0)),H46),H46) -> 2800 | J46: =+I46*12 -> 33600 | K46: =+I46/H46-1 -> 0.83908046 | L46: Studio | N46: 2000 | O46: 2.25 | P46: =IFERROR(SUMIF($D$46:$D$123,L46,$I$46:$I$123)/SUMIF($D$46:$D$123,L46,$E$46:$E$123),0) -> 0 | Q46: =IFERROR(AVERAGEIF($D$46:$D$123,L46,$H$46:$H$123),0) -> 0 | R46: =IFERROR(AVERAGEIF($D$46:$D$123,L46,$I$46:$I$123),0) -> 0
A47: 2 | B47: =+B46+1 -> 2 | C47: 1 | D47: 2BR | E47: 825 | F47: 2 | G47: =+EOMONTH($F$2,F47) -> 45900 | H47: 1764 | I47: =+IFERROR(IF(OR(C47=1,C47=2),INDEX($N$46:$N$51,MATCH(D47,$L$46:$L$51,0)),H47),H47) -> 2800 | J47: =+I47*12 -> 33600 | K47: =+I47/H47-1 -> 0.58730159 | L47: 1BR | N47: 2400 | O47: 2 | P47: =IFERROR(SUMIF($D$46:$D$123,L47,$I$46:$I$123)/SUMIF($D$46:$D$123,L47,$E$46:$E$123),0) -> 3.84 | Q47: =IFERROR(AVERAGEIF($D$46:$D$123,L47,$H$46:$H$123),0) -> 1544.0186 | R47: =IFERROR(AVERAGEIF($D$46:$D$123,L47,$I$46:$I$123),0) -> 2400
A48: 3 | B48: =+B47+1 -> 3 | C48: 1 | D48: 1BR | E48: 625 | F48: 2 | G48: =+EOMONTH($F$2,F48) -> 45900 | H48: 1457.71 | I48: =+IFERROR(IF(OR(C48=1,C48=2),INDEX($N$46:$N$51,MATCH(D48,$L$46:$L$51,0)),H48),H48) -> 2400 | J48: =+I48*12 -> 28800 | K48: =+I48/H48-1 -> 0.64641801 | L48: 2BR | N48: 2800 | O48: 1.9 | P48: =IFERROR(SUMIF($D$46:$D$123,L48,$I$46:$I$123)/SUMIF($D$46:$D$123,L48,$E$46:$E$123),0) -> 3.3939394 | Q48: =IFERROR(AVERAGEIF($D$46:$D$123,L48,$H$46:$H$123),0) -> 1891.2167 | R48: =IFERROR(AVERAGEIF($D$46:$D$123,L48,$I$46:$I$123),0) -> 2800
A49: 4 | B49: =+B48+1 -> 4 | C49: 1 | D49: 1BR | E49: 625 | F49: =+F46+1 -> 3 | G49: =+EOMONTH($F$2,F49) -> 45930 | H49: 1680 | I49: =+IFERROR(IF(OR(C49=1,C49=2),INDEX($N$46:$N$51,MATCH(D49,$L$46:$L$51,0)),H49),H49) -> 2400 | J49: =+I49*12 -> 28800 | K49: =+I49/H49-1 -> 0.42857143 | L49: 3BR | N49: 3500 | O49: 1.85 | P49: =IFERROR(SUMIF($D$46:$D$123,L49,$I$46:$I$123)/SUMIF($D$46:$D$123,L49,$E$46:$E$123),0) -> 0 | Q49: =IFERROR(AVERAGEIF($D$46:$D$123,L49,$H$46:$H$123),0) -> 0 | R49: =IFERROR(AVERAGEIF($D$46:$D$123,L49,$I$46:$I$123),0) -> 0
A50: 5 | B50: =+B49+1 -> 5 | C50: 1 | D50: 1BR | E50: 625 | F50: =+F47+1 -> 3 | G50: =+EOMONTH($F$2,F50) -> 45930 | H50: 1451.66 | I50: =+IFERROR(IF(OR(C50=1,C50=2),INDEX($N$46:$N$51,MATCH(D50,$L$46:$L$51,0)),H50),H50) -> 2400 | J50: =+I50*12 -> 28800 | K50: =+I50/H50-1 -> 0.65327969 | L50: 3BR / 2BA | N50: 3650 | O50: 1.8 | P50: =IFERROR(SUMIF($D$46:$D$123,L50,$I$46:$I$123)/SUMIF($D$46:$D$123,L50,$E$46:$E$123),0) -> 0 | Q50: =IFERROR(AVERAGEIF($D$46:$D$123,L50,$H$46:$H$123),0) -> 0 | R50: =IFERROR(AVERAGEIF($D$46:$D$123,L50,$I$46:$I$123),0) -> 0
A51: 6 | B51: =+B50+1 -> 6 | C51: 1 | D51: 1BR | E51: 625 | F51: =+F48+1 -> 3 | G51: =+EOMONTH($F$2,F51) -> 45930 | H51: 1627.5 | I51: =+IFERROR(IF(OR(C51=1,C51=2),INDEX($N$46:$N$51,MATCH(D51,$L$46:$L$51,0)),H51),H51) -> 2400 | J51: =+I51*12 -> 28800 | K51: =+I51/H51-1 -> 0.47465438 | L51: 4BR | N51: 4000 | O51: 1.75 | P51: =IFERROR(SUMIF($D$46:$D$123,L51,$I$46:$I$123)/SUMIF($D$46:$D$123,L51,$E$46:$E$123),0) -> 0 | Q51: =IFERROR(AVERAGEIF($D$46:$D$123,L51,$H$46:$H$123),0) -> 0 | R51: =IFERROR(AVERAGEIF($D$46:$D$123,L51,$I$46:$I$123),0) -> 0
A52: 7 | B52: =+B51+1 -> 7 | C52: 1 | D52: 1BR | E52: 625 | F52: =+F49+1 -> 4 | G52: =+EOMONTH($F$2,F52) -> 45961 | H52: 1881 | I52: =+IFERROR(IF(OR(C52=1,C52=2),INDEX($N$46:$N$51,MATCH(D52,$L$46:$L$51,0)),H52),H52) -> 2400 | J52: =+I52*12 -> 28800 | K52: =+I52/H52-1 -> 0.27591707 | L52: Underwriting PF Rent Roll | N52: =+J124+J134 -> 2275200
A53: 8 | B53: =+B52+1 -> 8 | C53: 1 | D53: 1BR | E53: 625 | F53: =+F50+1 -> 4 | G53: =+EOMONTH($F$2,F53) -> 45961 | H53: 1417.5 | I53: =+IFERROR(IF(OR(C53=1,C53=2),INDEX($N$46:$N$51,MATCH(D53,$L$46:$L$51,0)),H53),H53) -> 2400 | J53: =+I53*12 -> 28800 | K53: =+I53/H53-1 -> 0.69312169 | L53: Broker's PF Rent Roll | N53: =181800*12 -> 2181600
A54: 20 | B54: =+B53+1 -> 9 | C54: 1 | D54: 1BR | E54: 625 | F54: =+F51+1 -> 4 | G54: =+EOMONTH($F$2,F54) -> 45961 | H54: 1650 | I54: =+IFERROR(IF(OR(C54=1,C54=2),INDEX($N$46:$N$51,MATCH(D54,$L$46:$L$51,0)),H54),H54) -> 2400 | J54: =+I54*12 -> 28800 | K54: =+I54/H54-1 -> 0.45454545 | L54: Change in Rent Roll | N54: =+N52/N53-1 -> 0.04290429
A55: 21 | B55: =+B54+1 -> 10 | C55: 1 | D55: 1BR | E55: 625 | F55: =+F52+1 -> 5 | G55: =+EOMONTH($F$2,F55) -> 45991 | H55: 1391.18 | I55: =+IFERROR(IF(OR(C55=1,C55=2),INDEX($N$46:$N$51,MATCH(D55,$L$46:$L$51,0)),H55),H55) -> 2400 | J55: =+I55*12 -> 28800 | K55: =+I55/H55-1 -> 0.72515419
A56: 22 | B56: =+B55+1 -> 11 | C56: 1 | D56: 1BR | E56: 625 | F56: =+F53+1 -> 5 | G56: =+EOMONTH($F$2,F56) -> 45991 | H56: 1391.25 | I56: =+IFERROR(IF(OR(C56=1,C56=2),INDEX($N$46:$N$51,MATCH(D56,$L$46:$L$51,0)),H56),H56) -> 2400 | J56: =+I56*12 -> 28800 | K56: =+I56/H56-1 -> 0.72506739
A57: 23 | B57: =+B56+1 -> 12 | C57: 1 | D57: 1BR | E57: 625 | F57: =+F54+1 -> 5 | G57: =+EOMONTH($F$2,F57) -> 45991 | H57: 1428 | I57: =+IFERROR(IF(OR(C57=1,C57=2),INDEX($N$46:$N$51,MATCH(D57,$L$46:$L$51,0)),H57),H57) -> 2400 | J57: =+I57*12 -> 28800 | K57: =+I57/H57-1 -> 0.68067227
A58: 24 | B58: =+B57+1 -> 13 | C58: 1 | D58: 1BR | E58: 625 | F58: =+F55+1 -> 6 | G58: =+EOMONTH($F$2,F58) -> 46022 | H58: 1391.25 | I58: =+IFERROR(IF(OR(C58=1,C58=2),INDEX($N$46:$N$51,MATCH(D58,$L$46:$L$51,0)),H58),H58) -> 2400 | J58: =+I58*12 -> 28800 | K58: =+I58/H58-1 -> 0.72506739
A59: 25 | B59: =+B58+1 -> 14 | C59: 1 | D59: 1BR | E59: 625 | F59: =+F56+1 -> 6 | G59: =+EOMONTH($F$2,F59) -> 46022 | H59: 1776.5 | I59: =+IFERROR(IF(OR(C59=1,C59=2),INDEX($N$46:$N$51,MATCH(D59,$L$46:$L$51,0)),H59),H59) -> 2400 | J59: =+I59*12 -> 28800 | K59: =+I59/H59-1 -> 0.35097101
A60: 26 | B60: =+B59+1 -> 15 | C60: 1 | D60: 1BR | E60: 625 | F60: =+F57+1 -> 6 | G60: =+EOMONTH($F$2,F60) -> 46022 | H60: 1365 | I60: =+IFERROR(IF(OR(C60=1,C60=2),INDEX($N$46:$N$51,MATCH(D60,$L$46:$L$51,0)),H60),H60) -> 2400 | J60: =+I60*12 -> 28800 | K60: =+I60/H60-1 -> 0.75824176
A61: 27 | B61: =+B60+1 -> 16 | C61: 1 | D61: 1BR | E61: 625 | F61: =+F58+1 -> 7 | G61: =+EOMONTH($F$2,F61) -> 46053 | H61: 1548.75 | I61: =+IFERROR(IF(OR(C61=1,C61=2),INDEX($N$46:$N$51,MATCH(D61,$L$46:$L$51,0)),H61),H61) -> 2400 | J61: =+I61*12 -> 28800 | K61: =+I61/H61-1 -> 0.5496368
A62: 28 | B62: =+B61+1 -> 17 | C62: 1 | D62: 1BR | E62: 625 | F62: =+F59+1 -> 7 | G62: =+EOMONTH($F$2,F62) -> 46053 | H62: 1417.5 | I62: =+IFERROR(IF(OR(C62=1,C62=2),INDEX($N$46:$N$51,MATCH(D62,$L$46:$L$51,0)),H62),H62) -> 2400 | J62: =+I62*12 -> 28800 | K62: =+I62/H62-1 -> 0.69312169
A63: 29 | B63: =+B62+1 -> 18 | C63: 1 | D63: 1BR | E63: 625 | F63: =+F60+1 -> 7 | G63: =+EOMONTH($F$2,F63) -> 46053 | H63: 1494.01 | I63: =+IFERROR(IF(OR(C63=1,C63=2),INDEX($N$46:$N$51,MATCH(D63,$L$46:$L$51,0)),H63),H63) -> 2400 | J63: =+I63*12 -> 28800 | K63: =+I63/H63-1 -> 0.60641495
A64: 30 | B64: =+B63+1 -> 19 | C64: 1 | D64: 1BR | E64: 625 | F64: =+F61+1 -> 8 | G64: =+EOMONTH($F$2,F64) -> 46081 | H64: 1548.75 | I64: =+IFERROR(IF(OR(C64=1,C64=2),INDEX($N$46:$N$51,MATCH(D64,$L$46:$L$51,0)),H64),H64) -> 2400 | J64: =+I64*12 -> 28800 | K64: =+I64/H64-1 -> 0.5496368
A65: 31 | B65: =+B64+1 -> 20 | C65: 1 | D65: 1BR | E65: 625 | F65: =+F62+1 -> 8 | G65: =+EOMONTH($F$2,F65) -> 46081 | H65: 1344 | I65: =+IFERROR(IF(OR(C65=1,C65=2),INDEX($N$46:$N$51,MATCH(D65,$L$46:$L$51,0)),H65),H65) -> 2400 | J65: =+I65*12 -> 28800 | K65: =+I65/H65-1 -> 0.78571429
A66: 32 | B66: =+B65+1 -> 21 | C66: 1 | D66: 1BR | E66: 625 | F66: =+F63+1 -> 8 | G66: =+EOMONTH($F$2,F66) -> 46081 | H66: 1700 | I66: =+IFERROR(IF(OR(C66=1,C66=2),INDEX($N$46:$N$51,MATCH(D66,$L$46:$L$51,0)),H66),H66) -> 2400 | J66: =+I66*12 -> 28800 | K66: =+I66/H66-1 -> 0.41176471
... A83: 49 | B83: =+B82+1 -> 38 | C83: 1 | D83: 1BR | E83: 625 | F83: =+F80+1 -> 14 | G83: =+EOMONTH($F$2,F83) -> 46265 | H83: 1700 | I83: =+IFERROR(IF(OR(C83=1,C83=2),INDEX($N$46:$N$51,MATCH(D83,$L$46:$L$51,0)),H83),H83) -> 2400 | J83: =+I83*12 -> 28800 | K83: =+I83/H83-1 -> 0.41176471
A84: B | B84: =+B83+1 -> 39 | C84: 1 | D84: 2BR | E84: 825 | F84: =+F81+1 -> 14 | G84: =+EOMONTH($F$2,F84) -> 46265 | H84: 1391.25 | I84: =+IFERROR(IF(OR(C84=1,C84=2),INDEX($N$46:$N$51,MATCH(D84,$L$46:$L$51,0)),H84),H84) -> 2800 | J84: =+I84*12 -> 33600 | K84: =+I84/H84-1 -> 1.0125786
A85: 1 | B85: =+B84+1 -> 40 | C85: 1 | D85: 2BR | E85: 825 | F85: =+F82+1 -> 15 | G85: =+EOMONTH($F$2,F85) -> 46295 | H85: 2500 | I85: =+IFERROR(IF(OR(C85=1,C85=2),INDEX($N$46:$N$51,MATCH(D85,$L$46:$L$51,0)),H85),H85) -> 2800 | J85: =+I85*12 -> 33600 | K85: =+I85/H85-1 -> 0.12
A86: 2 | B86: =+B85+1 -> 41 | C86: 1 | D86: 2BR | E86: 825 | F86: =+F83+1 -> 15 | G86: =+EOMONTH($F$2,F86) -> 46295 | H86: 2194.5 | I86: =+IFERROR(IF(OR(C86=1,C86=2),INDEX($N$46:$N$51,MATCH(D86,$L$46:$L$51,0)),H86),H86) -> 2800 | J86: =+I86*12 -> 33600 | K86: =+I86/H86-1 -> 0.27591707
A87: 3 | B87: =+B86+1 -> 42 | C87: 1 | D87: 1BR | E87: 625 | F87: =+F84+1 -> 15 | G87: =+EOMONTH($F$2,F87) -> 46295 | H87: 1724.25 | I87: =+IFERROR(IF(OR(C87=1,C87=2),INDEX($N$46:$N$51,MATCH(D87,$L$46:$L$51,0)),H87),H87) -> 2400 | J87: =+I87*12 -> 28800 | K87: =+I87/H87-1 -> 0.39190953
A88: 4 | B88: =+B87+1 -> 43 | C88: 1 | D88: 1BR | E88: 625 | F88: =+F85+1 -> 16 | G88: =+EOMONTH($F$2,F88) -> 46326 | H88: 1755.6 | I88: =+IFERROR(IF(OR(C88=1,C88=2),INDEX($N$46:$N$51,MATCH(D88,$L$46:$L$51,0)),H88),H88) -> 2400 | J88: =+I88*12 -> 28800 | K88: =+I88/H88-1 -> 0.367054
A89: 5 | B89: =+B88+1 -> 44 | C89: 1 | D89: 1BR | E89: 625 | F89: =+F86+1 -> 16 | G89: =+EOMONTH($F$2,F89) -> 46326 | H89: 1417.5 | I89: =+IFERROR(IF(OR(C89=1,C89=2),INDEX($N$46:$N$51,MATCH(D89,$L$46:$L$51,0)),H89),H89) -> 2400 | J89: =+I89*12 -> 28800 | K89: =+I89/H89-1 -> 0.69312169
A90: 6 | B90: =+B89+1 -> 45 | C90: 1 | D90: 1BR | E90: 625 | F90: =+F87+1 -> 16 | G90: =+EOMONTH($F$2,F90) -> 46326 | H90: 1601.25 | I90: =+IFERROR(IF(OR(C90=1,C90=2),INDEX($N$46:$N$51,MATCH(D90,$L$46:$L$51,0)),H90),H90) -> 2400 | J90: =+I90*12 -> 28800 | K90: =+I90/H90-1 -> 0.49882904
A91: 7 | B91: =+B90+1 -> 46 | C91: 1 | D91: 1BR | E91: 625 | F91: =+F88+1 -> 17 | G91: =+EOMONTH($F$2,F91) -> 46356 | H91: 1732.5 | I91: =+IFERROR(IF(OR(C91=1,C91=2),INDEX($N$46:$N$51,MATCH(D91,$L$46:$L$51,0)),H91),H91) -> 2400 | J91: =+I91*12 -> 28800 | K91: =+I91/H91-1 -> 0.38528139
A92: 8 | B92: =+B91+1 -> 47 | C92: 1 | D92: 1BR | E92: 625 | F92: =+F89+1 -> 17 | G92: =+EOMONTH($F$2,F92) -> 46356 | H92: 1443.75 | I92: =+IFERROR(IF(OR(C92=1,C92=2),INDEX($N$46:$N$51,MATCH(D92,$L$46:$L$51,0)),H92),H92) -> 2400 | J92: =+I92*12 -> 28800 | K92: =+I92/H92-1 -> 0.66233766
A93: 20 | B93: =+B92+1 -> 48 | C93: 1 | D93: 1BR | E93: 625 | F93: =+F90+1 -> 17 | G93: =+EOMONTH($F$2,F93) -> 46356 | H93: 1417.5 | I93: =+IFERROR(IF(OR(C93=1,C93=2),INDEX($N$46:$N$51,MATCH(D93,$L$46:$L$51,0)),H93),H93) -> 2400 | J93: =+I93*12 -> 28800 | K93: =+I93/H93-1 -> 0.69312169
A94: 21 | B94: =+B93+1 -> 49 | C94: 1 | D94: 1BR | E94: 625 | F94: =+F91+1 -> 18 | G94: =+EOMONTH($F$2,F94) -> 46387 | H94: 1700 | I94: =+IFERROR(IF(OR(C94=1,C94=2),INDEX($N$46:$N$51,MATCH(D94,$L$46:$L$51,0)),H94),H94) -> 2400 | J94: =+I94*12 -> 28800 | K94: =+I94/H94-1 -> 0.41176471
A95: 22 | B95: =+B94+1 -> 50 | C95: 1 | D95: 1BR | E95: 625 | F95: =+F92+1 -> 18 | G95: =+EOMONTH($F$2,F95) -> 46387 | H95: 1819.13 | I95: =+IFERROR(IF(OR(C95=1,C95=2),INDEX($N$46:$N$51,MATCH(D95,$L$46:$L$51,0)),H95),H95) -> 2400 | J95: =+I95*12 -> 28800 | K95: =+I95/H95-1 -> 0.31931198
A96: 23 | B96: =+B95+1 -> 51 | C96: 1 | D96: 1BR | E96: 625 | F96: =+F93+1 -> 18 | G96: =+EOMONTH($F$2,F96) -> 46387 | H96: 1481.9 | I96: =+IFERROR(IF(OR(C96=1,C96=2),INDEX($N$46:$N$51,MATCH(D96,$L$46:$L$51,0)),H96),H96) -> 2400 | J96: =+I96*12 -> 28800 | K96: =+I96/H96-1 -> 0.61954248
... A122: 49 | B122: =+B121+1 -> 77 | C122: 1 | D122: 1BR | E122: 625 | F122: =+F119+1 -> 27 | G122: =+EOMONTH($F$2,F122) -> 46660 | H122: 1300 | I122: =+IFERROR(IF(OR(C122=1,C122=2),INDEX($N$46:$N$51,MATCH(D122,$L$46:$L$51,0)),H122),H122) -> 2400 | J122: =+I122*12 -> 28800 | K122: =+I122/H122-1 -> 0.84615385
A123: B | B123: =+B122+1 -> 78 | C123: 1 | D123: 2BR | E123: 825 | F123: =+F120+1 -> 27 | G123: =+EOMONTH($F$2,F123) -> 46660 | H123: 1975.05 | I123: =+IFERROR(IF(OR(C123=1,C123=2),INDEX($N$46:$N$51,MATCH(D123,$L$46:$L$51,0)),H123),H123) -> 2800 | J123: =+I123*12 -> 33600 | K123: =+I123/H123-1 -> 0.41768563
B124: Total Rental Income | D124: =COUNTA(B46:B123) -> 78 | E124: =SUM(E46:E123)/D124 -> 640.38462 | H124: =SUM(H46:H123) -> 122516.64 | I124: =SUM(I46:I123) -> 189600 | J124: =SUM(J46:J123) -> 2275200
B126: Amenity Income | D126: Start | E126: Utilization x | F126: Units = | G126: Usage | H126: Monthly Fee | I126: Monthly | J126: Annual
B127: Parking | D127: 1 | E127: 0.9 | F127: 24 | G127: =ROUND(F127*E127,0) -> 22 | H127: 75 | I127: =+H127*G127 -> 1650 | J127: =+I127*12 -> 19800
B128: Storage | D128: 6 | E128: 0.75 | F128: 50 | G128: =ROUND(F128*E128,0) -> 38 | H128: 30 | I128: =+H128*G128 -> 1140 | J128: =+I128*12 -> 13680
B129: Laundry | D129: 1 | E129: 1 | F129: =+$D$124 -> 78 | G129: =ROUND(F129*E129,0) -> 78 | H129: 11 | I129: =+H129*G129 -> 858 | J129: =+I129*12 -> 10296
B130: Amenity | D130: 1 | E130: 0.9 | F130: =+$D$124 -> 78 | G130: =ROUND(F130*E130,0) -> 70 | H130: 100 | I130: =+H130*G130 -> 7000 | J130: =+I130*12 -> 84000
B131: Total Amenity Income | I131: =+SUM(I127:I130) -> 10648 | J131: =+SUM(J127:J130) -> 127776
B133: Retail | I133: =+I126 -> Monthly | J133: =+J126 -> Annual
B134: Effective Gross Retail Income | I134: =+J134/12 -> 0 | J134: =+'Retail Assumptions'!J49 -> 0
B136: Rental Inflation | E136: 0.025 | G136: Amenity Inflation | I136: 0.02
B137: Expense Inflation | E137: 0.02
B139: Leasing Assumptions | I139: Initial Lease-up | N139: Ongoing Lease-up
B140: Rehab Time | G140: 2 | I140: Free Month's Rent | L140: 0 | N140: Free Month's Rent | P140: 0
B141: Lease-up Time | G141: 1 | I141: Broker Fee | L141: 1 | N141: Broker Fee | P141: 1
B142: Months of Lease-Up | G142: 5 | I142: Assumed Lease Term | L142: =12+L140 -> 12 | N142: Assumed Lease Term | P142: =12+P140 -> 12
B143: Units Leased per Month | G143: =+ROUND(D124/G142,0) -> 16 | I143: Initial Lease-up Cost | L143: =+SUM(L140:L141)/L142 -> 0.083333333 | N143: Annual Turnover | P143: 0.2
B144: Re-Stabilization Occurs | G144: =_xlfn.MAXIFS(F46:F123,C46:C123,1)+G141+G140 -> 30 | I144: ="Net Effective Rent on "&TEXT(L140+12,"#,##0.0")&" Month Lease" -> Net Effective Rent on 12.0 Month Lease | L144: =(I124/D124)*12/(12+L140) -> 2430.7692 | N144: Ongoing Lease-up Cost | P144: =+SUM(P140:P141)/P142*P143 -> 0.016666667
B145: Bad Debt | G145: 0
B146: Vacancy | G146: 0.05
B148: Operating Expenses | G148: Factor | H148: Statistic | I148: Monthly | J148: Annual | K148: Broker
B149: Property Taxes | G149: 3815.7179 | H149: =+$D$124 -> 78 | I149: =+J149/12 -> 24802.167 | J149: =+G149*H149 -> 297626 | K149: 280388
B150: Insurance | G150: 1200 | H150: =+$D$124 -> 78 | I150: =+J150/12 -> 7800 | J150: =+H150*G150 -> 93600 | K150: 58500
...

Sheet NOI Walk
S1: on Ask Price
B2: =+Assumptions!B45 -> Units | C2: =+Assumptions!D124 -> 78 | H2: Step-Up in Rent | K2: =+C4-C3 -> 860.04308 | M2: =Assumptions!I143 -> Initial Lease-up Cost | O2: =+Assumptions!L144 -> 2430.7692 | Q2: Year 1 NOI | R2: =SUMIFS($H$67:$EI$67,H16:EI16,"<=12") -> 934551.93 | S2: =+R2/Assumptions!$O$3 -> 0.062303462
B3: Current Rent / Unit | C3: =+Assumptions!H124/Assumptions!D124 -> 1570.7262 | H3: =Assumptions!B140 -> Rehab Time | K3: =Assumptions!G140 -> 2 | M3: =+Assumptions!N144 -> Ongoing Lease-up Cost | O3: =+Assumptions!P144 -> 0.016666667 | Q3: Seller's NOI | R3: 865253.4 | S3: =+R3/Assumptions!$O$3 -> 0.05768356
B4: Pro Forma Rent / Unit | C4: =+Assumptions!I124/Assumptions!D124 -> 2430.7692 | H4: =Assumptions!B141 -> Lease-up Time | K4: =Assumptions!G141 -> 1 | M4: =+Assumptions!B136 -> Rental Inflation | O4: =+Assumptions!E136 -> 0.025 | Q4: Change in NOI | R4: =+R2/R3-1 -> 0.080090448
A5: =+Assumptions!E127 -> 0.9 | B5: =+Assumptions!B127 -> Parking | C5: =+Assumptions!H127 -> 75 | H5: =Assumptions!B144 -> Re-Stabilization Occurs | K5: =Assumptions!G144 -> 30 | M5: =+Assumptions!G136 -> Amenity Inflation | O5: =+Assumptions!I136 -> 0.02 | Q5: Stabilized NOI | R5: {=+INDEX('NOI Walk'!H67:EI67,,MATCH(Assumptions!G144,'NOI Walk'!H16:EI16,0))*12} -> 1884115.2 | S5: =+R5/Assumptions!$O$3 -> 0.12560768
A6: =+Assumptions!E128 -> 0.75 | B6: =+Assumptions!B128 -> Storage | C6: =+Assumptions!H128 -> 30 | H6: =Assumptions!B145 -> Bad Debt | K6: =Assumptions!G145 -> 0 | M6: =+Assumptions!B137 -> Expense Inflation | O6: =+Assumptions!E137 -> 0.02
A7: =+Assumptions!E129 -> 1 | B7: =+Assumptions!B129 -> Laundry | C7: =+Assumptions!H129 -> 11 | H7: =Assumptions!B146 -> Vacancy | K7: =Assumptions!G146 -> 0.05
A8: =+Assumptions!E130 -> 0.9 | B8: Parking | C8: =+Assumptions!H130 -> 100
B10: Rent Inflation Factor | H10: =(1+($O$4/12))^H16 -> 1.0020833 | I10: =(1+($O$4/12))^I16 -> 1.004171 | J10: =(1+($O$4/12))^J16 -> 1.006263 | K10: =(1+($O$4/12))^K16 -> 1.0083594 | L10: =(1+($O$4/12))^L16 -> 1.0104602 | M10: =(1+($O$4/12))^M16 -> 1.0125653 | N10: =(1+($O$4/12))^N16 -> 1.0146748 | O10: =(1+($O$4/12))^O16 -> 1.0167887 | ... EI10: =(1+($O$4/12))^EI16 -> 1.3161541
B11: Amenity Inflation Factor | H11: =(1+($O$5/12))^H16 -> 1.0016667 | I11: =(1+($O$5/12))^I16 -> 1.0033361 | J11: =(1+($O$5/12))^J16 -> 1.0050083 | K11: =(1+($O$5/12))^K16 -> 1.0066834 | L11: =(1+($O$5/12))^L16 -> 1.0083612 | M11: =(1+($O$5/12))^M16 -> 1.0100418 | N11: =(1+($O$5/12))^N16 -> 1.0117252 | O11: =(1+($O$5/12))^O16 -> 1.0134114 | ... EI11: =(1+($O$5/12))^EI16 -> 1.2458486
B12: Expenses Inflation Factor | H12: =(1+($O$6/12))^H16 -> 1.0016667 | I12: =(1+($O$6/12))^I16 -> 1.0033361 | J12: =(1+($O$6/12))^J16 -> 1.0050083 | K12: =(1+($O$6/12))^K16 -> 1.0066834 | L12: =(1+($O$6/12))^L16 -> 1.0083612 | M12: =(1+($O$6/12))^M16 -> 1.0100418 | N12: =(1+($O$6/12))^N16 -> 1.0117252 | O12: =(1+($O$6/12))^O16 -> 1.0134114 | ... EI12: =(1+($O$6/12))^EI16 -> 1.2458486
B13: Timeline | H13: =IF(H16<$K$5,"Lease-up",IF(H16=$K$5,"Stabilization","-")) -> Lease-up | I13: =IF(I16<$K$5,"Lease-up",IF(I16=$K$5,"Stabilization","-")) -> Lease-up | J13: =IF(J16<$K$5,"Lease-up",IF(J16=$K$5,"Stabilization","-")) -> Lease-up | K13: =IF(K16<$K$5,"Lease-up",IF(K16=$K$5,"Stabilization","-")) -> Lease-up | L13: =IF(L16<$K$5,"Lease-up",IF(L16=$K$5,"Stabilization","-")) -> Lease-up | M13: =IF(M16<$K$5,"Lease-up",IF(M16=$K$5,"Stabilization","-")) -> Lease-up | N13: =IF(N16<$K$5,"Lease-up",IF(N16=$K$5,"Stabilization","-")) -> Lease-up | O13: =IF(O16<$K$5,"Lease-up",IF(O16=$K$5,"Stabilization","-")) -> Lease-up | ... EI13: =IF(EI16<$K$5,"Lease-up",IF(EI16=$K$5,"Stabilization","-")) -> -
H14: =YEAR(Model!H2) -> 2025 | I14: =YEAR(Model!I2) -> 2025 | J14: =YEAR(Model!J2) -> 2025 | K14: =YEAR(Model!K2) -> 2025 | L14: =YEAR(Model!L2) -> 2025 | M14: =YEAR(Model!M2) -> 2025 | N14: =YEAR(Model!N2) -> 2026 | O14: =YEAR(Model!O2) -> 2026 | ... DV14: =YEAR(Model!DV2) -> 2035 | DW14: =YEAR(Model!#REF!) -> #REF! | DX14: =YEAR(Model!EJ2) -> 1900 | DY14: =YEAR(Model!EK2) -> 1900 | DZ14: =YEAR(Model!EL2) -> 1900 | EA14: =YEAR(Model!EM2) -> #VALUE! | EB14: =YEAR(Model!EN2) -> 1900 | EC14: =YEAR(Model!EO2) -> 1900 | ED14: =YEAR(Model!EP2) -> 1900 | EE14: =YEAR(Model!EQ2) -> 1900 | ... EI14: =YEAR(Model!EU2) -> 1900
H15: =+ROUNDUP(H16/12,0) -> 1 | I15: =+ROUNDUP(I16/12,0) -> 1 | J15: =+ROUNDUP(J16/12,0) -> 1 | K15: =+ROUNDUP(K16/12,0) -> 1 | L15: =+ROUNDUP(L16/12,0) -> 1 | M15: =+ROUNDUP(M16/12,0) -> 1 | N15: =+ROUNDUP(N16/12,0) -> 1 | O15: =+ROUNDUP(O16/12,0) -> 1 | ... EI15: =+ROUNDUP(EI16/12,0) -> 11
H16: 1 | I16: =+H16+1 -> 2 | J16: =+I16+1 -> 3 | K16: =+J16+1 -> 4 | L16: =+K16+1 -> 5 | M16: =+L16+1 -> 6 | N16: =+M16+1 -> 7 | O16: =+N16+1 -> 8 | P16: =+O16+1 -> 9 | ... EI16: =+EH16+1 -> 132
B17: Beg. Units Leased | H17: =COUNTIF(Assumptions!H46:H123,">0") -> 78 | I17: =+H20 -> 78 | J17: =+I20 -> 75 | K17: =+J20 -> 72 | L17: =+K20 -> 69 | M17: =+L20 -> 69 | N17: =+M20 -> 69 | O17: =+N20 -> 69 | P17: =+O20 -> 69 | ... EI17: =+EH20 -> 78
B18: Units Vacated | H18: =-COUNTIFS(Assumptions!$C$46:$C$123,1,Assumptions!$F$46:$F$123,'NOI Walk'!H16,Assumptions!$H$46:$H$123,">0")-COUNTIFS(Assumptions!$C$46:$C$123,2,Assumptions!$F$46:$F$123,H16) -> 0 | I18: =-COUNTIFS(Assumptions!$C$46:$C$123,1,Assumptions!$F$46:$F$123,'NOI Walk'!I16,Assumptions!$H$46:$H$123,">0")-COUNTIFS(Assumptions!$C$46:$C$123,2,Assumptions!$F$46:$F$123,I16) -> -3 | J18: =-COUNTIFS(Assumptions!$C$46:$C$123,1,Assumptions!$F$46:$F$123,'NOI Walk'!J16,Assumptions!$H$46:$H$123,">0")-COUNTIFS(Assumptions!$C$46:$C$123,2,Assumptions!$F$46:$F$123,J16) -> -3 | K18: =-COUNTIFS(Assumptions!$C$46:$C$123,1,Assumptions!$F$46:$F$123,'NOI Walk'!K16,Assumptions!$H$46:$H$123,">0")-COUNTIFS(Assumptions!$C$46:$C$123,2,Assumptions!$F$46:$F$123,K16) -> -3 | L18: =-COUNTIFS(Assumptions!$C$46:$C$123,1,Assumptions!$F$46:$F$123,'NOI Walk'!L16,Assumptions!$H$46:$H$123,">0")-COUNTIFS(Assumptions!$C$46:$C$123,2,Assumptions!$F$46:$F$123,L16) -> -3 | M18: =-COUNTIFS(Assumptions!$C$46:$C$123,1,Assumptions!$F$46:$F$123,'NOI Walk'!M16,Assumptions!$H$46:$H$123,">0")-COUNTIFS(Assumptions!$C$46:$C$123,2,Assumptions!$F$46:$F$123,M16) -> -3 | N18: =-COUNTIFS(Assumptions!$C$46:$C$123,1,Assumptions!$F$46:$F$123,'NOI Walk'!N16,Assumptions!$H$46:$H$123,">0")-COUNTIFS(Assumptions!$C$46:$C$123,2,Assumptions!$F$46:$F$123,N16) -> -3 | O18: =-COUNTIFS(Assumptions!$C$46:$C$123,1,Assumptions!$F$46:$F$123,'NOI Walk'!O16,Assumptions!$H$46:$H$123,">0")-COUNTIFS(Assumptions!$C$46:$C$123,2,Assumptions!$F$46:$F$123,O16) -> -3 | ... EI18: =-COUNTIFS(Assumptions!$C$46:$C$123,1,Assumptions!$F$46:$F$123,'NOI Walk'!EI16,Assumptions!$H$46:$H$123,">0")-COUNTIFS(Assumptions!$C$46:$C$123,2,Assumptions!$F$46:$F$123,EI16) -> 0
B19: New Units Leased | H19: =COUNTIFS(Assumptions!$C$46:$C$123,1,Assumptions!$F$46:$F$123,'NOI Walk'!H16-SUM('NOI Walk'!$K$3:$K$4))+COUNTIFS(Assumptions!$C$46:$C$123,2,Assumptions!$F$46:$F$123,'NOI Walk'!H16) -> 0 | I19: =COUNTIFS(Assumptions!$C$46:$C$123,1,Assumptions!$F$46:$F$123,'NOI Walk'!I16-SUM('NOI Walk'!$K$3:$K$4))+COUNTIFS(Assumptions!$C$46:$C$123,2,Assumptions!$F$46:$F$123,'NOI Walk'!I16) -> 0 | J19: =COUNTIFS(Assumptions!$C$46:$C$123,1,Assumptions!$F$46:$F$123,'NOI Walk'!J16-SUM('NOI Walk'!$K$3:$K$4))+COUNTIFS(Assumptions!$C$46:$C$123,2,Assumptions!$F$46:$F$123,'NOI Walk'!J16) -> 0 | K19: =COUNTIFS(Assumptions!$C$46:$C$123,1,Assumptions!$F$46:$F$123,'NOI Walk'!K16-SUM('NOI Walk'!$K$3:$K$4))+COUNTIFS(Assumptions!$C$46:$C$123,2,Assumptions!$F$46:$F$123,'NOI Walk'!K16) -> 0 | L19: =COUNTIFS(Assumptions!$C$46:$C$123,1,Assumptions!$F$46:$F$123,'NOI Walk'!L16-SUM('NOI Walk'!$K$3:$K$4))+COUNTIFS(Assumptions!$C$46:$C$123,2,Assumptions!$F$46:$F$123,'NOI Walk'!L16) -> 3 | M19: =COUNTIFS(Assumptions!$C$46:$C$123,1,Assumptions!$F$46:$F$123,'NOI Walk'!M16-SUM('NOI Walk'!$K$3:$K$4))+COUNTIFS(Assumptions!$C$46:$C$123,2,Assumptions!$F$46:$F$123,'NOI Walk'!M16) -> 3 | N19: =COUNTIFS(Assumptions!$C$46:$C$123,1,Assumptions!$F$46:$F$123,'NOI Walk'!N16-SUM('NOI Walk'!$K$3:$K$4))+COUNTIFS(Assumptions!$C$46:$C$123,2,Assumptions!$F$46:$F$123,'NOI Walk'!N16) -> 3 | O19: =COUNTIFS(Assumptions!$C$46:$C$123,1,Assumptions!$F$46:$F$123,'NOI Walk'!O16-SUM('NOI Walk'!$K$3:$K$4))+COUNTIFS(Assumptions!$C$46:$C$123,2,Assumptions!$F$46:$F$123,'NOI Walk'!O16) -> 3 | ... EI19: =COUNTIFS(Assumptions!$C$46:$C$123,1,Assumptions!$F$46:$F$123,'NOI Walk'!EI16-SUM('NOI Walk'!$K$3:$K$4))+COUNTIFS(Assumptions!$C$46:$C$123,2,Assumptions!$F$46:$F$123,'NOI Walk'!EI16) -> 0
B20: End. Units Leased | H20: =SUM(H17:H19) -> 78 | I20: =SUM(I17:I19) -> 75 | J20: =SUM(J17:J19) -> 72 | K20: =SUM(K17:K19) -> 69 | L20: =SUM(L17:L19) -> 69 | M20: =SUM(M17:M19) -> 69 | N20: =SUM(N17:N19) -> 69 | O20: =SUM(O17:O19) -> 69 | ... EI20: =SUM(EI17:EI19) -> 78
B22: Gross Potential Rent | H22: =+$C$4*$C$2*H10 -> 189995 | I22: =+$C$4*$C$2*I10 -> 190390.82 | J22: =+$C$4*$C$2*J10 -> 190787.47 | K22: =+$C$4*$C$2*K10 -> 191184.94 | L22: =+$C$4*$C$2*L10 -> 191583.25 | M22: =+$C$4*$C$2*M10 -> 191982.38 | N22: =+$C$4*$C$2*N10 -> 192382.34 | O22: =+$C$4*$C$2*O10 -> 192783.14 | ... EI22: =+$C$4*$C$2*EI10 -> 249542.82
B23: Loss-to-Lease | H23: =($C$3-$C$4)*($C$2-SUM($H$19:H19))*H10 -> -67223.117 | I23: =($C$3-$C$4)*($C$2-SUM($H$19:I19))*I10 -> -67363.165 | J23: =($C$3-$C$4)*($C$2-SUM($H$19:J19))*J10 -> -67503.505 | K23: =($C$3-$C$4)*($C$2-SUM($H$19:K19))*K10 -> -67644.137 | L23: =($C$3-$C$4)*($C$2-SUM($H$19:L19))*L10 -> -65177.945 | M23: =($C$3-$C$4)*($C$2-SUM($H$19:M19))*M10 -> -62701.183 | N23: =($C$3-$C$4)*($C$2-SUM($H$19:N19))*N10 -> -60213.818 | O23: =($C$3-$C$4)*($C$2-SUM($H$19:O19))*O10 -> -57715.818 | ... EI23: =($C$3-$C$4)*($C$2-SUM($H$19:EI19))*EI10 -> 0
B24: In-Place Rental Income | H24: =+$C$3*($C$2+SUM($H$18:H18))*H10 -> 122771.88 | I24: =+$C$3*($C$2+SUM($H$18:I18))*I10 -> 118295.82 | J24: =+$C$3*($C$2+SUM($H$18:J18))*J10 -> 113800.58 | K24: =+$C$3*($C$2+SUM($H$18:K18))*K10 -> 109286.1 | L24: =+$C$3*($C$2+SUM($H$18:L18))*L10 -> 104752.31 | M24: =+$C$3*($C$2+SUM($H$18:M18))*M10 -> 100199.15 | N24: =+$C$3*($C$2+SUM($H$18:N18))*N10 -> 95626.574 | O24: =+$C$3*($C$2+SUM($H$18:O18))*O10 -> 91034.507 | ... EI24: =+$C$3*($C$2+SUM($H$18:EI18))*EI10 -> 0
B25: Pro Forma Rental Income | H25: =+SUM($H$19:H19)*$C$4*H10 -> 0 | I25: =+SUM($H$19:I19)*$C$4*I10 -> 0 | J25: =+SUM($H$19:J19)*$C$4*J10 -> 0 | K25: =+SUM($H$19:K19)*$C$4*K10 -> 0 | L25: =+SUM($H$19:L19)*$C$4*L10 -> 7368.5864 | M25: =+SUM($H$19:M19)*$C$4*M10 -> 14767.875 | N25: =+SUM($H$19:N19)*$C$4*N10 -> 22197.962 | O25: =+SUM($H$19:O19)*$C$4*O10 -> 29658.944 | ... EI25: =+SUM($H$19:EI19)*$C$4*EI10 -> 249542.82
B26: Vacancy | H26: =+IF(H16<$K$5,SUM(H24:H25)/(H22+H23)-1,-$K$7)*SUM(H22:H23) -> 2.7260834e-11 | I26: =+IF(I16<$K$5,SUM(I24:I25)/(I22+I23)-1,-$K$7)*SUM(I22:I23) -> -4731.833 | J26: =+IF(J16<$K$5,SUM(J24:J25)/(J22+J23)-1,-$K$7)*SUM(J22:J23) -> -9483.382 | K26: =+IF(K16<$K$5,SUM(K24:K25)/(K22+K23)-1,-$K$7)*SUM(K22:K23) -> -14254.708 | L26: =+IF(L16<$K$5,SUM(L24:L25)/(L22+L23)-1,-$K$7)*SUM(L22:L23) -> -14284.406 | M26: =+IF(M16<$K$5,SUM(M24:M25)/(M22+M23)-1,-$K$7)*SUM(M22:M23) -> -14314.165 | N26: =+IF(N16<$K$5,SUM(N24:N25)/(N22+N23)-1,-$K$7)*SUM(N22:N23) -> -14343.986 | O26: =+IF(O16<$K$5,SUM(O24:O25)/(O22+O23)-1,-$K$7)*SUM(O22:O23) -> -14373.869 | ... EI26: =+IF(EI16<$K$5,SUM(EI24:EI25)/(EI22+EI23)-1,-$K$7)*SUM(EI22:EI23) -> -12477.141
B27: Vacancy | H27: =-H26/(H22+H23) -> -2.220446e-16 | I27: =-I26/(I22+I23) -> 0.038461538 | J27: =-J26/(J22+J23) -> 0.076923077 | K27: =-K26/(K22+K23) -> 0.11538462 | L27: =-L26/(L22+L23) -> 0.1130048 | M27: =-M26/(M22+M23) -> 0.11072117 | N27: =-N26/(N22+N23) -> 0.10852801 | O27: =-O26/(O22+O23) -> 0.10642004 | ... EI27: =-EI26/(EI22+EI23) -> 0.05
B28: =B5&" Income" -> Parking Income | H28: =IF(H$16<Assumptions!$D127,0,$C5*H$20*H$11*$A5) -> 5273.775 | I28: =IF(I$16<Assumptions!$D127,0,$C5*I$20*I$11*$A5) -> 5079.3891 | J28: =IF(J$16<Assumptions!$D127,0,$C5*J$20*J$11*$A5) -> 4884.3405 | K28: =IF(K$16<Assumptions!$D127,0,$C5*K$20*K$11*$A5) -> 4688.6277 | L28: =IF(L$16<Assumptions!$D127,0,$C5*L$20*L$11*$A5) -> 4696.4421 | M28: =IF(M$16<Assumptions!$D127,0,$C5*M$20*M$11*$A5) -> 4704.2695 | N28: =IF(N$16<Assumptions!$D127,0,$C5*N$20*N$11*$A5) -> 4712.1099 | O28: =IF(O$16<Assumptions!$D127,0,$C5*O$20*O$11*$A5) -> 4719.9635 | ... EI28: =IF(EI$16<Assumptions!$D127,0,$C5*EI$20*EI$11*$A5) -> 6559.3927
B29: =B6&" Income" -> Storage Income | H29: =IF(H$16<Assumptions!$D128,0,$C6*H$20*H$11*$A6) -> 0 | I29: =IF(I$16<Assumptions!$D128,0,$C6*I$20*I$11*$A6) -> 0 | J29: =IF(J$16<Assumptions!$D128,0,$C6*J$20*J$11*$A6) -> 0 | K29: =IF(K$16<Assumptions!$D128,0,$C6*K$20*K$11*$A6) -> 0 | L29: =IF(L$16<Assumptions!$D128,0,$C6*L$20*L$11*$A6) -> 0 | M29: =IF(M$16<Assumptions!$D128,0,$C6*M$20*M$11*$A6) -> 1568.0898 | N29: =IF(N$16<Assumptions!$D128,0,$C6*N$20*N$11*$A6) -> 1570.7033 | O29: =IF(O$16<Assumptions!$D128,0,$C6*O$20*O$11*$A6) -> 1573.3212 | ... EI29: =IF(EI$16<Assumptions!$D128,0,$C6*EI$20*EI$11*$A6) -> 2186.4642
B30: =B7&" Income" -> Laundry Income | H30: =IF(H$16<Assumptions!$D129,0,$C7*H$20*H$11*$A7) -> 859.43 | I30: =IF(I$16<Assumptions!$D129,0,$C7*I$20*I$11*$A7) -> 827.75229 | J30: =IF(J$16<Assumptions!$D129,0,$C7*J$20*J$11*$A7) -> 795.9666 | K30: =IF(K$16<Assumptions!$D129,0,$C7*K$20*K$11*$A7) -> 764.07266 | L30: =IF(L$16<Assumptions!$D129,0,$C7*L$20*L$11*$A7) -> 765.34612 | M30: =IF(M$16<Assumptions!$D129,0,$C7*M$20*M$11*$A7) -> 766.6217 | N30: =IF(N$16<Assumptions!$D129,0,$C7*N$20*N$11*$A7) -> 767.8994 | O30: =IF(O$16<Assumptions!$D129,0,$C7*O$20*O$11*$A7) -> 769.17923 | ... EI30: =IF(EI$16<Assumptions!$D129,0,$C7*EI$20*EI$11*$A7) -> 1068.9381
B31: =B8&" Income" -> Parking Income | H31: =IF(H$16<Assumptions!$D130,0,$C8*Assumptions!$F$130*'NOI Walk'!H20/'NOI Walk'!$C$2*H$11*$A8) -> 7031.7 | I31: =IF(I$16<Assumptions!$D130,0,$C8*Assumptions!$F$130*'NOI Walk'!I20/'NOI Walk'!$C$2*I$11*$A8) -> 6772.5188 | J31: =IF(J$16<Assumptions!$D130,0,$C8*Assumptions!$F$130*'NOI Walk'!J20/'NOI Walk'!$C$2*J$11*$A8) -> 6512.454 | K31: =IF(K$16<Assumptions!$D130,0,$C8*Assumptions!$F$130*'NOI Walk'!K20/'NOI Walk'!$C$2*K$11*$A8) -> 6251.5036 | L31: =IF(L$16<Assumptions!$D130,0,$C8*Assumptions!$F$130*'NOI Walk'!L20/'NOI Walk'!$C$2*L$11*$A8) -> 6261.9228 | M31: =IF(M$16<Assumptions!$D130,0,$C8*Assumptions!$F$130*'NOI Walk'!M20/'NOI Walk'!$C$2*M$11*$A8) -> 6272.3593 | N31: =IF(N$16<Assumptions!$D130,0,$C8*Assumptions!$F$130*'NOI Walk'!N20/'NOI Walk'!$C$2*N$11*$A8) -> 6282.8133 | O31: =IF(O$16<Assumptions!$D130,0,$C8*Assumptions!$F$130*'NOI Walk'!O20/'NOI Walk'!$C$2*O$11*$A8) -> 6293.2846 | ... EI31: =IF(EI$16<Assumptions!$D130,0,$C8*Assumptions!$F$130*'NOI Walk'!EI20/'NOI Walk'!$C$2*EI$11*$A8) -> 8745.8569
B32: Turnover Costs | H32: =-IF(H16<$K$5,0,(H24*$O$3)) -> 0 | I32: =-IF(I16<$K$5,0,(I24*$O$3)) -> 0 | J32: =-IF(J16<$K$5,0,(J24*$O$3)) -> 0 | K32: =-IF(K16<$K$5,0,(K24*$O$3)) -> 0 | L32: =-IF(L16<$K$5,0,(L24*$O$3)) -> 0 | M32: =-IF(M16<$K$5,0,(M24*$O$3)) -> 0 | N32: =-IF(N16<$K$5,0,(N24*$O$3)) -> 0 | O32: =-IF(O16<$K$5,0,(O24*$O$3)) -> 0 | ... EI32: =-IF(EI16<$K$5,0,(EI24*$O$3)) -> 0
B33: Bad Debt | H33: =-$K$6*SUM(H22,H26) -> 0 | I33: =-$K$6*SUM(I22,I26) -> 0 | J33: =-$K$6*SUM(J22,J26) -> 0 | K33: =-$K$6*SUM(K22,K26) -> 0 | L33: =-$K$6*SUM(L22,L26) -> 0 | M33: =-$K$6*SUM(M22,M26) -> 0 | N33: =-$K$6*SUM(N22,N26) -> 0 | O33: =-$K$6*SUM(O22,O26) -> 0 | ... EI33: =-$K$6*SUM(EI22,EI26) -> 0
B34: Effective Gross Income | H34: =SUM(H28:H33,H24:H25) -> 135936.79 | I34: =SUM(I28:I33,I24:I25) -> 130975.48 | J34: =SUM(J28:J33,J24:J25) -> 125993.34 | K34: =SUM(K28:K33,K24:K25) -> 120990.3 | L34: =SUM(L28:L33,L24:L25) -> 123844.61 | M34: =SUM(M28:M33,M24:M25) -> 128278.37 | N34: =SUM(N28:N33,N24:N25) -> 131158.06 | O34: =SUM(O28:O33,O24:O25) -> 134049.2 | ... EI34: =SUM(EI28:EI33,EI24:EI25) -> 268103.47
B36: Operating Expenses
B37: =Assumptions!B149 -> Property Taxes | H37: =Assumptions!$I149*H$12 -> 24843.504 | I37: =Assumptions!$I149*I$12 -> 24884.909 | J37: =Assumptions!$I149*J$12 -> 24926.384 | K37: =Assumptions!$I149*K$12 -> 24967.928 | L37: =Assumptions!$I149*L$12 -> 25009.541 | M37: =Assumptions!$I149*M$12 -> 25051.224 | N37: =Assumptions!$I149*N$12 -> 25092.976 | O37: =Assumptions!$I149*O$12 -> 25134.798 | ... EI37: =Assumptions!$I149*EI$12 -> 30899.744
B38: =Assumptions!B150 -> Insurance | H38: =+Assumptions!$I150*H$12 -> 7813 | I38: =+Assumptions!$I150*I$12 -> 7826.0217 | J38: =+Assumptions!$I150*J$12 -> 7839.065 | K38: =+Assumptions!$I150*K$12 -> 7852.1301 | L38: =+Assumptions!$I150*L$12 -> 7865.217 | M38: =+Assumptions!$I150*M$12 -> 7878.3257 | N38: =+Assumptions!$I150*N$12 -> 7891.4563 | O38: =+Assumptions!$I150*O$12 -> 7904.6087 | ... EI38: =+Assumptions!$I150*EI$12 -> 9717.6187
B39: =Assumptions!B151 -> Water / Sewer | H39: =+Assumptions!$G$151/12*'NOI Walk'!H20*'NOI Walk'!H12 -> 3912.3431 | I39: =+Assumptions!$G$151/12*'NOI Walk'!I20*'NOI Walk'!I12 -> 3768.1381 | J39: =+Assumptions!$G$151/12*'NOI Walk'!J20*'NOI Walk'!J12 -> 3623.4416 | K39: =+Assumptions!$G$151/12*'NOI Walk'!K20*'NOI Walk'!K12 -> 3478.2523 | L39: =+Assumptions!$G$151/12*'NOI Walk'!L20*'NOI Walk'!L12 -> 3484.0494 | M39: =+Assumptions!$G$151/12*'NOI Walk'!M20*'NOI Walk'!M12 -> 3489.8561 | N39: =+Assumptions!$G$151/12*'NOI Walk'!N20*'NOI Walk'!N12 -> 3495.6726 | O39: =+Assumptions!$G$151/12*'NOI Walk'!O20*'NOI Walk'!O12 -> 3501.4987 | ... EI39: =+Assumptions!$G$151/12*'NOI Walk'!EI20*'NOI Walk'!EI12 -> 4866.0768
B40: =Assumptions!B152 -> Repairs & Maintenance | H40: =+Assumptions!$G$152/12*'NOI Walk'!H20*'NOI Walk'!H12 -> 3255.4167 | I40: =+Assumptions!$G$152/12*'NOI Walk'!I20*'NOI Walk'!I12 -> 3135.4253 | J40: =+Assumptions!$G$152/12*'NOI Walk'!J20*'NOI Walk'!J12 -> 3015.025 | K40: =+Assumptions!$G$152/12*'NOI Walk'!K20*'NOI Walk'!K12 -> 2894.2146 | L40: =+Assumptions!$G$152/12*'NOI Walk'!L20*'NOI Walk'!L12 -> 2899.0383 | M40: =+Assumptions!$G$152/12*'NOI Walk'!M20*'NOI Walk'!M12 -> 2903.8701 | N40: =+Assumptions!$G$152/12*'NOI Walk'!N20*'NOI Walk'!N12 -> 2908.7098 | O40: =+Assumptions!$G$152/12*'NOI Walk'!O20*'NOI Walk'!O12 -> 2913.5577 | ... EI40: =+Assumptions!$G$152/12*'NOI Walk'!EI20*'NOI Walk'!EI12 -> 4049.0078
B41: =Assumptions!B153 -> Elevator Contract | H41: =+Assumptions!$I153*H$12 -> 0 | I41: =+Assumptions!$I153*I$12 -> 0 | J41: =+Assumptions!$I153*J$12 -> 0 | K41: =+Assumptions!$I153*K$12 -> 0 | L41: =+Assumptions!$I153*L$12 -> 0 | M41: =+Assumptions!$I153*M$12 -> 0 | N41: =+Assumptions!$I153*N$12 -> 0 | O41: =+Assumptions!$I153*O$12 -> 0 | ... EI41: =+Assumptions!$I153*EI$12 -> 0
B42: =Assumptions!B154 -> Trash | H42: =+Assumptions!$I154*H$12 -> 200.33333 | I42: =+Assumptions!$I154*I$12 -> 200.66722 | J42: =+Assumptions!$I154*J$12 -> 201.00167 | K42: =+Assumptions!$I154*K$12 -> 201.33667 | L42: =+Assumptions!$I154*L$12 -> 201.67223 | M42: =+Assumptions!$I154*M$12 -> 202.00835 | N42: =+Assumptions!$I154*N$12 -> 202.34503 | O42: =+Assumptions!$I154*O$12 -> 202.68227 | ... EI42: =+Assumptions!$I154*EI$12 -> 249.16971
B43: =Assumptions!B155 -> Cleaning | H43: =+Assumptions!$I155*H$12 -> 976.625 | I43: =+Assumptions!$I155*I$12 -> 978.25271 | J43: =+Assumptions!$I155*J$12 -> 979.88313 | K43: =+Assumptions!$I155*K$12 -> 981.51627 | L43: =+Assumptions!$I155*L$12 -> 983.15213 | M43: =+Assumptions!$I155*M$12 -> 984.79072 | N43: =+Assumptions!$I155*N$12 -> 986.43203 | O43: =+Assumptions!$I155*O$12 -> 988.07609 | ... EI43: =+Assumptions!$I155*EI$12 -> 1214.7023
B44: =Assumptions!B156 -> Security, Internet | H44: =+Assumptions!$I156*H$12 -> 200.33333 | I44: =+Assumptions!$I156*I$12 -> 200.66722 | J44: =+Assumptions!$I156*J$12 -> 201.00167 | K44: =+Assumptions!$I156*K$12 -> 201.33667 | L44: =+Assumptions!$I156*L$12 -> 201.67223 | M44: =+Assumptions!$I156*M$12 -> 202.00835 | N44: =+Assumptions!$I156*N$12 -> 202.34503 | O44: =+Assumptions!$I156*O$12 -> 202.68227 | ... EI44: =+Assumptions!$I156*EI$12 -> 249.16971
B45: =Assumptions!B157 -> Pest Control | H45: =+Assumptions!$I157*H$12 -> 325.54167 | I45: =+Assumptions!$I157*I$12 -> 326.08424 | J45: =+Assumptions!$I157*J$12 -> 326.62771 | K45: =+Assumptions!$I157*K$12 -> 327.17209 | L45: =+Assumptions!$I157*L$12 -> 327.71738 | M45: =+Assumptions!$I157*M$12 -> 328.26357 | N45: =+Assumptions!$I157*N$12 -> 328.81068 | O45: =+Assumptions!$I157*O$12 -> 329.3587 | ... EI45: =+Assumptions!$I157*EI$12 -> 404.90078
B46: =Assumptions!B158 -> Super (Payroll) | H46: =+Assumptions!$I158*H$12 -> 3255.4167 | I46: =+Assumptions!$I158*I$12 -> 3260.8424 | J46: =+Assumptions!$I158*J$12 -> 3266.2771 | K46: =+Assumptions!$I158*K$12 -> 3271.7209 | L46: =+Assumptions!$I158*L$12 -> 3277.1738 | M46: =+Assumptions!$I158*M$12 -> 3282.6357 | N46: =+Assumptions!$I158*N$12 -> 3288.1068 | O46: =+Assumptions!$I158*O$12 -> 3293.587 | ... EI46: =+Assumptions!$I158*EI$12 -> 4049.0078
B47: =Assumptions!B159 -> Heat (Gas) | H47: =+Assumptions!$I159*H$12 -> 5624.6922 | I47: =+Assumptions!$I159*I$12 -> 5634.0667 | J47: =+Assumptions!$I159*J$12 -> 5643.4568 | K47: =+Assumptions!$I159*K$12 -> 5652.8626 | L47: =+Assumptions!$I159*L$12 -> 5662.284 | M47: =+Assumptions!$I159*M$12 -> 5671.7212 | N47: =+Assumptions!$I159*N$12 -> 5681.174 | O47: =+Assumptions!$I159*O$12 -> 5690.6427 | ... EI47: =+Assumptions!$I159*EI$12 -> 6995.8549
B48: =Assumptions!B160 -> Common Area Electric | H48: =+Assumptions!$I160*H$12 -> 282.47 | I48: =+Assumptions!$I160*I$12 -> 282.94078 | J48: =+Assumptions!$I160*J$12 -> 283.41235 | K48: =+Assumptions!$I160*K$12 -> 283.88471 | L48: =+Assumptions!$I160*L$12 -> 284.35785 | M48: =+Assumptions!$I160*M$12 -> 284.83178 | N48: =+Assumptions!$I160*N$12 -> 285.3065 | O48: =+Assumptions!$I160*O$12 -> 285.78201 | ... EI48: =+Assumptions!$I160*EI$12 -> 351.32929
B49: =Assumptions!B161 -> Landscaping / Snow Removal | H49: =+Assumptions!$I161*H$12 -> 500.83333 | I49: =+Assumptions!$I161*I$12 -> 501.66806 | J49: =+Assumptions!$I161*J$12 -> 502.50417 | K49: =+Assumptions!$I161*K$12 -> 503.34168 | L49: =+Assumptions!$I161*L$12 -> 504.18058 | M49: =+Assumptions!$I161*M$12 -> 505.02088 | N49: =+Assumptions!$I161*N$12 -> 505.86258 | O49: =+Assumptions!$I161*O$12 -> 506.70569 | ... EI49: =+Assumptions!$I161*EI$12 -> 622.92428
B50: =Assumptions!B162 -> Property Management | H50: =+Assumptions!$G$162*H34 -> 4078.1036 | I50: =+Assumptions!$G$162*I34 -> 3929.2645 | J50: =+Assumptions!$G$162*J34 -> 3779.8003 | K50: =+Assumptions!$G$162*K34 -> 3629.7091 | L50: =+Assumptions!$G$162*L34 -> 3715.3382 | M50: =+Assumptions!$G$162*M34 -> 3848.3511 | N50: =+Assumptions!$G$162*N34 -> 3934.7419 | O50: =+Assumptions!$G$162*O34 -> 4021.476 | ... EI50: =+Assumptions!$G$162*EI34 -> 8043.1042
B51: =Assumptions!B163 -> Accounting / Legal | H51: =+Assumptions!$I163*H$12 -> 208.68056 | I51: =+Assumptions!$I163*I$12 -> 209.02836 | J51: =+Assumptions!$I163*J$12 -> 209.37674 | K51: =+Assumptions!$I163*K$12 -> 209.7257 | L51: =+Assumptions!$I163*L$12 -> 210.07524 | M51: =+Assumptions!$I163*M$12 -> 210.42537 | N51: =+Assumptions!$I163*N$12 -> 210.77608 | O51: =+Assumptions!$I163*O$12 -> 211.12737 | ... EI51: =+Assumptions!$I163*EI$12 -> 259.55178
B52: =Assumptions!B164 -> Total Operating Expenses | H52: =SUM(H37:H51) -> 55477.293 | I52: =SUM(I37:I51) -> 55137.977 | J52: =SUM(J37:J51) -> 54797.258 | K52: =SUM(K37:K51) -> 54455.132 | L52: =SUM(L37:L51) -> 54625.47 | M52: =SUM(M37:M51) -> 54843.333 | N52: =SUM(N37:N51) -> 55014.715 | O52: =SUM(O37:O51) -> 55186.583 | ... EI52: =SUM(EI37:EI51) -> 71972.162
B54: Multifamily NOI | H54: =+H34-H52 -> 80459.495 | I54: =+I34-I52 -> 75837.508 | J54: =+J34-J52 -> 71196.087 | K54: =+K34-K52 -> 66535.171 | L54: =+L34-L52 -> 69219.137 | M54: =+M34-M52 -> 73435.037 | N54: =+N34-N52 -> 76143.347 | O54: =+O34-O52 -> 78862.617 | ... EI54: =+EI34-EI52 -> 196131.31
B55: NTM NOI | H55: =SUM(I54:T54,I51:T51) -> 949248.44 | I55: =SUM(J54:U54,J51:U51) -> 968825.43 | J55: =SUM(K54:V54,K51:V51) -> 995840.79 | K55: =SUM(L54:W54,L51:W51) -> 1030325.2 | L55: =SUM(M54:X54,M51:X51) -> 1064945.2 | M55: =SUM(N54:Y54,N51:Y51) -> 1098180 | N55: =SUM(O54:Z54,O51:Z51) -> 1131548.5 | O55: =SUM(P54:AA54,P51:AA51) -> 1165051.3 | ... CM55: =SUM(CN54:CY54,CN51:CY51) -> 2152998.7 | CN55: =SUM(CO54:EI54,CO51:EI51) -> 8783080.3 | CO55: =SUM(CP54:EJ54,CP51:EJ51) -> 8605420.2 | CP55: =SUM(CQ54:EK54,CQ51:EK51) -> 8427372.4 | CQ55: =SUM(CR54:EL54,CR51:EL51) -> 8248936 | CR55: =SUM(CS54:EM54,CS51:EM51) -> 8070110.2 | CS55: =SUM(CT54:EN54,CT51:EN51) -> 7890894.1 | CT55: =SUM(CU54:EO54,CU51:EO51) -> 7711286.9 | CU55: =SUM(CV54:EP54,CV51:EP51) -> 7531287.8 | ... EI55: =SUM(EJ54:GD54,EJ51:GD51) -> 0
B57: Capital Expenditures: Multifamily
B58: =+Assumptions!B167 -> Reserves | H58: =+Assumptions!$G$167*H34 -> 1359.3679 | I58: =+Assumptions!$G$167*I34 -> 1309.7548 | J58: =+Assumptions!$G$167*J34 -> 1259.9334 | K58: =+Assumptions!$G$167*K34 -> 1209.903 | L58: =+Assumptions!$G$167*L34 -> 1238.4461 | M58: =+Assumptions!$G$167*M34 -> 1282.7837 | N58: =+Assumptions!$G$167*N34 -> 1311.5806 | O58: =+Assumptions!$G$167*O34 -> 1340.492 | ... EI58: =+Assumptions!$G$167*EI34 -> 2681.0347
B59: Total Multifamily CapEx | H59: =SUM(H58:H58) -> 1359.3679 | I59: =SUM(I58:I58) -> 1309.7548 | J59: =SUM(J58:J58) -> 1259.9334 | K59: =SUM(K58:K58) -> 1209.903 | L59: =SUM(L58:L58) -> 1238.4461 | M59: =SUM(M58:M58) -> 1282.7837 | N59: =SUM(N58:N58) -> 1311.5806 | O59: =SUM(O58:O58) -> 1340.492 | ... EI59: =SUM(EI58:EI58) -> 2681.0347
B61: Retail NOI | H61: {=IFERROR(INDEX('Retail Assumptions'!$L$49:$EO$49,,MATCH(H16,'Retail Assumptions'!$L$5:$EO$5,0)),0)} -> 0 | I61: {=IFERROR(INDEX('Retail Assumptions'!$L$49:$EO$49,,MATCH(I16,'Retail Assumptions'!$L$5:$EO$5,0)),0)} -> 0 | J61: {=IFERROR(INDEX('Retail Assumptions'!$L$49:$EO$49,,MATCH(J16,'Retail Assumptions'!$L$5:$EO$5,0)),0)} -> 0 | K61: {=IFERROR(INDEX('Retail Assumptions'!$L$49:$EO$49,,MATCH(K16,'Retail Assumptions'!$L$5:$EO$5,0)),0)} -> 0 | L61: {=IFERROR(INDEX('Retail Assumptions'!$L$49:$EO$49,,MATCH(L16,'Retail Assumptions'!$L$5:$EO$5,0)),0)} -> 0 | M61: {=IFERROR(INDEX('Retail Assumptions'!$L$49:$EO$49,,MATCH(M16,'Retail Assumptions'!$L$5:$EO$5,0)),0)} -> 0 | N61: {=IFERROR(INDEX('Retail Assumptions'!$L$49:$EO$49,,MATCH(N16,'Retail Assumptions'!$L$5:$EO$5,0)),0)} -> 0 | O61: {=IFERROR(INDEX('Retail Assumptions'!$L$49:$EO$49,,MATCH(O16,'Retail Assumptions'!$L$5:$EO$5,0)),0)} -> 0 | ... EI61: {=IFERROR(INDEX('Retail Assumptions'!$L$49:$EO$49,,MATCH(EI16,'Retail Assumptions'!$L$5:$EO$5,0)),0)} -> 0
B62: NTM NOI | H62: =SUM(I61:T61) -> 0 | I62: =SUM(J61:U61) -> 0 | J62: =SUM(K61:V61) -> 0 | K62: =SUM(L61:W61) -> 0 | L62: =SUM(M61:X61) -> 0 | M62: =SUM(N61:Y61) -> 0 | N62: =SUM(O61:Z61) -> 0 | O62: =SUM(P61:AA61) -> 0 | ... CM62: =SUM(CN61:CY61) -> 0 | CN62: =SUM(CO61:EI61) -> 0 | CO62: =SUM(CP61:EJ61) -> 0 | CP62: =SUM(CQ61:EK61) -> 0 | CQ62: =SUM(CR61:EL61) -> 0 | CR62: =SUM(CS61:EM61) -> 0 | CS62: =SUM(CT61:EN61) -> 0 | CT62: =SUM(CU61:EO61) -> 0 | CU62: =SUM(CV61:EP61) -> 0 | ... CX62: =SUM(CY61:ES61) -> 0 | CY62: =SUM(EJ61:ET61) -> 0 | CZ62: =SUM(EJ61:EU61) -> 0 | DA62: =SUM(EK61:EV61) -> 0 | DB62: =SUM(EL61:EW61) -> 0 | DC62: =SUM(EM61:EX61) -> 0 | DD62: =SUM(EN61:EY61) -> 0 | DE62: =SUM(EO61:EZ61) -> 0 | DF62: =SUM(EP61:FA61) -> 0 | DG62: =SUM(EQ61:FB61) -> 0 | ... EI62: =SUM(FS61:GD61) -> 0
B64: Capital Expenditures: Retail
B65: Total Retail Leasing Cost Reserves | H65: =(H61>0)*'Retail Assumptions'!$J$57/12*'NOI Walk'!H12 -> 0 | I65: =(I61>0)*'Retail Assumptions'!$J$57/12*'NOI Walk'!I12 -> 0 | J65: =(J61>0)*'Retail Assumptions'!$J$57/12*'NOI Walk'!J12 -> 0 | K65: =(K61>0)*'Retail Assumptions'!$J$57/12*'NOI Walk'!K12 -> 0 | L65: =(L61>0)*'Retail Assumptions'!$J$57/12*'NOI Walk'!L12 -> 0 | M65: =(M61>0)*'Retail Assumptions'!$J$57/12*'NOI Walk'!M12 -> 0 | N65: =(N61>0)*'Retail Assumptions'!$J$57/12*'NOI Walk'!N12 -> 0 | O65: =(O61>0)*'Retail Assumptions'!$J$57/12*'NOI Walk'!O12 -> 0 | ... EI65: =(EI61>0)*'Retail Assumptions'!$J$57/12*'NOI Walk'!EI12 -> 0
B67: Total Property NOI | H67: =+H61+H54 -> 80459.495 | I67: =+I61+I54 -> 75837.508 | J67: =+J61+J54 -> 71196.087 | K67: =+K61+K54 -> 66535.171 | L67: =+L61+L54 -> 69219.137 | M67: =+M61+M54 -> 73435.037 | N67: =+N61+N54 -> 76143.347 | O67: =+O61+O54 -> 78862.617 | ... EI67: =+EI61+EI54 -> 196131.31
B68: Total Property NTM NOI | H68: =+H62+H55 -> 949248.44 | I68: =+I62+I55 -> 968825.43 | J68: =+J62+J55 -> 995840.79 | K68: =+K62+K55 -> 1030325.2 | L68: =+L62+L55 -> 1064945.2 | M68: =+M62+M55 -> 1098180 | N68: =+N62+N55 -> 1131548.5 | O68: =+O62+O55 -> 1165051.3 | ... EI68: =+EI62+EI55 -> 0

Sheet Debt Schedule
B2: =+Assumptions!B27 -> Acquisition Loan | M2: =Assumptions!B33 -> Permanent Loan
B3: =+Assumptions!B28 -> Origination | H3: =+Assumptions!G28 -> 0 | M3: =Assumptions!B35 -> Seasoning Period Post Stabilization | R3: =Assumptions!G35 -> 3
B4: =+Assumptions!I29 -> Rate | H4: =+Assumptions!L29 -> 0.1 | M4: =Assumptions!B36 -> Refinancing Month | R4: =Assumptions!G36 -> 33
B5: =+Assumptions!I30 -> Amortization | H5: =+Assumptions!L30 -> 30 | M5: =Assumptions!B37 -> Fixed Interest Rate | R5: =Assumptions!G37 -> 0.0618393
M6: =Assumptions!B39 -> Amortization | R6: =Assumptions!G39 -> 30
B7: Loan Constant | H7: =IF(H5=0,H4,PMT(H4/12,H5*12,-1)*12) -> 0.10530859 | M7: Loan Constant | R7: =PMT(R5/12,R6*12,-1)*12 -> 0.073371188
B8: Loan Size at Closing | H8: =+Assumptions!R30 -> 11250000 | M8: =Assumptions!I37 -> Max Perm. Loan | R8: =IF(Assumptions!G34="Yes",Assumptions!L37,0) -> 20678404
B11: Month | C11: Period | D11: Beg. Bal. | E11: Draws | F11: Principal | G11: Interest | H11: End. Bal. | M11: Month | N11: Period | O11: Beg. Bal. | P11: Principal | Q11: Interest | R11: End. Bal.
B12: =+Assumptions!G28 -> 0 | C12: 0 | H12: =+H8 -> 11250000 | M12: =+R4 -> 33 | N12: 0 | R12: =+R8 -> 20678404
B13: =+B12+1 -> 1 | C13: =+C12+1 -> 1 | D13: =IF(B13>Assumptions!$E$174,0,H12) -> 11250000 | E13: {=IFERROR(INDEX(Model!$G$44:$EI$44,,MATCH('Debt Schedule'!B13,Model!$G$4:$EI$4,0)),0)} -> 0 | F13: =IF(AND(Assumptions!$G$34="Yes",'Debt Schedule'!B13>Assumptions!$G$36),0,IF(B13>Assumptions!$E$174,0,-IFERROR(PPMT($H$4/12,C13,$H$5*12,-$H$8),0))) -> -4976.8016 | G13: =IF(AND(Assumptions!$G$34="yes",'Debt Schedule'!B13>Assumptions!$G$36),0,IFERROR(IF(B13>Assumptions!$E$174,0,IPMT($H$4/12,C13,$H$5*12,-$H$8)),$H$4/12*D13)) -> 93750 | H13: =SUM(D13:F13) -> 11245023 | M13: =+M12+1 -> 34 | N13: =+N12+1 -> 1 | O13: =IF(M13>Assumptions!$E$174,0,R12) -> 20678404 | P13: =IF(M13>Assumptions!$E$174,0,-PPMT($R$5/12,N13,$R$6*12,-$R$8)) -> -19871.754 | Q13: =IF(M13>Assumptions!$E$174,0,-IPMT($R$5/12,N13,$R$6*12,-$R$8)) -> -106561.5 | R13: =+P13+O13 -> 20658533
B14: =+B13+1 -> 2 | C14: =+C13+1 -> 2 | D14: =IF(B14>Assumptions!$E$174,0,H13) -> 11245023 | E14: {=IFERROR(INDEX(Model!$G$44:$EI$44,,MATCH('Debt Schedule'!B14,Model!$G$4:$EI$4,0)),0)} -> 0 | F14: =IF(AND(Assumptions!$G$34="Yes",'Debt Schedule'!B14>Assumptions!$G$36),0,IF(B14>Assumptions!$E$174,0,-IFERROR(PPMT($H$4/12,C14,$H$5*12,-$H$8),0))) -> -5018.275 | G14: =IF(AND(Assumptions!$G$34="yes",'Debt Schedule'!B14>Assumptions!$G$36),0,IFERROR(IF(B14>Assumptions!$E$174,0,IPMT($H$4/12,C14,$H$5*12,-$H$8)),$H$4/12*D14)) -> 93708.527 | H14: =SUM(D14:F14) -> 11240005 | M14: =+M13+1 -> 35 | N14: =+N13+1 -> 2 | O14: =IF(M14>Assumptions!$E$174,0,R13) -> 20658533 | P14: =IF(M14>Assumptions!$E$174,0,-PPMT($R$5/12,N14,$R$6*12,-$R$8)) -> -19974.159 | Q14: =IF(M14>Assumptions!$E$174,0,-IPMT($R$5/12,N14,$R$6*12,-$R$8)) -> -106459.1 | R14: =+P14+O14 -> 20638559
B15: =+B14+1 -> 3 | C15: =+C14+1 -> 3 | D15: =IF(B15>Assumptions!$E$174,0,H14) -> 11240005 | E15: {=IFERROR(INDEX(Model!$G$44:$EI$44,,MATCH('Debt Schedule'!B15,Model!$G$4:$EI$4,0)),0)} -> 0 | F15: =IF(AND(Assumptions!$G$34="Yes",'Debt Schedule'!B15>Assumptions!$G$36),0,IF(B15>Assumptions!$E$174,0,-IFERROR(PPMT($H$4/12,C15,$H$5*12,-$H$8),0))) -> -5060.0939 | G15: =IF(AND(Assumptions!$G$34="yes",'Debt Schedule'!B15>Assumptions!$G$36),0,IFERROR(IF(B15>Assumptions!$E$174,0,IPMT($H$4/12,C15,$H$5*12,-$H$8)),$H$4/12*D15)) -> 93666.708 | H15: =SUM(D15:F15) -> 11234945 | M15: =+M14+1 -> 36 | N15: =+N14+1 -> 3 | O15: =IF(M15>Assumptions!$E$174,0,R14) -> 20638559 | P15: =IF(M15>Assumptions!$E$174,0,-PPMT($R$5/12,N15,$R$6*12,-$R$8)) -> -20077.091 | Q15: =IF(M15>Assumptions!$E$174,0,-IPMT($R$5/12,N15,$R$6*12,-$R$8)) -> -106356.17 | R15: =+P15+O15 -> 20618481
B16: =+B15+1 -> 4 | C16: =+C15+1 -> 4 | D16: =IF(B16>Assumptions!$E$174,0,H15) -> 11234945 | E16: {=IFERROR(INDEX(Model!$G$44:$EI$44,,MATCH('Debt Schedule'!B16,Model!$G$4:$EI$4,0)),0)} -> 0 | F16: =IF(AND(Assumptions!$G$34="Yes",'Debt Schedule'!B16>Assumptions!$G$36),0,IF(B16>Assumptions!$E$174,0,-IFERROR(PPMT($H$4/12,C16,$H$5*12,-$H$8),0))) -> -5102.2614 | G16: =IF(AND(Assumptions!$G$34="yes",'Debt Schedule'!B16>Assumptions!$G$36),0,IFERROR(IF(B16>Assumptions!$E$174,0,IPMT($H$4/12,C16,$H$5*12,-$H$8)),$H$4/12*D16)) -> 93624.54 | H16: =SUM(D16:F16) -> 11229843 | M16: =+M15+1 -> 37 | N16: =+N15+1 -> 4 | O16: =IF(M16>Assumptions!$E$174,0,R15) -> 20618481 | P16: =IF(M16>Assumptions!$E$174,0,-PPMT($R$5/12,N16,$R$6*12,-$R$8)) -> -20180.554 | Q16: =IF(M16>Assumptions!$E$174,0,-IPMT($R$5/12,N16,$R$6*12,-$R$8)) -> -106252.7 | R16: =+P16+O16 -> 20598301
B17: =+B16+1 -> 5 | C17: =+C16+1 -> 5 | D17: =IF(B17>Assumptions!$E$174,0,H16) -> 11229843 | E17: {=IFERROR(INDEX(Model!$G$44:$EI$44,,MATCH('Debt Schedule'!B17,Model!$G$4:$EI$4,0)),0)} -> 0 | F17: =IF(AND(Assumptions!$G$34="Yes",'Debt Schedule'!B17>Assumptions!$G$36),0,IF(B17>Assumptions!$E$174,0,-IFERROR(PPMT($H$4/12,C17,$H$5*12,-$H$8),0))) -> -5144.7802 | G17: =IF(AND(Assumptions!$G$34="yes",'Debt Schedule'!B17>Assumptions!$G$36),0,IFERROR(IF(B17>Assumptions!$E$174,0,IPMT($H$4/12,C17,$H$5*12,-$H$8)),$H$4/12*D17)) -> 93582.021 | H17: =SUM(D17:F17) -> 11224698 | M17: =+M16+1 -> 38 | N17: =+N16+1 -> 5 | O17: =IF(M17>Assumptions!$E$174,0,R16) -> 20598301 | P17: =IF(M17>Assumptions!$E$174,0,-PPMT($R$5/12,N17,$R$6*12,-$R$8)) -> -20284.55 | Q17: =IF(M17>Assumptions!$E$174,0,-IPMT($R$5/12,N17,$R$6*12,-$R$8)) -> -106148.71 | R17: =+P17+O17 -> 20578016
B18: =+B17+1 -> 6 | C18: =+C17+1 -> 6 | D18: =IF(B18>Assumptions!$E$174,0,H17) -> 11224698 | E18: {=IFERROR(INDEX(Model!$G$44:$EI$44,,MATCH('Debt Schedule'!B18,Model!$G$4:$EI$4,0)),0)} -> 0 | F18: =IF(AND(Assumptions!$G$34="Yes",'Debt Schedule'!B18>Assumptions!$G$36),0,IF(B18>Assumptions!$E$174,0,-IFERROR(PPMT($H$4/12,C18,$H$5*12,-$H$8),0))) -> -5187.6534 | G18: =IF(AND(Assumptions!$G$34="yes",'Debt Schedule'!B18>Assumptions!$G$36),0,IFERROR(IF(B18>Assumptions!$E$174,0,IPMT($H$4/12,C18,$H$5*12,-$H$8)),$H$4/12*D18)) -> 93539.148 | H18: =SUM(D18:F18) -> 11219510 | M18: =+M17+1 -> 39 | N18: =+N17+1 -> 6 | O18: =IF(M18>Assumptions!$E$174,0,R17) -> 20578016 | P18: =IF(M18>Assumptions!$E$174,0,-PPMT($R$5/12,N18,$R$6*12,-$R$8)) -> -20389.082 | Q18: =IF(M18>Assumptions!$E$174,0,-IPMT($R$5/12,N18,$R$6*12,-$R$8)) -> -106044.18 | R18: =+P18+O18 -> 20557627
B19: =+B18+1 -> 7 | C19: =+C18+1 -> 7 | D19: =IF(B19>Assumptions!$E$174,0,H18) -> 11219510 | E19: {=IFERROR(INDEX(Model!$G$44:$EI$44,,MATCH('Debt Schedule'!B19,Model!$G$4:$EI$4,0)),0)} -> 0 | F19: =IF(AND(Assumptions!$G$34="Yes",'Debt Schedule'!B19>Assumptions!$G$36),0,IF(B19>Assumptions!$E$174,0,-IFERROR(PPMT($H$4/12,C19,$H$5*12,-$H$8),0))) -> -5230.8838 | G19: =IF(AND(Assumptions!$G$34="yes",'Debt Schedule'!B19>Assumptions!$G$36),0,IFERROR(IF(B19>Assumptions!$E$174,0,IPMT($H$4/12,C19,$H$5*12,-$H$8)),$H$4/12*D19)) -> 93495.918 | H19: =SUM(D19:F19) -> 11214279 | M19: =+M18+1 -> 40 | N19: =+N18+1 -> 7 | O19: =IF(M19>Assumptions!$E$174,0,R18) -> 20557627 | P19: =IF(M19>Assumptions!$E$174,0,-PPMT($R$5/12,N19,$R$6*12,-$R$8)) -> -20494.152 | Q19: =IF(M19>Assumptions!$E$174,0,-IPMT($R$5/12,N19,$R$6*12,-$R$8)) -> -105939.11 | R19: =+P19+O19 -> 20537133
B20: =+B19+1 -> 8 | C20: =+C19+1 -> 8 | D20: =IF(B20>Assumptions!$E$174,0,H19) -> 11214279 | E20: {=IFERROR(INDEX(Model!$G$44:$EI$44,,MATCH('Debt Schedule'!B20,Model!$G$4:$EI$4,0)),0)} -> 0 | F20: =IF(AND(Assumptions!$G$34="Yes",'Debt Schedule'!B20>Assumptions!$G$36),0,IF(B20>Assumptions!$E$174,0,-IFERROR(PPMT($H$4/12,C20,$H$5*12,-$H$8),0))) -> -5274.4745 | G20: =IF(AND(Assumptions!$G$34="yes",'Debt Schedule'!B20>Assumptions!$G$36),0,IFERROR(IF(B20>Assumptions!$E$174,0,IPMT($H$4/12,C20,$H$5*12,-$H$8)),$H$4/12*D20)) -> 93452.327 | H20: =SUM(D20:F20) -> 11209005 | M20: =+M19+1 -> 41 | N20: =+N19+1 -> 8 | O20: =IF(M20>Assumptions!$E$174,0,R19) -> 20537133 | P20: =IF(M20>Assumptions!$E$174,0,-PPMT($R$5/12,N20,$R$6*12,-$R$8)) -> -20599.764 | Q20: =IF(M20>Assumptions!$E$174,0,-IPMT($R$5/12,N20,$R$6*12,-$R$8)) -> -105833.49 | R20: =+P20+O20 -> 20516533
B21: =+B20+1 -> 9 | C21: =+C20+1 -> 9 | D21: =IF(B21>Assumptions!$E$174,0,H20) -> 11209005 | E21: {=IFERROR(INDEX(Model!$G$44:$EI$44,,MATCH('Debt Schedule'!B21,Model!$G$4:$EI$4,0)),0)} -> 0 | F21: =IF(AND(Assumptions!$G$34="Yes",'Debt Schedule'!B21>Assumptions!$G$36),0,IF(B21>Assumptions!$E$174,0,-IFERROR(PPMT($H$4/12,C21,$H$5*12,-$H$8),0))) -> -5318.4285 | G21: =IF(AND(Assumptions!$G$34="yes",'Debt Schedule'!B21>Assumptions!$G$36),0,IFERROR(IF(B21>Assumptions!$E$174,0,IPMT($H$4/12,C21,$H$5*12,-$H$8)),$H$4/12*D21)) -> 93408.373 | H21: =SUM(D21:F21) -> 11203686 | M21: =+M20+1 -> 42 | N21: =+N20+1 -> 9 | O21: =IF(M21>Assumptions!$E$174,0,R20) -> 20516533 | P21: =IF(M21>Assumptions!$E$174,0,-PPMT($R$5/12,N21,$R$6*12,-$R$8)) -> -20705.921 | Q21: =IF(M21>Assumptions!$E$174,0,-IPMT($R$5/12,N21,$R$6*12,-$R$8)) -> -105727.34 | R21: =+P21+O21 -> 20495827
B22: =+B21+1 -> 10 | C22: =+C21+1 -> 10 | D22: =IF(B22>Assumptions!$E$174,0,H21) -> 11203686 | E22: {=IFERROR(INDEX(Model!$G$44:$EI$44,,MATCH('Debt Schedule'!B22,Model!$G$4:$EI$4,0)),0)} -> 0 | F22: =IF(AND(Assumptions!$G$34="Yes",'Debt Schedule'!B22>Assumptions!$G$36),0,IF(B22>Assumptions!$E$174,0,-IFERROR(PPMT($H$4/12,C22,$H$5*12,-$H$8),0))) -> -5362.7487 | G22: =IF(AND(Assumptions!$G$34="yes",'Debt Schedule'!B22>Assumptions!$G$36),0,IFERROR(IF(B22>Assumptions!$E$174,0,IPMT($H$4/12,C22,$H$5*12,-$H$8)),$H$4/12*D22)) -> 93364.053 | H22: =SUM(D22:F22) -> 11198324 | M22: =+M21+1 -> 43 | N22: =+N21+1 -> 10 | O22: =IF(M22>Assumptions!$E$174,0,R21) -> 20495827 | P22: =IF(M22>Assumptions!$E$174,0,-PPMT($R$5/12,N22,$R$6*12,-$R$8)) -> -20812.624 | Q22: =IF(M22>Assumptions!$E$174,0,-IPMT($R$5/12,N22,$R$6*12,-$R$8)) -> -105620.64 | R22: =+P22+O22 -> 20475015
B23: =+B22+1 -> 11 | C23: =+C22+1 -> 11 | D23: =IF(B23>Assumptions!$E$174,0,H22) -> 11198324 | E23: {=IFERROR(INDEX(Model!$G$44:$EI$44,,MATCH('Debt Schedule'!B23,Model!$G$4:$EI$4,0)),0)} -> 0 | F23: =IF(AND(Assumptions!$G$34="Yes",'Debt Schedule'!B23>Assumptions!$G$36),0,IF(B23>Assumptions!$E$174,0,-IFERROR(PPMT($H$4/12,C23,$H$5*12,-$H$8),0))) -> -5407.4383 | G23: =IF(AND(Assumptions!$G$34="yes",'Debt Schedule'!B23>Assumptions!$G$36),0,IFERROR(IF(B23>Assumptions!$E$174,0,IPMT($H$4/12,C23,$H$5*12,-$H$8)),$H$4/12*D23)) -> 93319.363 | H23: =SUM(D23:F23) -> 11192916 | M23: =+M22+1 -> 44 | N23: =+N22+1 -> 11 | O23: =IF(M23>Assumptions!$E$174,0,R22) -> 20475015 | P23: =IF(M23>Assumptions!$E$174,0,-PPMT($R$5/12,N23,$R$6*12,-$R$8)) -> -20919.877 | Q23: =IF(M23>Assumptions!$E$174,0,-IPMT($R$5/12,N23,$R$6*12,-$R$8)) -> -105513.38 | R23: =+P23+O23 -> 20454095
B24: =+B23+1 -> 12 | C24: =+C23+1 -> 12 | D24: =IF(B24>Assumptions!$E$174,0,H23) -> 11192916 | E24: {=IFERROR(INDEX(Model!$G$44:$EI$44,,MATCH('Debt Schedule'!B24,Model!$G$4:$EI$4,0)),0)} -> 0 | F24: =IF(AND(Assumptions!$G$34="Yes",'Debt Schedule'!B24>Assumptions!$G$36),0,IF(B24>Assumptions!$E$174,0,-IFERROR(PPMT($H$4/12,C24,$H$5*12,-$H$8),0))) -> -5452.5003 | G24: =IF(AND(Assumptions!$G$34="yes",'Debt Schedule'!B24>Assumptions!$G$36),0,IFERROR(IF(B24>Assumptions!$E$174,0,IPMT($H$4/12,C24,$H$5*12,-$H$8)),$H$4/12*D24)) -> 93274.301 | H24: =SUM(D24:F24) -> 11187464 | M24: =+M23+1 -> 45 | N24: =+N23+1 -> 12 | O24: =IF(M24>Assumptions!$E$174,0,R23) -> 20454095 | P24: =IF(M24>Assumptions!$E$174,0,-PPMT($R$5/12,N24,$R$6*12,-$R$8)) -> -21027.683 | Q24: =IF(M24>Assumptions!$E$174,0,-IPMT($R$5/12,N24,$R$6*12,-$R$8)) -> -105405.58 | R24: =+P24+O24 -> 20433067
... B108: =+B107+1 -> 96 | C108: =+C107+1 -> 96 | D108: =IF(B108>Assumptions!$E$174,0,H107) -> 0 | E108: {=IFERROR(INDEX(Model!$G$44:$EI$44,,MATCH('Debt Schedule'!B108,Model!$G$4:$EI$4,0)),0)} -> 0 | F108: =IF(AND(Assumptions!$G$34="Yes",'Debt Schedule'!B108>Assumptions!$G$36),0,IF(B108>Assumptions!$E$174,0,-IFERROR(PPMT($H$4/12,C108,$H$5*12,-$H$8),0))) -> 0 | G108: =IF(AND(Assumptions!$G$34="yes",'Debt Schedule'!B108>Assumptions!$G$36),0,IFERROR(IF(B108>Assumptions!$E$174,0,IPMT($H$4/12,C108,$H$5*12,-$H$8)),$H$4/12*D108)) -> 0 | H108: =SUM(D108:F108) -> 0 | M108: =+M107+1 -> 129 | N108: =+N107+1 -> 96 | O108: =IF(M108>Assumptions!$E$174,0,R107) -> 0 | P108: =IF(M108>Assumptions!$E$174,0,-PPMT($R$5/12,N108,$R$6*12,-$R$8)) -> 0 | Q108: =IF(M108>Assumptions!$E$174,0,-IPMT($R$5/12,N108,$R$6*12,-$R$8)) -> 0 | R108: =+P108+O108 -> 0

Sheet Retail Assumptions
L3: =+EOMONTH(Assumptions!F2,'Retail Assumptions'!L5) -> 45838 | M3: =+EOMONTH(L3,1) -> 45869 | N3: =+EOMONTH(M3,1) -> 45900 | O3: =+EOMONTH(N3,1) -> 45930 | P3: =+EOMONTH(O3,1) -> 45961 | Q3: =+EOMONTH(P3,1) -> 45991 | R3: =+EOMONTH(Q3,1) -> 46022 | S3: =+EOMONTH(R3,1) -> 46053 | T3: =+EOMONTH(S3,1) -> 46081 | ... EO3: =+EOMONTH(EN3,1) -> 49887
B4: Base Retail Income | L4: =ROUNDUP(L5/12,0) -> 0 | M4: =ROUNDUP(M5/12,0) -> 1 | N4: =ROUNDUP(N5/12,0) -> 1 | O4: =ROUNDUP(O5/12,0) -> 1 | P4: =ROUNDUP(P5/12,0) -> 1 | Q4: =ROUNDUP(Q5/12,0) -> 1 | R4: =ROUNDUP(R5/12,0) -> 1 | S4: =ROUNDUP(S5/12,0) -> 1 | ... EO4: =ROUNDUP(EO5/12,0) -> 12
B5: Suite | C5: Tenant | E5: Lease Start | F5: SF | G5: Rent Start | H5: Annual Bumps | I5: Rent / SF / Yr. | J5: Annual Rent (Yr. 1) | L5: =+G19 -> 0 | M5: =+L5+1 -> 1 | N5: =+M5+1 -> 2 | O5: =+N5+1 -> 3 | P5: =+O5+1 -> 4 | Q5: =+P5+1 -> 5 | R5: =+Q5+1 -> 6 | S5: =+R5+1 -> 7 | T5: =+S5+1 -> 8 | ... EO5: =+EN5+1 -> 133
B6: 100 | C6: Commercial Tenant | E6: 1 | F6: 0 | G6: 1 | H6: 0.01 | I6: 0 | J6: =+I6*F6 -> 0 | L6: =($G6<=L$5)*($J6/12)*(1+$H6)^(ROUNDUP(MAX(L$5-$G6+1,0)/12,0)-1) -> 0 | M6: =($G6<=M$5)*($J6/12)*(1+$H6)^(ROUNDUP(MAX(M$5-$G6+1,0)/12,0)-1) -> 0 | N6: =($G6<=N$5)*($J6/12)*(1+$H6)^(ROUNDUP(MAX(N$5-$G6+1,0)/12,0)-1) -> 0 | O6: =($G6<=O$5)*($J6/12)*(1+$H6)^(ROUNDUP(MAX(O$5-$G6+1,0)/12,0)-1) -> 0 | P6: =($G6<=P$5)*($J6/12)*(1+$H6)^(ROUNDUP(MAX(P$5-$G6+1,0)/12,0)-1) -> 0 | Q6: =($G6<=Q$5)*($J6/12)*(1+$H6)^(ROUNDUP(MAX(Q$5-$G6+1,0)/12,0)-1) -> 0 | R6: =($G6<=R$5)*($J6/12)*(1+$H6)^(ROUNDUP(MAX(R$5-$G6+1,0)/12,0)-1) -> 0 | S6: =($G6<=S$5)*($J6/12)*(1+$H6)^(ROUNDUP(MAX(S$5-$G6+1,0)/12,0)-1) -> 0 | ... EO6: =($G6<=EO$5)*($J6/12)*(1+$H6)^(ROUNDUP(MAX(EO$5-$G6+1,0)/12,0)-1) -> 0
B7: =+B6+100 -> 200 | C7: [Retail Tenant] | E7: 1 | F7: 0 | G7: 0 | H7: 0.01 | I7: 0 | J7: =+I7*F7 -> 0 | L7: =($G7<=L$5)*($J7/12)*(1+$H7)^(ROUNDUP(MAX(L$5-$G7+1,0)/12,0)-1) -> 0 | M7: =($G7<=M$5)*($J7/12)*(1+$H7)^(ROUNDUP(MAX(M$5-$G7+1,0)/12,0)-1) -> 0 | N7: =($G7<=N$5)*($J7/12)*(1+$H7)^(ROUNDUP(MAX(N$5-$G7+1,0)/12,0)-1) -> 0 | O7: =($G7<=O$5)*($J7/12)*(1+$H7)^(ROUNDUP(MAX(O$5-$G7+1,0)/12,0)-1) -> 0 | P7: =($G7<=P$5)*($J7/12)*(1+$H7)^(ROUNDUP(MAX(P$5-$G7+1,0)/12,0)-1) -> 0 | Q7: =($G7<=Q$5)*($J7/12)*(1+$H7)^(ROUNDUP(MAX(Q$5-$G7+1,0)/12,0)-1) -> 0 | R7: =($G7<=R$5)*($J7/12)*(1+$H7)^(ROUNDUP(MAX(R$5-$G7+1,0)/12,0)-1) -> 0 | S7: =($G7<=S$5)*($J7/12)*(1+$H7)^(ROUNDUP(MAX(S$5-$G7+1,0)/12,0)-1) -> 0 | ... EO7: =($G7<=EO$5)*($J7/12)*(1+$H7)^(ROUNDUP(MAX(EO$5-$G7+1,0)/12,0)-1) -> 0
B8: =+B7+100 -> 300 | C8: [Retail Tenant] | E8: 1 | F8: 0 | G8: 0 | H8: 0.01 | I8: 0 | J8: =+I8*F8 -> 0 | L8: =($G8<=L$5)*($J8/12)*(1+$H8)^(ROUNDUP(MAX(L$5-$G8+1,0)/12,0)-1) -> 0 | M8: =($G8<=M$5)*($J8/12)*(1+$H8)^(ROUNDUP(MAX(M$5-$G8+1,0)/12,0)-1) -> 0 | N8: =($G8<=N$5)*($J8/12)*(1+$H8)^(ROUNDUP(MAX(N$5-$G8+1,0)/12,0)-1) -> 0 | O8: =($G8<=O$5)*($J8/12)*(1+$H8)^(ROUNDUP(MAX(O$5-$G8+1,0)/12,0)-1) -> 0 | P8: =($G8<=P$5)*($J8/12)*(1+$H8)^(ROUNDUP(MAX(P$5-$G8+1,0)/12,0)-1) -> 0 | Q8: =($G8<=Q$5)*($J8/12)*(1+$H8)^(ROUNDUP(MAX(Q$5-$G8+1,0)/12,0)-1) -> 0 | R8: =($G8<=R$5)*($J8/12)*(1+$H8)^(ROUNDUP(MAX(R$5-$G8+1,0)/12,0)-1) -> 0 | S8: =($G8<=S$5)*($J8/12)*(1+$H8)^(ROUNDUP(MAX(S$5-$G8+1,0)/12,0)-1) -> 0 | ... EO8: =($G8<=EO$5)*($J8/12)*(1+$H8)^(ROUNDUP(MAX(EO$5-$G8+1,0)/12,0)-1) -> 0
B9: =+B8+100 -> 400 | C9: [Retail Tenant] | E9: 1 | F9: 0 | G9: 0 | H9: 0.01 | I9: 0 | J9: =+I9*F9 -> 0 | L9: =($G9<=L$5)*($J9/12)*(1+$H9)^(ROUNDUP(MAX(L$5-$G9+1,0)/12,0)-1) -> 0 | M9: =($G9<=M$5)*($J9/12)*(1+$H9)^(ROUNDUP(MAX(M$5-$G9+1,0)/12,0)-1) -> 0 | N9: =($G9<=N$5)*($J9/12)*(1+$H9)^(ROUNDUP(MAX(N$5-$G9+1,0)/12,0)-1) -> 0 | O9: =($G9<=O$5)*($J9/12)*(1+$H9)^(ROUNDUP(MAX(O$5-$G9+1,0)/12,0)-1) -> 0 | P9: =($G9<=P$5)*($J9/12)*(1+$H9)^(ROUNDUP(MAX(P$5-$G9+1,0)/12,0)-1) -> 0 | Q9: =($G9<=Q$5)*($J9/12)*(1+$H9)^(ROUNDUP(MAX(Q$5-$G9+1,0)/12,0)-1) -> 0 | R9: =($G9<=R$5)*($J9/12)*(1+$H9)^(ROUNDUP(MAX(R$5-$G9+1,0)/12,0)-1) -> 0 | S9: =($G9<=S$5)*($J9/12)*(1+$H9)^(ROUNDUP(MAX(S$5-$G9+1,0)/12,0)-1) -> 0 | ... EO9: =($G9<=EO$5)*($J9/12)*(1+$H9)^(ROUNDUP(MAX(EO$5-$G9+1,0)/12,0)-1) -> 0
B10: =+B9+100 -> 500 | C10: [Retail Tenant] | E10: 1 | F10: 0 | G10: 0 | H10: 0.01 | I10: 0 | J10: =+I10*F10 -> 0 | L10: =($G10<=L$5)*($J10/12)*(1+$H10)^(ROUNDUP(MAX(L$5-$G10+1,0)/12,0)-1) -> 0 | M10: =($G10<=M$5)*($J10/12)*(1+$H10)^(ROUNDUP(MAX(M$5-$G10+1,0)/12,0)-1) -> 0 | N10: =($G10<=N$5)*($J10/12)*(1+$H10)^(ROUNDUP(MAX(N$5-$G10+1,0)/12,0)-1) -> 0 | O10: =($G10<=O$5)*($J10/12)*(1+$H10)^(ROUNDUP(MAX(O$5-$G10+1,0)/12,0)-1) -> 0 | P10: =($G10<=P$5)*($J10/12)*(1+$H10)^(ROUNDUP(MAX(P$5-$G10+1,0)/12,0)-1) -> 0 | Q10: =($G10<=Q$5)*($J10/12)*(1+$H10)^(ROUNDUP(MAX(Q$5-$G10+1,0)/12,0)-1) -> 0 | R10: =($G10<=R$5)*($J10/12)*(1+$H10)^(ROUNDUP(MAX(R$5-$G10+1,0)/12,0)-1) -> 0 | S10: =($G10<=S$5)*($J10/12)*(1+$H10)^(ROUNDUP(MAX(S$5-$G10+1,0)/12,0)-1) -> 0 | ... EO10: =($G10<=EO$5)*($J10/12)*(1+$H10)^(ROUNDUP(MAX(EO$5-$G10+1,0)/12,0)-1) -> 0
B11: =+B10+100 -> 600 | C11: [Retail Tenant] | E11: 1 | F11: 0 | G11: 0 | H11: 0.01 | I11: 0 | J11: =+I11*F11 -> 0 | L11: =($G11<=L$5)*($J11/12)*(1+$H11)^(ROUNDUP(MAX(L$5-$G11+1,0)/12,0)-1) -> 0 | M11: =($G11<=M$5)*($J11/12)*(1+$H11)^(ROUNDUP(MAX(M$5-$G11+1,0)/12,0)-1) -> 0 | N11: =($G11<=N$5)*($J11/12)*(1+$H11)^(ROUNDUP(MAX(N$5-$G11+1,0)/12,0)-1) -> 0 | O11: =($G11<=O$5)*($J11/12)*(1+$H11)^(ROUNDUP(MAX(O$5-$G11+1,0)/12,0)-1) -> 0 | P11: =($G11<=P$5)*($J11/12)*(1+$H11)^(ROUNDUP(MAX(P$5-$G11+1,0)/12,0)-1) -> 0 | Q11: =($G11<=Q$5)*($J11/12)*(1+$H11)^(ROUNDUP(MAX(Q$5-$G11+1,0)/12,0)-1) -> 0 | R11: =($G11<=R$5)*($J11/12)*(1+$H11)^(ROUNDUP(MAX(R$5-$G11+1,0)/12,0)-1) -> 0 | S11: =($G11<=S$5)*($J11/12)*(1+$H11)^(ROUNDUP(MAX(S$5-$G11+1,0)/12,0)-1) -> 0 | ... EO11: =($G11<=EO$5)*($J11/12)*(1+$H11)^(ROUNDUP(MAX(EO$5-$G11+1,0)/12,0)-1) -> 0
B12: =+B11+100 -> 700 | C12: [Retail Tenant] | E12: 1 | F12: 0 | G12: 0 | H12: 0.01 | I12: 0 | J12: =+I12*F12 -> 0 | L12: =($G12<=L$5)*($J12/12)*(1+$H12)^(ROUNDUP(MAX(L$5-$G12+1,0)/12,0)-1) -> 0 | M12: =($G12<=M$5)*($J12/12)*(1+$H12)^(ROUNDUP(MAX(M$5-$G12+1,0)/12,0)-1) -> 0 | N12: =($G12<=N$5)*($J12/12)*(1+$H12)^(ROUNDUP(MAX(N$5-$G12+1,0)/12,0)-1) -> 0 | O12: =($G12<=O$5)*($J12/12)*(1+$H12)^(ROUNDUP(MAX(O$5-$G12+1,0)/12,0)-1) -> 0 | P12: =($G12<=P$5)*($J12/12)*(1+$H12)^(ROUNDUP(MAX(P$5-$G12+1,0)/12,0)-1) -> 0 | Q12: =($G12<=Q$5)*($J12/12)*(1+$H12)^(ROUNDUP(MAX(Q$5-$G12+1,0)/12,0)-1) -> 0 | R12: =($G12<=R$5)*($J12/12)*(1+$H12)^(ROUNDUP(MAX(R$5-$G12+1,0)/12,0)-1) -> 0 | S12: =($G12<=S$5)*($J12/12)*(1+$H12)^(ROUNDUP(MAX(S$5-$G12+1,0)/12,0)-1) -> 0 | ... EO12: =($G12<=EO$5)*($J12/12)*(1+$H12)^(ROUNDUP(MAX(EO$5-$G12+1,0)/12,0)-1) -> 0
B13: =+B12+100 -> 800 | C13: [Retail Tenant] | E13: 1 | F13: 0 | G13: 0 | H13: 0.01 | I13: 0 | J13: =+I13*F13 -> 0 | L13: =($G13<=L$5)*($J13/12)*(1+$H13)^(ROUNDUP(MAX(L$5-$G13+1,0)/12,0)-1) -> 0 | M13: =($G13<=M$5)*($J13/12)*(1+$H13)^(ROUNDUP(MAX(M$5-$G13+1,0)/12,0)-1) -> 0 | N13: =($G13<=N$5)*($J13/12)*(1+$H13)^(ROUNDUP(MAX(N$5-$G13+1,0)/12,0)-1) -> 0 | O13: =($G13<=O$5)*($J13/12)*(1+$H13)^(ROUNDUP(MAX(O$5-$G13+1,0)/12,0)-1) -> 0 | P13: =($G13<=P$5)*($J13/12)*(1+$H13)^(ROUNDUP(MAX(P$5-$G13+1,0)/12,0)-1) -> 0 | Q13: =($G13<=Q$5)*($J13/12)*(1+$H13)^(ROUNDUP(MAX(Q$5-$G13+1,0)/12,0)-1) -> 0 | R13: =($G13<=R$5)*($J13/12)*(1+$H13)^(ROUNDUP(MAX(R$5-$G13+1,0)/12,0)-1) -> 0 | S13: =($G13<=S$5)*($J13/12)*(1+$H13)^(ROUNDUP(MAX(S$5-$G13+1,0)/12,0)-1) -> 0 | ... EO13: =($G13<=EO$5)*($J13/12)*(1+$H13)^(ROUNDUP(MAX(EO$5-$G13+1,0)/12,0)-1) -> 0
B14: =+B13+100 -> 900 | C14: [Retail Tenant] | E14: 1 | F14: 0 | G14: 0 | H14: 0.01 | I14: 0 | J14: =+I14*F14 -> 0 | L14: =($G14<=L$5)*($J14/12)*(1+$H14)^(ROUNDUP(MAX(L$5-$G14+1,0)/12,0)-1) -> 0 | M14: =($G14<=M$5)*($J14/12)*(1+$H14)^(ROUNDUP(MAX(M$5-$G14+1,0)/12,0)-1) -> 0 | N14: =($G14<=N$5)*($J14/12)*(1+$H14)^(ROUNDUP(MAX(N$5-$G14+1,0)/12,0)-1) -> 0 | O14: =($G14<=O$5)*($J14/12)*(1+$H14)^(ROUNDUP(MAX(O$5-$G14+1,0)/12,0)-1) -> 0 | P14: =($G14<=P$5)*($J14/12)*(1+$H14)^(ROUNDUP(MAX(P$5-$G14+1,0)/12,0)-1) -> 0 | Q14: =($G14<=Q$5)*($J14/12)*(1+$H14)^(ROUNDUP(MAX(Q$5-$G14+1,0)/12,0)-1) -> 0 | R14: =($G14<=R$5)*($J14/12)*(1+$H14)^(ROUNDUP(MAX(R$5-$G14+1,0)/12,0)-1) -> 0 | S14: =($G14<=S$5)*($J14/12)*(1+$H14)^(ROUNDUP(MAX(S$5-$G14+1,0)/12,0)-1) -> 0 | ... EO14: =($G14<=EO$5)*($J14/12)*(1+$H14)^(ROUNDUP(MAX(EO$5-$G14+1,0)/12,0)-1) -> 0
B15: =+B14+100 -> 1000 | C15: [Retail Tenant] | E15: 1 | F15: 0 | G15: 0 | H15: 0.01 | I15: 0 | J15: =+I15*F15 -> 0 | L15: =($G15<=L$5)*($J15/12)*(1+$H15)^(ROUNDUP(MAX(L$5-$G15+1,0)/12,0)-1) -> 0 | M15: =($G15<=M$5)*($J15/12)*(1+$H15)^(ROUNDUP(MAX(M$5-$G15+1,0)/12,0)-1) -> 0 | N15: =($G15<=N$5)*($J15/12)*(1+$H15)^(ROUNDUP(MAX(N$5-$G15+1,0)/12,0)-1) -> 0 | O15: =($G15<=O$5)*($J15/12)*(1+$H15)^(ROUNDUP(MAX(O$5-$G15+1,0)/12,0)-1) -> 0 | P15: =($G15<=P$5)*($J15/12)*(1+$H15)^(ROUNDUP(MAX(P$5-$G15+1,0)/12,0)-1) -> 0 | Q15: =($G15<=Q$5)*($J15/12)*(1+$H15)^(ROUNDUP(MAX(Q$5-$G15+1,0)/12,0)-1) -> 0 | R15: =($G15<=R$5)*($J15/12)*(1+$H15)^(ROUNDUP(MAX(R$5-$G15+1,0)/12,0)-1) -> 0 | S15: =($G15<=S$5)*($J15/12)*(1+$H15)^(ROUNDUP(MAX(S$5-$G15+1,0)/12,0)-1) -> 0 | ... EO15: =($G15<=EO$5)*($J15/12)*(1+$H15)^(ROUNDUP(MAX(EO$5-$G15+1,0)/12,0)-1) -> 0
B16: =+B15+100 -> 1100 | C16: [Retail Tenant] | E16: 1 | F16: 0 | G16: 0 | H16: 0.01 | I16: 0 | J16: =+I16*F16 -> 0 | L16: =($G16<=L$5)*($J16/12)*(1+$H16)^(ROUNDUP(MAX(L$5-$G16+1,0)/12,0)-1) -> 0 | M16: =($G16<=M$5)*($J16/12)*(1+$H16)^(ROUNDUP(MAX(M$5-$G16+1,0)/12,0)-1) -> 0 | N16: =($G16<=N$5)*($J16/12)*(1+$H16)^(ROUNDUP(MAX(N$5-$G16+1,0)/12,0)-1) -> 0 | O16: =($G16<=O$5)*($J16/12)*(1+$H16)^(ROUNDUP(MAX(O$5-$G16+1,0)/12,0)-1) -> 0 | P16: =($G16<=P$5)*($J16/12)*(1+$H16)^(ROUNDUP(MAX(P$5-$G16+1,0)/12,0)-1) -> 0 | Q16: =($G16<=Q$5)*($J16/12)*(1+$H16)^(ROUNDUP(MAX(Q$5-$G16+1,0)/12,0)-1) -> 0 | R16: =($G16<=R$5)*($J16/12)*(1+$H16)^(ROUNDUP(MAX(R$5-$G16+1,0)/12,0)-1) -> 0 | S16: =($G16<=S$5)*($J16/12)*(1+$H16)^(ROUNDUP(MAX(S$5-$G16+1,0)/12,0)-1) -> 0 | ... EO16: =($G16<=EO$5)*($J16/12)*(1+$H16)^(ROUNDUP(MAX(EO$5-$G16+1,0)/12,0)-1) -> 0
B17: =+B16+100 -> 1200 | C17: [Retail Tenant] | E17: 1 | F17: 0 | G17: 0 | H17: 0.01 | I17: 0 | J17: =+I17*F17 -> 0 | L17: =($G17<=L$5)*($J17/12)*(1+$H17)^(ROUNDUP(MAX(L$5-$G17+1,0)/12,0)-1) -> 0 | M17: =($G17<=M$5)*($J17/12)*(1+$H17)^(ROUNDUP(MAX(M$5-$G17+1,0)/12,0)-1) -> 0 | N17: =($G17<=N$5)*($J17/12)*(1+$H17)^(ROUNDUP(MAX(N$5-$G17+1,0)/12,0)-1) -> 0 | O17: =($G17<=O$5)*($J17/12)*(1+$H17)^(ROUNDUP(MAX(O$5-$G17+1,0)/12,0)-1) -> 0 | P17: =($G17<=P$5)*($J17/12)*(1+$H17)^(ROUNDUP(MAX(P$5-$G17+1,0)/12,0)-1) -> 0 | Q17: =($G17<=Q$5)*($J17/12)*(1+$H17)^(ROUNDUP(MAX(Q$5-$G17+1,0)/12,0)-1) -> 0 | R17: =($G17<=R$5)*($J17/12)*(1+$H17)^(ROUNDUP(MAX(R$5-$G17+1,0)/12,0)-1) -> 0 | S17: =($G17<=S$5)*($J17/12)*(1+$H17)^(ROUNDUP(MAX(S$5-$G17+1,0)/12,0)-1) -> 0 | ... EO17: =($G17<=EO$5)*($J17/12)*(1+$H17)^(ROUNDUP(MAX(EO$5-$G17+1,0)/12,0)-1) -> 0
B18: =+B17+100 -> 1300 | C18: [Retail Tenant] | E18: 1 | F18: 0 | G18: 0 | H18: 0.01 | I18: 0 | J18: =+I18*F18 -> 0 | L18: =($G18<=L$5)*($J18/12)*(1+$H18)^(ROUNDUP(MAX(L$5-$G18+1,0)/12,0)-1) -> 0 | M18: =($G18<=M$5)*($J18/12)*(1+$H18)^(ROUNDUP(MAX(M$5-$G18+1,0)/12,0)-1) -> 0 | N18: =($G18<=N$5)*($J18/12)*(1+$H18)^(ROUNDUP(MAX(N$5-$G18+1,0)/12,0)-1) -> 0 | O18: =($G18<=O$5)*($J18/12)*(1+$H18)^(ROUNDUP(MAX(O$5-$G18+1,0)/12,0)-1) -> 0 | P18: =($G18<=P$5)*($J18/12)*(1+$H18)^(ROUNDUP(MAX(P$5-$G18+1,0)/12,0)-1) -> 0 | Q18: =($G18<=Q$5)*($J18/12)*(1+$H18)^(ROUNDUP(MAX(Q$5-$G18+1,0)/12,0)-1) -> 0 | R18: =($G18<=R$5)*($J18/12)*(1+$H18)^(ROUNDUP(MAX(R$5-$G18+1,0)/12,0)-1) -> 0 | S18: =($G18<=S$5)*($J18/12)*(1+$H18)^(ROUNDUP(MAX(S$5-$G18+1,0)/12,0)-1) -> 0 | ... EO18: =($G18<=EO$5)*($J18/12)*(1+$H18)^(ROUNDUP(MAX(EO$5-$G18+1,0)/12,0)-1) -> 0
B19: Total Base Retail Income | E19: =MIN(E6:E18) -> 1 | F19: =SUM(F6:F18) -> 0 | G19: =MIN(G6:G18) -> 0 | H19: =SUMPRODUCT(H6:H18,J6:J18)/J19 -> #DIV/0! | I19: =IFERROR(SUMPRODUCT(I6:I18,F6:F18)/F19,0) -> 0 | J19: =SUM(J6:J18) -> 0 | L19: =SUM(L6:L18) -> 0 | M19: =SUM(M6:M18) -> 0 | N19: =SUM(N6:N18) -> 0 | O19: =SUM(O6:O18) -> 0 | P19: =SUM(P6:P18) -> 0 | Q19: =SUM(Q6:Q18) -> 0 | R19: =SUM(R6:R18) -> 0 | S19: =SUM(S6:S18) -> 0 | ... EO19: =SUM(EO6:EO18) -> 0
K20: Occ. | L20: =IFERROR(SUMIF($E$6:$E$18,"<="&L5,$F$6:$F$18)/$F$19,0) -> 0 | M20: =IFERROR(SUMIF($E$6:$E$18,"<="&M5,$F$6:$F$18)/$F$19,0) -> 0 | N20: =IFERROR(SUMIF($E$6:$E$18,"<="&N5,$F$6:$F$18)/$F$19,0) -> 0 | O20: =IFERROR(SUMIF($E$6:$E$18,"<="&O5,$F$6:$F$18)/$F$19,0) -> 0 | P20: =IFERROR(SUMIF($E$6:$E$18,"<="&P5,$F$6:$F$18)/$F$19,0) -> 0 | Q20: =IFERROR(SUMIF($E$6:$E$18,"<="&Q5,$F$6:$F$18)/$F$19,0) -> 0 | R20: =IFERROR(SUMIF($E$6:$E$18,"<="&R5,$F$6:$F$18)/$F$19,0) -> 0 | S20: =IFERROR(SUMIF($E$6:$E$18,"<="&S5,$F$6:$F$18)/$F$19,0) -> 0 | ... EO20: =IFERROR(SUMIF($E$6:$E$18,"<="&EO5,$F$6:$F$18)/$F$19,0) -> 0
B21: Recovery Income
B22: =+B5 -> Suite | C22: =+C5 -> Tenant | F22: Recovery Start | H22: Pro Rata Share | I22: Rec. / SF / Yr. | J22: Annual Recovery
B23: =+B6 -> 100 | C23: =+C6 -> Commercial Tenant | F23: 1 | H23: =IFERROR(F6/$F$19,0) -> 0 | I23: =IFERROR(J23/F6,0) -> 0 | J23: =+H23*$J$47 -> 0 | L23: =IFERROR((L$5>=$F23)*$H23*L$47,0) -> 0 | M23: =IFERROR((M$5>=$F23)*$H23*M$47,0) -> 0 | N23: =IFERROR((N$5>=$F23)*$H23*N$47,0) -> 0 | O23: =IFERROR((O$5>=$F23)*$H23*O$47,0) -> 0 | P23: =IFERROR((P$5>=$F23)*$H23*P$47,0) -> 0 | Q23: =IFERROR((Q$5>=$F23)*$H23*Q$47,0) -> 0 | R23: =IFERROR((R$5>=$F23)*$H23*R$47,0) -> 0 | S23: =IFERROR((S$5>=$F23)*$H23*S$47,0) -> 0 | ... EO23: =IFERROR((EO$5>=$F23)*$H23*EO$47,0) -> 0
B24: =+B7 -> 200 | C24: =+C7 -> [Retail Tenant] | F24: 24 | H24: =IFERROR(F7/$F$19,0) -> 0 | I24: =IFERROR(J24/F7,0) -> 0 | J24: =+H24*$J$47 -> 0 | L24: =IFERROR((L$5>=$F24)*$H24*L$47,0) -> 0 | M24: =IFERROR((M$5>=$F24)*$H24*M$47,0) -> 0 | N24: =IFERROR((N$5>=$F24)*$H24*N$47,0) -> 0 | O24: =IFERROR((O$5>=$F24)*$H24*O$47,0) -> 0 | P24: =IFERROR((P$5>=$F24)*$H24*P$47,0) -> 0 | Q24: =IFERROR((Q$5>=$F24)*$H24*Q$47,0) -> 0 | R24: =IFERROR((R$5>=$F24)*$H24*R$47,0) -> 0 | S24: =IFERROR((S$5>=$F24)*$H24*S$47,0) -> 0 | ... EO24: =IFERROR((EO$5>=$F24)*$H24*EO$47,0) -> 0
B25: =+B8 -> 300 | C25: =+C8 -> [Retail Tenant] | F25: 1 | H25: =IFERROR(F8/$F$19,0) -> 0 | I25: =IFERROR(J25/F8,0) -> 0 | J25: =+H25*$J$47 -> 0 | L25: =IFERROR((L$5>=$F25)*$H25*L$47,0) -> 0 | M25: =IFERROR((M$5>=$F25)*$H25*M$47,0) -> 0 | N25: =IFERROR((N$5>=$F25)*$H25*N$47,0) -> 0 | O25: =IFERROR((O$5>=$F25)*$H25*O$47,0) -> 0 | P25: =IFERROR((P$5>=$F25)*$H25*P$47,0) -> 0 | Q25: =IFERROR((Q$5>=$F25)*$H25*Q$47,0) -> 0 | R25: =IFERROR((R$5>=$F25)*$H25*R$47,0) -> 0 | S25: =IFERROR((S$5>=$F25)*$H25*S$47,0) -> 0 | ... EO25: =IFERROR((EO$5>=$F25)*$H25*EO$47,0) -> 0
B26: =+B9 -> 400 | C26: =+C9 -> [Retail Tenant] | F26: 1 | H26: =IFERROR(F9/$F$19,0) -> 0 | I26: =IFERROR(J26/F9,0) -> 0 | J26: =+H26*$J$47 -> 0 | L26: =IFERROR((L$5>=$F26)*$H26*L$47,0) -> 0 | M26: =IFERROR((M$5>=$F26)*$H26*M$47,0) -> 0 | N26: =IFERROR((N$5>=$F26)*$H26*N$47,0) -> 0 | O26: =IFERROR((O$5>=$F26)*$H26*O$47,0) -> 0 | P26: =IFERROR((P$5>=$F26)*$H26*P$47,0) -> 0 | Q26: =IFERROR((Q$5>=$F26)*$H26*Q$47,0) -> 0 | R26: =IFERROR((R$5>=$F26)*$H26*R$47,0) -> 0 | S26: =IFERROR((S$5>=$F26)*$H26*S$47,0) -> 0 | ... EO26: =IFERROR((EO$5>=$F26)*$H26*EO$47,0) -> 0
B27: =+B10 -> 500 | C27: =+C10 -> [Retail Tenant] | F27: 1 | H27: =IFERROR(F10/$F$19,0) -> 0 | I27: =IFERROR(J27/F10,0) -> 0 | J27: =+H27*$J$47 -> 0 | L27: =IFERROR((L$5>=$F27)*$H27*L$47,0) -> 0 | M27: =IFERROR((M$5>=$F27)*$H27*M$47,0) -> 0 | N27: =IFERROR((N$5>=$F27)*$H27*N$47,0) -> 0 | O27: =IFERROR((O$5>=$F27)*$H27*O$47,0) -> 0 | P27: =IFERROR((P$5>=$F27)*$H27*P$47,0) -> 0 | Q27: =IFERROR((Q$5>=$F27)*$H27*Q$47,0) -> 0 | R27: =IFERROR((R$5>=$F27)*$H27*R$47,0) -> 0 | S27: =IFERROR((S$5>=$F27)*$H27*S$47,0) -> 0 | ... EO27: =IFERROR((EO$5>=$F27)*$H27*EO$47,0) -> 0
B28: =+B11 -> 600 | C28: =+C11 -> [Retail Tenant] | F28: 1 | H28: =IFERROR(F11/$F$19,0) -> 0 | I28: =IFERROR(J28/F11,0) -> 0 | J28: =+H28*$J$47 -> 0 | L28: =IFERROR((L$5>=$F28)*$H28*L$47,0) -> 0 | M28: =IFERROR((M$5>=$F28)*$H28*M$47,0) -> 0 | N28: =IFERROR((N$5>=$F28)*$H28*N$47,0) -> 0 | O28: =IFERROR((O$5>=$F28)*$H28*O$47,0) -> 0 | P28: =IFERROR((P$5>=$F28)*$H28*P$47,0) -> 0 | Q28: =IFERROR((Q$5>=$F28)*$H28*Q$47,0) -> 0 | R28: =IFERROR((R$5>=$F28)*$H28*R$47,0) -> 0 | S28: =IFERROR((S$5>=$F28)*$H28*S$47,0) -> 0 | ... EO28: =IFERROR((EO$5>=$F28)*$H28*EO$47,0) -> 0
B29: =+B12 -> 700 | C29: =+C12 -> [Retail Tenant] | F29: 24 | H29: =IFERROR(F12/$F$19,0) -> 0 | I29: =IFERROR(J29/F12,0) -> 0 | J29: =+H29*$J$47 -> 0 | L29: =IFERROR((L$5>=$F29)*$H29*L$47,0) -> 0 | M29: =IFERROR((M$5>=$F29)*$H29*M$47,0) -> 0 | N29: =IFERROR((N$5>=$F29)*$H29*N$47,0) -> 0 | O29: =IFERROR((O$5>=$F29)*$H29*O$47,0) -> 0 | P29: =IFERROR((P$5>=$F29)*$H29*P$47,0) -> 0 | Q29: =IFERROR((Q$5>=$F29)*$H29*Q$47,0) -> 0 | R29: =IFERROR((R$5>=$F29)*$H29*R$47,0) -> 0 | S29: =IFERROR((S$5>=$F29)*$H29*S$47,0) -> 0 | ... EO29: =IFERROR((EO$5>=$F29)*$H29*EO$47,0) -> 0
B30: =+B13 -> 800 | C30: =+C13 -> [Retail Tenant] | F30: 36 | H30: =IFERROR(F13/$F$19,0) -> 0 | I30: =IFERROR(J30/F13,0) -> 0 | J30: =+H30*$J$47 -> 0 | L30: =IFERROR((L$5>=$F30)*$H30*L$47,0) -> 0 | M30: =IFERROR((M$5>=$F30)*$H30*M$47,0) -> 0 | N30: =IFERROR((N$5>=$F30)*$H30*N$47,0) -> 0 | O30: =IFERROR((O$5>=$F30)*$H30*O$47,0) -> 0 | P30: =IFERROR((P$5>=$F30)*$H30*P$47,0) -> 0 | Q30: =IFERROR((Q$5>=$F30)*$H30*Q$47,0) -> 0 | R30: =IFERROR((R$5>=$F30)*$H30*R$47,0) -> 0 | S30: =IFERROR((S$5>=$F30)*$H30*S$47,0) -> 0 | ... EO30: =IFERROR((EO$5>=$F30)*$H30*EO$47,0) -> 0
B31: =+B14 -> 900 | C31: =+C14 -> [Retail Tenant] | F31: 36 | H31: =IFERROR(F14/$F$19,0) -> 0 | I31: =IFERROR(J31/F14,0) -> 0 | J31: =+H31*$J$47 -> 0 | L31: =IFERROR((L$5>=$F31)*$H31*L$47,0) -> 0 | M31: =IFERROR((M$5>=$F31)*$H31*M$47,0) -> 0 | N31: =IFERROR((N$5>=$F31)*$H31*N$47,0) -> 0 | O31: =IFERROR((O$5>=$F31)*$H31*O$47,0) -> 0 | P31: =IFERROR((P$5>=$F31)*$H31*P$47,0) -> 0 | Q31: =IFERROR((Q$5>=$F31)*$H31*Q$47,0) -> 0 | R31: =IFERROR((R$5>=$F31)*$H31*R$47,0) -> 0 | S31: =IFERROR((S$5>=$F31)*$H31*S$47,0) -> 0 | ... EO31: =IFERROR((EO$5>=$F31)*$H31*EO$47,0) -> 0
B32: =+B15 -> 1000 | C32: =+C15 -> [Retail Tenant] | F32: 1 | H32: =IFERROR(F15/$F$19,0) -> 0 | I32: =IFERROR(J32/F15,0) -> 0 | J32: =+H32*$J$47 -> 0 | L32: =IFERROR((L$5>=$F32)*$H32*L$47,0) -> 0 | M32: =IFERROR((M$5>=$F32)*$H32*M$47,0) -> 0 | N32: =IFERROR((N$5>=$F32)*$H32*N$47,0) -> 0 | O32: =IFERROR((O$5>=$F32)*$H32*O$47,0) -> 0 | P32: =IFERROR((P$5>=$F32)*$H32*P$47,0) -> 0 | Q32: =IFERROR((Q$5>=$F32)*$H32*Q$47,0) -> 0 | R32: =IFERROR((R$5>=$F32)*$H32*R$47,0) -> 0 | S32: =IFERROR((S$5>=$F32)*$H32*S$47,0) -> 0 | ... EO32: =IFERROR((EO$5>=$F32)*$H32*EO$47,0) -> 0
B33: =+B16 -> 1100 | C33: =+C16 -> [Retail Tenant] | F33: 1 | H33: =IFERROR(F16/$F$19,0) -> 0 | I33: =IFERROR(J33/F16,0) -> 0 | J33: =+H33*$J$47 -> 0 | L33: =IFERROR((L$5>=$F33)*$H33*L$47,0) -> 0 | M33: =IFERROR((M$5>=$F33)*$H33*M$47,0) -> 0 | N33: =IFERROR((N$5>=$F33)*$H33*N$47,0) -> 0 | O33: =IFERROR((O$5>=$F33)*$H33*O$47,0) -> 0 | P33: =IFERROR((P$5>=$F33)*$H33*P$47,0) -> 0 | Q33: =IFERROR((Q$5>=$F33)*$H33*Q$47,0) -> 0 | R33: =IFERROR((R$5>=$F33)*$H33*R$47,0) -> 0 | S33: =IFERROR((S$5>=$F33)*$H33*S$47,0) -> 0 | ... EO33: =IFERROR((EO$5>=$F33)*$H33*EO$47,0) -> 0
B34: =+B17 -> 1200 | C34: =+C17 -> [Retail Tenant] | F34: 1 | H34: =IFERROR(F17/$F$19,0) -> 0 | I34: =IFERROR(J34/F17,0) -> 0 | J34: =+H34*$J$47 -> 0 | L34: =IFERROR((L$5>=$F34)*$H34*L$47,0) -> 0 | M34: =IFERROR((M$5>=$F34)*$H34*M$47,0) -> 0 | N34: =IFERROR((N$5>=$F34)*$H34*N$47,0) -> 0 | O34: =IFERROR((O$5>=$F34)*$H34*O$47,0) -> 0 | P34: =IFERROR((P$5>=$F34)*$H34*P$47,0) -> 0 | Q34: =IFERROR((Q$5>=$F34)*$H34*Q$47,0) -> 0 | R34: =IFERROR((R$5>=$F34)*$H34*R$47,0) -> 0 | S34: =IFERROR((S$5>=$F34)*$H34*S$47,0) -> 0 | ... EO34: =IFERROR((EO$5>=$F34)*$H34*EO$47,0) -> 0
B35: =+B18 -> 1300 | C35: =+C18 -> [Retail Tenant] | F35: 1 | H35: =IFERROR(F18/$F$19,0) -> 0 | I35: =IFERROR(J35/F18,0) -> 0 | J35: =+H35*$J$47 -> 0 | L35: =IFERROR((L$5>=$F35)*$H35*L$47,0) -> 0 | M35: =IFERROR((M$5>=$F35)*$H35*M$47,0) -> 0 | N35: =IFERROR((N$5>=$F35)*$H35*N$47,0) -> 0 | O35: =IFERROR((O$5>=$F35)*$H35*O$47,0) -> 0 | P35: =IFERROR((P$5>=$F35)*$H35*P$47,0) -> 0 | Q35: =IFERROR((Q$5>=$F35)*$H35*Q$47,0) -> 0 | R35: =IFERROR((R$5>=$F35)*$H35*R$47,0) -> 0 | S35: =IFERROR((S$5>=$F35)*$H35*S$47,0) -> 0 | ... EO35: =IFERROR((EO$5>=$F35)*$H35*EO$47,0) -> 0
B36: Total Recovery Income | F36: =MIN(F23:F35) -> 1 | I36: =IFERROR(J36/F19,0) -> 0 | J36: =SUM(J23:J35) -> 0 | L36: =SUM(L23:L35) -> 0 | M36: =SUM(M23:M35) -> 0 | N36: =SUM(N23:N35) -> 0 | O36: =SUM(O23:O35) -> 0 | P36: =SUM(P23:P35) -> 0 | Q36: =SUM(Q23:Q35) -> 0 | R36: =SUM(R23:R35) -> 0 | S36: =SUM(S23:S35) -> 0 | ... EO36: =SUM(EO23:EO35) -> 0
B38: Gross Potential Retail Income | I38: =IFERROR(J38/F19,0) -> 0 | J38: =+J36+J19 -> 0 | L38: =+L36+L19 -> 0 | M38: =+M36+M19 -> 0 | N38: =+N36+N19 -> 0 | O38: =+O36+O19 -> 0 | P38: =+P36+P19 -> 0 | Q38: =+Q36+Q19 -> 0 | R38: =+R36+R19 -> 0 | S38: =+S36+S19 -> 0 | ... EO38: =+EO36+EO19 -> 0
B39: Less: Vacancy and Bad Debt | G39: 0.05 | I39: =IFERROR(J39/$F$19,0) -> 0 | J39: =+SUM(J36,J19)*G39 -> 0 | L39: =-$G$39*L38 -> 0 | M39: =-$G$39*M38 -> 0 | N39: =-$G$39*N38 -> 0 | O39: =-$G$39*O38 -> 0 | P39: =-$G$39*P38 -> 0 | Q39: =-$G$39*Q38 -> 0 | R39: =-$G$39*R38 -> 0 | S39: =-$G$39*S38 -> 0 | ... EO39: =-$G$39*EO38 -> 0
B40: Gross Potential Retail Income | I40: =IFERROR(J40/F19,0) -> 0 | J40: =+J38-J39 -> 0 | L40: =SUM(L38:L39) -> 0 | M40: =SUM(M38:M39) -> 0 | N40: =SUM(N38:N39) -> 0 | O40: =SUM(O38:O39) -> 0 | P40: =SUM(P38:P39) -> 0 | Q40: =SUM(Q38:Q39) -> 0 | R40: =SUM(R38:R39) -> 0 | S40: =SUM(S38:S39) -> 0 | ... EO40: =SUM(EO38:EO39) -> 0
B42: Retail Operating Expenses | G42: Expense Growth | I42: Per SF / Yr. | J42: Annual
B43: CAM | G43: =+Assumptions!$E$137 -> 0.02 | I43: 0 | J43: =+$F$19*I43 -> 0 | L43: =IFERROR($J43/12*L$20*(1+$G43)^(ROUNDUP(L$5/12,0)-1),0) -> 0 | M43: =IFERROR($J43/12*M$20*(1+$G43)^(ROUNDUP(M$5/12,0)-1),0) -> 0 | N43: =IFERROR($J43/12*N$20*(1+$G43)^(ROUNDUP(N$5/12,0)-1),0) -> 0 | O43: =IFERROR($J43/12*O$20*(1+$G43)^(ROUNDUP(O$5/12,0)-1),0) -> 0 | P43: =IFERROR($J43/12*P$20*(1+$G43)^(ROUNDUP(P$5/12,0)-1),0) -> 0 | Q43: =IFERROR($J43/12*Q$20*(1+$G43)^(ROUNDUP(Q$5/12,0)-1),0) -> 0 | R43: =IFERROR($J43/12*R$20*(1+$G43)^(ROUNDUP(R$5/12,0)-1),0) -> 0 | S43: =IFERROR($J43/12*S$20*(1+$G43)^(ROUNDUP(S$5/12,0)-1),0) -> 0 | ... EO43: =IFERROR($J43/12*EO$20*(1+$G43)^(ROUNDUP(EO$5/12,0)-1),0) -> 0
B44: Management Fee | G44: =+Assumptions!$E$137 -> 0.02 | I44: 0 | J44: =+$F$19*I44 -> 0 | L44: =IFERROR($J44/12*L$20*(1+$G44)^(ROUNDUP(L$5/12,0)-1),0) -> 0 | M44: =IFERROR($J44/12*M$20*(1+$G44)^(ROUNDUP(M$5/12,0)-1),0) -> 0 | N44: =IFERROR($J44/12*N$20*(1+$G44)^(ROUNDUP(N$5/12,0)-1),0) -> 0 | O44: =IFERROR($J44/12*O$20*(1+$G44)^(ROUNDUP(O$5/12,0)-1),0) -> 0 | P44: =IFERROR($J44/12*P$20*(1+$G44)^(ROUNDUP(P$5/12,0)-1),0) -> 0 | Q44: =IFERROR($J44/12*Q$20*(1+$G44)^(ROUNDUP(Q$5/12,0)-1),0) -> 0 | R44: =IFERROR($J44/12*R$20*(1+$G44)^(ROUNDUP(R$5/12,0)-1),0) -> 0 | S44: =IFERROR($J44/12*S$20*(1+$G44)^(ROUNDUP(S$5/12,0)-1),0) -> 0 | ... EO44: =IFERROR($J44/12*EO$20*(1+$G44)^(ROUNDUP(EO$5/12,0)-1),0) -> 0
B45: Insurance | G45: =+Assumptions!$E$137 -> 0.02 | I45: 0 | J45: =+$F$19*I45 -> 0 | L45: =IFERROR($J45/12*L$20*(1+$G45)^(ROUNDUP(L$5/12,0)-1),0) -> 0 | M45: =IFERROR($J45/12*M$20*(1+$G45)^(ROUNDUP(M$5/12,0)-1),0) -> 0 | N45: =IFERROR($J45/12*N$20*(1+$G45)^(ROUNDUP(N$5/12,0)-1),0) -> 0 | O45: =IFERROR($J45/12*O$20*(1+$G45)^(ROUNDUP(O$5/12,0)-1),0) -> 0 | P45: =IFERROR($J45/12*P$20*(1+$G45)^(ROUNDUP(P$5/12,0)-1),0) -> 0 | Q45: =IFERROR($J45/12*Q$20*(1+$G45)^(ROUNDUP(Q$5/12,0)-1),0) -> 0 | R45: =IFERROR($J45/12*R$20*(1+$G45)^(ROUNDUP(R$5/12,0)-1),0) -> 0 | S45: =IFERROR($J45/12*S$20*(1+$G45)^(ROUNDUP(S$5/12,0)-1),0) -> 0 | ... EO45: =IFERROR($J45/12*EO$20*(1+$G45)^(ROUNDUP(EO$5/12,0)-1),0) -> 0
B46: Property Taxes | G46: =+Assumptions!$E$137 -> 0.02 | I46: 0 | J46: =+$F$19*I46 -> 0 | L46: =IFERROR($J46/12*L$20*(1+$G46)^(ROUNDUP(L$5/12,0)-1),0) -> 0 | M46: =IFERROR($J46/12*M$20*(1+$G46)^(ROUNDUP(M$5/12,0)-1),0) -> 0 | N46: =IFERROR($J46/12*N$20*(1+$G46)^(ROUNDUP(N$5/12,0)-1),0) -> 0 | O46: =IFERROR($J46/12*O$20*(1+$G46)^(ROUNDUP(O$5/12,0)-1),0) -> 0 | P46: =IFERROR($J46/12*P$20*(1+$G46)^(ROUNDUP(P$5/12,0)-1),0) -> 0 | Q46: =IFERROR($J46/12*Q$20*(1+$G46)^(ROUNDUP(Q$5/12,0)-1),0) -> 0 | R46: =IFERROR($J46/12*R$20*(1+$G46)^(ROUNDUP(R$5/12,0)-1),0) -> 0 | S46: =IFERROR($J46/12*S$20*(1+$G46)^(ROUNDUP(S$5/12,0)-1),0) -> 0 | ... EO46: =IFERROR($J46/12*EO$20*(1+$G46)^(ROUNDUP(EO$5/12,0)-1),0) -> 0
B47: Total Retail Operating Expenses | I47: =IFERROR(J47/F19,0) -> 0 | J47: =SUM(J43:J46) -> 0 | L47: =SUM(L43:L46) -> 0 | M47: =SUM(M43:M46) -> 0 | N47: =SUM(N43:N46) -> 0 | O47: =SUM(O43:O46) -> 0 | P47: =SUM(P43:P46) -> 0 | Q47: =SUM(Q43:Q46) -> 0 | R47: =SUM(R43:R46) -> 0 | S47: =SUM(S43:S46) -> 0 | ... EO47: =SUM(EO43:EO46) -> 0
B49: Effective Gross Retail Income | I49: =IFERROR(J49/$F$19,0) -> 0 | J49: =+SUM(J19,J36)-SUM(J39,J47) -> 0 | L49: =+L40-L47 -> 0 | M49: =+M40-M47 -> 0 | N49: =+N40-N47 -> 0 | O49: =+O40-O47 -> 0 | P49: =+P40-P47 -> 0 | Q49: =+Q40-Q47 -> 0 | R49: =+R40-R47 -> 0 | S49: =+S40-S47 -> 0 | ... EO49: =+EO40-EO47 -> 0
B51: Leasing Assumptions | D51: New Lease | E51: Renewal Lease | I51: New Lease | J51: Renewal Lease
B52: Renewal Probability | D52: =1-E52 -> 0.3 | E52: 0.7 | G52: Tenant Improvements | I52: =+$F$19*D52*D54 -> 0 | J52: =+$F$19*E52*E54 -> 0
B53: Retail Rent | D53: 25 | E53: 15 | G53: Leasing Commissions | I53: =+D52*$F$19*D53*D56*D55 -> 0 | J53: =+E52*$F$19*E53*E56*E55 -> 0
B54: TI's | D54: 20 | E54: 5 | G54: Total Leasing Costs | I54: =SUM(I52:I53) -> 0 | J54: =SUM(J52:J53) -> 0
B55: Leasing Commissions | D55: 0.07 | E55: 0.04 | G55: Annualized Leasing Costs | I55: =+I54/D56 -> 0 | J55: =+J54/E56 -> 0
B56: Lease Term | D56: 7 | E56: 5
G57: Total Leasing Cost Reserves | I57: =IFERROR(J57/F19,0) -> 0 | J57: =+J55+I55 -> 0

Sheet Closing Costs
B4: Closing Costs | G4: Beg. Mo. | H4: End. Mo. | J4: =+Model!G4 -> 0 | K4: =+Model!H4 -> 1 | L4: =+Model!I4 -> 2 | M4: =+Model!J4 -> 3 | N4: =+Model!K4 -> 4 | O4: =+Model!L4 -> 5 | P4: =+Model!M4 -> 6 | Q4: =+Model!N4 -> 7 | ... EL4: =+Model!EI4 -> 132
B5: Acquisition Fee | D5: 0.02 | E5: =+Assumptions!$G$23*D5 -> 300000 | G5: 0 | H5: 0 | J5: =IF(AND($G5=J$4,$H5=J$4),$E5,IF($G5>J$4,0,IF($H5<J$4,0,$E5/($H5-$G5+1)))) -> 300000 | K5: =IF(AND($G5=K$4,$H5=K$4),$E5,IF($G5>K$4,0,IF($H5<K$4,0,$E5/($H5-$G5+1)))) -> 0 | L5: =IF(AND($G5=L$4,$H5=L$4),$E5,IF($G5>L$4,0,IF($H5<L$4,0,$E5/($H5-$G5+1)))) -> 0 | M5: =IF(AND($G5=M$4,$H5=M$4),$E5,IF($G5>M$4,0,IF($H5<M$4,0,$E5/($H5-$G5+1)))) -> 0 | N5: =IF(AND($G5=N$4,$H5=N$4),$E5,IF($G5>N$4,0,IF($H5<N$4,0,$E5/($H5-$G5+1)))) -> 0 | O5: =IF(AND($G5=O$4,$H5=O$4),$E5,IF($G5>O$4,0,IF($H5<O$4,0,$E5/($H5-$G5+1)))) -> 0 | P5: =IF(AND($G5=P$4,$H5=P$4),$E5,IF($G5>P$4,0,IF($H5<P$4,0,$E5/($H5-$G5+1)))) -> 0 | Q5: =IF(AND($G5=Q$4,$H5=Q$4),$E5,IF($G5>Q$4,0,IF($H5<Q$4,0,$E5/($H5-$G5+1)))) -> 0 | ... EL5: =IF(AND($G5=EL$4,$H5=EL$4),$E5,IF($G5>EL$4,0,IF($H5<EL$4,0,$E5/($H5-$G5+1)))) -> 0
B6: Financing Fees: Acquisition Loan | D6: =+Assumptions!L28 -> 0.02 | E6: =+D6*Assumptions!G31 -> 225000 | G6: =+Assumptions!$G$28 -> 0 | H6: =+Assumptions!$G$28 -> 0 | J6: =IF(AND($G6=J$4,$H6=J$4),$E6,IF($G6>J$4,0,IF($H6<J$4,0,$E6/($H6-$G6+1)))) -> 225000 | K6: =IF(AND($G6=K$4,$H6=K$4),$E6,IF($G6>K$4,0,IF($H6<K$4,0,$E6/($H6-$G6+1)))) -> 0 | L6: =IF(AND($G6=L$4,$H6=L$4),$E6,IF($G6>L$4,0,IF($H6<L$4,0,$E6/($H6-$G6+1)))) -> 0 | M6: =IF(AND($G6=M$4,$H6=M$4),$E6,IF($G6>M$4,0,IF($H6<M$4,0,$E6/($H6-$G6+1)))) -> 0 | N6: =IF(AND($G6=N$4,$H6=N$4),$E6,IF($G6>N$4,0,IF($H6<N$4,0,$E6/($H6-$G6+1)))) -> 0 | O6: =IF(AND($G6=O$4,$H6=O$4),$E6,IF($G6>O$4,0,IF($H6<O$4,0,$E6/($H6-$G6+1)))) -> 0 | P6: =IF(AND($G6=P$4,$H6=P$4),$E6,IF($G6>P$4,0,IF($H6<P$4,0,$E6/($H6-$G6+1)))) -> 0 | Q6: =IF(AND($G6=Q$4,$H6=Q$4),$E6,IF($G6>Q$4,0,IF($H6<Q$4,0,$E6/($H6-$G6+1)))) -> 0 | ... EL6: =IF(AND($G6=EL$4,$H6=EL$4),$E6,IF($G6>EL$4,0,IF($H6<EL$4,0,$E6/($H6-$G6+1)))) -> 0
B7: Title Insurance | D7: 0.0035 | E7: =+Assumptions!$G$23*D7 -> 52500 | G7: 0 | H7: 0 | J7: =IF(AND($G7=J$4,$H7=J$4),$E7,IF($G7>J$4,0,IF($H7<J$4,0,$E7/($H7-$G7+1)))) -> 52500 | K7: =IF(AND($G7=K$4,$H7=K$4),$E7,IF($G7>K$4,0,IF($H7<K$4,0,$E7/($H7-$G7+1)))) -> 0 | L7: =IF(AND($G7=L$4,$H7=L$4),$E7,IF($G7>L$4,0,IF($H7<L$4,0,$E7/($H7-$G7+1)))) -> 0 | M7: =IF(AND($G7=M$4,$H7=M$4),$E7,IF($G7>M$4,0,IF($H7<M$4,0,$E7/($H7-$G7+1)))) -> 0 | N7: =IF(AND($G7=N$4,$H7=N$4),$E7,IF($G7>N$4,0,IF($H7<N$4,0,$E7/($H7-$G7+1)))) -> 0 | O7: =IF(AND($G7=O$4,$H7=O$4),$E7,IF($G7>O$4,0,IF($H7<O$4,0,$E7/($H7-$G7+1)))) -> 0 | P7: =IF(AND($G7=P$4,$H7=P$4),$E7,IF($G7>P$4,0,IF($H7<P$4,0,$E7/($H7-$G7+1)))) -> 0 | Q7: =IF(AND($G7=Q$4,$H7=Q$4),$E7,IF($G7>Q$4,0,IF($H7<Q$4,0,$E7/($H7-$G7+1)))) -> 0 | ... EL7: =IF(AND($G7=EL$4,$H7=EL$4),$E7,IF($G7>EL$4,0,IF($H7<EL$4,0,$E7/($H7-$G7+1)))) -> 0
B8: Broker-Dealer Fee | D8: 0.015 | E8: =6000000*D8+10000 -> 100000 | G8: 0 | H8: 0 | J8: =IF(AND($G8=J$4,$H8=J$4),$E8,IF($G8>J$4,0,IF($H8<J$4,0,$E8/($H8-$G8+1)))) -> 100000 | K8: =IF(AND($G8=K$4,$H8=K$4),$E8,IF($G8>K$4,0,IF($H8<K$4,0,$E8/($H8-$G8+1)))) -> 0 | L8: =IF(AND($G8=L$4,$H8=L$4),$E8,IF($G8>L$4,0,IF($H8<L$4,0,$E8/($H8-$G8+1)))) -> 0 | M8: =IF(AND($G8=M$4,$H8=M$4),$E8,IF($G8>M$4,0,IF($H8<M$4,0,$E8/($H8-$G8+1)))) -> 0 | N8: =IF(AND($G8=N$4,$H8=N$4),$E8,IF($G8>N$4,0,IF($H8<N$4,0,$E8/($H8-$G8+1)))) -> 0 | O8: =IF(AND($G8=O$4,$H8=O$4),$E8,IF($G8>O$4,0,IF($H8<O$4,0,$E8/($H8-$G8+1)))) -> 0 | P8: =IF(AND($G8=P$4,$H8=P$4),$E8,IF($G8>P$4,0,IF($H8<P$4,0,$E8/($H8-$G8+1)))) -> 0 | Q8: =IF(AND($G8=Q$4,$H8=Q$4),$E8,IF($G8>Q$4,0,IF($H8<Q$4,0,$E8/($H8-$G8+1)))) -> 0 | ... EL8: =IF(AND($G8=EL$4,$H8=EL$4),$E8,IF($G8>EL$4,0,IF($H8<EL$4,0,$E8/($H8-$G8+1)))) -> 0
B9: Appraisal | E9: 5000 | G9: 0 | H9: 0 | J9: =IF(AND($G9=J$4,$H9=J$4),$E9,IF($G9>J$4,0,IF($H9<J$4,0,$E9/($H9-$G9+1)))) -> 5000 | K9: =IF(AND($G9=K$4,$H9=K$4),$E9,IF($G9>K$4,0,IF($H9<K$4,0,$E9/($H9-$G9+1)))) -> 0 | L9: =IF(AND($G9=L$4,$H9=L$4),$E9,IF($G9>L$4,0,IF($H9<L$4,0,$E9/($H9-$G9+1)))) -> 0 | M9: =IF(AND($G9=M$4,$H9=M$4),$E9,IF($G9>M$4,0,IF($H9<M$4,0,$E9/($H9-$G9+1)))) -> 0 | N9: =IF(AND($G9=N$4,$H9=N$4),$E9,IF($G9>N$4,0,IF($H9<N$4,0,$E9/($H9-$G9+1)))) -> 0 | O9: =IF(AND($G9=O$4,$H9=O$4),$E9,IF($G9>O$4,0,IF($H9<O$4,0,$E9/($H9-$G9+1)))) -> 0 | P9: =IF(AND($G9=P$4,$H9=P$4),$E9,IF($G9>P$4,0,IF($H9<P$4,0,$E9/($H9-$G9+1)))) -> 0 | Q9: =IF(AND($G9=Q$4,$H9=Q$4),$E9,IF($G9>Q$4,0,IF($H9<Q$4,0,$E9/($H9-$G9+1)))) -> 0 | ... EL9: =IF(AND($G9=EL$4,$H9=EL$4),$E9,IF($G9>EL$4,0,IF($H9<EL$4,0,$E9/($H9-$G9+1)))) -> 0
B10: Inspection | E10: 3000 | G10: 0 | H10: 0 | J10: =IF(AND($G10=J$4,$H10=J$4),$E10,IF($G10>J$4,0,IF($H10<J$4,0,$E10/($H10-$G10+1)))) -> 3000 | K10: =IF(AND($G10=K$4,$H10=K$4),$E10,IF($G10>K$4,0,IF($H10<K$4,0,$E10/($H10-$G10+1)))) -> 0 | L10: =IF(AND($G10=L$4,$H10=L$4),$E10,IF($G10>L$4,0,IF($H10<L$4,0,$E10/($H10-$G10+1)))) -> 0 | M10: =IF(AND($G10=M$4,$H10=M$4),$E10,IF($G10>M$4,0,IF($H10<M$4,0,$E10/($H10-$G10+1)))) -> 0 | N10: =IF(AND($G10=N$4,$H10=N$4),$E10,IF($G10>N$4,0,IF($H10<N$4,0,$E10/($H10-$G10+1)))) -> 0 | O10: =IF(AND($G10=O$4,$H10=O$4),$E10,IF($G10>O$4,0,IF($H10<O$4,0,$E10/($H10-$G10+1)))) -> 0 | P10: =IF(AND($G10=P$4,$H10=P$4),$E10,IF($G10>P$4,0,IF($H10<P$4,0,$E10/($H10-$G10+1)))) -> 0 | Q10: =IF(AND($G10=Q$4,$H10=Q$4),$E10,IF($G10>Q$4,0,IF($H10<Q$4,0,$E10/($H10-$G10+1)))) -> 0 | ... EL10: =IF(AND($G10=EL$4,$H10=EL$4),$E10,IF($G10>EL$4,0,IF($H10<EL$4,0,$E10/($H10-$G10+1)))) -> 0
B11: Mansion Tax | E11: =+IF(Assumptions!G23>1000000,Assumptions!G23*1%,0) -> 150000 | G11: 0 | H11: 0 | J11: =IF(AND($G11=J$4,$H11=J$4),$E11,IF($G11>J$4,0,IF($H11<J$4,0,$E11/($H11-$G11+1)))) -> 150000 | K11: =IF(AND($G11=K$4,$H11=K$4),$E11,IF($G11>K$4,0,IF($H11<K$4,0,$E11/($H11-$G11+1)))) -> 0 | L11: =IF(AND($G11=L$4,$H11=L$4),$E11,IF($G11>L$4,0,IF($H11<L$4,0,$E11/($H11-$G11+1)))) -> 0 | M11: =IF(AND($G11=M$4,$H11=M$4),$E11,IF($G11>M$4,0,IF($H11<M$4,0,$E11/($H11-$G11+1)))) -> 0 | N11: =IF(AND($G11=N$4,$H11=N$4),$E11,IF($G11>N$4,0,IF($H11<N$4,0,$E11/($H11-$G11+1)))) -> 0 | O11: =IF(AND($G11=O$4,$H11=O$4),$E11,IF($G11>O$4,0,IF($H11<O$4,0,$E11/($H11-$G11+1)))) -> 0 | P11: =IF(AND($G11=P$4,$H11=P$4),$E11,IF($G11>P$4,0,IF($H11<P$4,0,$E11/($H11-$G11+1)))) -> 0 | Q11: =IF(AND($G11=Q$4,$H11=Q$4),$E11,IF($G11>Q$4,0,IF($H11<Q$4,0,$E11/($H11-$G11+1)))) -> 0 | ... EL11: =IF(AND($G11=EL$4,$H11=EL$4),$E11,IF($G11>EL$4,0,IF($H11<EL$4,0,$E11/($H11-$G11+1)))) -> 0
B12: Legal Closing Costs | E12: 5000 | G12: 0 | H12: 0 | J12: =IF(AND($G12=J$4,$H12=J$4),$E12,IF($G12>J$4,0,IF($H12<J$4,0,$E12/($H12-$G12+1)))) -> 5000 | K12: =IF(AND($G12=K$4,$H12=K$4),$E12,IF($G12>K$4,0,IF($H12<K$4,0,$E12/($H12-$G12+1)))) -> 0 | L12: =IF(AND($G12=L$4,$H12=L$4),$E12,IF($G12>L$4,0,IF($H12<L$4,0,$E12/($H12-$G12+1)))) -> 0 | M12: =IF(AND($G12=M$4,$H12=M$4),$E12,IF($G12>M$4,0,IF($H12<M$4,0,$E12/($H12-$G12+1)))) -> 0 | N12: =IF(AND($G12=N$4,$H12=N$4),$E12,IF($G12>N$4,0,IF($H12<N$4,0,$E12/($H12-$G12+1)))) -> 0 | O12: =IF(AND($G12=O$4,$H12=O$4),$E12,IF($G12>O$4,0,IF($H12<O$4,0,$E12/($H12-$G12+1)))) -> 0 | P12: =IF(AND($G12=P$4,$H12=P$4),$E12,IF($G12>P$4,0,IF($H12<P$4,0,$E12/($H12-$G12+1)))) -> 0 | Q12: =IF(AND($G12=Q$4,$H12=Q$4),$E12,IF($G12>Q$4,0,IF($H12<Q$4,0,$E12/($H12-$G12+1)))) -> 0 | ... EL12: =IF(AND($G12=EL$4,$H12=EL$4),$E12,IF($G12>EL$4,0,IF($H12<EL$4,0,$E12/($H12-$G12+1)))) -> 0
B13: Transfer Fees | E13: 750 | G13: 0 | H13: 0 | J13: =IF(AND($G13=J$4,$H13=J$4),$E13,IF($G13>J$4,0,IF($H13<J$4,0,$E13/($H13-$G13+1)))) -> 750 | K13: =IF(AND($G13=K$4,$H13=K$4),$E13,IF($G13>K$4,0,IF($H13<K$4,0,$E13/($H13-$G13+1)))) -> 0 | L13: =IF(AND($G13=L$4,$H13=L$4),$E13,IF($G13>L$4,0,IF($H13<L$4,0,$E13/($H13-$G13+1)))) -> 0 | M13: =IF(AND($G13=M$4,$H13=M$4),$E13,IF($G13>M$4,0,IF($H13<M$4,0,$E13/($H13-$G13+1)))) -> 0 | N13: =IF(AND($G13=N$4,$H13=N$4),$E13,IF($G13>N$4,0,IF($H13<N$4,0,$E13/($H13-$G13+1)))) -> 0 | O13: =IF(AND($G13=O$4,$H13=O$4),$E13,IF($G13>O$4,0,IF($H13<O$4,0,$E13/($H13-$G13+1)))) -> 0 | P13: =IF(AND($G13=P$4,$H13=P$4),$E13,IF($G13>P$4,0,IF($H13<P$4,0,$E13/($H13-$G13+1)))) -> 0 | Q13: =IF(AND($G13=Q$4,$H13=Q$4),$E13,IF($G13>Q$4,0,IF($H13<Q$4,0,$E13/($H13-$G13+1)))) -> 0 | ... EL13: =IF(AND($G13=EL$4,$H13=EL$4),$E13,IF($G13>EL$4,0,IF($H13<EL$4,0,$E13/($H13-$G13+1)))) -> 0
B14: Loan Processing Fees | E14: 1995 | G14: 0 | H14: 0 | J14: =IF(AND($G14=J$4,$H14=J$4),$E14,IF($G14>J$4,0,IF($H14<J$4,0,$E14/($H14-$G14+1)))) -> 1995 | K14: =IF(AND($G14=K$4,$H14=K$4),$E14,IF($G14>K$4,0,IF($H14<K$4,0,$E14/($H14-$G14+1)))) -> 0 | L14: =IF(AND($G14=L$4,$H14=L$4),$E14,IF($G14>L$4,0,IF($H14<L$4,0,$E14/($H14-$G14+1)))) -> 0 | M14: =IF(AND($G14=M$4,$H14=M$4),$E14,IF($G14>M$4,0,IF($H14<M$4,0,$E14/($H14-$G14+1)))) -> 0 | N14: =IF(AND($G14=N$4,$H14=N$4),$E14,IF($G14>N$4,0,IF($H14<N$4,0,$E14/($H14-$G14+1)))) -> 0 | O14: =IF(AND($G14=O$4,$H14=O$4),$E14,IF($G14>O$4,0,IF($H14<O$4,0,$E14/($H14-$G14+1)))) -> 0 | P14: =IF(AND($G14=P$4,$H14=P$4),$E14,IF($G14>P$4,0,IF($H14<P$4,0,$E14/($H14-$G14+1)))) -> 0 | Q14: =IF(AND($G14=Q$4,$H14=Q$4),$E14,IF($G14>Q$4,0,IF($H14<Q$4,0,$E14/($H14-$G14+1)))) -> 0 | ... EL14: =IF(AND($G14=EL$4,$H14=EL$4),$E14,IF($G14>EL$4,0,IF($H14<EL$4,0,$E14/($H14-$G14+1)))) -> 0
B15: Filing and Recording Fees | E15: 500 | G15: 0 | H15: 0 | J15: =IF(AND($G15=J$4,$H15=J$4),$E15,IF($G15>J$4,0,IF($H15<J$4,0,$E15/($H15-$G15+1)))) -> 500 | K15: =IF(AND($G15=K$4,$H15=K$4),$E15,IF($G15>K$4,0,IF($H15<K$4,0,$E15/($H15-$G15+1)))) -> 0 | L15: =IF(AND($G15=L$4,$H15=L$4),$E15,IF($G15>L$4,0,IF($H15<L$4,0,$E15/($H15-$G15+1)))) -> 0 | M15: =IF(AND($G15=M$4,$H15=M$4),$E15,IF($G15>M$4,0,IF($H15<M$4,0,$E15/($H15-$G15+1)))) -> 0 | N15: =IF(AND($G15=N$4,$H15=N$4),$E15,IF($G15>N$4,0,IF($H15<N$4,0,$E15/($H15-$G15+1)))) -> 0 | O15: =IF(AND($G15=O$4,$H15=O$4),$E15,IF($G15>O$4,0,IF($H15<O$4,0,$E15/($H15-$G15+1)))) -> 0 | P15: =IF(AND($G15=P$4,$H15=P$4),$E15,IF($G15>P$4,0,IF($H15<P$4,0,$E15/($H15-$G15+1)))) -> 0 | Q15: =IF(AND($G15=Q$4,$H15=Q$4),$E15,IF($G15>Q$4,0,IF($H15<Q$4,0,$E15/($H15-$G15+1)))) -> 0 | ... EL15: =IF(AND($G15=EL$4,$H15=EL$4),$E15,IF($G15>EL$4,0,IF($H15<EL$4,0,$E15/($H15-$G15+1)))) -> 0
B16: Escrow / Prepaid: Insurance | E16: =+Assumptions!J150 -> 93600 | G16: 0 | H16: 0 | J16: =IF(AND($G16=J$4,$H16=J$4),$E16,IF($G16>J$4,0,IF($H16<J$4,0,$E16/($H16-$G16+1)))) -> 93600 | K16: =IF(AND($G16=K$4,$H16=K$4),$E16,IF($G16>K$4,0,IF($H16<K$4,0,$E16/($H16-$G16+1)))) -> 0 | L16: =IF(AND($G16=L$4,$H16=L$4),$E16,IF($G16>L$4,0,IF($H16<L$4,0,$E16/($H16-$G16+1)))) -> 0 | M16: =IF(AND($G16=M$4,$H16=M$4),$E16,IF($G16>M$4,0,IF($H16<M$4,0,$E16/($H16-$G16+1)))) -> 0 | N16: =IF(AND($G16=N$4,$H16=N$4),$E16,IF($G16>N$4,0,IF($H16<N$4,0,$E16/($H16-$G16+1)))) -> 0 | O16: =IF(AND($G16=O$4,$H16=O$4),$E16,IF($G16>O$4,0,IF($H16<O$4,0,$E16/($H16-$G16+1)))) -> 0 | P16: =IF(AND($G16=P$4,$H16=P$4),$E16,IF($G16>P$4,0,IF($H16<P$4,0,$E16/($H16-$G16+1)))) -> 0 | Q16: =IF(AND($G16=Q$4,$H16=Q$4),$E16,IF($G16>Q$4,0,IF($H16<Q$4,0,$E16/($H16-$G16+1)))) -> 0 | ... EL16: =IF(AND($G16=EL$4,$H16=EL$4),$E16,IF($G16>EL$4,0,IF($H16<EL$4,0,$E16/($H16-$G16+1)))) -> 0
B17: Escrow / Prepaid: Property Taxes | E17: =+Assumptions!J149/4 -> 74406.5 | G17: 0 | H17: 0 | J17: =IF(AND($G17=J$4,$H17=J$4),$E17,IF($G17>J$4,0,IF($H17<J$4,0,$E17/($H17-$G17+1)))) -> 74406.5 | K17: =IF(AND($G17=K$4,$H17=K$4),$E17,IF($G17>K$4,0,IF($H17<K$4,0,$E17/($H17-$G17+1)))) -> 0 | L17: =IF(AND($G17=L$4,$H17=L$4),$E17,IF($G17>L$4,0,IF($H17<L$4,0,$E17/($H17-$G17+1)))) -> 0 | M17: =IF(AND($G17=M$4,$H17=M$4),$E17,IF($G17>M$4,0,IF($H17<M$4,0,$E17/($H17-$G17+1)))) -> 0 | N17: =IF(AND($G17=N$4,$H17=N$4),$E17,IF($G17>N$4,0,IF($H17<N$4,0,$E17/($H17-$G17+1)))) -> 0 | O17: =IF(AND($G17=O$4,$H17=O$4),$E17,IF($G17>O$4,0,IF($H17<O$4,0,$E17/($H17-$G17+1)))) -> 0 | P17: =IF(AND($G17=P$4,$H17=P$4),$E17,IF($G17>P$4,0,IF($H17<P$4,0,$E17/($H17-$G17+1)))) -> 0 | Q17: =IF(AND($G17=Q$4,$H17=Q$4),$E17,IF($G17>Q$4,0,IF($H17<Q$4,0,$E17/($H17-$G17+1)))) -> 0 | ... EL17: =IF(AND($G17=EL$4,$H17=EL$4),$E17,IF($G17>EL$4,0,IF($H17<EL$4,0,$E17/($H17-$G17+1)))) -> 0
B18: Contingency | D18: 0.05 | E18: =+D18*SUM(E5:E17) -> 50587.575 | G18: =+H18 -> 0 | H18: =MAX(H5:H15) -> 0 | J18: =IF(AND($G18=J$4,$H18=J$4),$E18,IF($G18>J$4,0,IF($H18<J$4,0,$E18/($H18-$G18+1)))) -> 50587.575 | K18: =IF(AND($G18=K$4,$H18=K$4),$E18,IF($G18>K$4,0,IF($H18<K$4,0,$E18/($H18-$G18+1)))) -> 0 | L18: =IF(AND($G18=L$4,$H18=L$4),$E18,IF($G18>L$4,0,IF($H18<L$4,0,$E18/($H18-$G18+1)))) -> 0 | M18: =IF(AND($G18=M$4,$H18=M$4),$E18,IF($G18>M$4,0,IF($H18<M$4,0,$E18/($H18-$G18+1)))) -> 0 | N18: =IF(AND($G18=N$4,$H18=N$4),$E18,IF($G18>N$4,0,IF($H18<N$4,0,$E18/($H18-$G18+1)))) -> 0 | O18: =IF(AND($G18=O$4,$H18=O$4),$E18,IF($G18>O$4,0,IF($H18<O$4,0,$E18/($H18-$G18+1)))) -> 0 | P18: =IF(AND($G18=P$4,$H18=P$4),$E18,IF($G18>P$4,0,IF($H18<P$4,0,$E18/($H18-$G18+1)))) -> 0 | Q18: =IF(AND($G18=Q$4,$H18=Q$4),$E18,IF($G18>Q$4,0,IF($H18<Q$4,0,$E18/($H18-$G18+1)))) -> 0 | ... EL18: =IF(AND($G18=EL$4,$H18=EL$4),$E18,IF($G18>EL$4,0,IF($H18<EL$4,0,$E18/($H18-$G18+1)))) -> 0
B19: Total Closing Costs | E19: =SUM(E5:E18) -> 1062339.1 | J19: =SUM(J5:J18) -> 1062339.1 | K19: =SUM(K5:K18) -> 0 | L19: =SUM(L5:L18) -> 0 | M19: =SUM(M5:M18) -> 0 | N19: =SUM(N5:N18) -> 0 | O19: =SUM(O5:O18) -> 0 | P19: =SUM(P5:P18) -> 0 | Q19: =SUM(Q5:Q18) -> 0 | ... EL19: =SUM(EL5:EL18) -> 0

Sheet Legal and Pre-Dev
B4: Legal and Pre-Development Costs | G4: Beg. Mo. | H4: End. Mo. | J4: =+Model!G4 -> 0 | K4: =+Model!H4 -> 1 | L4: =+Model!I4 -> 2 | M4: =+Model!J4 -> 3 | N4: =+Model!K4 -> 4 | O4: =+Model!L4 -> 5 | P4: =+Model!M4 -> 6 | Q4: =+Model!N4 -> 7 | ... EL4: =+Model!EI4 -> 132
B5: Business Formation, Partnership Legal | E5: 15000 | G5: 0 | H5: 0 | J5: =IF(AND($G5=J$4,$H5=J$4),$E5,IF($G5>J$4,0,IF($H5<J$4,0,$E5/($H5-$G5+1)))) -> 15000 | K5: =IF(AND($G5=K$4,$H5=K$4),$E5,IF($G5>K$4,0,IF($H5<K$4,0,$E5/($H5-$G5+1)))) -> 0 | L5: =IF(AND($G5=L$4,$H5=L$4),$E5,IF($G5>L$4,0,IF($H5<L$4,0,$E5/($H5-$G5+1)))) -> 0 | M5: =IF(AND($G5=M$4,$H5=M$4),$E5,IF($G5>M$4,0,IF($H5<M$4,0,$E5/($H5-$G5+1)))) -> 0 | N5: =IF(AND($G5=N$4,$H5=N$4),$E5,IF($G5>N$4,0,IF($H5<N$4,0,$E5/($H5-$G5+1)))) -> 0 | O5: =IF(AND($G5=O$4,$H5=O$4),$E5,IF($G5>O$4,0,IF($H5<O$4,0,$E5/($H5-$G5+1)))) -> 0 | P5: =IF(AND($G5=P$4,$H5=P$4),$E5,IF($G5>P$4,0,IF($H5<P$4,0,$E5/($H5-$G5+1)))) -> 0 | Q5: =IF(AND($G5=Q$4,$H5=Q$4),$E5,IF($G5>Q$4,0,IF($H5<Q$4,0,$E5/($H5-$G5+1)))) -> 0 | ... EL5: =IF(AND($G5=EL$4,$H5=EL$4),$E5,IF($G5>EL$4,0,IF($H5<EL$4,0,$E5/($H5-$G5+1)))) -> 0
B6: Fees, Permits | E6: 500 | G6: 0 | H6: 0 | J6: =IF(AND($G6=J$4,$H6=J$4),$E6,IF($G6>J$4,0,IF($H6<J$4,0,$E6/($H6-$G6+1)))) -> 500 | K6: =IF(AND($G6=K$4,$H6=K$4),$E6,IF($G6>K$4,0,IF($H6<K$4,0,$E6/($H6-$G6+1)))) -> 0 | L6: =IF(AND($G6=L$4,$H6=L$4),$E6,IF($G6>L$4,0,IF($H6<L$4,0,$E6/($H6-$G6+1)))) -> 0 | M6: =IF(AND($G6=M$4,$H6=M$4),$E6,IF($G6>M$4,0,IF($H6<M$4,0,$E6/($H6-$G6+1)))) -> 0 | N6: =IF(AND($G6=N$4,$H6=N$4),$E6,IF($G6>N$4,0,IF($H6<N$4,0,$E6/($H6-$G6+1)))) -> 0 | O6: =IF(AND($G6=O$4,$H6=O$4),$E6,IF($G6>O$4,0,IF($H6<O$4,0,$E6/($H6-$G6+1)))) -> 0 | P6: =IF(AND($G6=P$4,$H6=P$4),$E6,IF($G6>P$4,0,IF($H6<P$4,0,$E6/($H6-$G6+1)))) -> 0 | Q6: =IF(AND($G6=Q$4,$H6=Q$4),$E6,IF($G6>Q$4,0,IF($H6<Q$4,0,$E6/($H6-$G6+1)))) -> 0 | ... EL6: =IF(AND($G6=EL$4,$H6=EL$4),$E6,IF($G6>EL$4,0,IF($H6<EL$4,0,$E6/($H6-$G6+1)))) -> 0
B7: Environmental Testing (Tank Sweep) | E7: 1000 | G7: 0 | H7: 0 | J7: =IF(AND($G7=J$4,$H7=J$4),$E7,IF($G7>J$4,0,IF($H7<J$4,0,$E7/($H7-$G7+1)))) -> 1000 | K7: =IF(AND($G7=K$4,$H7=K$4),$E7,IF($G7>K$4,0,IF($H7<K$4,0,$E7/($H7-$G7+1)))) -> 0 | L7: =IF(AND($G7=L$4,$H7=L$4),$E7,IF($G7>L$4,0,IF($H7<L$4,0,$E7/($H7-$G7+1)))) -> 0 | M7: =IF(AND($G7=M$4,$H7=M$4),$E7,IF($G7>M$4,0,IF($H7<M$4,0,$E7/($H7-$G7+1)))) -> 0 | N7: =IF(AND($G7=N$4,$H7=N$4),$E7,IF($G7>N$4,0,IF($H7<N$4,0,$E7/($H7-$G7+1)))) -> 0 | O7: =IF(AND($G7=O$4,$H7=O$4),$E7,IF($G7>O$4,0,IF($H7<O$4,0,$E7/($H7-$G7+1)))) -> 0 | P7: =IF(AND($G7=P$4,$H7=P$4),$E7,IF($G7>P$4,0,IF($H7<P$4,0,$E7/($H7-$G7+1)))) -> 0 | Q7: =IF(AND($G7=Q$4,$H7=Q$4),$E7,IF($G7>Q$4,0,IF($H7<Q$4,0,$E7/($H7-$G7+1)))) -> 0 | ... EL7: =IF(AND($G7=EL$4,$H7=EL$4),$E7,IF($G7>EL$4,0,IF($H7<EL$4,0,$E7/($H7-$G7+1)))) -> 0
B8: Lender's Legal for Financing | E8: 2500 | G8: 0 | H8: 0 | J8: =IF(AND($G8=J$4,$H8=J$4),$E8,IF($G8>J$4,0,IF($H8<J$4,0,$E8/($H8-$G8+1)))) -> 2500 | K8: =IF(AND($G8=K$4,$H8=K$4),$E8,IF($G8>K$4,0,IF($H8<K$4,0,$E8/($H8-$G8+1)))) -> 0 | L8: =IF(AND($G8=L$4,$H8=L$4),$E8,IF($G8>L$4,0,IF($H8<L$4,0,$E8/($H8-$G8+1)))) -> 0 | M8: =IF(AND($G8=M$4,$H8=M$4),$E8,IF($G8>M$4,0,IF($H8<M$4,0,$E8/($H8-$G8+1)))) -> 0 | N8: =IF(AND($G8=N$4,$H8=N$4),$E8,IF($G8>N$4,0,IF($H8<N$4,0,$E8/($H8-$G8+1)))) -> 0 | O8: =IF(AND($G8=O$4,$H8=O$4),$E8,IF($G8>O$4,0,IF($H8<O$4,0,$E8/($H8-$G8+1)))) -> 0 | P8: =IF(AND($G8=P$4,$H8=P$4),$E8,IF($G8>P$4,0,IF($H8<P$4,0,$E8/($H8-$G8+1)))) -> 0 | Q8: =IF(AND($G8=Q$4,$H8=Q$4),$E8,IF($G8>Q$4,0,IF($H8<Q$4,0,$E8/($H8-$G8+1)))) -> 0 | ... EL8: =IF(AND($G8=EL$4,$H8=EL$4),$E8,IF($G8>EL$4,0,IF($H8<EL$4,0,$E8/($H8-$G8+1)))) -> 0
B9: Borrower's Legal for Financing | E9: 2500 | G9: 0 | H9: 0 | J9: =IF(AND($G9=J$4,$H9=J$4),$E9,IF($G9>J$4,0,IF($H9<J$4,0,$E9/($H9-$G9+1)))) -> 2500 | K9: =IF(AND($G9=K$4,$H9=K$4),$E9,IF($G9>K$4,0,IF($H9<K$4,0,$E9/($H9-$G9+1)))) -> 0 | L9: =IF(AND($G9=L$4,$H9=L$4),$E9,IF($G9>L$4,0,IF($H9<L$4,0,$E9/($H9-$G9+1)))) -> 0 | M9: =IF(AND($G9=M$4,$H9=M$4),$E9,IF($G9>M$4,0,IF($H9<M$4,0,$E9/($H9-$G9+1)))) -> 0 | N9: =IF(AND($G9=N$4,$H9=N$4),$E9,IF($G9>N$4,0,IF($H9<N$4,0,$E9/($H9-$G9+1)))) -> 0 | O9: =IF(AND($G9=O$4,$H9=O$4),$E9,IF($G9>O$4,0,IF($H9<O$4,0,$E9/($H9-$G9+1)))) -> 0 | P9: =IF(AND($G9=P$4,$H9=P$4),$E9,IF($G9>P$4,0,IF($H9<P$4,0,$E9/($H9-$G9+1)))) -> 0 | Q9: =IF(AND($G9=Q$4,$H9=Q$4),$E9,IF($G9>Q$4,0,IF($H9<Q$4,0,$E9/($H9-$G9+1)))) -> 0 | ... EL9: =IF(AND($G9=EL$4,$H9=EL$4),$E9,IF($G9>EL$4,0,IF($H9<EL$4,0,$E9/($H9-$G9+1)))) -> 0
B10: Cost Segregation Study | E10: 7000 | G10: 0 | H10: 0 | J10: =IF(AND($G10=J$4,$H10=J$4),$E10,IF($G10>J$4,0,IF($H10<J$4,0,$E10/($H10-$G10+1)))) -> 7000 | K10: =IF(AND($G10=K$4,$H10=K$4),$E10,IF($G10>K$4,0,IF($H10<K$4,0,$E10/($H10-$G10+1)))) -> 0 | L10: =IF(AND($G10=L$4,$H10=L$4),$E10,IF($G10>L$4,0,IF($H10<L$4,0,$E10/($H10-$G10+1)))) -> 0 | M10: =IF(AND($G10=M$4,$H10=M$4),$E10,IF($G10>M$4,0,IF($H10<M$4,0,$E10/($H10-$G10+1)))) -> 0 | N10: =IF(AND($G10=N$4,$H10=N$4),$E10,IF($G10>N$4,0,IF($H10<N$4,0,$E10/($H10-$G10+1)))) -> 0 | O10: =IF(AND($G10=O$4,$H10=O$4),$E10,IF($G10>O$4,0,IF($H10<O$4,0,$E10/($H10-$G10+1)))) -> 0 | P10: =IF(AND($G10=P$4,$H10=P$4),$E10,IF($G10>P$4,0,IF($H10<P$4,0,$E10/($H10-$G10+1)))) -> 0 | Q10: =IF(AND($G10=Q$4,$H10=Q$4),$E10,IF($G10>Q$4,0,IF($H10<Q$4,0,$E10/($H10-$G10+1)))) -> 0 | ... EL10: =IF(AND($G10=EL$4,$H10=EL$4),$E10,IF($G10>EL$4,0,IF($H10<EL$4,0,$E10/($H10-$G10+1)))) -> 0
B11: Contingency | D11: 0.05 | E11: =+D11*SUM(E5:E10) -> 1425 | G11: =+H11 -> 0 | H11: =MAX(H5:H10) -> 0 | J11: =IF(AND($G11=J$4,$H11=J$4),$E11,IF($G11>J$4,0,IF($H11<J$4,0,$E11/($H11-$G11+1)))) -> 1425 | K11: =IF(AND($G11=K$4,$H11=K$4),$E11,IF($G11>K$4,0,IF($H11<K$4,0,$E11/($H11-$G11+1)))) -> 0 | L11: =IF(AND($G11=L$4,$H11=L$4),$E11,IF($G11>L$4,0,IF($H11<L$4,0,$E11/($H11-$G11+1)))) -> 0 | M11: =IF(AND($G11=M$4,$H11=M$4),$E11,IF($G11>M$4,0,IF($H11<M$4,0,$E11/($H11-$G11+1)))) -> 0 | N11: =IF(AND($G11=N$4,$H11=N$4),$E11,IF($G11>N$4,0,IF($H11<N$4,0,$E11/($H11-$G11+1)))) -> 0 | O11: =IF(AND($G11=O$4,$H11=O$4),$E11,IF($G11>O$4,0,IF($H11<O$4,0,$E11/($H11-$G11+1)))) -> 0 | P11: =IF(AND($G11=P$4,$H11=P$4),$E11,IF($G11>P$4,0,IF($H11<P$4,0,$E11/($H11-$G11+1)))) -> 0 | Q11: =IF(AND($G11=Q$4,$H11=Q$4),$E11,IF($G11>Q$4,0,IF($H11<Q$4,0,$E11/($H11-$G11+1)))) -> 0 | ... EL11: =IF(AND($G11=EL$4,$H11=EL$4),$E11,IF($G11>EL$4,0,IF($H11<EL$4,0,$E11/($H11-$G11+1)))) -> 0
B12: Total Legal and Pre-Development Costs | E12: =SUM(E5:E11) -> 29925 | J12: =SUM(J5:J11) -> 29925 | K12: =SUM(K5:K11) -> 0 | L12: =SUM(L5:L11) -> 0 | M12: =SUM(M5:M11) -> 0 | N12: =SUM(N5:N11) -> 0 | O12: =SUM(O5:O11) -> 0 | P12: =SUM(P5:P11) -> 0 | Q12: =SUM(Q5:Q11) -> 0 | ... EL12: =SUM(EL5:EL11) -> 0

Sheet Reserves
B4: Reserves | G4: Beg. Mo. | H4: End. Mo. | J4: =+Model!G4 -> 0 | K4: =+Model!H4 -> 1 | L4: =+Model!I4 -> 2 | M4: =+Model!J4 -> 3 | N4: =+Model!K4 -> 4 | O4: =+Model!L4 -> 5 | P4: =+Model!M4 -> 6 | Q4: =+Model!N4 -> 7 | ... EL4: =+Model!EI4 -> 132
B5: Loan Draws | E5: 0 | G5: 0 | H5: 0 | J5: =IF(AND($G5=J$4,$H5=J$4),$E5,IF($G5>J$4,0,IF($H5<J$4,0,$E5/($H5-$G5+1)))) -> 0 | K5: =IF(AND($G5=K$4,$H5=K$4),$E5,IF($G5>K$4,0,IF($H5<K$4,0,$E5/($H5-$G5+1)))) -> 0 | L5: =IF(AND($G5=L$4,$H5=L$4),$E5,IF($G5>L$4,0,IF($H5<L$4,0,$E5/($H5-$G5+1)))) -> 0 | M5: =IF(AND($G5=M$4,$H5=M$4),$E5,IF($G5>M$4,0,IF($H5<M$4,0,$E5/($H5-$G5+1)))) -> 0 | N5: =IF(AND($G5=N$4,$H5=N$4),$E5,IF($G5>N$4,0,IF($H5<N$4,0,$E5/($H5-$G5+1)))) -> 0 | O5: =IF(AND($G5=O$4,$H5=O$4),$E5,IF($G5>O$4,0,IF($H5<O$4,0,$E5/($H5-$G5+1)))) -> 0 | P5: =IF(AND($G5=P$4,$H5=P$4),$E5,IF($G5>P$4,0,IF($H5<P$4,0,$E5/($H5-$G5+1)))) -> 0 | Q5: =IF(AND($G5=Q$4,$H5=Q$4),$E5,IF($G5>Q$4,0,IF($H5<Q$4,0,$E5/($H5-$G5+1)))) -> 0 | ... EL5: =IF(AND($G5=EL$4,$H5=EL$4),$E5,IF($G5>EL$4,0,IF($H5<EL$4,0,$E5/($H5-$G5+1)))) -> 0
B6: Cash Reserve: Debt Service | E6: =+Assumptions!G31*Assumptions!L27/12 -> 99449.295 | G6: 0 | H6: 0 | J6: =IF(AND($G6=J$4,$H6=J$4),$E6,IF($G6>J$4,0,IF($H6<J$4,0,$E6/($H6-$G6+1)))) -> 99449.295 | K6: =IF(AND($G6=K$4,$H6=K$4),$E6,IF($G6>K$4,0,IF($H6<K$4,0,$E6/($H6-$G6+1)))) -> 0 | L6: =IF(AND($G6=L$4,$H6=L$4),$E6,IF($G6>L$4,0,IF($H6<L$4,0,$E6/($H6-$G6+1)))) -> 0 | M6: =IF(AND($G6=M$4,$H6=M$4),$E6,IF($G6>M$4,0,IF($H6<M$4,0,$E6/($H6-$G6+1)))) -> 0 | N6: =IF(AND($G6=N$4,$H6=N$4),$E6,IF($G6>N$4,0,IF($H6<N$4,0,$E6/($H6-$G6+1)))) -> 0 | O6: =IF(AND($G6=O$4,$H6=O$4),$E6,IF($G6>O$4,0,IF($H6<O$4,0,$E6/($H6-$G6+1)))) -> 0 | P6: =IF(AND($G6=P$4,$H6=P$4),$E6,IF($G6>P$4,0,IF($H6<P$4,0,$E6/($H6-$G6+1)))) -> 0 | Q6: =IF(AND($G6=Q$4,$H6=Q$4),$E6,IF($G6>Q$4,0,IF($H6<Q$4,0,$E6/($H6-$G6+1)))) -> 0 | ... EL6: =IF(AND($G6=EL$4,$H6=EL$4),$E6,IF($G6>EL$4,0,IF($H6<EL$4,0,$E6/($H6-$G6+1)))) -> 0
B7: Cash Reserve: Mechanicals | E7: 10000 | G7: 0 | H7: 0 | J7: =IF(AND($G7=J$4,$H7=J$4),$E7,IF($G7>J$4,0,IF($H7<J$4,0,$E7/($H7-$G7+1)))) -> 10000 | K7: =IF(AND($G7=K$4,$H7=K$4),$E7,IF($G7>K$4,0,IF($H7<K$4,0,$E7/($H7-$G7+1)))) -> 0 | L7: =IF(AND($G7=L$4,$H7=L$4),$E7,IF($G7>L$4,0,IF($H7<L$4,0,$E7/($H7-$G7+1)))) -> 0 | M7: =IF(AND($G7=M$4,$H7=M$4),$E7,IF($G7>M$4,0,IF($H7<M$4,0,$E7/($H7-$G7+1)))) -> 0 | N7: =IF(AND($G7=N$4,$H7=N$4),$E7,IF($G7>N$4,0,IF($H7<N$4,0,$E7/($H7-$G7+1)))) -> 0 | O7: =IF(AND($G7=O$4,$H7=O$4),$E7,IF($G7>O$4,0,IF($H7<O$4,0,$E7/($H7-$G7+1)))) -> 0 | P7: =IF(AND($G7=P$4,$H7=P$4),$E7,IF($G7>P$4,0,IF($H7<P$4,0,$E7/($H7-$G7+1)))) -> 0 | Q7: =IF(AND($G7=Q$4,$H7=Q$4),$E7,IF($G7>Q$4,0,IF($H7<Q$4,0,$E7/($H7-$G7+1)))) -> 0 | ... EL7: =IF(AND($G7=EL$4,$H7=EL$4),$E7,IF($G7>EL$4,0,IF($H7<EL$4,0,$E7/($H7-$G7+1)))) -> 0
B8: Cash Reserve: Roof | E8: 10000 | G8: 0 | H8: 0 | J8: =IF(AND($G8=J$4,$H8=J$4),$E8,IF($G8>J$4,0,IF($H8<J$4,0,$E8/($H8-$G8+1)))) -> 10000 | K8: =IF(AND($G8=K$4,$H8=K$4),$E8,IF($G8>K$4,0,IF($H8<K$4,0,$E8/($H8-$G8+1)))) -> 0 | L8: =IF(AND($G8=L$4,$H8=L$4),$E8,IF($G8>L$4,0,IF($H8<L$4,0,$E8/($H8-$G8+1)))) -> 0 | M8: =IF(AND($G8=M$4,$H8=M$4),$E8,IF($G8>M$4,0,IF($H8<M$4,0,$E8/($H8-$G8+1)))) -> 0 | N8: =IF(AND($G8=N$4,$H8=N$4),$E8,IF($G8>N$4,0,IF($H8<N$4,0,$E8/($H8-$G8+1)))) -> 0 | O8: =IF(AND($G8=O$4,$H8=O$4),$E8,IF($G8>O$4,0,IF($H8<O$4,0,$E8/($H8-$G8+1)))) -> 0 | P8: =IF(AND($G8=P$4,$H8=P$4),$E8,IF($G8>P$4,0,IF($H8<P$4,0,$E8/($H8-$G8+1)))) -> 0 | Q8: =IF(AND($G8=Q$4,$H8=Q$4),$E8,IF($G8>Q$4,0,IF($H8<Q$4,0,$E8/($H8-$G8+1)))) -> 0 | ... EL8: =IF(AND($G8=EL$4,$H8=EL$4),$E8,IF($G8>EL$4,0,IF($H8<EL$4,0,$E8/($H8-$G8+1)))) -> 0
B9: Cash Reserve: Cash for Keys | C9: 59 | D9: 7500 | E9: =+D9*C9 -> 442500 | G9: 0 | H9: 0 | J9: =IF(AND($G9=J$4,$H9=J$4),$E9,IF($G9>J$4,0,IF($H9<J$4,0,$E9/($H9-$G9+1)))) -> 442500 | K9: =IF(AND($G9=K$4,$H9=K$4),$E9,IF($G9>K$4,0,IF($H9<K$4,0,$E9/($H9-$G9+1)))) -> 0 | L9: =IF(AND($G9=L$4,$H9=L$4),$E9,IF($G9>L$4,0,IF($H9<L$4,0,$E9/($H9-$G9+1)))) -> 0 | M9: =IF(AND($G9=M$4,$H9=M$4),$E9,IF($G9>M$4,0,IF($H9<M$4,0,$E9/($H9-$G9+1)))) -> 0 | N9: =IF(AND($G9=N$4,$H9=N$4),$E9,IF($G9>N$4,0,IF($H9<N$4,0,$E9/($H9-$G9+1)))) -> 0 | O9: =IF(AND($G9=O$4,$H9=O$4),$E9,IF($G9>O$4,0,IF($H9<O$4,0,$E9/($H9-$G9+1)))) -> 0 | P9: =IF(AND($G9=P$4,$H9=P$4),$E9,IF($G9>P$4,0,IF($H9<P$4,0,$E9/($H9-$G9+1)))) -> 0 | Q9: =IF(AND($G9=Q$4,$H9=Q$4),$E9,IF($G9>Q$4,0,IF($H9<Q$4,0,$E9/($H9-$G9+1)))) -> 0 | ... EL9: =IF(AND($G9=EL$4,$H9=EL$4),$E9,IF($G9>EL$4,0,IF($H9<EL$4,0,$E9/($H9-$G9+1)))) -> 0
B10: Leasing Cost Reserves | C10: =IFERROR(SUMIFS(Assumptions!$C$46:$C$123,Assumptions!$C$46:$C$123,1),0) -> 78 | D10: =+Assumptions!L144 -> 2430.7692 | E10: =+D10*C10 -> 189600 | G10: 0 | H10: 0 | J10: =IF(AND($G10=J$4,$H10=J$4),$E10,IF($G10>J$4,0,IF($H10<J$4,0,$E10/($H10-$G10+1)))) -> 189600 | K10: =IF(AND($G10=K$4,$H10=K$4),$E10,IF($G10>K$4,0,IF($H10<K$4,0,$E10/($H10-$G10+1)))) -> 0 | L10: =IF(AND($G10=L$4,$H10=L$4),$E10,IF($G10>L$4,0,IF($H10<L$4,0,$E10/($H10-$G10+1)))) -> 0 | M10: =IF(AND($G10=M$4,$H10=M$4),$E10,IF($G10>M$4,0,IF($H10<M$4,0,$E10/($H10-$G10+1)))) -> 0 | N10: =IF(AND($G10=N$4,$H10=N$4),$E10,IF($G10>N$4,0,IF($H10<N$4,0,$E10/($H10-$G10+1)))) -> 0 | O10: =IF(AND($G10=O$4,$H10=O$4),$E10,IF($G10>O$4,0,IF($H10<O$4,0,$E10/($H10-$G10+1)))) -> 0 | P10: =IF(AND($G10=P$4,$H10=P$4),$E10,IF($G10>P$4,0,IF($H10<P$4,0,$E10/($H10-$G10+1)))) -> 0 | Q10: =IF(AND($G10=Q$4,$H10=Q$4),$E10,IF($G10>Q$4,0,IF($H10<Q$4,0,$E10/($H10-$G10+1)))) -> 0 | ... EL10: =IF(AND($G10=EL$4,$H10=EL$4),$E10,IF($G10>EL$4,0,IF($H10<EL$4,0,$E10/($H10-$G10+1)))) -> 0
B11: Contingency | D11: 0.05 | E11: =+D11*SUM(E5:E10) -> 37577.465 | G11: =+H11 -> 0 | H11: =MAX(H5:H10) -> 0 | J11: =IF(AND($G11=J$4,$H11=J$4),$E11,IF($G11>J$4,0,IF($H11<J$4,0,$E11/($H11-$G11+1)))) -> 37577.465 | K11: =IF(AND($G11=K$4,$H11=K$4),$E11,IF($G11>K$4,0,IF($H11<K$4,0,$E11/($H11-$G11+1)))) -> 0 | L11: =IF(AND($G11=L$4,$H11=L$4),$E11,IF($G11>L$4,0,IF($H11<L$4,0,$E11/($H11-$G11+1)))) -> 0 | M11: =IF(AND($G11=M$4,$H11=M$4),$E11,IF($G11>M$4,0,IF($H11<M$4,0,$E11/($H11-$G11+1)))) -> 0 | N11: =IF(AND($G11=N$4,$H11=N$4),$E11,IF($G11>N$4,0,IF($H11<N$4,0,$E11/($H11-$G11+1)))) -> 0 | O11: =IF(AND($G11=O$4,$H11=O$4),$E11,IF($G11>O$4,0,IF($H11<O$4,0,$E11/($H11-$G11+1)))) -> 0 | P11: =IF(AND($G11=P$4,$H11=P$4),$E11,IF($G11>P$4,0,IF($H11<P$4,0,$E11/($H11-$G11+1)))) -> 0 | Q11: =IF(AND($G11=Q$4,$H11=Q$4),$E11,IF($G11>Q$4,0,IF($H11<Q$4,0,$E11/($H11-$G11+1)))) -> 0 | ... EL11: =IF(AND($G11=EL$4,$H11=EL$4),$E11,IF($G11>EL$4,0,IF($H11<EL$4,0,$E11/($H11-$G11+1)))) -> 0
B12: Total Reserves | E12: =SUM(E5:E11) -> 789126.76 | J12: =SUM(J5:J11) -> 789126.76 | K12: =SUM(K5:K11) -> 0 | L12: =SUM(L5:L11) -> 0 | M12: =SUM(M5:M11) -> 0 | N12: =SUM(N5:N11) -> 0 | O12: =SUM(O5:O11) -> 0 | P12: =SUM(P5:P11) -> 0 | Q12: =SUM(Q5:Q11) -> 0 | ... EL12: =SUM(EL5:EL11) -> 0

Sheet Hard Costs
B4: Hard Costs | D4: =+Assumptions!G25 -> 55000 | G4: Beg. Mo. | H4: End. Mo. | J4: =+Model!G4 -> 0 | K4: =+Model!H4 -> 1 | L4: =+Model!I4 -> 2 | M4: =+Model!J4 -> 3 | N4: =+Model!K4 -> 4 | O4: =+Model!L4 -> 5 | P4: =+Model!M4 -> 6 | Q4: =+Model!N4 -> 7 | ... EL4: =+Model!EI4 -> 132
B5: Demo | E5: 20000 | G5: 0 | H5: 0 | J5: =IF(AND($G5=J$4,$H5=J$4),$E5,IF($G5>J$4,0,IF($H5<J$4,0,$E5/($H5-$G5+1)))) -> 20000 | K5: =IF(AND($G5=K$4,$H5=K$4),$E5,IF($G5>K$4,0,IF($H5<K$4,0,$E5/($H5-$G5+1)))) -> 0 | L5: =IF(AND($G5=L$4,$H5=L$4),$E5,IF($G5>L$4,0,IF($H5<L$4,0,$E5/($H5-$G5+1)))) -> 0 | M5: =IF(AND($G5=M$4,$H5=M$4),$E5,IF($G5>M$4,0,IF($H5<M$4,0,$E5/($H5-$G5+1)))) -> 0 | N5: =IF(AND($G5=N$4,$H5=N$4),$E5,IF($G5>N$4,0,IF($H5<N$4,0,$E5/($H5-$G5+1)))) -> 0 | O5: =IF(AND($G5=O$4,$H5=O$4),$E5,IF($G5>O$4,0,IF($H5<O$4,0,$E5/($H5-$G5+1)))) -> 0 | P5: =IF(AND($G5=P$4,$H5=P$4),$E5,IF($G5>P$4,0,IF($H5<P$4,0,$E5/($H5-$G5+1)))) -> 0 | Q5: =IF(AND($G5=Q$4,$H5=Q$4),$E5,IF($G5>Q$4,0,IF($H5<Q$4,0,$E5/($H5-$G5+1)))) -> 0 | ... EL5: =IF(AND($G5=EL$4,$H5=EL$4),$E5,IF($G5>EL$4,0,IF($H5<EL$4,0,$E5/($H5-$G5+1)))) -> 0
B6: Dumpsters and Permits | E6: 10000 | G6: 2 | H6: 11 | J6: =IF(AND($G6=J$4,$H6=J$4),$E6,IF($G6>J$4,0,IF($H6<J$4,0,$E6/($H6-$G6+1)))) -> 0 | K6: =IF(AND($G6=K$4,$H6=K$4),$E6,IF($G6>K$4,0,IF($H6<K$4,0,$E6/($H6-$G6+1)))) -> 0 | L6: =IF(AND($G6=L$4,$H6=L$4),$E6,IF($G6>L$4,0,IF($H6<L$4,0,$E6/($H6-$G6+1)))) -> 1000 | M6: =IF(AND($G6=M$4,$H6=M$4),$E6,IF($G6>M$4,0,IF($H6<M$4,0,$E6/($H6-$G6+1)))) -> 1000 | N6: =IF(AND($G6=N$4,$H6=N$4),$E6,IF($G6>N$4,0,IF($H6<N$4,0,$E6/($H6-$G6+1)))) -> 1000 | O6: =IF(AND($G6=O$4,$H6=O$4),$E6,IF($G6>O$4,0,IF($H6<O$4,0,$E6/($H6-$G6+1)))) -> 1000 | P6: =IF(AND($G6=P$4,$H6=P$4),$E6,IF($G6>P$4,0,IF($H6<P$4,0,$E6/($H6-$G6+1)))) -> 1000 | Q6: =IF(AND($G6=Q$4,$H6=Q$4),$E6,IF($G6>Q$4,0,IF($H6<Q$4,0,$E6/($H6-$G6+1)))) -> 1000 | ... EL6: =IF(AND($G6=EL$4,$H6=EL$4),$E6,IF($G6>EL$4,0,IF($H6<EL$4,0,$E6/($H6-$G6+1)))) -> 0
B7: Storage Buildout | C7: 50 | D7: 1500 | E7: =+D7*C7 -> 75000 | G7: 5 | H7: 6 | J7: =IF(AND($G7=J$4,$H7=J$4),$E7,IF($G7>J$4,0,IF($H7<J$4,0,$E7/($H7-$G7+1)))) -> 0 | K7: =IF(AND($G7=K$4,$H7=K$4),$E7,IF($G7>K$4,0,IF($H7<K$4,0,$E7/($H7-$G7+1)))) -> 0 | L7: =IF(AND($G7=L$4,$H7=L$4),$E7,IF($G7>L$4,0,IF($H7<L$4,0,$E7/($H7-$G7+1)))) -> 0 | M7: =IF(AND($G7=M$4,$H7=M$4),$E7,IF($G7>M$4,0,IF($H7<M$4,0,$E7/($H7-$G7+1)))) -> 0 | N7: =IF(AND($G7=N$4,$H7=N$4),$E7,IF($G7>N$4,0,IF($H7<N$4,0,$E7/($H7-$G7+1)))) -> 0 | O7: =IF(AND($G7=O$4,$H7=O$4),$E7,IF($G7>O$4,0,IF($H7<O$4,0,$E7/($H7-$G7+1)))) -> 37500 | P7: =IF(AND($G7=P$4,$H7=P$4),$E7,IF($G7>P$4,0,IF($H7<P$4,0,$E7/($H7-$G7+1)))) -> 37500 | Q7: =IF(AND($G7=Q$4,$H7=Q$4),$E7,IF($G7>Q$4,0,IF($H7<Q$4,0,$E7/($H7-$G7+1)))) -> 0 | ... EL7: =IF(AND($G7=EL$4,$H7=EL$4),$E7,IF($G7>EL$4,0,IF($H7<EL$4,0,$E7/($H7-$G7+1)))) -> 0
B8: Structural Repair | E8: 0 | G8: 0 | H8: 0 | J8: =IF(AND($G8=J$4,$H8=J$4),$E8,IF($G8>J$4,0,IF($H8<J$4,0,$E8/($H8-$G8+1)))) -> 0 | K8: =IF(AND($G8=K$4,$H8=K$4),$E8,IF($G8>K$4,0,IF($H8<K$4,0,$E8/($H8-$G8+1)))) -> 0 | L8: =IF(AND($G8=L$4,$H8=L$4),$E8,IF($G8>L$4,0,IF($H8<L$4,0,$E8/($H8-$G8+1)))) -> 0 | M8: =IF(AND($G8=M$4,$H8=M$4),$E8,IF($G8>M$4,0,IF($H8<M$4,0,$E8/($H8-$G8+1)))) -> 0 | N8: =IF(AND($G8=N$4,$H8=N$4),$E8,IF($G8>N$4,0,IF($H8<N$4,0,$E8/($H8-$G8+1)))) -> 0 | O8: =IF(AND($G8=O$4,$H8=O$4),$E8,IF($G8>O$4,0,IF($H8<O$4,0,$E8/($H8-$G8+1)))) -> 0 | P8: =IF(AND($G8=P$4,$H8=P$4),$E8,IF($G8>P$4,0,IF($H8<P$4,0,$E8/($H8-$G8+1)))) -> 0 | Q8: =IF(AND($G8=Q$4,$H8=Q$4),$E8,IF($G8>Q$4,0,IF($H8<Q$4,0,$E8/($H8-$G8+1)))) -> 0 | ... EL8: =IF(AND($G8=EL$4,$H8=EL$4),$E8,IF($G8>EL$4,0,IF($H8<EL$4,0,$E8/($H8-$G8+1)))) -> 0
B9: Mechancial Replacements | E9: 0 | G9: 0 | H9: 0 | J9: =IF(AND($G9=J$4,$H9=J$4),$E9,IF($G9>J$4,0,IF($H9<J$4,0,$E9/($H9-$G9+1)))) -> 0 | K9: =IF(AND($G9=K$4,$H9=K$4),$E9,IF($G9>K$4,0,IF($H9<K$4,0,$E9/($H9-$G9+1)))) -> 0 | L9: =IF(AND($G9=L$4,$H9=L$4),$E9,IF($G9>L$4,0,IF($H9<L$4,0,$E9/($H9-$G9+1)))) -> 0 | M9: =IF(AND($G9=M$4,$H9=M$4),$E9,IF($G9>M$4,0,IF($H9<M$4,0,$E9/($H9-$G9+1)))) -> 0 | N9: =IF(AND($G9=N$4,$H9=N$4),$E9,IF($G9>N$4,0,IF($H9<N$4,0,$E9/($H9-$G9+1)))) -> 0 | O9: =IF(AND($G9=O$4,$H9=O$4),$E9,IF($G9>O$4,0,IF($H9<O$4,0,$E9/($H9-$G9+1)))) -> 0 | P9: =IF(AND($G9=P$4,$H9=P$4),$E9,IF($G9>P$4,0,IF($H9<P$4,0,$E9/($H9-$G9+1)))) -> 0 | Q9: =IF(AND($G9=Q$4,$H9=Q$4),$E9,IF($G9>Q$4,0,IF($H9<Q$4,0,$E9/($H9-$G9+1)))) -> 0 | ... EL9: =IF(AND($G9=EL$4,$H9=EL$4),$E9,IF($G9>EL$4,0,IF($H9<EL$4,0,$E9/($H9-$G9+1)))) -> 0
B10: Common Area Refresh | E10: 5000 | G10: 10 | H10: 10 | J10: =IF(AND($G10=J$4,$H10=J$4),$E10,IF($G10>J$4,0,IF($H10<J$4,0,$E10/($H10-$G10+1)))) -> 0 | K10: =IF(AND($G10=K$4,$H10=K$4),$E10,IF($G10>K$4,0,IF($H10<K$4,0,$E10/($H10-$G10+1)))) -> 0 | L10: =IF(AND($G10=L$4,$H10=L$4),$E10,IF($G10>L$4,0,IF($H10<L$4,0,$E10/($H10-$G10+1)))) -> 0 | M10: =IF(AND($G10=M$4,$H10=M$4),$E10,IF($G10>M$4,0,IF($H10<M$4,0,$E10/($H10-$G10+1)))) -> 0 | N10: =IF(AND($G10=N$4,$H10=N$4),$E10,IF($G10>N$4,0,IF($H10<N$4,0,$E10/($H10-$G10+1)))) -> 0 | O10: =IF(AND($G10=O$4,$H10=O$4),$E10,IF($G10>O$4,0,IF($H10<O$4,0,$E10/($H10-$G10+1)))) -> 0 | P10: =IF(AND($G10=P$4,$H10=P$4),$E10,IF($G10>P$4,0,IF($H10<P$4,0,$E10/($H10-$G10+1)))) -> 0 | Q10: =IF(AND($G10=Q$4,$H10=Q$4),$E10,IF($G10>Q$4,0,IF($H10<Q$4,0,$E10/($H10-$G10+1)))) -> 0 | ... EL10: =IF(AND($G10=EL$4,$H10=EL$4),$E10,IF($G10>EL$4,0,IF($H10<EL$4,0,$E10/($H10-$G10+1)))) -> 0
B11: Exterior Façade | E11: 10000 | G11: 5 | H11: 5 | J11: =IF(AND($G11=J$4,$H11=J$4),$E11,IF($G11>J$4,0,IF($H11<J$4,0,$E11/($H11-$G11+1)))) -> 0 | K11: =IF(AND($G11=K$4,$H11=K$4),$E11,IF($G11>K$4,0,IF($H11<K$4,0,$E11/($H11-$G11+1)))) -> 0 | L11: =IF(AND($G11=L$4,$H11=L$4),$E11,IF($G11>L$4,0,IF($H11<L$4,0,$E11/($H11-$G11+1)))) -> 0 | M11: =IF(AND($G11=M$4,$H11=M$4),$E11,IF($G11>M$4,0,IF($H11<M$4,0,$E11/($H11-$G11+1)))) -> 0 | N11: =IF(AND($G11=N$4,$H11=N$4),$E11,IF($G11>N$4,0,IF($H11<N$4,0,$E11/($H11-$G11+1)))) -> 0 | O11: =IF(AND($G11=O$4,$H11=O$4),$E11,IF($G11>O$4,0,IF($H11<O$4,0,$E11/($H11-$G11+1)))) -> 10000 | P11: =IF(AND($G11=P$4,$H11=P$4),$E11,IF($G11>P$4,0,IF($H11<P$4,0,$E11/($H11-$G11+1)))) -> 0 | Q11: =IF(AND($G11=Q$4,$H11=Q$4),$E11,IF($G11>Q$4,0,IF($H11<Q$4,0,$E11/($H11-$G11+1)))) -> 0 | ... EL11: =IF(AND($G11=EL$4,$H11=EL$4),$E11,IF($G11>EL$4,0,IF($H11<EL$4,0,$E11/($H11-$G11+1)))) -> 0
B12: Entrance Repair | E12: 0 | G12: 0 | H12: 0 | J12: =IF(AND($G12=J$4,$H12=J$4),$E12,IF($G12>J$4,0,IF($H12<J$4,0,$E12/($H12-$G12+1)))) -> 0 | K12: =IF(AND($G12=K$4,$H12=K$4),$E12,IF($G12>K$4,0,IF($H12<K$4,0,$E12/($H12-$G12+1)))) -> 0 | L12: =IF(AND($G12=L$4,$H12=L$4),$E12,IF($G12>L$4,0,IF($H12<L$4,0,$E12/($H12-$G12+1)))) -> 0 | M12: =IF(AND($G12=M$4,$H12=M$4),$E12,IF($G12>M$4,0,IF($H12<M$4,0,$E12/($H12-$G12+1)))) -> 0 | N12: =IF(AND($G12=N$4,$H12=N$4),$E12,IF($G12>N$4,0,IF($H12<N$4,0,$E12/($H12-$G12+1)))) -> 0 | O12: =IF(AND($G12=O$4,$H12=O$4),$E12,IF($G12>O$4,0,IF($H12<O$4,0,$E12/($H12-$G12+1)))) -> 0 | P12: =IF(AND($G12=P$4,$H12=P$4),$E12,IF($G12>P$4,0,IF($H12<P$4,0,$E12/($H12-$G12+1)))) -> 0 | Q12: =IF(AND($G12=Q$4,$H12=Q$4),$E12,IF($G12>Q$4,0,IF($H12<Q$4,0,$E12/($H12-$G12+1)))) -> 0 | ... EL12: =IF(AND($G12=EL$4,$H12=EL$4),$E12,IF($G12>EL$4,0,IF($H12<EL$4,0,$E12/($H12-$G12+1)))) -> 0
B13: Parking | E13: 0 | G13: 0 | H13: 0 | J13: =IF(AND($G13=J$4,$H13=J$4),$E13,IF($G13>J$4,0,IF($H13<J$4,0,$E13/($H13-$G13+1)))) -> 0 | K13: =IF(AND($G13=K$4,$H13=K$4),$E13,IF($G13>K$4,0,IF($H13<K$4,0,$E13/($H13-$G13+1)))) -> 0 | L13: =IF(AND($G13=L$4,$H13=L$4),$E13,IF($G13>L$4,0,IF($H13<L$4,0,$E13/($H13-$G13+1)))) -> 0 | M13: =IF(AND($G13=M$4,$H13=M$4),$E13,IF($G13>M$4,0,IF($H13<M$4,0,$E13/($H13-$G13+1)))) -> 0 | N13: =IF(AND($G13=N$4,$H13=N$4),$E13,IF($G13>N$4,0,IF($H13<N$4,0,$E13/($H13-$G13+1)))) -> 0 | O13: =IF(AND($G13=O$4,$H13=O$4),$E13,IF($G13>O$4,0,IF($H13<O$4,0,$E13/($H13-$G13+1)))) -> 0 | P13: =IF(AND($G13=P$4,$H13=P$4),$E13,IF($G13>P$4,0,IF($H13<P$4,0,$E13/($H13-$G13+1)))) -> 0 | Q13: =IF(AND($G13=Q$4,$H13=Q$4),$E13,IF($G13>Q$4,0,IF($H13<Q$4,0,$E13/($H13-$G13+1)))) -> 0 | ... EL13: =IF(AND($G13=EL$4,$H13=EL$4),$E13,IF($G13>EL$4,0,IF($H13<EL$4,0,$E13/($H13-$G13+1)))) -> 0
B14: Unit Rehabs | C14: =IFERROR(SUMIFS(Assumptions!$C$46:$C$123,Assumptions!$C$46:$C$123,1),0) -> 78 | D14: 28500 | E14: =+D14*C14 -> 2223000 | G14: 2 | H14: 24 | J14: =IF(AND($G14=J$4,$H14=J$4),$E14,IF($G14>J$4,0,IF($H14<J$4,0,$E14/($H14-$G14+1)))) -> 0 | K14: =IF(AND($G14=K$4,$H14=K$4),$E14,IF($G14>K$4,0,IF($H14<K$4,0,$E14/($H14-$G14+1)))) -> 0 | L14: =IF(AND($G14=L$4,$H14=L$4),$E14,IF($G14>L$4,0,IF($H14<L$4,0,$E14/($H14-$G14+1)))) -> 96652.174 | M14: =IF(AND($G14=M$4,$H14=M$4),$E14,IF($G14>M$4,0,IF($H14<M$4,0,$E14/($H14-$G14+1)))) -> 96652.174 | N14: =IF(AND($G14=N$4,$H14=N$4),$E14,IF($G14>N$4,0,IF($H14<N$4,0,$E14/($H14-$G14+1)))) -> 96652.174 | O14: =IF(AND($G14=O$4,$H14=O$4),$E14,IF($G14>O$4,0,IF($H14<O$4,0,$E14/($H14-$G14+1)))) -> 96652.174 | P14: =IF(AND($G14=P$4,$H14=P$4),$E14,IF($G14>P$4,0,IF($H14<P$4,0,$E14/($H14-$G14+1)))) -> 96652.174 | Q14: =IF(AND($G14=Q$4,$H14=Q$4),$E14,IF($G14>Q$4,0,IF($H14<Q$4,0,$E14/($H14-$G14+1)))) -> 96652.174 | ... EL14: =IF(AND($G14=EL$4,$H14=EL$4),$E14,IF($G14>EL$4,0,IF($H14<EL$4,0,$E14/($H14-$G14+1)))) -> 0
B15: Contingency | D15: 0.1 | E15: =+D15*SUM(E5:E14) -> 234300 | G15: =+H15 -> 24 | H15: =MAX(H5:H14) -> 24 | J15: =IF(AND($G15=J$4,$H15=J$4),$E15,IF($G15>J$4,0,IF($H15<J$4,0,$E15/($H15-$G15+1)))) -> 0 | K15: =IF(AND($G15=K$4,$H15=K$4),$E15,IF($G15>K$4,0,IF($H15<K$4,0,$E15/($H15-$G15+1)))) -> 0 | L15: =IF(AND($G15=L$4,$H15=L$4),$E15,IF($G15>L$4,0,IF($H15<L$4,0,$E15/($H15-$G15+1)))) -> 0 | M15: =IF(AND($G15=M$4,$H15=M$4),$E15,IF($G15>M$4,0,IF($H15<M$4,0,$E15/($H15-$G15+1)))) -> 0 | N15: =IF(AND($G15=N$4,$H15=N$4),$E15,IF($G15>N$4,0,IF($H15<N$4,0,$E15/($H15-$G15+1)))) -> 0 | O15: =IF(AND($G15=O$4,$H15=O$4),$E15,IF($G15>O$4,0,IF($H15<O$4,0,$E15/($H15-$G15+1)))) -> 0 | P15: =IF(AND($G15=P$4,$H15=P$4),$E15,IF($G15>P$4,0,IF($H15<P$4,0,$E15/($H15-$G15+1)))) -> 0 | Q15: =IF(AND($G15=Q$4,$H15=Q$4),$E15,IF($G15>Q$4,0,IF($H15<Q$4,0,$E15/($H15-$G15+1)))) -> 0 | ... EL15: =IF(AND($G15=EL$4,$H15=EL$4),$E15,IF($G15>EL$4,0,IF($H15<EL$4,0,$E15/($H15-$G15+1)))) -> 0
B16: Total Hard Costs | D16: =+E16/D4 -> 46.86 | E16: =SUM(E5:E15) -> 2577300 | J16: =SUM(J5:J15) -> 20000 | K16: =SUM(K5:K15) -> 0 | L16: =SUM(L5:L15) -> 97652.174 | M16: =SUM(M5:M15) -> 97652.174 | N16: =SUM(N5:N15) -> 97652.174 | O16: =SUM(O5:O15) -> 145152.17 | P16: =SUM(P5:P15) -> 135152.17 | Q16: =SUM(Q5:Q15) -> 97652.174 | ... EL16: =SUM(EL5:EL15) -> 0

Sheet 1-month Term SOFR
B8: 1-month Term SOFR
B9: 45717
P11: Date | Q11: 1-month Term SOFR
O12: =EOMONTH(P12,0) -> 45747 | P12: 45727 | Q12: 0.0433017
O13: =EOMONTH(P13,0) -> 45777 | P13: 45758 | Q13: 0.0430529
O14: =EOMONTH(P14,0) -> 45808 | P14: 45789 | Q14: 0.0422185
O15: =EOMONTH(P15,0) -> 45838 | P15: 45819 | Q15: 0.0412577
O16: =EOMONTH(P16,0) -> 45869 | P16: 45849 | Q16: 0.0403625
O17: =EOMONTH(P17,0) -> 45900 | P17: 45880 | Q17: 0.0395926
O18: =EOMONTH(P18,0) -> 45930 | P18: 45911 | Q18: 0.0381025
O19: =EOMONTH(P19,0) -> 45961 | P19: 45944 | Q19: 0.0378538
O20: =EOMONTH(P20,0) -> 45991 | P20: 45973 | Q20: 0.0378518
O21: =EOMONTH(P21,0) -> 46022 | P21: 46002 | Q21: 0.0367114
O22: =EOMONTH(P22,0) -> 46053 | P22: 46034 | Q22: 0.0364455
O23: =EOMONTH(P23,0) -> 46081 | P23: 46064 | Q23: 0.03644
... O34: =EOMONTH(P34,0) -> 46418 | P34: 46398 | Q34: 0.035608
B35: For the latest rates, please visit: | O35: =EOMONTH(P35,0) -> 46446 | P35: 46429 | Q35: 0.0356781
B36: https://chathamdirect.com/rates | O36: =EOMONTH(P36,0) -> 46477 | P36: 46457 | Q36: 0.0357753
O37: =EOMONTH(P37,0) -> 46507 | P37: 46489 | Q37: 0.0358666
O38: =EOMONTH(P38,0) -> 46538 | P38: 46518 | Q38: 0.0359579
O39: =EOMONTH(P39,0) -> 46568 | P39: 46549 | Q39: 0.036051
O40: =EOMONTH(P40,0) -> 46599 | P40: 46580 | Q40: 0.0361432
O41: =EOMONTH(P41,0) -> 46630 | P41: 46610 | Q41: 0.0362381
O42: =EOMONTH(P42,0) -> 46660 | P42: 46643 | Q42: 0.0363245
O43: =EOMONTH(P43,0) -> 46691 | P43: 46672 | Q43: 0.0364114
O44: =EOMONTH(P44,0) -> 46721 | P44: 46703 | Q44: 0.0365
O45: =EOMONTH(P45,0) -> 46752 | P45: 46734 | Q45: 0.0365877
O46: =EOMONTH(P46,0) -> 46783 | P46: 46763 | Q46: 0.0366689
O47: =EOMONTH(P47,0) -> 46812 | P47: 46794 | Q47: 0.0367548
O48: =EOMONTH(P48,0) -> 46843 | P48: 46825 | Q48: 0.0368393
... O132: =EOMONTH(P132,0) -> 49399 | P132: 49380 | Q132: 0.0402355

Sheet FROM BROKER>>>

Sheet Income & Expenses
A1: 265-275 Beech St, Hackensack, NJ
C3: # Units | D3: =G7 -> 78 | F3: Residential Unit Mix
B4: ANNUAL INCOME | C4: PER UNIT | D4: TOTAL | F4: Unit Type | G4: # Units | H4: Current Rent | I4: Avg Current Rent | J4: Market Rent
B5: Market Residential Rent | C5: =D5/$D$3 -> 27969.231 | D5: =J7*12 -> 2181600 | F5: 1BR | G5: 72 | H5: $1,219-$1,881 | I5: 1544 | J5: 2300
B6: Loss to lease | C6: =D6/$D$3 -> -9120.5169 | D6: =D7-D5 -> -711400.32 | F6: 2BR | G6: 6 | H6: $1,391-$2,500 | I6: 1891 | J6: 2700
B7: Annual Rental Income | C7: =D7/$D$3 -> 18848.714 | D7: =H7*12 -> 1470199.7 | F7: Total | G7: =SUM(G5:G6) -> 78 | H7: ='Rent Roll'!C81 -> 122516.64 | J7: ='Rent Roll'!E81 -> 181800
B8: Less Vacancy | C8: =D8/$D$3 -> -565.46142 | D8: =-(D7)*3% -> -44105.99 | F8: Average | I8: =H7/G7 -> 1570.7262 | J8: =J7/G7 -> 2330.7692
B9: Effective Rental Income | C9: =D9/$D$3 -> 18283.252 | D9: =SUM(D7:D8) -> 1426093.7
B10: Parking Income | C10: =D10/$D$3 -> 591.53846 | D10: ='Rent Roll'!D81*12 -> 46140
B11: Laundry Income | C11: =D11/$D$3 -> 137.5 | D11: 10725
B12: Gross Operating Income | C12: =SUM(C9:C10) -> 18874.791 | D12: =SUM(D9:D11) -> 1482958.7
F13: Underwriting Assumptions
B14: ANNUAL EXPENSES | C14: PER UNIT | D14: TOTAL | F14: Income
B15: Real Estate Taxes | C15: =D15/$D$3 -> 3594.7179 | D15: 280388 | F15: Market Rent | G15: See rent roll
B16: Insurance | C16: =D16/$D$3 -> 750 | D16: =750*D3 -> 58500 | F16: Annual Rental Income | G16: See rent roll
B17: Payroll | C17: =D17/$D$3 -> 500 | D17: =500*D3 -> 39000 | F17: Vacancy | G17: 3% Estimate
B18: Heat | C18: =D18/$D$3 -> 863.89372 | D18: 67383.71 | F18: Parking Income | G18: See rent roll
B19: Electric | C19: =D19/$D$3 -> 78.701154 | D19: 6138.69 | F19: Expenses
B20: Water & Sewer | C20: =D20/$D$3 -> 600.89744 | D20: 46870 | F20: Real Estate Taxes | G20: Actual; County Records
B21: Repairs & Maintenance | C21: =D21/$D$3 -> 500 | D21: =500*D3 -> 39000 | F21: Management Fee | G21: Estimated at 3% of ERI
B22: Management Fee | C22: =D22/$D$3 -> 548.49757 | D22: =0.03*D9 -> 42782.811 | F22: Repairs & Maintenance | G22: Per unit estimate
B23: Total Expenses | C23: =SUM(C15:C22) -> 7436.7078 | D23: =SUM(D15:D22) -> 580063.21 | F23: Insurance | G23: Per unit estimate
B24: Net Operating Income | C24: =C12-C23 -> 11438.083 | D24: =D12-D23 -> 902895.48 | F24: Payroll | G24: Per unit estimate
B25: Plus Loss to Lease | D25: =-D6 -> 711400.32 | F25: All other expenses | G25: Actuals / Owner's figures
B26: Market Net Operating Income | C26: =D26/D3 -> 20696.1 | D26: =SUM(D24:D25) -> 1614295.8

Sheet Rent Roll
A1: Rent Roll: 265-275 Beech St, Hackensack, NJ
A2: Unit | B2: Unit Type | C2: Rent | D2: Parking | E2: Market Rent
A3: 1 | B3: 2BR | C3: 1522.5 | D3: 0 | E3: 2700
A4: 2 | B4: 2BR | C4: 1764 | D4: 100 | E4: 2700
A5: 3 | B5: 1BR | C5: 1457.71 | D5: 130 | E5: 2300
A6: 4 | B6: 1BR | C6: 1680 | D6: 0 | E6: 2300
A7: 5 | B7: 1BR | C7: 1451.66 | D7: 50 | E7: 2300
A8: 6 | B8: 1BR | C8: 1627.5 | D8: 115 | E8: 2300
A9: 7 | B9: 1BR | C9: 1881 | D9: 65 | E9: 2300
A10: 8 | B10: 1BR | C10: 1417.5 | D10: 50 | E10: 2300
A11: 20 | B11: 1BR | C11: 1650 | D11: 130 | E11: 2300
A12: 21 | B12: 1BR | C12: 1391.18 | D12: 65 | E12: 2300
A13: 22 | B13: 1BR | C13: 1391.25 | D13: 0 | E13: 2300
A14: 23 | B14: 1BR | C14: 1428 | D14: 100 | E14: 2300
... A22: 31 | B22: 1BR | C22: 1344 | D22: 50 | E22: 2300
A23: 32 | B23: 1BR | C23: 1700 | D23: =65+35 -> 100 | E23: 2300
A24: 33 | B24: 1BR | C24: 1412.25 | D24: 0 | E24: 2300
A25: 34 | B25: 1BR | C25: 1522.5 | D25: 0 | E25: 2300
A26: 35 | B26: 1BR | C26: 1627.5 | D26: 65 | E26: 2300
A27: 36 | B27: 1BR | C27: 1522.5 | D27: 50 | E27: 2300
A28: 37 | B28: 1BR | C28: 1444.72 | D28: 100 | E28: 2300
A29: 38 | B29: 1BR | C29: 1785 | D29: 50 | E29: 2300
A30: 39 | B30: 1BR | C30: 1451.66 | D30: 50 | E30: 2300
A31: 40 | B31: 1BR | C31: 1548.75 | D31: 50 | E31: 2300
A32: 41 | B32: 1BR | C32: 1443.75 | D32: 0 | E32: 2300
A33: 42 | B33: 1BR | C33: 1391.25 | D33: 50 | E33: 2300
A34: 43 | B34: 1BR | C34: 1219 | D34: 0 | E34: 2300
A35: 44 | B35: 1BR | C35: 1600 | D35: 50 | E35: 2300
... A40: 49 | B40: 1BR | C40: 1700 | D40: 50 | E40: 2300
A41: B | B41: 2BR | C41: 1391.25 | D41: 100 | E41: 2700
A42: 1 | B42: 2BR | C42: 2500 | D42: 65 | E42: 2700
A43: 2 | B43: 2BR | C43: 2194.5 | D43: 50 | E43: 2700
A44: 3 | B44: 1BR | C44: 1724.25 | D44: 65 | E44: 2300
A45: 4 | B45: 1BR | C45: 1755.6 | D45: 65 | E45: 2300
A46: 5 | B46: 1BR | C46: 1417.5 | D46: 100 | E46: 2300
A47: 6 | B47: 1BR | C47: 1601.25 | D47: 100 | E47: 2300
A48: 7 | B48: 1BR | C48: 1732.5 | D48: 0 | E48: 2300
A49: 8 | B49: 1BR | C49: 1443.75 | D49: 50 | E49: 2300 | G49: 0 | H49: =COUNTIF($D$3:$D$80,G49) -> 23
A50: 20 - VACANT | B50: 1BR | C50: 1417.5 | D50: 130 | E50: 2300 | G50: 50 | H50: =COUNTIF($D$3:$D$80,G50) -> 28
A51: 21 | B51: 1BR | C51: 1700 | D51: 0 | E51: 2300 | G51: 65 | H51: =COUNTIF($D$3:$D$80,G51) -> 12
A52: 22 | B52: 1BR | C52: 1819.13 | D52: 50 | E52: 2300 | G52: 100 | H52: =COUNTIF($D$3:$D$80,G52) -> 9
A53: 23 | B53: 1BR | C53: 1481.9 | D53: 50 | E53: 2300 | G53: 130 | H53: =COUNTIF($D$3:$D$80,G53) -> 5
A54: 24 | B54: 1BR | C54: 1680 | D54: 0 | E54: 2300
A55: 25 | B55: 1BR | C55: 1439.57 | D55: 100 | E55: 2300 | G55: 24 spots x $75 (tandem)
A56: 26 | B56: 1BR | C56: 1417.5 | D56: 0 | E56: 2300 | G56: Remaining is $100 (regular)
A57: 27 | B57: 1BR | C57: 1416.58 | D57: 100 | E57: 2300 | G57: start this month 12-18
A58: 28 | B58: 1BR | C58: 1457.71 | D58: 50 | E58: 2300
A59: 29 | B59: 1BR | C59: 1627.5 | D59: 65 | E59: 2300
A60: 30 | B60: 1BR | C60: 1700 | D60: 0 | E60: 2300
A61: 31 | B61: 1BR | C61: 1522.5 | D61: 0 | E61: 2300
A62: 32 | B62: 1BR | C62: 1451.66 | D62: 50 | E62: 2300
A63: 33 | B63: 1BR | C63: 1481.9 | D63: 0 | E63: 2300
A64: 34 | B64: 1BR | C64: 1700 | D64: 0 | E64: 2300
A65: 35 | B65: 1BR | C65: 1482 | D65: 50 | E65: 2300
A66: 36 | B66: 1BR | C66: 1785 | D66: 130 | E66: 2300
A67: 37 | B67: 1BR | C67: 1522.5 | D67: 50 | E67: 2300
A68: 38 | B68: 1BR | C68: 1575 | D68: 65 | E68: 2300
A69: 39 - VACANT | B69: 1BR | C69: 1607.47 | D69: 50 | E69: 2300
A70: 40 | B70: 1BR | C70: 1470 | D70: 65 | E70: 2300
A71: 41 | B71: 1BR | C71: 1600 | D71: 0 | E71: 2300
A72: 42 | B72: 1BR | C72: 1391.25 | D72: 50 | E72: 2300
A73: 43 | B73: 1BR | C73: 1640.39 | D73: 130 | E73: 2300
A74: 44 | B74: 1BR | C74: 1700 | D74: 65 | E74: 2300
A75: 45 | B75: 1BR | C75: 1672 | D75: 0 | E75: 2300
A76: 46 | B76: 1BR | C76: 1481.9 | D76: 50 | E76: 2300
A77: 47 | B77: 1BR | C77: 1459.5 | D77: 0 | E77: 2300
A78: 48 | B78: 1BR | C78: 1700.74 | D78: 0 | E78: 2300
A79: 49 | B79: 1BR | C79: 1300 | D79: 50 | E79: 2300
A80: B | B80: 2BR | C80: 1975.05 | D80: 65 | E80: 2700
A81: Totals: | B81: =COUNTA(A3:A80) -> 78 | C81: =SUM(C3:C80) -> 122516.64 | D81: =SUM(D3:D80) -> 3845 | E81: =SUM(E3:E80) -> 181800
